Workbook
Name БР: ИТОГ!$U$42
Name ГИС: ИТОГ!$U$35
Name ЗОКИИ: ИТОГ!$U$37
Name КИИ: ИТОГ!$U$36
Name КТ: ИТОГ!$U$41
Name ЛИЦ: ИТОГ!$U$34
Name Лицензия: ИТОГ!$U$34
Name ПДН: ИТОГ!$U$38
Name СК: ИТОГ!$U$44
Name СКЗИ: ИТОГ!$U$43
Name СКПДН: ИТОГ!$U$39
Name СТОРПДН: ИТОГ!$U$38
Name СУДПДН: ИТОГ!$U$40
Name ЦУКБ: ИТОГ!$L$3

Sheet Описание
D2: Индекс кибербезопасности
B10: Данный файл предназначен для проведения самооценки состояния информационной безопасности и расчета итогового "Индекса кибербезопасности".
B13: Для работы с файлом необходимо заполнить данные в ячейках с желтым фоном на листах с зелеными ярлычками.
B14: На вкладке "ИТОГ" отображается сводный график достижения целевого уровня кибербезопасности.
B15: Лист "Расчет" - это итоговая служебная таблица, на которой осуществляется промежуточный расчет, он не предназначен для редактирования
B18: Рассчет индекса ведется как некоторая усредненная величина показателей по отдельным доменам кибербезопасности.
B19: В каждой отдельной вкладке домена строится своя диаграмма и рассчитывается свой локальный индекс.

Sheet ИТОГ
D2: Итоговый рассчетный индекс кибербезопасности и диаграмма достижения целевых показателей в различных доменах информационной безопасности | L2: Целевой уровень | O2: =IF(ЦУКБ="кб 2", W3, IF(ЦУКБ="КБ 1", U3, Y3)) -> 0 | U2: КБ1 | W2: КБ2 | Y2: КБ3
L3: КБ 3 | P3: на | Q3: =Расчет!M2 -> 46038 | S3: =Расчет!M3 -> 0 | U3: =Расчет!T3 -> 0 | W3: =Расчет!S3 -> 0 | Y3: =Расчет!R3 -> 0
U34: да | V34: Лицензиат ФСТЭК/ФСБ
U35: да | V35: Участие в госконтрактах на разработку/сопровождение ГИС
U36: да | V36: Субьект КИИ
U37: да | V37: Наличие ЗОКИИ
U38: да | V38: Обработка сторонних ПДН
U39: да | V39: Спец. Категории ПДН
U40: да | V40: ПДН о судимости
U41: да | V41: Наличие Коммерческой тайны
U42: да | V42: Безопасная разработка
U43: да | V43: СКЗИ ГОСТ
U44: нет | V44: Подключены сервисы Сервисной Компании

Sheet Расчет
C1: КБ3 | D1: КБ2 | E1: КБ1 | F1: Исторические данные | H1: Исторические данные середину 2024 г. | I1: Исторические данные на конец 2024 г. | J1: Архивные расчетные данные на 31.12.2024 | K1: Расчетные данные на 31.12.2026 | L1: Расчетные данные на | M1: Текущий показатель | N1: Флаг внимания | P1: Степень выполнения расчетного показателя | R1: Степень достижения КБ3 | S1: Степень достижения КБ2 | T1: Степень достижения КБ1
B2: Дата заполнения | F2: 45017 | G2: 45291 | H2: 45444 | M2: =TODAY() -> 46038
B3: ИНДЕКС КИБЕРБЕЗОПАСНОСТИ | C3: =AVERAGE(C4:C44) -> 4.8651098 | D3: =AVERAGE(D4:D44) -> 3.634862 | E3: =AVERAGE(E4:E44) -> 1.8501809 | F3: =0.3*( SUM(F23+F24+F25+F26+F27*IF(СКЗИ="да",1,0)) / (1+1+1+1+1*IF(СКЗИ="да",1,0)) ) +0.2*(SUM(F17+F18*IF(СКЗИ="да",1,0)+(F19+F20)*IF(КИИ="да",1,0)+F22*IF(КТ="да",1,0)) / (1+1*IF(СКЗИ="да",1,0)+(2)*IF(КИИ="да",1,0)+1*IF(КТ="да",1,0)) ) +0.3*(SUM(F4,F21,F28,#REF!,F37,F38)/6) +0.2*(SUM(F39:F44,F29:F36,F6:F14,F16,F5, F15*IF(БР="да",1,0)) / (25+1*IF(БР="да",1,0))) -> #REF! | G3: =0.3*( SUM(G23+G24+G25+G26+G27*IF(СКЗИ="да",1,0)) / (1+1+1+1+1*IF(СКЗИ="да",1,0)) ) +0.2*(SUM(G17+G18*IF(СКЗИ="да",1,0)+(G19+G20)*IF(КИИ="да",1,0)+G22*IF(КТ="да",1,0)) / (1+1*IF(СКЗИ="да",1,0)+(2)*IF(КИИ="да",1,0)+1*IF(КТ="да",1,0)) ) +0.3*(SUM(G4,G21,G28,#REF!,G37,G38)/6) +0.2*(SUM(G39:G44,G29:G36,G6:G14,G16,G5, G15*IF(БР="да",1,0)) / (25+1*IF(БР="да",1,0))) -> #REF! | H3: =0.3*( SUM(H23+H24+H25+H26+H27*IF(СКЗИ="да",1,0)) / (1+1+1+1+1*IF(СКЗИ="да",1,0)) ) +0.2*(SUM(H17+H18*IF(СКЗИ="да",1,0)+(H19+H20)*IF(КИИ="да",1,0)+H22*IF(КТ="да",1,0)) / (1+1*IF(СКЗИ="да",1,0)+(2)*IF(КИИ="да",1,0)+1*IF(КТ="да",1,0)) ) +0.3*(SUM(H4,H21,H28,#REF!,H37,H38)/6) +0.2*(SUM(H39:H44,H29:H36,H6:H14,H16,H5, H15*IF(БР="да",1,0)) / (25+1*IF(БР="да",1,0))) -> #REF! | I3: =0.3*( SUM(I23+I24+I25+I26+I27*IF(СКЗИ="да",1,0)) / (1+1+1+1+1*IF(СКЗИ="да",1,0)) ) +0.2*(SUM(I17+I18*IF(СКЗИ="да",1,0)+(I19+I20)*IF(КИИ="да",1,0)+I22*IF(КТ="да",1,0)) / (1+1*IF(СКЗИ="да",1,0)+(2)*IF(КИИ="да",1,0)+1*IF(КТ="да",1,0)) ) +0.3*(SUM(I4,I21,I28,#REF!,I37,I38)/6) +0.2*(SUM(I39:I44,I29:I36,I6:I14,I16,I5, I15*IF(БР="да",1,0)) / (25+1*IF(БР="да",1,0))) -> #REF! | J3: =0.3*( SUM(J23+J24+J25+J26+J27*IF(СКЗИ="да",1,0)) / (1+1+1+1+1*IF(СКЗИ="да",1,0)) ) +0.2*(SUM(J17+J18*IF(СКЗИ="да",1,0)+(J19+J20)*IF(КИИ="да",1,0)+J22*IF(КТ="да",1,0)) / (1+1*IF(СКЗИ="да",1,0)+(2)*IF(КИИ="да",1,0)+1*IF(КТ="да",1,0)) ) +0.3*(SUM(J4,J21,J28,#REF!,J37,J38)/6) +0.2*(SUM(J39:J44,J29:J36,J6:J14,J16,J5, J15*IF(БР="да",1,0)) / (25+1*IF(БР="да",1,0))) -> #REF! | K3: =0.3*( SUM(K23+K24+K25+K26+K27*IF(СКЗИ="да",1,0)) / (1+1+1+1+1*IF(СКЗИ="да",1,0)) ) +0.2*(SUM(K17+K18*IF(СКЗИ="да",1,0)+(K19+K20)*IF(КИИ="да",1,0)+K22*IF(КТ="да",1,0)) / (1+1*IF(СКЗИ="да",1,0)+(2)*IF(КИИ="да",1,0)+1*IF(КТ="да",1,0)) ) +0.3*(SUM(K4,K21,K28,#REF!,K37,K38)/6) +0.2*(SUM(K39:K44,K29:K36,K6:K14,K16,K5, K15*IF(БР="да",1,0)) / (25+1*IF(БР="да",1,0))) -> #DIV/0! | L3: =AVERAGE(L4:L44) -> 4.8651098 | M3: =AVERAGE(M4:M44) -> 0 | O3: прирост (дек.24- т.вр) | R3: =0.65*( SUM(R23+R24+R25+R26+R27*IF(СКЗИ="да",1,0)+R28+R29+R30+R31+R32+R33+R34+R35+R36) / (1+1+1+1+1*IF(СКЗИ="да",1,0)+5+4) ) +0.2*(SUM(R17+R18*IF(СКЗИ="да",1,0)+(R19+R20)*IF(КИИ="да",1,0)+R21+R22*IF(КТ="да",1,0)) / (1+IF(СКЗИ="да",1,0)+(2)*IF(КИИ="да",1,0)+1+IF(КТ="да",1,0)) ) +0.15*(SUM(R4:R13,R15,R16,R37:R44) / (10+1+1+8)) -> 0 | S3: =0.65*( SUM(S23+S24+S25+S26+S27*IF(СКЗИ="да",1,0)+S28+S29+S30+S31+S32+S33)/(1+1+1+1+1*IF(СКЗИ="да",1,0)+6)) +0.2*(SUM(S17+S18*IF(СКЗИ="да",1,0)+(S19+S20)*IF(КИИ="да",1,0)+S21+S22*IF(КТ="да",1,0))/(1+IF(СКЗИ="да",1,0)+(2)*IF(КИИ="да",1,0)+1+IF(КТ="да",1,0)) ) +0.15*(SUM(S4:S13,S15,S16,S37:S44) / (10+1+1+8)) -> 0 | T3: =0.65*( SUM(T23+T24+T25+T26+T27*IF(СКЗИ="да",1,0)) / (1+1+1+1+1*IF(СКЗИ="да",1,0)) ) +0.2*(SUM(T17+T18*IF(СКЗИ="да",1,0)+(T19+T20)*IF(КИИ="да",1,0)+T21+T22*IF(КТ="да",1,0)) / (1+IF(СКЗИ="да",1,0)+(2)*IF(КИИ="да",1,0)+1+IF(КТ="да",1,0)) ) +0.15*(SUM(T4:T10,T12:T13,T15,T16,T39:T43) / (9+1+1+5)) -> 0
A4: СУИБ | B4: ='Управление ИБ'!B42 -> Система управления ИБ | C4: ='Управление ИБ'!D42 -> 5 | D4: ='Управление ИБ'!E42 -> 4.64 | E4: ='Управление ИБ'!F42 -> 2.5 | F4: 0 | G4: 0 | H4: 0 | I4: 0 | J4: 0 | K4: ='Управление ИБ'!J42 -> #DIV/0! | L4: ='Управление ИБ'!K42 -> 5 | M4: ='Управление ИБ'!L42 -> 0 | N4: =L4-M4 -> 5 | O4: =I4-M4 -> 0 | P4: =1-IF(L4=0,0,IF(($M4-L4)>=0,1,1-(L4-$M4)/L4)) -> 1 | R4: ='Управление ИБ'!P42 -> 0 | S4: ='Управление ИБ'!Q42 -> 0 | T4: ='Управление ИБ'!R42 -> 0
B5: ='Управление ИБ'!B43 -> Управление рисками | C5: ='Управление ИБ'!D43 -> 4.8 | D5: ='Управление ИБ'!E43 -> 2 | E5: ='Управление ИБ'!F43 -> 1 | F5: 0 | G5: 0 | H5: 0 | I5: 0 | J5: 0 | K5: ='Управление ИБ'!J43 -> #DIV/0! | L5: ='Управление ИБ'!K43 -> 4.8 | M5: ='Управление ИБ'!L43 -> 0 | N5: =L5-M5 -> 4.8 | O5: =I5-M5 -> 0 | P5: =1-IF(L5=0,0,IF(($M5-L5)>=0,1,1-(L5-$M5)/L5)) -> 1 | R5: ='Управление ИБ'!P43 -> 0 | S5: ='Управление ИБ'!Q43 -> 0 | T5: ='Управление ИБ'!R43 -> 0
B6: ='Управление ИБ'!B45 -> Инвентаризация | C6: ='Управление ИБ'!D45 -> 4.9285714 | D6: ='Управление ИБ'!E45 -> 3.1857143 | E6: ='Управление ИБ'!F45 -> 1.2142857 | F6: 0 | G6: 0 | H6: 0 | I6: 0 | J6: 0 | K6: ='Управление ИБ'!J45 -> #DIV/0! | L6: ='Управление ИБ'!K45 -> 4.9285714 | M6: ='Управление ИБ'!L45 -> 0 | N6: =L6-M6 -> 4.9285714 | O6: =I6-M6 -> 0 | P6: =1-IF(L6=0,0,IF(($M6-L6)>=0,1,1-(L6-$M6)/L6)) -> 1 | R6: ='Управление ИБ'!P45 -> 0 | S6: ='Управление ИБ'!Q45 -> 0 | T6: ='Управление ИБ'!R45 -> 0
B7: ='Управление ИБ'!B46 -> Управление активами | C7: ='Управление ИБ'!D46 -> 4.8 | D7: ='Управление ИБ'!E46 -> 3.16 | E7: ='Управление ИБ'!F46 -> 0.52 | F7: 0 | G7: 0 | H7: 0 | I7: 0 | J7: 0 | K7: ='Управление ИБ'!J46 -> #DIV/0! | L7: ='Управление ИБ'!K46 -> 4.8 | M7: ='Управление ИБ'!L46 -> 0 | N7: =L7-M7 -> 4.8 | O7: =I7-M7 -> 0 | P7: =1-IF(L7=0,0,IF(($M7-L7)>=0,1,1-(L7-$M7)/L7)) -> 1 | R7: ='Управление ИБ'!P46 -> 0 | S7: ='Управление ИБ'!Q46 -> 0 | T7: ='Управление ИБ'!R46 -> 0
B8: ='Управление ИБ'!B47 -> Управление доступом | C8: ='Управление ИБ'!D47 -> 4.46 | D8: ='Управление ИБ'!E47 -> 3.26 | E8: ='Управление ИБ'!F47 -> 2.14 | F8: 0 | G8: 0 | H8: 0 | I8: 0 | J8: 0 | K8: ='Управление ИБ'!J47 -> #DIV/0! | L8: ='Управление ИБ'!K47 -> 4.46 | M8: ='Управление ИБ'!L47 -> 0 | N8: =L8-M8 -> 4.46 | O8: =I8-M8 -> 0 | P8: =1-IF(L8=0,0,IF(($M8-L8)>=0,1,1-(L8-$M8)/L8)) -> 1 | R8: ='Управление ИБ'!P47 -> 0 | S8: ='Управление ИБ'!Q47 -> 0 | T8: ='Управление ИБ'!R47 -> 0
B9: ='Управление ИБ'!B48 -> Идентификация и аутентификация | C9: ='Управление ИБ'!D48 -> 5 | D9: ='Управление ИБ'!E48 -> 4.6 | E9: ='Управление ИБ'!F48 -> 3.3111111 | F9: 0 | G9: 0 | H9: 0 | I9: 0 | J9: 0 | K9: ='Управление ИБ'!J48 -> #DIV/0! | L9: ='Управление ИБ'!K48 -> 5 | M9: ='Управление ИБ'!L48 -> 0 | N9: =L9-M9 -> 5 | O9: =I9-M9 -> 0 | P9: =1-IF(L9=0,0,IF(($M9-L9)>=0,1,1-(L9-$M9)/L9)) -> 1 | R9: ='Управление ИБ'!P48 -> 0 | S9: ='Управление ИБ'!Q48 -> 0 | T9: ='Управление ИБ'!R48 -> 0
B10: ='Управление ИБ'!B49 -> Защита данных и информации | C10: ='Управление ИБ'!D49 -> 4.55 | D10: ='Управление ИБ'!E49 -> 3.7 | E10: ='Управление ИБ'!F49 -> 1.2 | F10: 0 | G10: 0 | H10: 0 | I10: 0 | J10: 0 | K10: ='Управление ИБ'!J49 -> #DIV/0! | L10: ='Управление ИБ'!K49 -> 4.55 | M10: ='Управление ИБ'!L49 -> 0 | N10: =L10-M10 -> 4.55 | O10: =I10-M10 -> 0 | P10: =1-IF(L10=0,0,IF(($M10-L10)>=0,1,1-(L10-$M10)/L10)) -> 1 | R10: ='Управление ИБ'!P49 -> 0 | S10: ='Управление ИБ'!Q49 -> 0 | T10: ='Управление ИБ'!R49 -> 0
B11: ='Управление ИБ'!B50 -> Обеспечение доступности | C11: ='Управление ИБ'!D50 -> 5 | D11: ='Управление ИБ'!E50 -> 2.92 | E11: ='Управление ИБ'!F50 -> 0 | F11: 0 | G11: 0 | H11: 0 | I11: 0 | J11: 0 | K11: ='Управление ИБ'!J50 -> #DIV/0! | L11: ='Управление ИБ'!K50 -> 5 | M11: ='Управление ИБ'!L50 -> 0 | N11: =L11-M11 -> 5 | O11: =I11-M11 -> 0 | P11: =1-IF(L11=0,0,IF(($M11-L11)>=0,1,1-(L11-$M11)/L11)) -> 1 | R11: ='Управление ИБ'!P50 -> 0 | S11: ='Управление ИБ'!Q50 -> 0
B12: ='Управление ИБ'!B51 -> Персонал | C12: ='Управление ИБ'!D51 -> 5 | D12: ='Управление ИБ'!E51 -> 5 | E12: ='Управление ИБ'!F51 -> 5 | F12: 0 | G12: 0 | H12: 0 | I12: 0 | J12: 0 | K12: ='Управление ИБ'!J51 -> #DIV/0! | L12: ='Управление ИБ'!K51 -> 5 | M12: ='Управление ИБ'!L51 -> 0 | N12: =L12-M12 -> 5 | O12: =I12-M12 -> 0 | P12: =1-IF(L12=0,0,IF(($M12-L12)>=0,1,1-(L12-$M12)/L12)) -> 1 | R12: ='Управление ИБ'!P51 -> 0 | S12: ='Управление ИБ'!Q51 -> 0 | T12: ='Управление ИБ'!R51 -> 0
B13: ='Управление ИБ'!B52 -> Осведомленность пользователей и обучение персонала | C13: ='Управление ИБ'!D52 -> 5 | D13: ='Управление ИБ'!E52 -> 3.2 | E13: ='Управление ИБ'!F52 -> 1.6 | F13: 0 | G13: 0 | H13: 0 | I13: 0 | J13: 0 | K13: ='Управление ИБ'!J52 -> #DIV/0! | L13: ='Управление ИБ'!K52 -> 5 | M13: ='Управление ИБ'!L52 -> 0 | N13: =L13-M13 -> 5 | O13: =I13-M13 -> 0 | P13: =1-IF(L13=0,0,IF(($M13-L13)>=0,1,1-(L13-$M13)/L13)) -> 1 | R13: ='Управление ИБ'!P52 -> 0 | S13: ='Управление ИБ'!Q52 -> 0 | T13: ='Управление ИБ'!R52 -> 0
B14: ='Управление ИБ'!B53 -> Процессы | C14: ='Управление ИБ'!D53 -> 4.1428571 | D14: ='Управление ИБ'!E53 -> 2.7904762 | E14: ='Управление ИБ'!F53 -> 0.6952381 | F14: 0 | G14: 0 | H14: 0 | I14: 0 | J14: 0 | K14: ='Управление ИБ'!J53 -> 0 | L14: ='Управление ИБ'!K53 -> 4.1428571 | M14: ='Управление ИБ'!L53 -> 0 | N14: =L14-M14 -> 4.1428571 | O14: =I14-M14 -> 0 | P14: =1-IF(L14=0,0,IF(($M14-L14)>=0,1,1-(L14-$M14)/L14)) -> 1
B15: ='Управление ИБ'!B54 -> Приобретение, разработка и обслуживание систем и ПО | C15: ='Управление ИБ'!D54 -> 5 | D15: ='Управление ИБ'!E54 -> 3.8545455 | E15: ='Управление ИБ'!F54 -> 1.0181818 | F15: 0 | G15: 0 | H15: 0 | I15: 0 | J15: 0 | K15: ='Управление ИБ'!J54 -> #DIV/0! | L15: ='Управление ИБ'!K54 -> 5 | M15: ='Управление ИБ'!L54 -> 0 | N15: =L15-M15 -> 5 | O15: =I15-M15 -> 0 | P15: =1-IF(L15=0,0,IF(($M15-L15)>=0,1,1-(L15-$M15)/L15)) -> 1 | R15: ='Управление ИБ'!P54 -> 0 | S15: ='Управление ИБ'!Q54 -> 0 | T15: ='Управление ИБ'!R54 -> 0
B16: ='Управление ИБ'!B55 -> Физический доступ | C16: ='Управление ИБ'!D55 -> 5 | D16: ='Управление ИБ'!E55 -> 4.64 | E16: ='Управление ИБ'!F55 -> 4.32 | F16: 0 | G16: 0 | H16: 0 | I16: 0 | J16: 0 | K16: ='Управление ИБ'!J55 -> #DIV/0! | L16: ='Управление ИБ'!K55 -> 5 | M16: ='Управление ИБ'!L55 -> 0 | N16: =L16-M16 -> 5 | O16: =I16-M16 -> 0 | P16: =1-IF(L16=0,0,IF(($M16-L16)>=0,1,1-(L16-$M16)/L16)) -> 1 | R16: ='Управление ИБ'!P55 -> 0 | S16: ='Управление ИБ'!Q55 -> 0 | T16: ='Управление ИБ'!R55 -> 0
A17: ='Нормативное соответствие'!B1 -> Нормативное соответствие | B17: ='Нормативное соответствие'!B42 -> Персональные данные | C17: ='Нормативное соответствие'!D42 -> 5 | D17: ='Нормативное соответствие'!E42 -> 5 | E17: ='Нормативное соответствие'!F42 -> 5 | F17: 0 | G17: 0 | H17: 0 | I17: 0 | J17: 0 | K17: ='Нормативное соответствие'!J42 -> #DIV/0! | L17: ='Нормативное соответствие'!K42 -> 5 | M17: ='Нормативное соответствие'!L42 -> 0 | N17: =L17-M17 -> 5 | O17: =I17-M17 -> 0 | P17: =1-IF(L17=0,0,IF(($M17-L17)>=0,1,1-(L17-$M17)/L17)) -> 1 | R17: =IF(C17=0,0,IF(($M17-C17)>=0,1,1-(C17-$M17)/C17)) -> 0 | S17: =IF(D17=0,0,IF(($M17-D17)>=0,1,1-(D17-$M17)/D17)) -> 0 | T17: =IF(E17=0,0,IF(($M17-E17)>=0,1,1-(E17-$M17)/E17)) -> 0
B18: СКЗИ (ГОСТ) | C18: ='Нормативное соответствие'!D45 -> 5 | D18: ='Нормативное соответствие'!E45 -> 5 | E18: ='Нормативное соответствие'!F45 -> 5 | F18: 0 | G18: 0 | H18: 0 | I18: 0 | J18: 0 | K18: ='Нормативное соответствие'!J45 -> #DIV/0! | L18: ='Нормативное соответствие'!K45 -> 5 | M18: ='Нормативное соответствие'!L45 -> 0 | N18: =L18-M18 -> 5 | O18: =I18-M18 -> 0 | P18: =1-IF(L18=0,0,IF(($M18-L18)>=0,1,1-(L18-$M18)/L18)) -> 1 | R18: =IF(C18=0,0,IF(($M18-C18)>=0,1,1-(C18-$M18)/C18)) -> 0 | S18: =IF(D18=0,0,IF(($M18-D18)>=0,1,1-(D18-$M18)/D18)) -> 0 | T18: =IF(E18=0,0,IF(($M18-E18)>=0,1,1-(E18-$M18)/E18)) -> 0
B19: ='Нормативное соответствие'!B43 -> КИИ | C19: ='Нормативное соответствие'!D43 -> 5 | D19: ='Нормативное соответствие'!E43 -> 5 | E19: ='Нормативное соответствие'!F43 -> 2.88 | F19: 0 | G19: 0 | H19: 0 | I19: 0 | J19: 0 | K19: ='Нормативное соответствие'!J43 -> #DIV/0! | L19: ='Нормативное соответствие'!K43 -> 5 | M19: ='Нормативное соответствие'!L43 -> 0 | N19: =L19-M19 -> 5 | O19: =I19-M19 -> 0 | P19: =1-IF(L19=0,0,IF(($M19-L19)>=0,1,1-(L19-$M19)/L19)) -> 1 | R19: =IF(C19=0,0,IF(($M19-C19)>=0,1,1-(C19-$M19)/C19)) -> 0 | S19: =IF(D19=0,0,IF(($M19-D19)>=0,1,1-(D19-$M19)/D19)) -> 0 | T19: =IF(E19=0,0,IF(($M19-E19)>=0,1,1-(E19-$M19)/E19)) -> 0
B20: ='Нормативное соответствие'!B46 -> 250 указ | C20: ='Нормативное соответствие'!D46 -> 5 | D20: ='Нормативное соответствие'!E46 -> 5 | E20: ='Нормативное соответствие'!F46 -> 5 | F20: 0 | G20: 0 | H20: 0 | I20: 0 | J20: 0 | K20: ='Нормативное соответствие'!J46 -> #DIV/0! | L20: ='Нормативное соответствие'!K46 -> 5 | M20: ='Нормативное соответствие'!L46 -> 0 | N20: =L20-M20 -> 5 | O20: =I20-M20 -> 0 | P20: =1-IF(L20=0,0,IF(($M20-L20)>=0,1,1-(L20-$M20)/L20)) -> 1 | R20: =IF(C20=0,0,IF(($M20-C20)>=0,1,1-(C20-$M20)/C20)) -> 0 | S20: =IF(D20=0,0,IF(($M20-D20)>=0,1,1-(D20-$M20)/D20)) -> 0 | T20: =IF(E20=0,0,IF(($M20-E20)>=0,1,1-(E20-$M20)/E20)) -> 0
B21: ='Управление ИБ'!B44 -> Управление рисками в цепочке поставок | C21: ='Управление ИБ'!D44 -> 5 | D21: ='Управление ИБ'!E44 -> 3.8 | E21: ='Управление ИБ'!F44 -> 2.7333333 | F21: 0 | G21: 0 | H21: 0 | I21: 0 | J21: 0 | K21: ='Управление ИБ'!J44 -> #DIV/0! | L21: ='Управление ИБ'!K44 -> 5 | M21: ='Управление ИБ'!L44 -> 0 | N21: =L21-M21 -> 5 | O21: =I21-M21 -> 0 | P21: =1-IF(L21=0,0,IF(($M21-L21)>=0,1,1-(L21-$M21)/L21)) -> 1 | R21: ='Управление ИБ'!P44 -> 0 | S21: ='Управление ИБ'!Q44 -> 0 | T21: ='Управление ИБ'!R44 -> 0
B22: ='Нормативное соответствие'!B44 -> Коммерческая тайна | C22: ='Нормативное соответствие'!D44 -> 5 | D22: ='Нормативное соответствие'!E44 -> 5 | E22: ='Нормативное соответствие'!F44 -> 5 | F22: 0 | G22: 0 | H22: 0 | I22: 0 | J22: 0 | K22: ='Нормативное соответствие'!J44 -> #DIV/0! | L22: ='Нормативное соответствие'!K44 -> 5 | M22: ='Нормативное соответствие'!L44 -> 0 | N22: =L22-M22 -> 5 | O22: =I22-M22 -> 0 | P22: =1-IF(L22=0,0,IF(($M22-L22)>=0,1,1-(L22-$M22)/L22)) -> 1 | R22: =IF(C22=0,0,IF(($M22-C22)>=0,1,1-(C22-$M22)/C22)) -> 0 | S22: =IF(D22=0,0,IF(($M22-D22)>=0,1,1-(D22-$M22)/D22)) -> 0 | T22: =IF(E22=0,0,IF(($M22-E22)>=0,1,1-(E22-$M22)/E22)) -> 0
A23: СЗИ | B23: =СЗИ!B29 -> Защита от ВПО | C23: =СЗИ!D29 -> 4.59375 | D23: =СЗИ!E29 -> 4.1875 | E23: =СЗИ!F29 -> 3.04375 | F23: 0 | G23: 0 | H23: 0 | I23: 0 | J23: 0 | K23: =СЗИ!J29 -> #DIV/0! | L23: =СЗИ!K29 -> 4.59375 | M23: =СЗИ!L29 -> 0 | N23: =L23-M23 -> 4.59375 | O23: =I23-M23 -> 0 | P23: =1-IF(L23=0,0,IF(($M23-L23)>=0,1,1-(L23-$M23)/L23)) -> 1 | R23: =СЗИ!P29 -> 0 | S23: =СЗИ!Q29 -> 0 | T23: =СЗИ!R29 -> 0
B24: 2FA | C24: =СЗИ!D30 -> 5 | D24: =СЗИ!E30 -> 5 | E24: =СЗИ!F30 -> 5 | F24: 0 | G24: 0 | H24: 0 | I24: 0 | J24: 0 | K24: =СЗИ!J30 -> 0 | L24: =СЗИ!K30 -> 5 | M24: =СЗИ!L30 -> 0 | N24: =L24-M24 -> 5 | O24: =I24-M24 -> 0 | P24: =1-IF(L24=0,0,IF(($M24-L24)>=0,1,1-(L24-$M24)/L24)) -> 1 | R24: =СЗИ!P30 -> 0 | S24: =СЗИ!Q30 -> 0 | T24: =СЗИ!R30 -> 0
B25: CPT | C25: =СЗИ!D31 -> 4.6666667 | D25: =СЗИ!E31 -> 4.3333333 | E25: =СЗИ!F31 -> 3.6666667 | F25: 0 | G25: 0 | H25: 0 | I25: 0 | J25: 0 | K25: =СЗИ!J31 -> 0 | L25: =СЗИ!K31 -> 4.6666667 | M25: =СЗИ!L31 -> 0 | N25: =L25-M25 -> 4.6666667 | O25: =I25-M25 -> 0 | P25: =1-IF(L25=0,0,IF(($M25-L25)>=0,1,1-(L25-$M25)/L25)) -> 1 | R25: =СЗИ!P31 -> 0 | S25: =СЗИ!Q31 -> 0 | T25: =СЗИ!R31 -> 0
B26: RA VPN | C26: =СЗИ!D32 -> 5 | D26: =СЗИ!E32 -> 5 | E26: =СЗИ!F32 -> 4.55 | F26: 0 | G26: 0 | H26: 0 | I26: 0 | J26: 0 | K26: =СЗИ!J32 -> 0 | L26: =СЗИ!K32 -> 5 | M26: =СЗИ!L32 -> 0 | N26: =L26-M26 -> 5 | O26: =I26-M26 -> 0 | P26: =1-IF(L26=0,0,IF(($M26-L26)>=0,1,1-(L26-$M26)/L26)) -> 1 | R26: =СЗИ!P32 -> 0 | S26: =СЗИ!Q32 -> 0 | T26: =СЗИ!R32 -> 0
B27: СКЗИ (ГОСТ) Site-to-Site | C27: =СЗИ!D33 -> 5 | D27: =СЗИ!E33 -> 5 | E27: =СЗИ!F33 -> 4.4 | F27: 0 | G27: 0 | H27: 0 | I27: 0 | J27: 0 | K27: =СЗИ!J33 -> 0 | L27: =СЗИ!K33 -> 5 | M27: =СЗИ!L33 -> 0 | N27: =L27-M27 -> 5 | O27: =I27-M27 -> 0 | P27: =1-IF(L27=0,0,IF(($M27-L27)>=0,1,1-(L27-$M27)/L27)) -> 1 | R27: =СЗИ!P33 -> 0 | S27: =СЗИ!Q33 -> 0 | T27: =СЗИ!R33 -> 0
B28: =Мониторинг!B39 -> SIEM (внедрение системы как СЗИ) | C28: =СЗИ!D34 -> 4.9038462 | D28: =СЗИ!E34 -> 3.5230769 | E28: =СЗИ!F34 -> 0 | F28: 0 | G28: 0 | H28: 0 | I28: 0 | J28: 0 | K28: =СЗИ!J34 -> #DIV/0! | L28: =СЗИ!K34 -> 4.9038462 | M28: =СЗИ!L34 -> 0 | N28: =L28-M28 -> 4.9038462 | O28: =I28-M28 -> 0 | P28: =1-IF(L28=0,0,IF(($M28-L28)>=0,1,1-(L28-$M28)/L28)) -> 1 | R28: =СЗИ!P34 -> 0 | S28: =СЗИ!Q34 -> 0
B29: МСЭ\NGFW | C29: =СЗИ!D35 -> 5 | D29: =СЗИ!E35 -> 4.1 | E29: =СЗИ!F35 -> 0 | F29: 0 | G29: 0 | H29: 0 | I29: 0 | J29: 0 | K29: =СЗИ!J35 -> #DIV/0! | L29: =СЗИ!K35 -> 5 | M29: =СЗИ!L35 -> 0 | N29: =L29-M29 -> 5 | O29: =I29-M29 -> 0 | P29: =1-IF(L29=0,0,IF(($M29-L29)>=0,1,1-(L29-$M29)/L29)) -> 1 | R29: =СЗИ!P35 -> 0 | S29: =СЗИ!Q35 -> 0
B30: Прокси-сервер | C30: =СЗИ!D36 -> 5 | D30: =СЗИ!E36 -> 3.025 | E30: =СЗИ!F36 -> 0 | F30: 0 | G30: 0 | H30: 0 | I30: 0 | J30: 0 | K30: =СЗИ!J36 -> #DIV/0! | L30: =СЗИ!K36 -> 5 | M30: =СЗИ!L36 -> 0 | N30: =L30-M30 -> 5 | O30: =I30-M30 -> 0 | P30: =1-IF(L30=0,0,IF(($M30-L30)>=0,1,1-(L30-$M30)/L30)) -> 1 | R30: =СЗИ!P36 -> 0 | S30: =СЗИ!Q36 -> 0
B31: =СЗИ!B37 -> Сканер уязвимостей | C31: =СЗИ!D37 -> 4.6666667 | D31: =СЗИ!E37 -> 3.7333333 | E31: =СЗИ!F37 -> 0 | F31: 0 | G31: 0 | H31: 0 | I31: 0 | J31: 0 | K31: =СЗИ!J37 -> #DIV/0! | L31: =СЗИ!K37 -> 4.6666667 | M31: =СЗИ!L37 -> 0 | N31: =L31-M31 -> 4.6666667 | O31: =I31-M31 -> 0 | P31: =1-IF(L31=0,0,IF(($M31-L31)>=0,1,1-(L31-$M31)/L31)) -> 1 | R31: =СЗИ!P37 -> 0 | S31: =СЗИ!Q37 -> 0
B32: Anti-DDoS | C32: =СЗИ!D38 -> 5 | D32: =СЗИ!E38 -> 3.8 | E32: =СЗИ!F38 -> 0 | F32: 0 | G32: 0 | H32: 0 | I32: 0 | J32: 0 | K32: =СЗИ!J38 -> #DIV/0! | L32: =СЗИ!K38 -> 5 | M32: =СЗИ!L38 -> 0 | N32: =L32-M32 -> 5 | O32: =I32-M32 -> 0 | P32: =1-IF(L32=0,0,IF(($M32-L32)>=0,1,1-(L32-$M32)/L32)) -> 1 | R32: =СЗИ!P38 -> 0 | S32: =СЗИ!Q38 -> 0
B33: AntiSPAM | C33: =СЗИ!D39 -> 5 | D33: =СЗИ!E39 -> 5 | E33: =СЗИ!F39 -> 0 | F33: 0 | G33: 0 | H33: 0 | I33: 0 | J33: 0 | K33: =СЗИ!J39 -> #DIV/0! | L33: =СЗИ!K39 -> 5 | M33: =СЗИ!L39 -> 0 | N33: =L33-M33 -> 5 | O33: =I33-M33 -> 0 | P33: =1-IF(L33=0,0,IF(($M33-L33)>=0,1,1-(L33-$M33)/L33)) -> 1 | R33: =СЗИ!P39 -> 0 | S33: =СЗИ!Q39 -> 0
B34: WAF | C34: =СЗИ!D40 -> 5 | D34: =СЗИ!E40 -> 0 | E34: =СЗИ!F40 -> 0 | F34: 0 | G34: 0 | H34: 0 | I34: 0 | J34: 0 | K34: =СЗИ!J40 -> #DIV/0! | L34: =СЗИ!K40 -> 5 | M34: =СЗИ!L40 -> 0 | N34: =L34-M34 -> 5 | O34: =I34-M34 -> 0 | P34: =1-IF(L34=0,0,IF(($M34-L34)>=0,1,1-(L34-$M34)/L34)) -> 1 | R34: =СЗИ!P40 -> 0
B35: PAM | C35: =СЗИ!D41 -> 5 | D35: =СЗИ!E41 -> 0 | E35: =СЗИ!F41 -> 0 | F35: 0 | G35: 0 | H35: 0 | I35: 0 | J35: 0 | K35: =СЗИ!J41 -> 0 | L35: =СЗИ!K41 -> 5 | M35: =СЗИ!L41 -> 0 | N35: =L35-M35 -> 5 | O35: =I35-M35 -> 0 | P35: =1-IF(L35=0,0,IF(($M35-L35)>=0,1,1-(L35-$M35)/L35)) -> 1 | R35: =СЗИ!P41 -> 0
B36: DLP | C36: =СЗИ!D42 -> 4.8571429 | D36: =СЗИ!E42 -> 0 | E36: =СЗИ!F42 -> 0 | F36: 0 | G36: 0 | H36: 0 | I36: 0 | J36: 0 | K36: =СЗИ!J42 -> 0 | L36: =СЗИ!K42 -> 4.8571429 | M36: =СЗИ!L42 -> 0 | N36: =L36-M36 -> 4.8571429 | O36: =I36-M36 -> 0 | P36: =1-IF(L36=0,0,IF(($M36-L36)>=0,1,1-(L36-$M36)/L36)) -> 1 | R36: =СЗИ!P42 -> 0
B37: Аномалии и хранение событий | C37: =Мониторинг!D38 -> 5 | D37: =Мониторинг!E38 -> 5 | E37: =Мониторинг!F38 -> 0 | F37: 0 | G37: 0 | H37: 0 | I37: 0 | J37: 0 | K37: =Мониторинг!J38 -> #DIV/0! | L37: =Мониторинг!K38 -> 5 | M37: =Мониторинг!L38 -> 0 | N37: =L37-M37 -> 5 | O37: =I37-M37 -> 0 | P37: =1-IF(L37=0,0,IF(($M37-L37)>=0,1,1-(L37-$M37)/L37)) -> 1 | R37: =IF(C37=0,0,IF(($M37-C37)>=0,1,1-(C37-$M37)/C37)) -> 0 | S37: =IF(D37=0,0,IF(($M37-D37)>=0,1,1-(D37-$M37)/D37)) -> 0
B38: =Мониторинг!B40 -> Мониторинг - Процессы | C38: =Мониторинг!D40 -> 4 | D38: =Мониторинг!E40 -> 2.6 | E38: =Мониторинг!F40 -> 0 | F38: 0 | G38: 0 | H38: 0 | I38: 0 | J38: 0 | K38: =Мониторинг!J40 -> #DIV/0! | L38: =Мониторинг!K40 -> 4 | M38: =Мониторинг!L40 -> 0 | N38: =L38-M38 -> 4 | O38: =I38-M38 -> 0 | P38: =1-IF(L38=0,0,IF(($M38-L38)>=0,1,1-(L38-$M38)/L38)) -> 1 | R38: =IF(C38=0,0,IF(($M38-C38)>=0,1,1-(C38-$M38)/C38)) -> 0 | S38: =IF(D38=0,0,IF(($M38-D38)>=0,1,1-(D38-$M38)/D38)) -> 0
A39: Реагирование | B39: =Реагирование!B30 -> Планирование реагирования | C39: =Реагирование!D30 -> 4.5 | D39: =Реагирование!E30 -> 3.1 | E39: =Реагирование!F30 -> 0.5 | F39: 0 | G39: 0 | H39: 0 | I39: 0 | J39: 0 | K39: =Реагирование!J30 -> #DIV/0! | L39: =Реагирование!K30 -> 4.5 | M39: =Реагирование!L30 -> 0 | N39: =L39-M39 -> 4.5 | O39: =I39-M39 -> 0 | P39: =1-IF(L39=0,0,IF(($M39-L39)>=0,1,1-(L39-$M39)/L39)) -> 1 | R39: =IF(C39=0,0,IF(($M39-C39)>=0,1,1-(C39-$M39)/C39)) -> 0 | S39: =IF(D39=0,0,IF(($M39-D39)>=0,1,1-(D39-$M39)/D39)) -> 0 | T39: =IF(E39=0,0,IF(($M39-E39)>=0,1,1-(E39-$M39)/E39)) -> 0
B40: =Реагирование!B31 -> Коммуникации (реагирование на инциденты) | C40: =Реагирование!D31 -> 5 | D40: =Реагирование!E31 -> 3.2 | E40: =Реагирование!F31 -> 0.64 | F40: 0 | G40: 0 | H40: 0 | I40: 0 | J40: 0 | K40: =Реагирование!J31 -> #DIV/0! | L40: =Реагирование!K31 -> 5 | M40: =Реагирование!L31 -> 0 | N40: =L40-M40 -> 5 | O40: =I40-M40 -> 0 | P40: =1-IF(L40=0,0,IF(($M40-L40)>=0,1,1-(L40-$M40)/L40)) -> 1 | R40: =IF(C40=0,0,IF(($M40-C40)>=0,1,1-(C40-$M40)/C40)) -> 0 | S40: =IF(D40=0,0,IF(($M40-D40)>=0,1,1-(D40-$M40)/D40)) -> 0 | T40: =IF(E40=0,0,IF(($M40-E40)>=0,1,1-(E40-$M40)/E40)) -> 0
B41: =Реагирование!B33 -> Плейбуки по реагированию | C41: =Реагирование!D33 -> 5 | D41: =Реагирование!E33 -> 3.6363636 | E41: =Реагирование!F33 -> 1.8181818 | F41: 0 | G41: 0 | H41: 0 | I41: 0 | J41: 0 | K41: =Реагирование!J33 -> #DIV/0! | L41: =Реагирование!K33 -> 5 | M41: =Реагирование!L33 -> 0 | N41: =L41-M41 -> 5 | O41: =I41-M41 -> 0 | P41: =1-IF(L41=0,0,IF(($M41-L41)>=0,1,1-(L41-$M41)/L41)) -> 1 | R41: =IF(C41=0,0,IF(($M41-C41)>=0,1,1-(C41-$M41)/C41)) -> 0 | S41: =IF(D41=0,0,IF(($M41-D41)>=0,1,1-(D41-$M41)/D41)) -> 0 | T41: =IF(E41=0,0,IF(($M41-E41)>=0,1,1-(E41-$M41)/E41)) -> 0
B42: =Реагирование!B32 -> Анализ и расследование | C42: =Реагирование!D32 -> 4.6 | D42: =Реагирование!E32 -> 3.84 | E42: =Реагирование!F32 -> 1.04 | F42: 0 | G42: 0 | H42: 0 | I42: 0 | J42: 0 | K42: =Реагирование!J32 -> #DIV/0! | L42: =Реагирование!K32 -> 4.6 | M42: =Реагирование!L32 -> 0 | N42: =L42-M42 -> 4.6 | O42: =I42-M42 -> 0 | P42: =1-IF(L42=0,0,IF(($M42-L42)>=0,1,1-(L42-$M42)/L42)) -> 1 | R42: =IF(C42=0,0,IF(($M42-C42)>=0,1,1-(C42-$M42)/C42)) -> 0 | S42: =IF(D42=0,0,IF(($M42-D42)>=0,1,1-(D42-$M42)/D42)) -> 0 | T42: =IF(E42=0,0,IF(($M42-E42)>=0,1,1-(E42-$M42)/E42)) -> 0
A43: Восстановление | B43: =Восстановление!B31 -> Планирование восстановления | C43: =Восстановление!D27 -> 5 | D43: =Восстановление!E27 -> 3.6 | E43: =Восстановление!F27 -> 1.0666667 | F43: 0 | G43: 0 | H43: 0 | I43: 0 | J43: 0 | K43: =Восстановление!J27 -> #DIV/0! | L43: =Восстановление!K27 -> 5 | M43: =Восстановление!L27 -> 0 | N43: =L43-M43 -> 5 | O43: =I43-M43 -> 0 | P43: =1-IF(L43=0,0,IF(($M43-L43)>=0,1,1-(L43-$M43)/L43)) -> 1 | R43: =IF(C43=0,0,IF(($M43-C43)>=0,1,1-(C43-$M43)/C43)) -> 0 | S43: =IF(D43=0,0,IF(($M43-D43)>=0,1,1-(D43-$M43)/D43)) -> 0 | T43: =IF(E43=0,0,IF(($M43-E43)>=0,1,1-(E43-$M43)/E43)) -> 0
B44: =Восстановление!B41 -> Восстановление - Коммуникации | C44: =Восстановление!D28 -> 5 | D44: =Восстановление!E28 -> 1.6 | E44: =Восстановление!F28 -> 0 | F44: 0 | G44: 0 | H44: 0 | I44: 0 | J44: 0 | K44: =Восстановление!J28 -> #DIV/0! | L44: =Восстановление!K28 -> 5 | M44: =Восстановление!L28 -> 0 | N44: =L44-M44 -> 5 | O44: =I44-M44 -> 0 | P44: =1-IF(L44=0,0,IF(($M44-L44)>=0,1,1-(L44-$M44)/L44)) -> 1 | R44: =IF(C44=0,0,IF(($M44-C44)>=0,1,1-(C44-$M44)/C44)) -> 0 | S44: =IF(D44=0,0,IF(($M44-D44)>=0,1,1-(D44-$M44)/D44)) -> 0
R45: =SUM(Расчет!R23:R36)/COUNTA(Расчет!R23:R36) -> 0 | S45: =SUM(Расчет!S23:S33)/COUNTA(Расчет!S23:S33) -> 0 | T45: =SUM(Расчет!T23:T27)/COUNTA(Расчет!T23:T27) -> 0 | U45: Реализация технических мер
R46: =SUM(R4:R13,R15,R16,R38:R44)/COUNTA(R4:R13,R15,R16,R38:R44) -> 0 | S46: =SUM(S4:S13,S15,S16,S38:S44)/COUNTA(S4:S13,S15,S16,S38:S44) -> 0 | T46: =SUM(T4:T10,T12,T13,T15,T16,T39:T43)/COUNTA(T4:T10,T12,T13,T15,T16,T39:T43) -> 0 | U46: Организационные меры
R47: =SUM(R17:R22)/COUNTA(R17:R22) -> 0 | S47: =SUM(S17:S22)/COUNTA(S17:S22) -> 0 | T47: =SUM(T17:T22)/COUNTA(T17:T22) -> 0 | U47: Нормативное соответствие
R49: =SUM(R28,R37,R38:R42)/COUNTA(R28,R37,R38:R42) -> 0 | S49: =SUM(S28,S37,S38:S42)/COUNTA(S28,S37,S38:S42) -> 0 | T49: =SUM(T39:T42)/COUNTA(T39:T42) -> 0 | U49: Мониторинг и реагирование
R50: =R15 -> 0 | S50: =S15 -> 0 | T50: =T15 -> 0 | U50: Безопасная разработка
C53: КБ3 | D53: КБ2 | E53: КБ1 | F53: Исторические данные | J53: Расчетные данные на 31.12.2025 | L53: =L1 -> Расчетные данные на | M53: Текущий показатель
B54: Дата заполнения | F54: 45017 | G54: 45291 | J54: 46022 | L54: 46022 | M54: =TODAY() -> 46038
A55: ='Управление ИБ'!B1 -> Система управления ИБ | C55: =AVERAGE(C4:C16) -> 4.8216484 | D55: =AVERAGE(D4:D16) -> 3.6115951 | E55: =AVERAGE(E4:E16) -> 1.8860628 | L55: =AVERAGE(L4:L16) -> 4.8216484 | M55: =AVERAGE(M4:M16) -> 0
A56: Нормативное соответствие | C56: =AVERAGE(C17:C22) -> 5 | D56: =AVERAGE(D17:D22) -> 4.8 | E56: =AVERAGE(E17:E22) -> 4.2688889 | L56: =AVERAGE(L17:L22) -> 5 | M56: =AVERAGE(M17:M22) -> 0
A57: СЗИ | C57: =AVERAGE(C23:C36) -> 4.9062909 | D57: =AVERAGE(D23:D36) -> 3.3358745 | E57: =AVERAGE(E23:E36) -> 1.475744 | L57: =AVERAGE(L23:L36) -> 4.9062909 | M57: =AVERAGE(M23:M36) -> 0
A58: Мониторинг | C58: =AVERAGE(C37:C38) -> 4.5 | D58: =AVERAGE(D37:D38) -> 3.8 | E58: =AVERAGE(E37:E38) -> 0 | L58: =AVERAGE(L37:L38) -> 4.5 | M58: =AVERAGE(M37:M38) -> 0
A59: Реагирование | C59: =AVERAGE(C39:C42) -> 4.775 | D59: =AVERAGE(D39:D42) -> 3.4440909 | E59: =AVERAGE(E39:E42) -> 0.99954545 | L59: =AVERAGE(L39:L42) -> 4.775 | M59: =AVERAGE(M39:M42) -> 0
A60: Восстановление | C60: =AVERAGE(C43:C44) -> 5 | D60: =AVERAGE(D43:D44) -> 2.6 | E60: =AVERAGE(E43:E44) -> 0.53333333 | L60: =AVERAGE(L43:L44) -> 5 | M60: =AVERAGE(M43:M44) -> 0

Sheet Программа
A1: ПЛАН ОБЕСПЕЧЕНИЯ И РАЗВИТИЯ ИБ ООО "РОМАШКА" НА 2026 г.
A2: СОГЛАСОВАНО: | S2: УТВЕРЖДЕНО:
A3: Вице-Президент по развитию и обеспечению информационной безопасности ПАО "Ростелеком" | O3: Рекомендации по заполнению (удалить при печати): 1. Столбец "Индикатор (статус выполнения)" используем для формирования программы, используя фильтр: цвет ячейки - Красный; 2. Столбец "Мероприятия ДЗО" предназначен для формирования мероприятий применимых к конкретному ДЗО, с учетом специфики и достаточным уровнем детализации, сформированных в соответствии с рекомендациями Блока ИБ (столбец - "Рекомендации ПАО"); 3. Столбец "Доп .ФОТ (руб.)" не требуется разбивать по каждой статье (мероприятию), достаточно указать в одном мероприятии полную стоимость затрат на ФОТ. | S3: Генеральный директор ООО "Ромашка"
A4: Чугунов А.В. | W4: Иванов И.И.
A5: (ФИО) | D5: (Подпись) | S5: (Подпись) | W5: (ФИО)
A6: 13.11.2025 г. | W6: 13.11.2025 г.
A7: (Дата) | W7: (Дата)
A8: Тематика | B8: Домен | C8: Наименование показателя | D8: Сокращенное наименование | E8: КБ3 | F8: КБ2 | G8: КБ1 | H8: Приоритет | I8: Уровень КБ | L8: =SUBTOTAL(3,L10:L9523) -> 76 | N8: ="Всего: " & SUBTOTAL(3,N10:N9523) -> Всего: 76 | O8: ="Всего: " & SUBTOTAL(3,O10:O9523) -> Всего: 76 | P8: ="Всего: " & SUBTOTAL(3,P10:P9523) -> Всего: 76 | Q8: ="Всего: " & SUBTOTAL(3,Q10:Q9523) -> Всего: 76 | R8: ="Всего: " & SUBTOTAL(3,R10:R9523) -> Всего: 0 | S8: Плановый срок выполнения | T8: Статус | U8: =SUBTOTAL(9,U10:U453) -> 0 | V8: =SUBTOTAL(9,V10:V453) -> 0 | W8: =SUBTOTAL(9,W10:W453) -> 0 | X8: =SUBTOTAL(9,X10:X453) -> 0
J9: Расчетный показатель 2025 | K9: Начальный показатель (на 01.25) | L9: Текущий показатель | M9: Динамика | N9: Индикатор (статус выполнения) | O9: Рекомендации ПАО | P9: Мероприятия ДЗО | Q9: Артефакты достижения | R9: Методика проверки | U9: CAPEX (руб.) | V9: OPEX (руб.) | W9: Доп. ФОТ (руб.) | X9: Итог (руб.)
A10: Восстановление | B10: Планирование восстановления | C10: =Восстановление!B36 -> Выполняется регулярное создание резервных копий в соответствии с регламентом | D10: =Восстановление!C36 -> ВССТ.ПЛН.5 | E10: =Восстановление!D36 -> 5 | F10: =Восстановление!E36 -> 3.2 | G10: =Восстановление!F36 -> 3.2 | H10: =Восстановление!S36 -> 22.05 | I10: =IF(H10<=200,"КБ1",IF(H10<=300,"КБ2","КБ3")) -> КБ1 | J10: =Восстановление!K36 -> 5 | K10: =Восстановление!I36 -> 0 | L10: =Восстановление!L36 -> 0 | M10: =IF(K10=J10," ",L10-K10) -> 0 | N10: =IF(H10<100,IF(L10>=G10,0,J10-L10),IF(H10<300,IF(L10>=F10,0,J10-L10),IF(L10>=E10,0,J10-L10))) -> 5 | O10: =Восстановление!T36 -> - Обеспечить регулярное создание резервных копий | P10: Заполнить | Q10: Выгрузка конфигураций ПО для резервного копирования/ скрипты - Снимки экрана мест хранения резервных копий - Скан-копия договора о предоставлении услуги резервного копирования / Электронная версия договора с реквизитами ЭП | T10: Не готово | U10: 0 | V10: 0 | W10: 0 | X10: =SUM(U10:W10) -> 0
A11: Восстановление | B11: Планирование восстановления | C11: =Восстановление!B37 -> Резервные копии хранятся на сторонних площадках | D11: =Восстановление!C37 -> ВССТ.ПЛН.6 | E11: =Восстановление!D37 -> 5 | F11: =Восстановление!E37 -> 3.2 | G11: =Восстановление!F37 -> 1.6 | H11: =Восстановление!S37 -> 22.06 | I11: =IF(H11<=200,"КБ1",IF(H11<=300,"КБ2","КБ3")) -> КБ1 | J11: =Восстановление!K37 -> 5 | K11: =Восстановление!I37 -> 0 | L11: =Восстановление!L37 -> 0 | M11: =IF(K11=J11," ",L11-K11) -> 0 | N11: =IF(H11<100,IF(L11>=G11,0,J11-L11),IF(H11<300,IF(L11>=F11,0,J11-L11),IF(L11>=E11,0,J11-L11))) -> 5 | O11: =Восстановление!T37 -> - Обеспечить хранение резервных копий вне площадки расположения ИА | P11: Заполнить | Q11: Выгрузка конфигураций ПО для резервного копирования/ скрипты - Снимки экрана мест хранения резервных копий - Скан-копия договора о предоставлении услуги резервного копирования / Электронная версия договора с реквизитами ЭП | T11: Не готово | U11: 0 | V11: 0 | W11: 0 | X11: =SUM(U11:W11) -> 0
A12: Восстановление | B12: Планирование восстановления | C12: =Восстановление!B38 -> Определены требования восстановления и проводятся тестирования | D12: =Восстановление!C38 -> ВССТ.ПЛН.7 | E12: =Восстановление!D38 -> 5 | F12: =Восстановление!E38 -> 3.2 | G12: =Восстановление!F38 -> 1.6 | H12: =Восстановление!S38 -> 22.07 | I12: =IF(H12<=200,"КБ1",IF(H12<=300,"КБ2","КБ3")) -> КБ1 | J12: =Восстановление!K38 -> 5 | K12: =Восстановление!I38 -> 0 | L12: =Восстановление!L38 -> 0 | M12: =IF(K12=J12," ",L12-K12) -> 0 | N12: =IF(H12<100,IF(L12>=G12,0,J12-L12),IF(H12<300,IF(L12>=F12,0,J12-L12),IF(L12>=E12,0,J12-L12))) -> 5 | O12: =Восстановление!T38 -> -Разработать и протестировать планы восстановления | P12: Заполнить | Q12: 1. Формализованный план восстановления 2.Отчет о проведенном тестировании | T12: Не готово | U12: 0 | V12: 0 | W12: 0 | X12: =SUM(U12:W12) -> 0
A13: Восстановление | B13: Планирование восстановления | C13: =Восстановление!B39 -> Тестирование планов по реагированию и восстановлению проводятся совместно с поставщиками и сторонними провайдерами (имеющими доступ в инфраструктуру Общества) | D13: =Восстановление!C39 -> ВССТ.ПЛН.8 | E13: =Восстановление!D39 -> 5 | F13: =Восстановление!E39 -> 3.2 | G13: =Восстановление!F39 -> 1.6 | H13: =Восстановление!S39 -> 22.08 | I13: =IF(H13<=200,"КБ1",IF(H13<=300,"КБ2","КБ3")) -> КБ1 | J13: =Восстановление!K39 -> 5 | K13: =Восстановление!I39 -> 0 | L13: =Восстановление!L39 -> 0 | M13: =IF(K13=J13," ",L13-K13) -> 0 | N13: =IF(H13<100,IF(L13>=G13,0,J13-L13),IF(H13<300,IF(L13>=F13,0,J13-L13),IF(L13>=E13,0,J13-L13))) -> 5 | O13: =Восстановление!T39 -> - Включить в договоры обязательства поставщика содействовать при проведении восстановительных мероприятий/ Определить SLA; - Определить ответственных за взаимодействие и их полномочия. | P13: Заполнить | Q13: 1. Формализованные требования к договорам с поставщиками услуг | T13: Не готово | U13: 0 | V13: 0 | W13: 0 | X13: 0
A14: Восстановление | B14: Планирование восстановления | C14: =Восстановление!B40 -> Планы восстановления совершенствуются по результатам тестирования и реагирования | D14: =Восстановление!C40 -> ВССТ.ПЛН.9 | E14: =Восстановление!D40 -> 5 | F14: =Восстановление!E40 -> 3.2 | G14: =Восстановление!F40 -> 1.6 | H14: =Восстановление!S40 -> 22.09 | I14: =IF(H14<=200,"КБ1",IF(H14<=300,"КБ2","КБ3")) -> КБ1 | J14: =Восстановление!K40 -> 5 | K14: =Восстановление!I40 -> 0 | L14: =Восстановление!L40 -> 0 | M14: =IF(K14=J14," ",L14-K14) -> 0 | N14: =IF(H14<100,IF(L14>=G14,0,J14-L14),IF(H14<300,IF(L14>=F14,0,J14-L14),IF(L14>=E14,0,J14-L14))) -> 5 | O14: =Восстановление!T40 -> - Проводить анализ результатов тестирования планов восстановления. Фиксировать отклонения от планов. | P14: Заполнить | Q14: 1. Справки/аналитические записки, материалы/служебные записки | T14: Не готово | U14: 0 | V14: 0 | W14: 0 | X14: =SUM(U14:W14) -> 0
A15: Нормативное соответствие | B15: 250 Указ | C15: ='250'!B53 -> Подготовлено и утверждено положение о заместителе, ответственном за обеспечение ИБ, в соответствии с требованиями Постановления Правительства РФ от 15.07.2022 № 1272 | D15: ='250'!C53 -> НС.250.ОУ.2 | E15: ='250'!D53 -> 5 | F15: ='250'!E53 -> 5 | G15: ='250'!F53 -> 5 | H15: ='Нормативное соответствие'!S111 -> 9.01 | I15: =IF(H15<=200, "КБ1", IF(H15<=300, "КБ2", "КБ3")) -> КБ1 | J15: ='250'!K53 -> 5 | K15: ='250'!I53 -> 0 | L15: ='250'!L53 -> 0 | M15: =IF(K15=J15," ",L15-K15) -> 0 | N15: =IF(H15<100, IF(L15>=G15,0,J15-L15), IF(H15<300, IF(L15>=F15,0,J15-L15), IF(L15>=E15,0,J15-L15))) -> 5 | O15: ='250'!S53 -> - Разработать и утвердить положение о заместителе, ответсвенном за обеспечение ИБ - Ознакомить с положением заместителя, ответственного за обеспечение ИБ | P15: Заполнить | Q15: 1. Утвержденное положение о заместителе, ответственном за обеспечение ИБ в соответствии с Постановлением Правительства РФ от 15.07.2022 № 1272 2. Листы ознакомления | T15: Не готово | U15: 0 | V15: 0 | W15: 0 | X15: =SUM(U15:W15) -> 0
A16: Нормативное соответствие | B16: 250 Указ | C16: ='250'!B54 -> Заместитель по ИБ входит в состав коллегиальных органов Общества | D16: ='250'!C54 -> НС.250.ОУ.3 | E16: ='250'!D54 -> 5 | F16: ='250'!E54 -> 5 | G16: ='250'!F54 -> 5 | H16: ='Нормативное соответствие'!S111 -> 9.01 | I16: =IF(H16<=200, "КБ1", IF(H16<=300, "КБ2", "КБ3")) -> КБ1 | J16: ='250'!K54 -> 5 | K16: ='250'!I54 -> 0 | L16: ='250'!L54 -> 0 | M16: =IF(K16=J16," ",L16-K16) -> 0 | N16: =IF(H16<100, IF(L16>=G16,0,J16-L16), IF(H16<300, IF(L16>=F16,0,J16-L16), IF(L16>=E16,0,J16-L16))) -> 5 | O16: ='250'!S54 -> - При наличии коллегиальных органов (правление, совет директоров) возложить полномочия ответственного за обеспечение ИБ на руководителя, входящего в состав указанных коллегиальных органов или включить ответственного за обеспечение ИБ в их состав. | P16: Заполнить | Q16: Предусмотрено в типовом Положении о заместителе руководителя организации, ответственном за обеспечение ИБ в соответствии с Постановлением Правительства РФ от 15.07.2022 № 1272. | T16: Не готово | U16: 0 | V16: 0 | W16: 0 | X16: =SUM(U16:W16) -> 0
A17: Нормативное соответствие | B17: 250 Указ | C17: ='250'!B55 -> Проводится обучение пользователей по ИБ | D17: ='250'!C55 -> НС.250.ОУ.4 | E17: ='250'!D55 -> 5 | F17: ='250'!E55 -> 5 | G17: ='250'!F55 -> 5 | H17: ='Нормативное соответствие'!S111 -> 9.01 | I17: =IF(H17<=200, "КБ1", IF(H17<=300, "КБ2", "КБ3")) -> КБ1 | J17: ='250'!K55 -> 5 | K17: ='250'!I55 -> 0 | L17: ='250'!L55 -> 0 | M17: =IF(K17=J17," ",L17-K17) -> 0 | N17: =IF(H17<100, IF(L17>=G17,0,J17-L17), IF(H17<300, IF(L17>=F17,0,J17-L17), IF(L17>=E17,0,J17-L17))) -> 5 | O17: ='250'!S55 -> - Разработать и утвердить правила и процедуры информирования и обучения персонала; - Переодически проводить обучение персонала правилам эксплуатации отдельных средств защиты информации, включая проведение практических занятий с персоналом; - Проводить контроль осведомленности персонала об угрозах безопасности информации и уровня знаний персонала по вопросам обеспечения ИБ - Актуализировать правила и процедуры информирования и обучения персонала | P17: Заполнить | Q17: 1) Разработанный внутренний нормативный документ: "Положение о повышении осведомленности работников"; 2) Организация рассылок работникам Общества с наиболее актуальной информацией в области информационной безопасности (угрозы информационной безопасности, схемы мошенничества, правила безопасной работы); 3) Организация обучения работников в очной/заочной форме (например, онлайн курсы с последующим тестированием знаний) | T17: Не готово | U17: 0 | V17: 0 | W17: 0 | X17: =SUM(U17:W17) -> 0
A18: Нормативное соответствие | B18: 250 Указ | C18: ='250'!B56 -> Заместитель руководителя Общества имеет необходимое обучение | D18: ='250'!C56 -> НС.250.ОУ.5 | E18: ='250'!D56 -> 5 | F18: ='250'!E56 -> 5 | G18: ='250'!F56 -> 5 | H18: ='Нормативное соответствие'!S111 -> 9.01 | I18: =IF(H18<=200, "КБ1", IF(H18<=300, "КБ2", "КБ3")) -> КБ1 | J18: ='250'!K56 -> 5 | K18: ='250'!I56 -> 0 | L18: ='250'!L56 -> 0 | M18: =IF(K18=J18," ",L18-K18) -> 0 | N18: =IF(H18<100, IF(L18>=G18,0,J18-L18), IF(H18<300, IF(L18>=F18,0,J18-L18), IF(L18>=E18,0,J18-L18))) -> 5 | O18: ='250'!S56 -> - Ответственное лицо должно иметь высшее образование (не ниже уровня специалитета, магистратуры) по направлению обеспечения информационной безопасности (далее – ИБ): ­ 10.0 - 01 «Информационная безопасность»; ­ 10.0 - 01 «Компьютерная безопасность»; ­ 10.0 - 02 «ИБ телекоммуникационных систем»; ­ 10.0 - 03 «ИБ автоматизированных систем»; ­ 10.0 - 04 «Информационно-аналитические системы безопасности»; ­ 10.0 - 05 «Безопасность ИТ в правоохранительных органах». Если ответственное лицо имеет высшее образование по другому направлению подготовки (специальности), то ответственное лицо обязано пройти обучение по программе профессиональной переподготовки по направлению 'Информационная безопасность'. Минимальный срок профессиональной переподготовки — 250 академических часов. | P18: Заполнить | Q18: Скан-копия диплома/свидетельства о переподготовке | T18: Не готово | U18: 0 | V18: 0 | W18: 0 | X18: =SUM(U18:W18) -> 0
A19: Нормативное соответствие | B19: 250 Указ | C19: ='250'!B57 -> Заместитель руководителя Общества проходит регулярное повышение квалификации | D19: ='250'!C57 -> НС.250.ОУ.6 | E19: ='250'!D57 -> 5 | F19: ='250'!E57 -> 5 | G19: ='250'!F57 -> 5 | H19: ='Нормативное соответствие'!S111 -> 9.01 | I19: =IF(H19<=200, "КБ1", IF(H19<=300, "КБ2", "КБ3")) -> КБ1 | J19: ='250'!K57 -> 5 | K19: ='250'!I57 -> 0 | L19: ='250'!L57 -> 0 | M19: =IF(K19=J19," ",L19-K19) -> 0 | N19: =IF(H19<100, IF(L19>=G19,0,J19-L19), IF(H19<300, IF(L19>=F19,0,J19-L19), IF(L19>=E19,0,J19-L19))) -> 5 | O19: ='250'!S57 -> - Ответственное лицо обязано проходит повышение квалификации не менее одного раза в 3 года | P19: Заполнить | Q19: Скан-копии свидетельств о повышении квалификации | T19: Не готово | U19: 0 | V19: 0 | W19: 0 | X19: =SUM(U19:W19) -> 0
A20: Нормативное соответствие | B20: 250 Указ | C20: ='250'!B58 -> Документы по цифровой трансформации и т.п проходят согласование с ИБ | D20: ='250'!C58 -> НС.250.ОУ.7 | E20: ='250'!D58 -> 5 | F20: ='250'!E58 -> 5 | G20: ='250'!F58 -> 5 | H20: ='Нормативное соответствие'!S111 -> 9.01 | I20: =IF(H20<=200, "КБ1", IF(H20<=300, "КБ2", "КБ3")) -> КБ1 | J20: ='250'!K58 -> 5 | K20: ='250'!I58 -> 0 | L20: ='250'!L58 -> 0 | M20: =IF(K20=J20," ",L20-K20) -> 0 | N20: =IF(H20<100, IF(L20>=G20,0,J20-L20), IF(H20<300, IF(L20>=F20,0,J20-L20), IF(L20>=E20,0,J20-L20))) -> 5 | O20: ='250'!S58 -> - Основополагающие документы Общества в сфере ИТ, цифровизации и цифровой трансформации должны быть согласованы с заместителем руководителя, ответственным за обеспечение ИБ | P20: Заполнить | Q20: Скан-копии ВНД и листов согласования/выгрузка и системы ЭД | T20: Не готово | U20: 0 | V20: 0 | W20: 0 | X20: =SUM(U20:W20) -> 0
A21: Нормативное соответствие | B21: 250 Указ | C21: ='250'!B59 -> Проводится регулярное повышение осведомленности | D21: ='250'!C59 -> НС.250.ОУ.8 | E21: ='250'!D59 -> 5 | F21: ='250'!E59 -> 5 | G21: ='250'!F59 -> 5 | H21: ='Нормативное соответствие'!S111 -> 9.01 | I21: =IF(H21<=200, "КБ1", IF(H21<=300, "КБ2", "КБ3")) -> КБ1 | J21: ='250'!K59 -> 5 | K21: ='250'!I59 -> 0 | L21: ='250'!L59 -> 0 | M21: =IF(K21=J21," ",L21-K21) -> 0 | N21: =IF(H21<100, IF(L21>=G21,0,J21-L21), IF(H21<300, IF(L21>=F21,0,J21-L21), IF(L21>=E21,0,J21-L21))) -> 5 | O21: ='250'!S59 -> - Наладить регулярное информирование руководства Общества о компьютерных инцидентах и текущем уровне ИБ в Общества. | P21: Заполнить | Q21: Ежегодный отчёт руководству Общества (в рамках отчёта по ежегодному Плану мероприятий. | T21: Не готово | U21: 0 | V21: 0 | W21: 0 | X21: =SUM(U21:W21) -> 0
A22: Нормативное соответствие | B22: 250 Указ | C22: ='250'!B62 -> Утверждено положение о подразделении, обеспечивающим ИБ в соответствии с требованиями Постановления Правительства РФ от 15.07.2022 № 1272 | D22: ='250'!C62 -> НС.250.ПДР.2 | E22: ='250'!D62 -> 5 | F22: ='250'!E62 -> 5 | G22: ='250'!F62 -> 5 | H22: ='Нормативное соответствие'!S112 -> 9.02 | I22: =IF(H22<=200, "КБ1", IF(H22<=300, "КБ2", "КБ3")) -> КБ1 | J22: ='250'!K62 -> 5 | K22: ='250'!I62 -> 0 | L22: ='250'!L62 -> 0 | M22: =IF(K22=J22," ",L22-K22) -> 0 | N22: =IF(H22<100, IF(L22>=G22,0,J22-L22), IF(H22<300, IF(L22>=F22,0,J22-L22), IF(L22>=E22,0,J22-L22))) -> 5 | O22: ='250'!S62 -> - Разработать и утвердить положение о структурном подразделении, ответсвенном за обеспечение ИБ - Ознакомить с положением подразделение, ответственное за обеспечение ИБ | P22: Заполнить | Q22: Утвержденное положение о структурном подразделении, ответственном за обеспечение ИБ, в соответствии с требованиями ПП от 15.07.2022 № 1272 | T22: Не готово | U22: 0 | V22: 0 | W22: 0 | X22: =SUM(U22:W22) -> 0
A23: Нормативное соответствие | B23: 250 Указ | C23: ='250'!B63 -> Подразделение подчинено заместителю руководителю Общества, ответственному за ИБ | D23: ='250'!C63 -> НС.250.ПДР.3 | E23: ='250'!D63 -> 5 | F23: ='250'!E63 -> 5 | G23: ='250'!F63 -> 5 | H23: ='Нормативное соответствие'!S112 -> 9.02 | I23: =IF(H23<=200, "КБ1", IF(H23<=300, "КБ2", "КБ3")) -> КБ1 | J23: ='250'!K62 -> 5 | K23: ='250'!I63 -> 0 | L23: ='250'!L63 -> 0 | M23: =IF(K23=J23," ",L23-K23) -> 0 | N23: =IF(H23<100, IF(L23>=G23,0,J23-L23), IF(H23<300, IF(L23>=F23,0,J23-L23), IF(L23>=E23,0,J23-L23))) -> 5 | O23: ='250'!S63 -> - Подчинить подразделение, ответственное за обеспечение ИБ, заместителю руководителю Общества, ответственному за ИБ, в соответствии со орг. структурой Общества | P23: Заполнить | Q23: Утвержденное положение о структурном подразделении, ответственном за обеспечение ИБ, в соответствии с требованиями ПП от 15.07.2022 № 1272 | T23: Не готово | U23: 0 | V23: 0 | W23: 0 | X23: =SUM(U23:W23) -> 0
A24: Нормативное соответствие | B24: 250 Указ | C24: ='250'!B65 -> Все привлекаемые к осуществлению мероприятий по ИБ организации имеют лицензии | D24: ='250'!C65 -> НС.250.ПДРД.1 | E24: ='250'!D65 -> 5 | F24: ='250'!E65 -> 5 | G24: ='250'!F65 -> 5 | H24: ='Нормативное соответствие'!S113 -> 9.03 | I24: =IF(H24<=200, "КБ1", IF(H24<=300, "КБ2", "КБ3")) -> КБ1 | J24: ='250'!K65 -> 5 | K24: ='250'!I65 -> 0 | L24: ='250'!L65 -> 0 | M24: =IF(K24=J24," ",L24-K24) -> 0 | N24: =IF(H24<100, IF(L24>=G24,0,J24-L24), IF(H24<300, IF(L24>=F24,0,J24-L24), IF(L24>=E24,0,J24-L24))) -> 5 | O24: ='250'!S65 -> - Привлекать к мероприятиям по ИБ только организации имеющие лицензии ФСТЭК и ФСБ | P24: Заполнить | Q24: Скан-копии договоров с подрядчиками, скан-копии лицензий | T24: Не готово | U24: 0 | V24: 0 | W24: 0 | X24: =SUM(U24:W24) -> 0
A25: Нормативное соответствие | B25: 250 Указ | C25: ='250'!B66 -> Привлекаемый SOC имеет аккредитацию | D25: ='250'!C66 -> НС.250.ПДРД.2 | E25: ='250'!D66 -> 5 | F25: ='250'!E66 -> 5 | G25: ='250'!F66 -> 5 | H25: ='Нормативное соответствие'!S113 -> 9.03 | I25: =IF(H25<=200, "КБ1", IF(H25<=300, "КБ2", "КБ3")) -> КБ1 | J25: ='250'!K66 -> 5 | K25: ='250'!I66 -> 0 | L25: ='250'!L66 -> 0 | M25: =IF(K25=J25," ",L25-K25) -> 0 | N25: =IF(H25<100, IF(L25>=G25,0,J25-L25), IF(H25<300, IF(L25>=F25,0,J25-L25), IF(L25>=E25,0,J25-L25))) -> 5 | O25: ='250'!S66 -> - При заключении договора с SOC убедиться в наличии аккредитации | P25: Заполнить | Q25: Скан-копия договора на предоставление услуг SOC | T25: Не готово | U25: 0 | V25: 0 | W25: 0 | X25: =SUM(U25:W25) -> 0
A26: Нормативное соответствие | B26: 250 Указ | C26: ='250'!B67 -> Привлекаемые для оценки защищенности организации имеют лицензию ФСТЭК | D26: ='250'!C67 -> НС.250.ПДРД.3 | E26: ='250'!D67 -> 5 | F26: ='250'!E67 -> 5 | G26: ='250'!F67 -> 5 | H26: ='Нормативное соответствие'!S113 -> 9.03 | I26: =IF(H26<=200, "КБ1", IF(H26<=300, "КБ2", "КБ3")) -> КБ1 | J26: ='250'!K67 -> 5 | K26: ='250'!I67 -> 0 | L26: ='250'!L67 -> 0 | M26: =IF(K26=J26," ",L26-K26) -> 0 | N26: =IF(H26<100, IF(L26>=G26,0,J26-L26), IF(H26<300, IF(L26>=F26,0,J26-L26), IF(L26>=E26,0,J26-L26))) -> 5 | O26: ='250'!S67 -> - Определить и привлечь организацию для оценки уровня защищенности информационных систем ,имеющих соответствующие лицензии ФСТЭК и ФСБ (https://reestr.fstec.ru/reg1). - Сформировать техническое задание на выполнение работ по оценке уровня защищенности. - Получить отчетные документы в бумажном и в электронном виде от лицензиата по результатам оценки уровня защищенности информационных систем. - На основании распоряжения Правительства РФ от 2 - 0 - 2022 N 1661-р (ред. от 0 - 0 - 2023) 'Об утверждении перечня ключевых органов (организаций), которым необходимо осуществить мероприятия по оценке уровня защищенности своих информационных систем с привлечением организаций, имеющих соответствующие лицензии ФСБ России и ФСТЭК Росси' предоставить отчетные документы по оценке уровня защищенности информационных систем Правительству РФ, а также в адрес ФСТЭК и ФСБ России на основании соответствующего запроса. | P26: Заполнить | Q26: Скан-копия договора с подрядчиком, скан копия лицензии | T26: Не готово | U26: 0 | V26: 0 | W26: 0 | X26: =SUM(U26:W26) -> 0
A27: Нормативное соответствие | B27: 250 Указ | C27: ='250'!B68 -> Привлекаемые для оценки защищенности организации имеют лицензию ФСБ | D27: ='250'!C68 -> НС.250.ПДРД.4 | E27: ='250'!D68 -> 5 | F27: ='250'!E68 -> 5 | G27: ='250'!F68 -> 5 | H27: ='Нормативное соответствие'!S113 -> 9.03 | I27: =IF(H27<=200, "КБ1", IF(H27<=300, "КБ2", "КБ3")) -> КБ1 | J27: ='250'!K68 -> 5 | K27: ='250'!I68 -> 0 | L27: ='250'!L68 -> 0 | M27: =IF(K27=J27," ",L27-K27) -> 0 | N27: =IF(H27<100, IF(L27>=G27,0,J27-L27), IF(H27<300, IF(L27>=F27,0,J27-L27), IF(L27>=E27,0,J27-L27))) -> 5 | O27: ='250'!S68 -> - Определить и привлечь организацию для оценки уровня защищенности информационных систем ,имеющих соответствующие лицензии ФСТЭК и ФСБ (https://reestr.fstec.ru/reg1). - Сформировать техническое задание на выполнение работ по оценке уровня защищенности. - Получить отчетные документы в бумажном и в электронном виде от лицензиата по результатам оценки уровня защищенности информационных систем. - На основании распоряжения Правительства РФ от 2 - 0 - 2022 N 1661-р (ред. от 0 - 0 - 2023) 'Об утверждении перечня ключевых органов (организаций), которым необходимо осуществить мероприятия по оценке уровня защищенности своих информационных систем с привлечением организаций, имеющих соответствующие лицензии ФСБ России и ФСТЭК Росси' предоставить отчетные документы по оценке уровня защищенности информационных систем Правительству РФ, а также в адрес ФСТЭК и ФСБ России на основании соответствующего запроса. | P27: Заполнить | Q27: Скан-копия договора с подрядчиком, скан копия лицензии | T27: Не готово | U27: 0 | V27: 0 | W27: 0 | X27: =SUM(U27:W27) -> 0
A28: Нормативное соответствие | B28: 250 Указ | C28: ='250'!B70 -> Произведена инвентаризация СЗИ на предмет выявления импортного | D28: ='250'!C70 -> НС.250.СЗИ.1 | E28: ='250'!D70 -> 5 | F28: ='250'!E70 -> 5 | G28: ='250'!F70 -> 5 | H28: ='Нормативное соответствие'!S114 -> 9.04 | I28: =IF(H28<=200,"КБ1",IF(H28<=300,"КБ2","КБ3")) -> КБ1 | J28: ='250'!K70 -> 5 | K28: ='250'!I70 -> 0 | L28: ='250'!L70 -> 0 | M28: =IF(K28=J28," ",L28-K28) -> 0 | N28: =IF(H28<100,IF(L28>=G28,0,J28-L28),IF(H28<300,IF(L28>=F28,0,J28-L28),IF(L28>=E28,0,J28-L28))) -> 5 | O28: ='250'!S70 -> - Провести инвентаризацию используемых средств защиты информации и выявить все средства из недружественных государств | P28: Заполнить | Q28: Перечень используемых средств защиты информации из недружественных государств | T28: Не готово | U28: 0 | V28: 0 | W28: 0 | X28: =SUM(U28:W28) -> 0
A29: Нормативное соответствие | B29: 250 Указ | C29: ='250'!B71 -> Проведена оценка возможности перехода на отечественное | D29: ='250'!C71 -> НС.250.СЗИ.2 | E29: ='250'!D71 -> 5 | F29: ='250'!E71 -> 5 | G29: ='250'!F71 -> 5 | H29: ='Нормативное соответствие'!S114 -> 9.04 | I29: =IF(H29<=200,"КБ1",IF(H29<=300,"КБ2","КБ3")) -> КБ1 | J29: ='250'!K71 -> 5 | K29: ='250'!I71 -> 0 | L29: ='250'!L71 -> 0 | M29: =IF(K29=J29," ",L29-K29) -> 0 | N29: =IF(H29<100,IF(L29>=G29,0,J29-L29),IF(H29<300,IF(L29>=F29,0,J29-L29),IF(L29>=E29,0,J29-L29))) -> 5 | O29: ='250'!S71 -> - Провести оценку возможности перехода с используемых средств защиты информации из недружественных государств на иные решения (отечественные, open source или из дружественных государств). | P29: Заполнить | Q29: Результат анализа возможности перехода | T29: Не готово | U29: 0 | V29: 0 | W29: 0 | X29: =SUM(U29:W29) -> 0
A30: Нормативное соответствие | B30: 250 Указ | C30: ='250'!B72 -> Подготовлен план перехода | D30: ='250'!C72 -> НС.250.СЗИ.3 | E30: ='250'!D72 -> 5 | F30: ='250'!E72 -> 5 | G30: ='250'!F72 -> 5 | H30: ='Нормативное соответствие'!S114 -> 9.04 | I30: =IF(H30<=200,"КБ1",IF(H30<=300,"КБ2","КБ3")) -> КБ1 | J30: ='250'!K72 -> 5 | K30: ='250'!I72 -> 0 | L30: ='250'!L72 -> 0 | M30: =IF(K30=J30," ",L30-K30) -> 0 | N30: =IF(H30<100,IF(L30>=G30,0,J30-L30),IF(H30<300,IF(L30>=F30,0,J30-L30),IF(L30>=E30,0,J30-L30))) -> 5 | O30: ='250'!S72 -> - Подготовить план перехода со средств защиты информации из недружественных государств. | P30: Заполнить | Q30: Утвержденный План перехода | T30: Не готово | U30: 0 | V30: 0 | W30: 0 | X30: =SUM(U30:W30) -> 0
A31: Нормативное соответствие | B31: 250 Указ | C31: ='250'!B73 -> Осуществлено пилотирование | D31: ='250'!C73 -> НС.250.СЗИ.4 | E31: ='250'!D73 -> 5 | F31: ='250'!E73 -> 5 | G31: ='250'!F73 -> 5 | H31: ='Нормативное соответствие'!S114 -> 9.04 | I31: =IF(H31<=200,"КБ1",IF(H31<=300,"КБ2","КБ3")) -> КБ1 | J31: ='250'!K73 -> 5 | K31: ='250'!I73 -> 0 | L31: ='250'!L73 -> 0 | M31: =IF(K31=J31," ",L31-K31) -> 0 | N31: =IF(H31<100,IF(L31>=G31,0,J31-L31),IF(H31<300,IF(L31>=F31,0,J31-L31),IF(L31>=E31,0,J31-L31))) -> 5 | O31: ='250'!S73 -> - Осуществить пилотирование решений, выбранных для замены средствам защиты информации из недружественных государств | P31: Заполнить | Q31: Документ по результатам проведения пилотирования | T31: Не готово | U31: 0 | V31: 0 | W31: 0 | X31: =SUM(U31:W31) -> 0
A32: Нормативное соответствие | B32: 250 Указ | C32: ='250'!B74 -> Сделан выбор и осуществлено внедрение выбранного СЗИ | D32: ='250'!C74 -> НС.250.СЗИ.5 | E32: ='250'!D74 -> 5 | F32: ='250'!E74 -> 5 | G32: ='250'!F74 -> 5 | H32: ='Нормативное соответствие'!S114 -> 9.04 | I32: =IF(H32<=200,"КБ1",IF(H32<=300,"КБ2","КБ3")) -> КБ1 | J32: ='250'!K74 -> 5 | K32: ='250'!I74 -> 0 | L32: ='250'!L74 -> 0 | M32: =IF(K32=J32," ",L32-K32) -> 0 | N32: =IF(H32<100,IF(L32>=G32,0,J32-L32),IF(H32<300,IF(L32>=F32,0,J32-L32),IF(L32>=E32,0,J32-L32))) -> 5 | O32: ='250'!S74 -> - Внедрить выбранные средства защиты информации. | P32: Заполнить | Q32: Утвержденный Акт ввода в эксплуатацию средств защиты информации. | T32: Не готово | U32: 0 | V32: 0 | W32: 0 | X32: =SUM(U32:W32) -> 0
A33: Нормативное соответствие | B33: 250 Указ | C33: ='250'!B76 -> Утвержден регламент взаимодействия с ГосСОПКА | D33: ='250'!C76 -> НС.250.СОПКА.1 | E33: ='250'!D76 -> 5 | F33: ='250'!E76 -> 5 | G33: ='250'!F76 -> 5 | H33: ='Нормативное соответствие'!S115 -> 9.05 | I33: =IF(H33<=200,"КБ1",IF(H33<=300,"КБ2","КБ3")) -> КБ1 | J33: ='250'!K76 -> 5 | K33: ='250'!I76 -> 0 | L33: ='250'!L76 -> 0 | M33: =IF(K33=J33," ",L33-K33) -> 0 | N33: =IF(H33<100,IF(L33>=G33,0,J33-L33),IF(H33<300,IF(L33>=F33,0,J33-L33),IF(L33>=E33,0,J33-L33))) -> 5 | O33: ='250'!S76 -> - Подписать Соглашение о взаимодействии Публичного акционерного общества Ростелеком и ДЗО в области обнаружения, предупреждения и ликвидации последствий компьютерных атак ; - Разработать и утверждить ОРД и ВНД, регламентирующие взаимодействие с Корпоративным центром ГосСОПКА (на базе SOC Департамент мониторинга и реагирования на компьютерные инциденты КЦ ПАО 'Ростелеком; далее - КЦ ГосСОПКА): - утвердить регламент информирования ФСБ России (НКЦКИ) о компьютерных инцидентах; - Утвердить перечень информации о компьютерных инцидентах, связанных с функционированием объектов КИИ; - Разработать и утвердить правила и процедуры реагирования на компьютерные инциденты. | P33: Заполнить | Q33: Соглашение между ПАО "Ростелеком" и ДЗО в области обнаружения, предупреждения и ликвидации последствий компьютерных атак Утвержденный набор ВНД и ОРД | T33: Не готово | U33: 0 | V33: 0 | W33: 0 | X33: =SUM(U33:W33) -> 0
A34: Нормативное соответствие | B34: 250 Указ | C34: ='250'!B77 -> Осуществляется мониторинг ресурсов | D34: ='250'!C77 -> НС.250.СОПКА.2 | E34: ='250'!D77 -> 5 | F34: ='250'!E77 -> 5 | G34: ='250'!F77 -> 5 | H34: ='Нормативное соответствие'!S115 -> 9.05 | I34: =IF(H34<=200,"КБ1",IF(H34<=300,"КБ2","КБ3")) -> КБ1 | J34: ='250'!K77 -> 5 | K34: ='250'!I77 -> 0 | L34: ='250'!L77 -> 0 | M34: =IF(K34=J34," ",L34-K34) -> 0 | N34: =IF(H34<100,IF(L34>=G34,0,J34-L34),IF(H34<300,IF(L34>=F34,0,J34-L34),IF(L34>=E34,0,J34-L34))) -> 5 | O34: ='250'!S77 -> - Выполнить подключение ЗОКИИ к КЦ ГосСОПКА - Организовать двустороннее взаимодействие с КЦ ГосСОПКА по мониторингу защищенности ЗОКИИ, принадлежащих Обществу или используемых ею | P34: Заполнить | Q34: Утвержденный Регламент взаимодействия с КЦ ГосСОПКА | T34: Не готово | U34: 0 | V34: 0 | W34: 0 | X34: =SUM(U34:W34) -> 0
A35: Нормативное соответствие | B35: 250 Указ | C35: ='250'!B78 -> Организовано взаимодействие с должностными лицами ФСБ России по результатам мониторинга | D35: ='250'!C78 -> НС.250.СОПКА.3 | E35: ='250'!D78 -> 5 | F35: ='250'!E78 -> 5 | G35: ='250'!F78 -> 5 | H35: ='Нормативное соответствие'!S115 -> 9.05 | I35: =IF(H35<=200,"КБ1",IF(H35<=300,"КБ2","КБ3")) -> КБ1 | J35: ='250'!K78 -> 5 | K35: ='250'!I78 -> 0 | L35: ='250'!L78 -> 0 | M35: =IF(K35=J35," ",L35-K35) -> 0 | N35: =IF(H35<100,IF(L35>=G35,0,J35-L35),IF(H35<300,IF(L35>=F35,0,J35-L35),IF(L35>=E35,0,J35-L35))) -> 5 | O35: ='250'!S78 -> - Запросить информацию у КЦ ГосСОПКА по поводу организации взаимодействия с должностными лицами ФСБ России и ее территориальных органов по результатам мониторинга защищенности информационных ресурсов Общества. | P35: Заполнить | Q35: Утвержденный Регламент информирования ФСБ России (НКЦКИ) о компьютерных инцидентах | T35: Не готово | U35: 0 | V35: 0 | W35: 0 | X35: =SUM(U35:W35) -> 0
A36: Нормативное соответствие | B36: 250 Указ | C36: ='250'!B79 -> Заключено соглашение с НКЦКИ | D36: ='250'!C79 -> НС.250.СОПКА.4 | E36: ='250'!D79 -> 5 | F36: ='250'!E79 -> 5 | G36: ='250'!F79 -> 5 | H36: ='Нормативное соответствие'!S115 -> 9.05 | I36: =IF(H36<=200,"КБ1",IF(H36<=300,"КБ2","КБ3")) -> КБ1 | J36: ='250'!K79 -> 5 | K36: ='250'!I79 -> 0 | L36: ='250'!L79 -> 0 | M36: =IF(K36=J36," ",L36-K36) -> 0 | N36: =IF(H36<100,IF(L36>=G36,0,J36-L36),IF(H36<300,IF(L36>=F36,0,J36-L36),IF(L36>=E36,0,J36-L36))) -> 5 | O36: ='250'!S79 -> - Запросить информацию у КЦ ГосСОПКА по поводу соглашения с НКЦКИ - Разработать и утвердить план реагирования на компьютерные инциденты и принятия мер по ликвидации последствий компьютерных атак самостоятельно или совместно с НКЦКИ. - Направить План на согласование в НКЦКИ | P36: Заполнить | Q36: Утвержденный План реагирования на компьютерные инциденты и принятия мер по ликвидации последствий компьютерных атак | T36: Не готово | U36: 0 | V36: 0 | W36: 0 | X36: =SUM(U36:W36) -> 0
A37: Нормативное соответствие | B37: 250 Указ | C37: ='250'!B80 -> Организовано взаимодействие с НКЦКИ | D37: ='250'!C80 -> НС.250.СОПКА.5 | E37: ='250'!D80 -> 5 | F37: ='250'!E80 -> 5 | G37: ='250'!F80 -> 5 | H37: ='Нормативное соответствие'!S115 -> 9.05 | I37: =IF(H37<=200,"КБ1",IF(H37<=300,"КБ2","КБ3")) -> КБ1 | J37: ='250'!K80 -> 5 | K37: ='250'!I80 -> 0 | L37: ='250'!L80 -> 0 | M37: =IF(K37=J37," ",L37-K37) -> 0 | N37: =IF(H37<100,IF(L37>=G37,0,J37-L37),IF(H37<300,IF(L37>=F37,0,J37-L37),IF(L37>=E37,0,J37-L37))) -> 5 | O37: ='250'!S80 -> - Запросить информацию у КЦ ГосСОПКА по поводу организации взаимодействия с НКЦКИ - Уведомить НКЦКИ о передаче информации по компьютерным инцидентам через КЦ ГосСОПКА | P37: Заполнить | Q37: Письмо в адрес Директора НКЦКИ письмо о принятом решении информировать НКЦКИ через КЦ ГосСОПКА | T37: Не готово | U37: 0 | V37: 0 | W37: 0 | X37: =SUM(U37:W37) -> 0
A38: Нормативное соответствие | B38: КИИ | C38: ='Нормативное соответствие'!B75 -> Полномочия по обеспечению ИБ возложены на заместителя руководителя Общества | D38: ='Нормативное соответствие'!C75 -> НС.КИИ.1 | E38: ='Нормативное соответствие'!D75 -> 5 | F38: ='Нормативное соответствие'!E75 -> 5 | G38: ='Нормативное соответствие'!F75 -> 5 | H38: ='Нормативное соответствие'!S75 -> 8.01 | I38: =IF(H38<=200, "КБ1", IF(H38<=300, "КБ2", "КБ3")) -> КБ1 | J38: ='Нормативное соответствие'!K75 -> 5 | K38: ='Нормативное соответствие'!I75 -> 0 | L38: ='Нормативное соответствие'!L75 -> 0 | M38: =IF(K38=J38," ",L38-K38) -> 0 | N38: =IF(H38<100, IF(L38>=G38,0,J38-L38), IF(H38<300, IF(L38>=F38,0,J38-L38), IF(L38>=E38,0,J38-L38))) -> 5 | O38: ='Нормативное соответствие'!T75 -> - В соотвествии с приказом 235 с Приказом ФСТЭК от 21 декабря 2017 г. N 235 Об утверждении Требований к созданию систем безопасности значимых объектов критической информационной инфраструктуры Российской Федерации и обеспечению их функционирования: - Определить полномочия для подразделения, ответственное за ИБ (как минимум уровня отдела ИБ); - Подготовить положение о подразделении, обеспечивающим ИБ в Обществе; - Создать выделенное подразделение, ответственное за ИБ (как минимум уровня отдела ИБ): - Утвердить приказом по орг. структуре создание подразделения ИБ; - Утвердить положение о подразделении, обеспечивающим ИБ в Обществе; - Распоряжением/приказом определить подразделение ИБ, как подразделение Общества, ответственное за обеспечение безопасности значимых объектов КИИ; Если 2-3 работника подчиняются главному инженеру (тех. директору) или заместителю по безопасности (экономической и физической), то этих 2-3 работников необходимо выделить в отдельный отдел информационной безопасности. | P38: Заполнить | Q38: 1) Положение "О подразделении, обеспечивающем ИБ" в соответствии с Постановлением Правительства РФ от 15.07.2022 № 1272. 2) Приказ "О назначении ответственных за обеспечение безопасности значимых объектов критической информационной инфраструктуры"; 3) Приказ о создании отдельного структурного подразделение (СП) по ИБ или возложие функций по обеспечению ИБ на действующих работников СП по ИТ (при их отсутствии возложение обязанностей допустимо на иную техническую должность, приближенную к ИТ). | T38: Не готово | U38: 0 | V38: 0 | W38: 0 | X38: =SUM(U38:W38) -> 0
A39: Нормативное соответствие | B39: КИИ | C39: ='Нормативное соответствие'!B88 -> Взаимодействие с ГОССОПКА | D39: ='Нормативное соответствие'!C88 -> НС.КИИ.14 | E39: ='Нормативное соответствие'!D88 -> 5 | F39: ='Нормативное соответствие'!E88 -> 5 | G39: ='Нормативное соответствие'!F88 -> 5 | H39: ='Нормативное соответствие'!S88 -> 8.14 | I39: =IF(H39<=200, "КБ1", IF(H39<=300, "КБ2", "КБ3")) -> КБ1 | J39: ='Нормативное соответствие'!K88 -> 5 | K39: ='Нормативное соответствие'!I88 -> 0 | L39: ='Нормативное соответствие'!L88 -> 0 | M39: =IF(K39=J39," ",L39-K39) -> 0 | N39: =IF(H39<100, IF(L39>=G39,0,J39-L39), IF(H39<300, IF(L39>=F39,0,J39-L39), IF(L39>=E39,0,J39-L39))) -> 5 | O39: ='Нормативное соответствие'!T88 -> - Выполнить подключение ЗОКИИ к Корпоративному центру ГосСОПКА (на базе SOC Департамент мониторинга и реагирования на компьютерные инциденты КЦ ПАО Ростелеком; далее - КЦ ГосСОПКА): 1. Подписать Соглашение о взаимодействии Публичного акционерного общества Ростелеком и ДЗО в области обнаружения, предупреждения и ликвидации последствий компьютерных атак 2. Разработать и утвердить ОРД и ВНД, регламентирующие взаимодействие с КЦ ГосСОПКА: - утвердить регламент информирования ФСБ России (НКЦКИ) о компьютерных инцидентах; - Утвердить перечень информации о компьютерных инцидентах, связанных с функционированием объектов КИИ; - Разработать и утвердить правила и процедуры реагирования на компьютерные инциденты. - Разработать и утвердить план реагирования на компьютерные инциденты и принятия мер по ликвидации последствий компьютерных атак самостоятельно или совместно с НКЦКИ. - Направить План на согласование в НКЦКИ. | P39: Заполнить | Q39: 1) Скан договора на подключение к КЦ ГосСОПКА ПАО "Ростелеком" 2) Регламент взаимодействия с КЦ ГосСОПКА или 1) Соглашение с подписью сторон с НКЦКИ о взаимодействии в области обнаружения, предупреждения и ликвидации последствий компьютерных атак; 2) Утвержденный Регламент взаимодействия при осуществлении информационного обмена в области обнаружения, предупреждения и ликвидации последствий компьютерных атак. | T39: Не готово | U39: 0 | V39: 0 | W39: 0 | X39: =SUM(U39:W39) -> 0
A40: Нормативное соответствие | B40: КИИ | C40: ='Нормативное соответствие'!B89 -> Предоставлены своевременные ответы на запросы ФСТЭК России о выполнении мер по защите информации, рекомендованных к реализации (ответы предоставлены на более чем 95% запросов) | D40: ='Нормативное соответствие'!C89 -> НС.КИИ.15 | E40: ='Нормативное соответствие'!D89 -> 5 | F40: ='Нормативное соответствие'!E89 -> 5 | G40: ='Нормативное соответствие'!F89 -> 3.2 | H40: ='Нормативное соответствие'!S89 -> 8.15 | I40: =IF(H40<=200, "КБ1", IF(H40<=300, "КБ2", "КБ3")) -> КБ1 | J40: ='Нормативное соответствие'!K89 -> 5 | K40: ='Нормативное соответствие'!I89 -> 0 | L40: ='Нормативное соответствие'!L89 -> 0 | M40: =IF(K40=J40," ",L40-K40) -> 0 | N40: =IF(H40<100, IF(L40>=G40,0,J40-L40), IF(H40<300, IF(L40>=F40,0,J40-L40), IF(L40>=E40,0,J40-L40))) -> 5 | O40: ='Нормативное соответствие'!T89 -> - Определить ответственного сотрудника за взаимодействие с гос.регуляторами в области запросов КИИ | P40: Заполнить | Q40: ОРД с указанием ответственного работника за взаимодействие с гос.регуляторами в области запросов КИИ | T40: Не готово | U40: 0 | V40: 0 | W40: 0 | X40: =SUM(U40:W40) -> 0
A41: Нормативное соответствие | B41: КИИ | C41: ='Нормативное соответствие'!B76 -> Функции по обеспечению Иб возложены на структурное подразделение | D41: ='Нормативное соответствие'!C76 -> НС.КИИ.2 | E41: ='Нормативное соответствие'!D76 -> 5 | F41: ='Нормативное соответствие'!E76 -> 5 | G41: ='Нормативное соответствие'!F76 -> 5 | H41: ='Нормативное соответствие'!S76 -> 8.02 | I41: =IF(H41<=200, "КБ1", IF(H41<=300, "КБ2", "КБ3")) -> КБ1 | J41: ='Нормативное соответствие'!K76 -> 5 | K41: ='Нормативное соответствие'!I76 -> 0 | L41: ='Нормативное соответствие'!L76 -> 0 | M41: =IF(K41=J41," ",L41-K41) -> 0 | N41: =IF(H41<100, IF(L41>=G41,0,J41-L41), IF(H41<300, IF(L41>=F41,0,J41-L41), IF(L41>=E41,0,J41-L41))) -> 5 | O41: ='Нормативное соответствие'!T76 -> - В соотвествии с приказом 235 с Приказом ФСТЭК от 21 декабря 2017 г. N 235 Об утверждении Требований к созданию систем безопасности значимых объектов критической информационной инфраструктуры Российской Федерации и обеспечению их функционирования: - Определить полномочия для подразделения, ответственное за ИБ (как минимум уровня отдела ИБ); - Подготовить положение о подразделении, обеспечивающим ИБ в Обществе; - Создать выделенное подразделение, ответственное за ИБ (как минимум уровня отдела ИБ): - Утвердить приказом по орг. структуре создание подразделения ИБ; - Утвердить положение о подразделении, обеспечивающим ИБ в Обществе; - Распоряжением/приказом определить подразделение ИБ, как подразделение Общества, ответственное за обеспечение безопасности значимых объектов КИИ; Если 2-3 работника подчиняются главному инженеру (тех. директору) или заместителю по безопасности (экономической и физической), то этих 2-3 работников необходимо выделить в отдельный отдел информационной безопасности. | P41: Заполнить | Q41: 1) Положение "О подразделении, обеспечивающем ИБ" в соответствии с Постановлением Правительства РФ от 15.07.2022 № 1272. 2) Приказ "О назначении ответственных за обеспечение безопасности значимых объектов критической информационной инфраструктуры"; 3) Приказ о создании отдельного структурного подразделение (СП) по ИБ или возложие функций по обеспечению ИБ на действующих работников СП по ИТ (при их отсутствии возложение обязанностей допустимо на иную техническую должность, приближенную к ИТ). | T41: Не готово | U41: 0 | V41: 0 | W41: 0 | X41: =SUM(U41:W41) -> 0
A42: Нормативное соответствие | B42: КИИ | C42: ='Нормативное соответствие'!B77 -> Создана Комиссия по категорированию объектов КИИ | D42: ='Нормативное соответствие'!C77 -> НС.КИИ.3 | E42: ='Нормативное соответствие'!D77 -> 5 | F42: ='Нормативное соответствие'!E77 -> 5 | G42: ='Нормативное соответствие'!F77 -> 5 | H42: ='Нормативное соответствие'!S77 -> 8.03 | I42: =IF(H42<=200, "КБ1", IF(H42<=300, "КБ2", "КБ3")) -> КБ1 | J42: ='Нормативное соответствие'!K77 -> 5 | K42: ='Нормативное соответствие'!I77 -> 0 | L42: ='Нормативное соответствие'!L77 -> 0 | M42: =IF(K42=J42," ",L42-K42) -> 0 | N42: =IF(H42<100, IF(L42>=G42,0,J42-L42), IF(H42<300, IF(L42>=F42,0,J42-L42), IF(L42>=E42,0,J42-L42))) -> 5 | O42: ='Нормативное соответствие'!T77 -> - В соотвествии с Постановлением Правительства РФ от 08.02.2018 N 127 Об утверждении Правил категорирования объектов критической информационной инфраструктуры Российской Федерации, а также перечня показателей критериев значимости объектов критической информационной инфраструктуры Российской Федерации и их значений: 1.Определить полномочия для комиссии по категорированию 2.Подготовить и утвердить Положение о работе Комиссии по категорированию (описывается процесс и порядок работы комиссии) 3. Определить состав комиссии по категорированию согласно пункту 11 ПП127 4. Утвердить приказом состав комиссии по Обществу | P42: Заполнить | Q42: 1) Приказ о создании Комиссии по категорированию объектов КИИ 2) Утвержденное Положение о работе Комиссии по категорированию объектов КИИ | T42: Не готово | U42: 0 | V42: 0 | W42: 0 | X42: =SUM(U42:W42) -> 0
A43: Нормативное соответствие | B43: КИИ | C43: ='Нормативное соответствие'!B78 -> Проведен анализ критичных процессов, сформирован перечень систем, подлежащих категорированию (ИС, ИТКС, АСУ) | D43: ='Нормативное соответствие'!C78 -> НС.КИИ.4 | E43: ='Нормативное соответствие'!D78 -> 5 | F43: ='Нормативное соответствие'!E78 -> 5 | G43: ='Нормативное соответствие'!F78 -> 5 | H43: ='Нормативное соответствие'!S78 -> 8.04 | I43: =IF(H43<=200, "КБ1", IF(H43<=300, "КБ2", "КБ3")) -> КБ1 | J43: ='Нормативное соответствие'!K78 -> 5 | K43: ='Нормативное соответствие'!I78 -> 0 | L43: ='Нормативное соответствие'!L78 -> 0 | M43: =IF(K43=J43," ",L43-K43) -> 0 | N43: =IF(H43<100, IF(L43>=G43,0,J43-L43), IF(H43<300, IF(L43>=F43,0,J43-L43), IF(L43>=E43,0,J43-L43))) -> 5 | O43: ='Нормативное соответствие'!T78 -> - В соответствии с Постановлением Правительства РФ № 127 и Методическими указаниями по категорированию объектов критической информационной инфраструктуры, принадлежащих субъектам критической информационной инфраструктуры, осуществляющим деятельность в отрасли связи (утв. Минцифры России): 1.Провести анализ и определить список управленческих, технологических, производственных, финансово- экономических и (или) иных процессов в рамках выполнения функций (полномочий) или осуществления видов деятельности организации 2.Выявить посредством анализа управленческих, технологических, производственных, финансово-экономических и (или) иных процессов в рамках выполнения функций (полномочий) или осуществления видов деятельности , нарушение и (или) прекращение которых может привести к негативным социальным, политическим, экономическим, экологическим последствиям, последствиям для обеспечения обороны страны, безопасности государства и правопорядка (далее - критические процессы). 3.Определить список систем и сервисов, которые выполняют и/или обеспечивают критчиеские процессы (п. 2) - перечень этих систем и будет являться перечнем объектов КИИ, подлежащим категорированию. 4. Перечень объектов КИИ, подлежащих категорированию, вынести на рассмотрение комиссии по категорированию объектов КИИ Общества. | P43: Заполнить | Q43: Перечень объектов КИИ подлежащих категорированию. | T43: Не готово | U43: 0 | V43: 0 | W43: 0 | X43: =SUM(U43:W43) -> 0
A44: Нормативное соответствие | B44: КИИ | C44: ='Нормативное соответствие'!B79 -> Проведено категорирование объктов КИИ | D44: ='Нормативное соответствие'!C79 -> НС.КИИ.5 | E44: ='Нормативное соответствие'!D79 -> 5 | F44: ='Нормативное соответствие'!E79 -> 5 | G44: ='Нормативное соответствие'!F79 -> 5 | H44: ='Нормативное соответствие'!S79 -> 8.05 | I44: =IF(H44<=200, "КБ1", IF(H44<=300, "КБ2", "КБ3")) -> КБ1 | J44: ='Нормативное соответствие'!K79 -> 5 | K44: ='Нормативное соответствие'!I79 -> 0 | L44: ='Нормативное соответствие'!L79 -> 0 | M44: =IF(K44=J44," ",L44-K44) -> 0 | N44: =IF(H44<100, IF(L44>=G44,0,J44-L44), IF(H44<300, IF(L44>=F44,0,J44-L44), IF(L44>=E44,0,J44-L44))) -> 5 | O44: ='Нормативное соответствие'!T79 -> - В соответствии с Постановлением Правительства РФ № 127 и Методическими указаниями по категорированию объектов критической информационной инфраструктуры, принадлежащих субъектам критической информационной инфраструктуры, осуществляющим деятельность в отрасли связи (утв. Минцифры России 1.Провести оценку в соответствии с перечнем показателей критериев значимости масштаба возможных последствий в случае возникновения компьютерного инцидента на объектах КИИ. 2. Присвоить каждому из объектов КИИ одной из категорий значимости, либо принятие решения комиссией по категорированию об отсутствии необходимости присвоения им одной из категорий значимости. 3. Утвердить у руководителя организации акты категорирования объектов КИИ (для каждого объекта КИИ). 4. Уведомить ФСТЭК России о результатах категторирования ОКИИ. 5. Получить подвтерждение из ФСТЭК России о корректности, проведенного категорирования и внесении в Реестр ЗОКИИ (значимых объектов КИИ) РФ. | P44: Заполнить | Q44: 1) Утвержденные руководителем Акты категорирования 2) Сканы писем, направленных в ФСТЭК России по результатам проведения заседаний Комиссии по категорированию объектов КИИ 3) Сканы писем от ФСТЭК России о внесении объектов КИИ в реестр значимых объектов КИИ | T44: Не готово | U44: 0 | V44: 0 | W44: 0 | X44: =SUM(U44:W44) -> 0
A45: Нормативное соответствие | B45: КИИ | C45: ='Нормативное соответствие'!B80 -> Сведения о системах передаются в ФСТЭК России | D45: ='Нормативное соответствие'!C80 -> НС.КИИ.6 | E45: ='Нормативное соответствие'!D80 -> 5 | F45: ='Нормативное соответствие'!E80 -> 5 | G45: ='Нормативное соответствие'!F80 -> 5 | H45: ='Нормативное соответствие'!S80 -> 8.06 | I45: =IF(H45<=200, "КБ1", IF(H45<=300, "КБ2", "КБ3")) -> КБ1 | J45: ='Нормативное соответствие'!K80 -> 5 | K45: ='Нормативное соответствие'!I80 -> 0 | L45: ='Нормативное соответствие'!L80 -> 0 | M45: =IF(K45=J45," ",L45-K45) -> 0 | N45: =IF(H45<100, IF(L45>=G45,0,J45-L45), IF(H45<300, IF(L45>=F45,0,J45-L45), IF(L45>=E45,0,J45-L45))) -> 5 | O45: ='Нормативное соответствие'!T80 -> - В соответствии с Постановлением Правительства РФ № 127 и Приказ ФСТЭК России от 6 декабря 2017 г. N 227. 1. Во ФСТЭК России направить сведения о результатах категорирования ОКИИ в течение 10 рабочих дней после утверждения актов категорирования объектов КИИ; 2. При изменениях состава ОКИИ направлять во ФСТЭК России сведения об изменениях в составе ОКИИ в течение 20 рабочих дней со дня их изменения на бумажном и электронном носителях. 3.Получить подвтерждение из ФСТЭК России о корректности проведенного категорирования и внесении в Реестр ЗОКИИ РФ, либо внесение в Реестр ЗОКИИ РФ изменений сведений об ОКИИ. | P45: Заполнить | Q45: 1) Сканы писем, направленных в ФСТЭК России по результатам проведения заседаний Комиссии по категорированию объектов КИИ 2) Сканы писем, направленных в ФСТЭК России со сведениями состава ЗОКИИ | T45: Не готово | U45: 0 | V45: 0 | W45: 0 | X45: =SUM(U45:W45) -> 0
A46: Нормативное соответствие | B46: КИИ | C46: ='Нормативное соответствие'!B83 -> Проведены мероприятия по оценке уровня защищенности информационных систем с привлечением организаций, имеющих соответствующие лицензии ФСБ России и ФСТЭК России | D46: ='Нормативное соответствие'!C83 -> НС.КИИ.9 | E46: ='Нормативное соответствие'!D83 -> 5 | F46: ='Нормативное соответствие'!E83 -> 5 | G46: ='Нормативное соответствие'!F83 -> 5 | H46: ='Нормативное соответствие'!S83 -> 8.09 | I46: =IF(H46<=200, "КБ1", IF(H46<=300, "КБ2", "КБ3")) -> КБ1 | J46: ='Нормативное соответствие'!K83 -> 5 | K46: ='Нормативное соответствие'!I83 -> 0 | L46: ='Нормативное соответствие'!L83 -> 0 | M46: =IF(K46=J46," ",L46-K46) -> 0 | N46: =IF(H46<100, IF(L46>=G46,0,J46-L46), IF(H46<300, IF(L46>=F46,0,J46-L46), IF(L46>=E46,0,J46-L46))) -> 5 | O46: ='Нормативное соответствие'!T83 -> - Использовать для СОИБ КИИ: - средства защиты информации (СрЗИ) сертифицированные на соответствие требованиям по безопасности (требования к классу защищенности разные, в зависимости от категории значимости ЗОКИИ); - СрЗИ прошедшие оценку соответствия в форме испытаний или приемки, которые проводятся субъектами критической информационной инфраструктуры самостоятельно или с привлечением организаций. В случае п. 2 и привлечения организаций, имеющих в соответствии с законодательством Российской Федерации лицензии на деятельность в области защиты информации: - Определить и привлечь организацию для оценки уровня защищенности информационных систем ,имеющих соответствующие лицензии ФСТЭК и ФСБ (https://reestr.fstec.ru/reg1). - Сформировать техническое задание на выполнение работ по оценке уровня защищенности. - Получить отчетные документы в бумажном и в электронном виде от лицензиата по результатам оценки уровня защищенности информационных систем. - На основании распоряжения Правительства РФ от 2 - 0 - 2022 N 1661-р (ред. от 0 - 0 - 2023) Об утверждении перечня ключевых органов (организаций), которым необходимо осуществить мероприятия по оценке уровня защищенности своих информационных систем с привлечением организаций, имеющих соответствующие лицензии ФСБ России и ФСТЭК Росси предоставить отчетные документы по оценке уровня защищенности информационных систем Правительству РФ, а также в адрес ФСТЭК и ФСБ России на основании соответствующего запроса. | P46: Заполнить | Q46: 1) Программа и методика испытаний и оценки соответствия СрЗИ; 2) Протоколы испытаний СрЗИ (с привлечением сторонних организаций либо собственными силами). | T46: Не готово | U46: 0 | V46: 0 | W46: 0 | X46: =SUM(U46:W46) -> 0
A47: Нормативное соответствие | B47: Коммерческая тайна | C47: ='Нормативное соответствие'!B91 -> Определен перечень КТ | D47: ='Нормативное соответствие'!C91 -> НС.КТ.1 | E47: ='Нормативное соответствие'!D91 -> 5 | F47: ='Нормативное соответствие'!E91 -> 5 | G47: ='Нормативное соответствие'!F91 -> 5 | H47: ='Нормативное соответствие'!S91 -> 40.01 | I47: =IF(H47<=200, "КБ1", IF(H47<=300, "КБ2", "КБ3")) -> КБ1 | J47: ='Нормативное соответствие'!K91 -> 5 | K47: ='Нормативное соответствие'!I91 -> 0 | L47: ='Нормативное соответствие'!L91 -> 0 | M47: =IF(K47=J47," ",L47-K47) -> 0 | N47: =IF(H47<100, IF(L47>=G47,0,J47-L47), IF(H47<300, IF(L47>=F47,0,J47-L47), IF(L47>=E47,0,J47-L47))) -> 5 | O47: ='Нормативное соответствие'!T91 -> - Определить и утвердить перечень информации, составляющей КТ, взяв за основу определение из п.2 ст. 3 ФЗ № 98; - Ознакомить сотрудников с перечнем. | P47: Заполнить | Q47: Утвержденный перечень информации, составляющей коммерческую тайну | T47: Не готово | U47: 0 | V47: 0 | W47: 0 | X47: =SUM(U47:W47) -> 0
A48: Нормативное соответствие | B48: Коммерческая тайна | C48: ='Нормативное соответствие'!B92 -> Организовано и осуществляется маркирование материальных носителей КТ, или включение в состав реквизита документа грифа КТ | D48: ='Нормативное соответствие'!C92 -> НС.КТ.2 | E48: ='Нормативное соответствие'!D92 -> 5 | F48: ='Нормативное соответствие'!E92 -> 5 | G48: ='Нормативное соответствие'!F92 -> 5 | H48: ='Нормативное соответствие'!S92 -> 40.02 | I48: =IF(H48<=200, "КБ1", IF(H48<=300, "КБ2", "КБ3")) -> КБ1 | J48: ='Нормативное соответствие'!K92 -> 5 | K48: ='Нормативное соответствие'!I92 -> 0 | L48: ='Нормативное соответствие'!L92 -> 0 | M48: =IF(K48=J48," ",L48-K48) -> 0 | N48: =IF(H48<100, IF(L48>=G48,0,J48-L48), IF(H48<300, IF(L48>=F48,0,J48-L48), IF(L48>=E48,0,J48-L48))) -> 5 | O48: ='Нормативное соответствие'!T92 -> Организовать и осуществлять маркирование материальных носителей КТ | P48: Заполнить | Q48: фото/скан-копии материальных носителей с КТ (без раскрытия КТ), фото, скан, скрин журнала (бумажный, ЕСЭД) учета МТ с КТ | T48: Не готово | U48: 0 | V48: 0 | W48: 0 | X48: =SUM(U48:W48) -> 0
A49: Нормативное соответствие | B49: Коммерческая тайна | C49: ='Нормативное соответствие'!B93 -> Организован и осуществляется учет лиц, получивших доступ к КТ, и (или) лиц, которым такая информация была предоставлена или передана | D49: ='Нормативное соответствие'!C93 -> НС.КТ.3 | E49: ='Нормативное соответствие'!D93 -> 5 | F49: ='Нормативное соответствие'!E93 -> 5 | G49: ='Нормативное соответствие'!F93 -> 5 | H49: ='Нормативное соответствие'!S93 -> 40.03 | I49: =IF(H49<=200, "КБ1", IF(H49<=300, "КБ2", "КБ3")) -> КБ1 | J49: ='Нормативное соответствие'!K93 -> 5 | K49: ='Нормативное соответствие'!I93 -> 0 | L49: ='Нормативное соответствие'!L93 -> 0 | M49: =IF(K49=J49," ",L49-K49) -> 0 | N49: =IF(H49<100, IF(L49>=G49,0,J49-L49), IF(H49<300, IF(L49>=F49,0,J49-L49), IF(L49>=E49,0,J49-L49))) -> 5 | O49: ='Нормативное соответствие'!T93 -> Организовать и осуществлятьучет лиц имеющих доступ к КТ | P49: Заполнить | Q49: Фото, скан, скрин ж-ла (бумажный, ЕСЭД, иная ИС), где учитываются факты получения, предоставления и прередачи КТ соответствующим лицам | T49: Не готово | U49: 0 | V49: 0 | W49: 0 | X49: =SUM(U49:W49) -> 0
A50: Нормативное соответствие | B50: Коммерческая тайна | C50: ='Нормативное соответствие'!B94 -> Отношения по использованию КТ с работниками регулируются на основании трудовых договоров, а с контрагентами на основании гражданско-правовых договоров | D50: ='Нормативное соответствие'!C94 -> НС.КТ.4 | E50: ='Нормативное соответствие'!D94 -> 5 | F50: ='Нормативное соответствие'!E94 -> 5 | G50: ='Нормативное соответствие'!F94 -> 5 | H50: ='Нормативное соответствие'!S94 -> 40.04 | I50: =IF(H50<=200,"КБ1",IF(H50<=300,"КБ2","КБ3")) -> КБ1 | J50: ='Нормативное соответствие'!K94 -> 5 | K50: ='Нормативное соответствие'!I94 -> 0 | L50: ='Нормативное соответствие'!L94 -> 0 | M50: =IF(K50=J50," ",L50-K50) -> 0 | N50: =IF(H50<100,IF(L50>=G50,0,J50-L50),IF(H50<300,IF(L50>=F50,0,J50-L50),IF(L50>=E50,0,J50-L50))) -> 5 | O50: ='Нормативное соответствие'!T94 -> - Разработать шаблон соглашения о неразглашении информации, составляющей КТ; - Включить соглашение в трудовые договоры, а также договоры с контрагентами. | P50: Заполнить | Q50: Утвержденные формы типового ТД с работниками и NDA для контрагентов, содержащие положения, регулирующие отношения по использованию КТ, а также по одному примеру заключенного ТД с работником и ГПД с контрагентом (без раскрытия КТ) | T50: Не готово | U50: 0 | V50: 0 | W50: 0 | X50: =SUM(U50:W50) -> 0
A51: Нормативное соответствие | B51: Коммерческая тайна | C51: ='Нормативное соответствие'!B95 -> Определен порядок обращения с КТ и контроля за соблюдением такого порядка | D51: ='Нормативное соответствие'!C95 -> НС.КТ.5 | E51: ='Нормативное соответствие'!D95 -> 5 | F51: ='Нормативное соответствие'!E95 -> 5 | G51: ='Нормативное соответствие'!F95 -> 5 | H51: ='Нормативное соответствие'!S95 -> 40.05 | I51: =IF(H51<=200,"КБ1",IF(H51<=300,"КБ2","КБ3")) -> КБ1 | J51: ='Нормативное соответствие'!K95 -> 5 | K51: ='Нормативное соответствие'!I95 -> 0 | L51: ='Нормативное соответствие'!L95 -> 0 | M51: =IF(K51=J51," ",L51-K51) -> 0 | N51: =IF(H51<100,IF(L51>=G51,0,J51-L51),IF(H51<300,IF(L51>=F51,0,J51-L51),IF(L51>=E51,0,J51-L51))) -> 5 | O51: ='Нормативное соответствие'!T95 -> - Разработать и утвердить локальный документ, который определяет порядок обращения с КТ. Ознакомить сотрудников.Проводить актуализацию ВНД | P51: Заполнить | Q51: Утвержденный документ (со всеми реквизитами, предусмотренными делопроизводством), а также документ (например, отчет или акт с реквизитами, предусмотренными делопроизводством ) об осуществленном контроле соблюдения порядка | T51: Не готово | U51: 0 | V51: 0 | W51: 0 | X51: =SUM(U51:W51) -> 0
A52: Нормативное соответствие | B52: Коммерческая тайна | C52: ='Нормативное соответствие'!B96 -> В трудовом договоре с руководителем Общества предусмотрены его обязанности по обеспечению охраны КТ | D52: ='Нормативное соответствие'!C96 -> НС.КТ.6 | E52: ='Нормативное соответствие'!D96 -> 5 | F52: ='Нормативное соответствие'!E96 -> 5 | G52: ='Нормативное соответствие'!F96 -> 5 | H52: ='Нормативное соответствие'!S96 -> 40.06 | I52: =IF(H52<=200,"КБ1",IF(H52<=300,"КБ2","КБ3")) -> КБ1 | J52: ='Нормативное соответствие'!K96 -> 5 | K52: ='Нормативное соответствие'!I96 -> 0 | L52: ='Нормативное соответствие'!L96 -> 0 | M52: =IF(K52=J52," ",L52-K52) -> 0 | N52: =IF(H52<100,IF(L52>=G52,0,J52-L52),IF(H52<300,IF(L52>=F52,0,J52-L52),IF(L52>=E52,0,J52-L52))) -> 5 | O52: ='Нормативное соответствие'!T96 -> В трудовом договоре с руководителем Общества предусмотреть его обязанности по обеспечению охраны КТ | P52: Заполнить | Q52: Фото, скан ТД или его частей, позволяющих оценить с кем заключен ТД (реквизиты и подписи сторон), раздел (обзац), содержащий обязанности руководителя Общества по обеспечению охраны КТ | T52: Не готово | U52: 0 | V52: 0 | W52: 0 | X52: =SUM(U52:W52) -> 0
A53: Нормативное соответствие | B53: Коммерческая тайна | C53: ='Нормативное соответствие'!B97 -> Работник Общества знакомится под расписку с документами Общества, устанавливающими режим КТ в Обществе и мерами отвественности за его нарушение, а также с полученными докуменами контрагента, содержащего сведения КТ в рамках исполнения своих трудовых обязанностей | D53: ='Нормативное соответствие'!C97 -> НС.КТ.7 | E53: ='Нормативное соответствие'!D97 -> 5 | F53: ='Нормативное соответствие'!E97 -> 5 | G53: ='Нормативное соответствие'!F97 -> 5 | H53: ='Нормативное соответствие'!S97 -> 40.07 | I53: =IF(H53<=200,"КБ1",IF(H53<=300,"КБ2","КБ3")) -> КБ1 | J53: ='Нормативное соответствие'!K97 -> 5 | K53: ='Нормативное соответствие'!I97 -> 0 | L53: ='Нормативное соответствие'!L97 -> 0 | M53: =IF(K53=J53," ",L53-K53) -> 0 | N53: =IF(H53<100,IF(L53>=G53,0,J53-L53),IF(H53<300,IF(L53>=F53,0,J53-L53),IF(L53>=E53,0,J53-L53))) -> 5 | O53: ='Нормативное соответствие'!T97 -> Обеспечить ознакомление работников Общества, допущенных к КТ, под подпись с документами Общества, устанавливающими режим КТ | P53: Заполнить | Q53: Фото или скан листа ознакомления или скрин из ЕСЭД по которому можно определить какой работник когда и с каким документом ознакомился | T53: Не готово | U53: 0 | V53: 0 | W53: 0 | X53: =SUM(U53:W53) -> 0
A54: Нормативное соответствие | B54: Коммерческая тайна | C54: ='Нормативное соответствие'!B98 -> Доступ работника к КТ осуществляется с его согласия, если это не предусмотрено его трудовыми обязанностями | D54: ='Нормативное соответствие'!C98 -> НС.КТ.8 | E54: ='Нормативное соответствие'!D98 -> 5 | F54: ='Нормативное соответствие'!E98 -> 5 | G54: ='Нормативное соответствие'!F98 -> 5 | H54: ='Нормативное соответствие'!S98 -> 40.08 | I54: =IF(H54<=200,"КБ1",IF(H54<=300,"КБ2","КБ3")) -> КБ1 | J54: ='Нормативное соответствие'!K98 -> 5 | K54: ='Нормативное соответствие'!I98 -> 0 | L54: ='Нормативное соответствие'!L98 -> 0 | M54: =IF(K54=J54," ",L54-K54) -> 0 | N54: =IF(H54<100,IF(L54>=G54,0,J54-L54),IF(H54<300,IF(L54>=F54,0,J54-L54),IF(L54>=E54,0,J54-L54))) -> 5 | O54: ='Нормативное соответствие'!T98 -> -Определить порядок доступа работников к КТ, если таковой не предусмотрен трудовыми договорами. | P54: Заполнить | Q54: Если применимо, то артефакт такого согласия (например, материальное согласие или скрин с ИС, в которой реализована подобная процедура получения и хранения согласия) | T54: Не готово | U54: 0 | V54: 0 | W54: 0 | X54: =SUM(U54:W54) -> 0
A55: Нормативное соответствие | B55: ПДн | C55: ='Нормативное соответствие'!B50 -> Наличие политики в отношении обработки ПДН, соответствующей требованиям законодательтсва (https://62.rkn.gov.ru/directions/p3535/p6528) | D55: ='Нормативное соответствие'!C50 -> НС.ПР.5.8.15.1 | E55: ='Нормативное соответствие'!D50 -> 5 | F55: ='Нормативное соответствие'!E50 -> 5 | G55: ='Нормативное соответствие'!F50 -> 5 | H55: ='Нормативное соответствие'!S50 -> 26.01 | I55: =IF(H55<=200,"КБ1",IF(H55<=300,"КБ2","КБ3")) -> КБ1 | J55: ='Нормативное соответствие'!K50 -> 5 | K55: ='Нормативное соответствие'!I50 -> 0 | L55: ='Нормативное соответствие'!L50 -> 0 | M55: =IF(K55=J55," ",L55-K55) -> 0 | N55: =IF(H55<100,IF(L55>=G55,0,J55-L55),IF(H55<300,IF(L55>=F55,0,J55-L55),IF(L55>=E55,0,J55-L55))) -> 5 | O55: ='Нормативное соответствие'!T50 -> - Разработать и утвердить Политику по обработке персональных данных в Обществе - Обеспечить регулярную проверку актуальности Политики по обработке персональных данных в Обществе и её соответствия действующим нормам законодательства | P55: Заполнить | Q55: Утвержденная Политика по обработке персональных данных | T55: Не готово | U55: 0 | V55: 0 | W55: 0 | X55: =SUM(U55:W55) -> 0
A56: Нормативное соответствие | B56: ПДн | C56: ='Нормативное соответствие'!B59 -> Наличие документа, подтверждающего определение угроз безопасности ПДн при их обработке в ИСПДн | D56: ='Нормативное соответствие'!C59 -> НС.ПР.5.8.15.10 | E56: ='Нормативное соответствие'!D59 -> 5 | F56: ='Нормативное соответствие'!E59 -> 5 | G56: ='Нормативное соответствие'!F59 -> 5 | H56: ='Нормативное соответствие'!S59 -> 26.1 | I56: =IF(H56<=200,"КБ1",IF(H56<=300,"КБ2","КБ3")) -> КБ1 | J56: ='Нормативное соответствие'!K59 -> 5 | K56: ='Нормативное соответствие'!I59 -> 0 | L56: ='Нормативное соответствие'!L59 -> 0 | M56: =IF(K56=J56," ",L56-K56) -> 0 | N56: =IF(H56<100,IF(L56>=G56,0,J56-L56),IF(H56<300,IF(L56>=F56,0,J56-L56),IF(L56>=E56,0,J56-L56))) -> 5 | O56: ='Нормативное соответствие'!T59 -> Разработать нормативный документ, в котором определены угрозы безопасности ПДн при их обработке в ИСПДн; | P56: Заполнить | Q56: Утвержденная Модель угроз и модель нарушителя информационной безопасности для каждой ИСПДн, включенной в перечень ИСПДн | T56: Не готово | U56: 0 | V56: 0 | W56: 0 | X56: =SUM(U56:W56) -> 0
A57: Нормативное соответствие | B57: ПДн | C57: ='Нормативное соответствие'!B60 -> Направлено отдельное уведомление в Роскомнадзор в случае трансграничной передачи персональных данных | D57: ='Нормативное соответствие'!C60 -> НС.ПР.5.8.15.11 | E57: ='Нормативное соответствие'!D60 -> 5 | F57: ='Нормативное соответствие'!E60 -> 5 | G57: ='Нормативное соответствие'!F60 -> 5 | H57: ='Нормативное соответствие'!S60 -> 26.11 | I57: =IF(H57<=200,"КБ1",IF(H57<=300,"КБ2","КБ3")) -> КБ1 | J57: ='Нормативное соответствие'!K60 -> 5 | K57: ='Нормативное соответствие'!I60 -> 0 | L57: ='Нормативное соответствие'!L60 -> 0 | M57: =IF(K57=J57," ",L57-K57) -> 0 | N57: =IF(H57<100,IF(L57>=G57,0,J57-L57),IF(H57<300,IF(L57>=F57,0,J57-L57),IF(L57>=E57,0,J57-L57))) -> 5 | O57: ='Нормативное соответствие'!T60 -> - Разработать и направить в Роскомнадзор Уведомление о намерении осуществлять трансграничную передачу персональных данных (при наличии такого вида обработки); - Разработать процесс внесения изменений в Уведомление Роскомнадзора о намерении осуществлять трансграничную передачу персональных данных для всех новых организуемых бизнес-процессов, предусматривающих трансграничную передачу персональных данных | P57: Заполнить | Q57: Уведомление о трансграничной передаче с обратной связью о разрешнии Роскомнадзором осуществлять такую передачу (при необходимости трансграничной передачи ПДн) | T57: Не готово | U57: 0 | V57: 0 | W57: 0 | X57: =SUM(U57:W57) -> 0
A58: Нормативное соответствие | B58: ПДн | C58: ='Нормативное соответствие'!B61 -> При сборе персональных данных, в том числе посредством информационно-телекоммуникационной сети "Интернет", запись, систематизация, накопление, хранение, уточнение (обновление, изменение), извлечение персональных данных граждан Российской Федерации с использованием баз данных, находящихся за пределами территории Российской Федерации, не допускаются. | D58: ='Нормативное соответствие'!C61 -> НС.ПР.5.8.15.12 | E58: ='Нормативное соответствие'!D61 -> 5 | F58: ='Нормативное соответствие'!E61 -> 5 | G58: ='Нормативное соответствие'!F61 -> 5 | H58: ='Нормативное соответствие'!S61 -> 26.12 | I58: =IF(H58<=200,"КБ1",IF(H58<=300,"КБ2","КБ3")) -> КБ1 | J58: ='Нормативное соответствие'!K61 -> 5 | K58: ='Нормативное соответствие'!I61 -> 0 | L58: ='Нормативное соответствие'!L61 -> 0 | M58: =IF(K58=J58," ",L58-K58) -> 0 | N58: =IF(H58<100,IF(L58>=G58,0,J58-L58),IF(H58<300,IF(L58>=F58,0,J58-L58),IF(L58>=E58,0,J58-L58))) -> 5 | O58: ='Нормативное соответствие'!T61 -> - Провести аудит фактического размещения баз данных, обеспечивающих систематизацию, накопление, хранение, уточнение (обновления, изменения), извлечение персональных данных граждан РФ; - В случае выявления баз данных, размещенных за пределами территории РФ, запланировать модернизацию инфраструктуры, предусматривающую релокацию таких баз; - Разработать процесс учета всех баз данных организации, обеспечивающих систематизацию, накопление, хранение, уточнение (обновления, изменения), извлечение персональных данных, с указанием их местонахождения | P58: Заполнить | Q58: Формализованный перечень ИСПДн с указанием адресов их размещения | T58: Не готово | U58: 0 | V58: 0 | W58: 0 | X58: =SUM(U58:W58) -> 0
A59: Нормативное соответствие | B59: ПДн | C59: ='Нормативное соответствие'!B62 -> Наличие перечня ИСПДН | D59: ='Нормативное соответствие'!C62 -> НС.ПР.5.8.15.13 | E59: ='Нормативное соответствие'!D62 -> 5 | F59: ='Нормативное соответствие'!E62 -> 5 | G59: ='Нормативное соответствие'!F62 -> 5 | H59: ='Нормативное соответствие'!S62 -> 26.13 | I59: =IF(H59<=200,"КБ1",IF(H59<=300,"КБ2","КБ3")) -> КБ1 | J59: ='Нормативное соответствие'!K62 -> 5 | K59: ='Нормативное соответствие'!I62 -> 0 | L59: ='Нормативное соответствие'!L62 -> 0 | M59: =IF(K59=J59," ",L59-K59) -> 0 | N59: =IF(H59<100,IF(L59>=G59,0,J59-L59),IF(H59<300,IF(L59>=F59,0,J59-L59),IF(L59>=E59,0,J59-L59))) -> 5 | O59: ='Нормативное соответствие'!T62 -> - Разработать и утвердить ВНД, определяющий угрозы безопасности персональных данных при их обработке в организации; - Убедиться, что для всех информационных систем персональных данных организации определены угрозы безопасности персональных данных | P59: Заполнить | Q59: Формализованный перечень ИСПДн с указанием адресов их размещения | T59: Не готово | U59: 0 | V59: 0 | W59: 0 | X59: =SUM(U59:W59) -> 0
A60: Нормативное соответствие | B60: ПДн | C60: ='Нормативное соответствие'!B63 -> Учет машинных носителей персональных данных; | D60: ='Нормативное соответствие'!C63 -> НС.ПР.5.8.15.14 | E60: ='Нормативное соответствие'!D63 -> 5 | F60: ='Нормативное соответствие'!E63 -> 5 | G60: ='Нормативное соответствие'!F63 -> 5 | H60: ='Нормативное соответствие'!S63 -> 26.14 | I60: =IF(H60<=200,"КБ1",IF(H60<=300,"КБ2","КБ3")) -> КБ1 | J60: ='Нормативное соответствие'!K63 -> 5 | K60: ='Нормативное соответствие'!I63 -> 0 | L60: ='Нормативное соответствие'!L63 -> 0 | M60: =IF(K60=J60," ",L60-K60) -> 0 | N60: =IF(H60<100,IF(L60>=G60,0,J60-L60),IF(H60<300,IF(L60>=F60,0,J60-L60),IF(L60>=E60,0,J60-L60))) -> 5 | O60: ='Нормативное соответствие'!T63 -> - Разработать и утвердить ВНД, определяющий порядок использования съемных носителей информации, в т.ч. правила их учета; - Запланировать регулярный процесс контроля ведения учета съемных носителей информации | P60: Заполнить | Q60: Утвержденное Положение (инструкция) по использованию машинных носителей информации, в которое включен раздел про хранение и учет носителей. В качестве приложения Журнал регистрации, учета и выдачи МНИ | T60: Не готово | U60: 0 | V60: 0 | W60: 0 | X60: =SUM(U60:W60) -> 0
A61: Нормативное соответствие | B61: ПДн | C61: ='Нормативное соответствие'!B64 -> Наличие документов, подтверждающих определение уровня защищенности ПДн в ИСПДн | D61: ='Нормативное соответствие'!C64 -> НС.ПР.5.8.15.15 | E61: ='Нормативное соответствие'!D64 -> 5 | F61: ='Нормативное соответствие'!E64 -> 5 | G61: ='Нормативное соответствие'!F64 -> 5 | H61: ='Нормативное соответствие'!S64 -> 26.15 | I61: =IF(H61<=200,"КБ1",IF(H61<=300,"КБ2","КБ3")) -> КБ1 | J61: ='Нормативное соответствие'!K64 -> 5 | K61: ='Нормативное соответствие'!I64 -> 0 | L61: ='Нормативное соответствие'!L64 -> 0 | M61: =IF(K61=J61," ",L61-K61) -> 0 | N61: =IF(H61<100,IF(L61>=G61,0,J61-L61),IF(H61<300,IF(L61>=F61,0,J61-L61),IF(L61>=E61,0,J61-L61))) -> 5 | O61: ='Нормативное соответствие'!T64 -> - Разработать и утвердить Акты категорирования для каждой ИСПДн; | P61: Заполнить | Q61: Акт определения уровня защищенности персональных данных для каждой ИСПДн, включенной в перечень ИСПДн | T61: Не готово | U61: 0 | V61: 0 | W61: 0 | X61: =SUM(U61:W61) -> 0
A62: Нормативное соответствие | B62: ПДн | C62: ='Нормативное соответствие'!B65 -> Проводится периодический внутренний контроль и (или) аудит соответствия обработки персональных данных Федеральному закону №152-ФЗ "О персональных данных" и принятым требованиям к защите персональных данных, политике в отношении обработки персональных данных и прочим внутренним нормативным документам. | D62: ='Нормативное соответствие'!C65 -> НС.ПР.5.8.15.16 | E62: ='Нормативное соответствие'!D65 -> 5 | F62: ='Нормативное соответствие'!E65 -> 5 | G62: ='Нормативное соответствие'!F65 -> 5 | H62: ='Нормативное соответствие'!S65 -> 26.16 | I62: =IF(H62<=200,"КБ1",IF(H62<=300,"КБ2","КБ3")) -> КБ1 | J62: ='Нормативное соответствие'!K65 -> 5 | K62: ='Нормативное соответствие'!I65 -> 0 | L62: ='Нормативное соответствие'!L65 -> 0 | M62: =IF(K62=J62," ",L62-K62) -> 0 | N62: =IF(H62<100,IF(L62>=G62,0,J62-L62),IF(H62<300,IF(L62>=F62,0,J62-L62),IF(L62>=E62,0,J62-L62))) -> 5 | O62: ='Нормативное соответствие'!T65 -> - Разработать и утвердить Положение о проведении контроля информационной безопасности (в т.ч. устанавливающий порядок проведения аудита соответствия обработки персональных данных требованиям ФЗ-152); - Разработать и утвердить План проведения контроля информационной безопасности и (или) аудита соответствия обработки персональных данных требованиям ФЗ-152 | P62: Заполнить | Q62: Утвержденное Положение о проведении внутреннего контроля и(или) аудита, приложением к которому определить план проведения, программу, отчет | T62: Не готово | U62: 0 | V62: 0 | W62: 0 | X62: =SUM(U62:W62) -> 0
A63: Нормативное соответствие | B63: ПДн | C63: ='Нормативное соответствие'!B66 -> Наличие оценки вреда, который может быть причинен субъектам персональных данных в случае нарушения законодательства в области персональных данных, в соответствии с требованиями, установленными Роскомнадзором. | D63: ='Нормативное соответствие'!C66 -> НС.ПР.5.8.15.17 | E63: ='Нормативное соответствие'!D66 -> 5 | F63: ='Нормативное соответствие'!E66 -> 5 | G63: ='Нормативное соответствие'!F66 -> 5 | H63: ='Нормативное соответствие'!S66 -> 26.17 | I63: =IF(H63<=200,"КБ1",IF(H63<=300,"КБ2","КБ3")) -> КБ1 | J63: ='Нормативное соответствие'!K66 -> 5 | K63: ='Нормативное соответствие'!I66 -> 0 | L63: ='Нормативное соответствие'!L66 -> 0 | M63: =IF(K63=J63," ",L63-K63) -> 0 | N63: =IF(H63<100,IF(L63>=G63,0,J63-L63),IF(H63<300,IF(L63>=F63,0,J63-L63),IF(L63>=E63,0,J63-L63))) -> 5 | O63: ='Нормативное соответствие'!T66 -> 1.Ответственныи за организацию обработки персональных данных либо комиссией провести процедуру оценку вреда. В ходе оценки определить в соответствии с требованиями Приказа Росконадзора № 178 одну из степеней вреда, который может быть причинен субъекту персональных данных - высокую, среднюю или низкую; 2) Оформить результаты оценки вреда Актом. | P63: Заполнить | Q63: Акт оценки вреда, который может быть причинен субъектам персональных данных в случае нарушения требований Федерального закона "О персональных данных" | T63: Не готово | U63: 0 | V63: 0 | W63: 0 | X63: =SUM(U63:W63) -> 0
A64: Нормативное соответствие | B64: ПДн | C64: ='Нормативное соответствие'!B67 -> Осуществляется информирование Роскомнадзора об инцидентах, связанных с обработкой персональных данных, повлекших нарушение прав субъектов персональных данных, с момента выявления такого инцидента в порядке, определенном Федеральным законом 152-ФЗ "О персональных данных". | D64: ='Нормативное соответствие'!C67 -> НС.ПР.5.8.15.18 | E64: ='Нормативное соответствие'!D67 -> 5 | F64: ='Нормативное соответствие'!E67 -> 5 | G64: ='Нормативное соответствие'!F67 -> 5 | H64: ='Нормативное соответствие'!S67 -> 26.18 | I64: =IF(H64<=200,"КБ1",IF(H64<=300,"КБ2","КБ3")) -> КБ1 | J64: ='Нормативное соответствие'!K67 -> 5 | K64: ='Нормативное соответствие'!I67 -> 0 | L64: ='Нормативное соответствие'!L67 -> 0 | M64: =IF(K64=J64," ",L64-K64) -> 0 | N64: =IF(H64<100,IF(L64>=G64,0,J64-L64),IF(H64<300,IF(L64>=F64,0,J64-L64),IF(L64>=E64,0,J64-L64))) -> 5 | O64: ='Нормативное соответствие'!T67 -> - Выстроить в организации сквозной процесс по сбору информации об инцидентах, связанных с обработкой персональных данных, повлекших нарушение прав субъектов персональных данных, установить временные ограничения; - Регламентировать процесс по информированию Роскомнадзора об инцидентах, связанных с обработкой персональных данных, повлекших нарушение прав субъектов персональных данных, в сроки и порядке согласно п. - 1 Ст.21 ФЗ № 152; 3) Запланировать регулярный процесс контроля информирования Роскомнадзора об инцидентах, связанных с обработкой персональных данных, повлекших нарушение прав субъектов персональных данных (в случае их обнаружения) | P64: Заполнить | Q64: Формализованный Регламент взаимодействия внутренних подразделений по информированию координирующего подразделения организации в части сбора информации об инцидентах | T64: Не готово | U64: 0 | V64: 0 | W64: 0 | X64: =SUM(U64:W64) -> 0
A65: Нормативное соответствие | B65: ПДн | C65: ='Нормативное соответствие'!B68 -> Организовано периодическое ознакомление работников, непосредственно осуществляющих обработку персональных данных, с положениями законодательства Российской Федерации о персональных данных, в том числе с требованиями к защите персональных данных и внутренними нормативными документами по вопросам обработки персональных данных | D65: ='Нормативное соответствие'!C68 -> НС.ПР.5.8.15.19 | E65: ='Нормативное соответствие'!D68 -> 5 | F65: ='Нормативное соответствие'!E68 -> 5 | G65: ='Нормативное соответствие'!F68 -> 5 | H65: ='Нормативное соответствие'!S68 -> 26.19 | I65: =IF(H65<=200,"КБ1",IF(H65<=300,"КБ2","КБ3")) -> КБ1 | J65: ='Нормативное соответствие'!K68 -> 5 | K65: ='Нормативное соответствие'!I68 -> 0 | L65: ='Нормативное соответствие'!L68 -> 0 | M65: =IF(K65=J65," ",L65-K65) -> 0 | N65: =IF(H65<100,IF(L65>=G65,0,J65-L65),IF(H65<300,IF(L65>=F65,0,J65-L65),IF(L65>=E65,0,J65-L65))) -> 5 | O65: ='Нормативное соответствие'!T68 -> - Выстроить в организации процесс по ознакомлению работников, непосредственно осуществляющих обработку персональных данных, с положениями законодательства РФ и ВНД организации по вопросам обработки и обеспечения безопасности персональных данных (в т.ч. при трудоустройстве); 2) Закрепить данный процесс в ВНД | P65: Заполнить | Q65: Положение о повышении осведомленности работников по вопросам информационной безопасности Либо раздел в Положении об обработке персональных данных, в котором описан раздел об ознакомлении работников, а также механизм проверок осведомленности персонала в области защиты информации | T65: Не готово | U65: 0 | V65: 0 | W65: 0 | X65: =SUM(U65:W65) -> 0
A66: Нормативное соответствие | B66: ПДн | C66: ='Нормативное соответствие'!B51 -> Политика опубликована и/или доступна (вебсайт или иные ресурсы) для чтения субъектам ПДН | D66: ='Нормативное соответствие'!C51 -> НС.ПР.5.8.15.2 | E66: ='Нормативное соответствие'!D51 -> 5 | F66: ='Нормативное соответствие'!E51 -> 5 | G66: ='Нормативное соответствие'!F51 -> 5 | H66: ='Нормативное соответствие'!S51 -> 26.02 | I66: =IF(H66<=200,"КБ1",IF(H66<=300,"КБ2","КБ3")) -> КБ1 | J66: ='Нормативное соответствие'!K51 -> 5 | K66: ='Нормативное соответствие'!I51 -> 0 | L66: ='Нормативное соответствие'!L51 -> 0 | M66: =IF(K66=J66," ",L66-K66) -> 0 | N66: =IF(H66<100,IF(L66>=G66,0,J66-L66),IF(H66<300,IF(L66>=F66,0,J66-L66),IF(L66>=E66,0,J66-L66))) -> 5 | O66: ='Нормативное соответствие'!T51 -> - Разместить Политику по обработке персональных данных в Организации (или выписку из неё) на веб-сайте Организации; - Разместить печатную версию Политики по обработке персональных данных в Организации в общедоступной части офиса Организации; - Обеспечить ознакомление всех работников Организации с Политикой по обработке персональных данных в Организации (с возможностью подтверждения такого ознакомления - посредством системы электронного документооборота или под роспись на бумажном носителе | P66: Заполнить | Q66: Ссылка на сайт организации (страницу, где размещена Политика, при условии обработки ПДн посредством телекоммуникационных каналов) Снимок экрана внутреннего информационного портала, либо адрес и фото размещенной Политики на стенде в офисе (в случае отсутствия сайта) | T66: Не готово | U66: 0 | V66: 0 | W66: 0 | X66: =SUM(U66:W66) -> 0
A67: Нормативное соответствие | B67: ПДн | C67: ='Нормативное соответствие'!B69 -> Наличие перечня лиц, доступ которых к ПДн, обрабатываемым в ИСПДн, необходим им для выполнения служебных (трудовых) обязанностей | D67: ='Нормативное соответствие'!C69 -> НС.ПР.5.8.15.20 | E67: ='Нормативное соответствие'!D69 -> 5 | F67: ='Нормативное соответствие'!E69 -> 5 | G67: ='Нормативное соответствие'!F69 -> 5 | H67: ='Нормативное соответствие'!S69 -> 26.2 | I67: =IF(H67<=200, "КБ1", IF(H67<=300, "КБ2", "КБ3")) -> КБ1 | J67: ='Нормативное соответствие'!K69 -> 5 | K67: ='Нормативное соответствие'!I69 -> 0 | L67: ='Нормативное соответствие'!L69 -> 0 | M67: =IF(K67=J67," ",L67-K67) -> 0 | N67: =IF(H67<100, IF(L67>=G67,0,J67-L67), IF(H67<300, IF(L67>=F67,0,J67-L67), IF(L67>=E67,0,J67-L67))) -> 5 | O67: ='Нормативное соответствие'!T69 -> Разработать и утвердить перечень лиц, доступ которых к ПДн, обрабатываемым в ИСПДн, необходим им для выполнения служебных (трудовых) обязанностей | P67: Заполнить | Q67: Утвержденный перечень лиц, доступ которых к ПДн, обрабатываемым в ИСПДн, необходим им для выполнения служебных (трудовых) обязанностей | T67: Не готово | U67: 0 | V67: 0 | W67: 0 | X67: =SUM(U67:W67) -> 0
A68: Нормативное соответствие | B68: ПДн | C68: ='Нормативное соответствие'!B70 -> Определены места хранения персональных данных (материальных носителей), а также перечни лиц, осуществляющих обработку персональных данных либо имеющих к ним доступ | D68: ='Нормативное соответствие'!C70 -> НС.ПР.5.8.15.21 | E68: ='Нормативное соответствие'!D70 -> 5 | F68: ='Нормативное соответствие'!E70 -> 5 | G68: ='Нормативное соответствие'!F70 -> 5 | H68: ='Нормативное соответствие'!S70 -> 26.21 | I68: =IF(H68<=200, "КБ1", IF(H68<=300, "КБ2", "КБ3")) -> КБ1 | J68: ='Нормативное соответствие'!K70 -> 5 | K68: ='Нормативное соответствие'!I70 -> 0 | L68: ='Нормативное соответствие'!L70 -> 0 | M68: =IF(K68=J68," ",L68-K68) -> 0 | N68: =IF(H68<100, IF(L68>=G68,0,J68-L68), IF(H68<300, IF(L68>=F68,0,J68-L68), IF(L68>=E68,0,J68-L68))) -> 5 | O68: ='Нормативное соответствие'!T70 -> - Определить и утвердить перечень мест хранения персональных данных/материальных носителей - Регламентировать порядок закрепления мест хранения, а также актуализации информации о местах хранения - Утвердить перечень лиц, осуществляющих обработку персональных данных и/или имеющих к ним доступ - Обеспечить регулярную проверку актуальности имеющихся перечней мест хранения и лиц, осуществляющих обработку персональных данных и/или имеющих к ним доступ | P68: Заполнить | Q68: Утвержденный Перечень помещений специально оборудованных для хранения материальных носителей, содержащих персональные данные и иную конфиденциальную информацию, расположенных на объектах Организации, и лиц, осуществляющих обработку персональных данных либо имеющих к ним доступ | T68: Не готово | U68: 0 | V68: 0 | W68: 0 | X68: =SUM(U68:W68) -> 0
A69: Нормативное соответствие | B69: ПДн | C69: ='Нормативное соответствие'!B71 -> Определены и соблюдаются меры, необходимые для обеспечения сохранности персональных данных и исключающие несанкционированный к ним доступ при хранении материальных носителей, а также перечень лиц, ответственных за реализацию указанных мер (наличие запираемых шкафов, сигнализации и пр.) | D69: ='Нормативное соответствие'!C71 -> НС.ПР.5.8.15.22 | E69: ='Нормативное соответствие'!D71 -> 5 | F69: ='Нормативное соответствие'!E71 -> 5 | G69: ='Нормативное соответствие'!F71 -> 5 | H69: ='Нормативное соответствие'!S71 -> 26.22 | I69: =IF(H69<=200, "КБ1", IF(H69<=300, "КБ2", "КБ3")) -> КБ1 | J69: ='Нормативное соответствие'!K71 -> 5 | K69: ='Нормативное соответствие'!I71 -> 0 | L69: ='Нормативное соответствие'!L71 -> 0 | M69: =IF(K69=J69," ",L69-K69) -> 0 | N69: =IF(H69<100, IF(L69>=G69,0,J69-L69), IF(H69<300, IF(L69>=F69,0,J69-L69), IF(L69>=E69,0,J69-L69))) -> 5 | O69: ='Нормативное соответствие'!T71 -> - Разработать и утвердить перечень мер, необходимых для обеспечения сохранности персональных данных и исключающих несанкционированный доступ к ним при хранении материальных носителей; - Назначить работников, ответственных за реализацию мер; - Проводить плановые и внеплановые проверки соблюдения закрепленных в ВНД мер, необходимых для обеспечения сохранности персональных данных | P69: Заполнить | Q69: Формализованная Инструкция по работе с материальными носителям, содержащими персональные данные и иную конфиденциальную информацию (работа, размещение, хранение, ответственные) | T69: Не готово | U69: 0 | V69: 0 | W69: 0 | X69: =SUM(U69:W69) -> 0
A70: Нормативное соответствие | B70: ПДн | C70: ='Нормативное соответствие'!B72 -> Организован процесс уничтожения перс.данных в соответствии с требованиями Приказа Роскомнадзора от 28.10.2022 № 179 "Об утверждении Требований к подтверждению уничтожения персональных данных" | D70: ='Нормативное соответствие'!C72 -> НС.ПР.5.8.15.23 | E70: ='Нормативное соответствие'!D72 -> 5 | F70: ='Нормативное соответствие'!E72 -> 5 | G70: ='Нормативное соответствие'!F72 -> 5 | H70: ='Нормативное соответствие'!S72 -> 26.23 | I70: =IF(H70<=200, "КБ1", IF(H70<=300, "КБ2", "КБ3")) -> КБ1 | J70: ='Нормативное соответствие'!K72 -> 5 | K70: ='Нормативное соответствие'!I72 -> 0 | L70: ='Нормативное соответствие'!L72 -> 0 | M70: =IF(K70=J70," ",L70-K70) -> 0 | N70: =IF(H70<100, IF(L70>=G70,0,J70-L70), IF(H70<300, IF(L70>=F70,0,J70-L70), IF(L70>=E70,0,J70-L70))) -> 5 | O70: ='Нормативное соответствие'!T72 -> - Регламентировать и внедрить процесс уничтожения данных в соответствии с требованиями приказа Роскомнадзор № 179; | P70: Заполнить | Q70: Раздел в Положениие об обработке персональных данных, регламентирующий процесс уничтожения ПДн, а также форму актов об уничтожении ПДн | T70: Не готово | U70: 0 | V70: 0 | W70: 0 | X70: =SUM(U70:W70) -> 0
A71: Нормативное соответствие | B71: ПДн | C71: ='Нормативное соответствие'!B73 -> Обеспечена защита персональных данных при их передаче/выходе за пределы контролируемой зоны организации | D71: ='Нормативное соответствие'!C73 -> НС.ПР.5.8.15.24 | E71: ='Нормативное соответствие'!D73 -> 5 | F71: ='Нормативное соответствие'!E73 -> 5 | G71: ='Нормативное соответствие'!F73 -> 5 | H71: ='Нормативное соответствие'!S73 -> 26.24 | I71: =IF(H71<=200, "КБ1", IF(H71<=300, "КБ2", "КБ3")) -> КБ1 | J71: ='Нормативное соответствие'!K73 -> 5 | K71: ='Нормативное соответствие'!I73 -> 0 | L71: ='Нормативное соответствие'!L73 -> 0 | M71: =IF(K71=J71," ",L71-K71) -> 0 | N71: =IF(H71<100, IF(L71>=G71,0,J71-L71), IF(H71<300, IF(L71>=F71,0,J71-L71), IF(L71>=E71,0,J71-L71))) -> 5 | O71: ='Нормативное соответствие'!T73 -> - Регламентировать требования по защите персональных данных при их передаче/выходе за пределы контролируемой зоны организации, в т.ч. применение сертифицированных средств криптографической защиты информации (СКЗИ); - Определить требуемый класс СКЗИ в соответствии с моделью нарушителя; - Включить требования по защите персональных данных при их передаче как обязательные при заключении договоров с третьимм лицами; - Осуществлять проверку выполнения требований по защите персональных данных при их передаче | P71: Заполнить | Q71: Модель нарушителя информационной безопасности в ИСПДн Типовое соглашение по обеспечению ИБ для включения в договоры с третьими лицами, включающее требование по шифрованию | T71: Не готово | U71: 0 | V71: 0 | W71: 0 | X71: =SUM(U71:W71) -> 0
A72: Нормативное соответствие | B72: ПДн | C72: ='Нормативное соответствие'!B52 -> Назначено лицо, ответственное за организацию обработки персональных данных, определены его функции и обязанности | D72: ='Нормативное соответствие'!C52 -> НС.ПР.5.8.15.3 | E72: ='Нормативное соответствие'!D52 -> 5 | F72: ='Нормативное соответствие'!E52 -> 5 | G72: ='Нормативное соответствие'!F52 -> 5 | H72: ='Нормативное соответствие'!S52 -> 26.03 | I72: =IF(H72<=200,"КБ1",IF(H72<=300,"КБ2","КБ3")) -> КБ1 | J72: ='Нормативное соответствие'!K52 -> 5 | K72: ='Нормативное соответствие'!I52 -> 0 | L72: ='Нормативное соответствие'!L52 -> 0 | M72: =IF(K72=J72," ",L72-K72) -> 0 | N72: =IF(H72<100,IF(L72>=G72,0,J72-L72),IF(H72<300,IF(L72>=F72,0,J72-L72),IF(L72>=E72,0,J72-L72))) -> 5 | O72: ='Нормативное соответствие'!T52 -> - Разработать и утвердить Приказ о назначении лица, ответственного за организацию обработки персональных данных. | P72: Заполнить | Q72: Приказ о назначении лица, ответственного за организацию обработки персональных данных и инструкцию ответственного за организацию обработки ПДн Положение об ответственном за организацию обработки персональных данных | T72: Не готово | U72: 0 | V72: 0 | W72: 0 | X72: =SUM(U72:W72) -> 0
A73: Нормативное соответствие | B73: ПДн | C73: ='Нормативное соответствие'!B53 -> Уведомление об обработке персональных данных направлено в Роскомнадзор, сведения об организации в реестре РКН поддерживаются в акутальном состоянии | D73: ='Нормативное соответствие'!C53 -> НС.ПР.5.8.15.4 | E73: ='Нормативное соответствие'!D53 -> 5 | F73: ='Нормативное соответствие'!E53 -> 5 | G73: ='Нормативное соответствие'!F53 -> 5 | H73: ='Нормативное соответствие'!S53 -> 26.04 | I73: =IF(H73<=200,"КБ1",IF(H73<=300,"КБ2","КБ3")) -> КБ1 | J73: ='Нормативное соответствие'!K53 -> 5 | K73: ='Нормативное соответствие'!I53 -> 0 | L73: ='Нормативное соответствие'!L53 -> 0 | M73: =IF(K73=J73," ",L73-K73) -> 0 | N73: =IF(H73<100,IF(L73>=G73,0,J73-L73),IF(H73<300,IF(L73>=F73,0,J73-L73),IF(L73>=E73,0,J73-L73))) -> 5 | O73: ='Нормативное соответствие'!T53 -> - Разработать и направить в Роскомнадзор Уведомление об обработке персональных данных | P73: Заполнить | Q73: Уведомление об обработке персональных данных, содержащее актуальные сведения об организации | T73: Не готово | U73: 0 | V73: 0 | W73: 0 | X73: =SUM(U73:W73) -> 0
A74: Нормативное соответствие | B74: ПДн | C74: ='Нормативное соответствие'!B54 -> Наличие ВНД, регламентирующих порядок реализации процессов обработки ПДН в соответствии с рекомендациями ПАО "Ростелеком" (размещено на киберпортале) | D74: ='Нормативное соответствие'!C54 -> НС.ПР.5.8.15.5 | E74: ='Нормативное соответствие'!D54 -> 5 | F74: ='Нормативное соответствие'!E54 -> 5 | G74: ='Нормативное соответствие'!F54 -> 5 | H74: ='Нормативное соответствие'!S54 -> 26.05 | I74: =IF(H74<=200,"КБ1",IF(H74<=300,"КБ2","КБ3")) -> КБ1 | J74: ='Нормативное соответствие'!K54 -> 5 | K74: ='Нормативное соответствие'!I54 -> 0 | L74: ='Нормативное соответствие'!L54 -> 0 | M74: =IF(K74=J74," ",L74-K74) -> 0 | N74: =IF(H74<100,IF(L74>=G74,0,J74-L74),IF(H74<300,IF(L74>=F74,0,J74-L74),IF(L74>=E74,0,J74-L74))) -> 5 | O74: ='Нормативное соответствие'!T54 -> - Провести процедуру сверки указанных в Уведомлении об обработке персональных данных сведений и реально существующих процессов обработки персональных данных в организации; - В случае выявления необходимости, актуализировать и направить повторно Уведомление в Роскомнадзор; - Запланировать регулярный процесс сверки указанных в Уведомлении об обработке персональных данных сведений и реально существующих процессов обработки персональных данных в организации и подачи актуальных сведений в Роскомнадзор | P74: Заполнить | Q74: Уведомление об обработке персональных данных, содержащее актуальные сведения об организации | T74: Не готово | U74: 0 | V74: 0 | W74: 0 | X74: =SUM(U74:W74) -> 0
A75: Нормативное соответствие | B75: ПДн | C75: ='Нормативное соответствие'!B55 -> Наличие согласия на обработку персональных данных от субъекта персональных данных в соответствии с законодательством РФ | D75: ='Нормативное соответствие'!C55 -> НС.ПР.5.8.15.6 | E75: ='Нормативное соответствие'!D55 -> 5 | F75: ='Нормативное соответствие'!E55 -> 5 | G75: ='Нормативное соответствие'!F55 -> 5 | H75: ='Нормативное соответствие'!S55 -> 26.06 | I75: =IF(H75<=200,"КБ1",IF(H75<=300,"КБ2","КБ3")) -> КБ1 | J75: ='Нормативное соответствие'!K55 -> 5 | K75: ='Нормативное соответствие'!I55 -> 0 | L75: ='Нормативное соответствие'!L55 -> 0 | M75: =IF(K75=J75," ",L75-K75) -> 0 | N75: =IF(H75<100,IF(L75>=G75,0,J75-L75),IF(H75<300,IF(L75>=F75,0,J75-L75),IF(L75>=E75,0,J75-L75))) -> 5 | O75: ='Нормативное соответствие'!T55 -> - Провести процедуру определения оснований для обработки персональных данных для каждой заявленной в ВНД организации цели их обработки; - Разработать формы Согласия на обработку персональных данных от субъекта персональных данных для всех случаев (целей) обработки персональных данных в организации, для которых отсутствует иное законное основание; - Обеспечить сбор Согласий на обработку персональных данных от субъектов персональных данных согласно разработанным формам; - Разработать процесс учета и хранения Согласий на обработку персональных данных от субъектов персональных данных для всех случаев (целей) обработки персональных данных в организации | P75: Заполнить | Q75: примеры согласий, а также ВНД, регламентирующий их форму | T75: Не готово | U75: 0 | V75: 0 | W75: 0 | X75: =SUM(U75:W75) -> 0
A76: Нормативное соответствие | B76: ПДн | C76: ='Нормативное соответствие'!B56 -> При поступлении на работу работник дает согласие на передачу его персональных данных третьим лицам | D76: ='Нормативное соответствие'!C56 -> НС.ПР.5.8.15.7 | E76: ='Нормативное соответствие'!D56 -> 5 | F76: ='Нормативное соответствие'!E56 -> 5 | G76: ='Нормативное соответствие'!F56 -> 5 | H76: ='Нормативное соответствие'!S56 -> 26.07 | I76: =IF(H76<=200,"КБ1",IF(H76<=300,"КБ2","КБ3")) -> КБ1 | J76: ='Нормативное соответствие'!K56 -> 5 | K76: ='Нормативное соответствие'!I56 -> 0 | L76: ='Нормативное соответствие'!L56 -> 0 | M76: =IF(K76=J76," ",L76-K76) -> 0 | N76: =IF(H76<100,IF(L76>=G76,0,J76-L76),IF(H76<300,IF(L76>=F76,0,J76-L76),IF(L76>=E76,0,J76-L76))) -> 5 | O76: ='Нормативное соответствие'!T56 -> - Разработать или получить в Блоке ИБ ПАО Ростелеком типовую форму Согласия на передачу персональных данных работника; - Провести аудит процессов обработки персональных данных работников с целью выявления случаев их передачи третьим лицам; - Проанализировать выявленные случаи передачи персональных данных работников третьим лицам на предмет отсеивания случаев, когда такая передача осуществляется в целях соблюдения законодательства Российской федерации; - Адаптировать форму Согласия на передачу персональных данных работника для выявленных случаев, не имеющих правовых оснований для передачи; - Разработать процесс учета и хранения Согласий на передачу персональных данных работников третьим лицам; - Разработать и внедрить процедуру адаптации формы Согласия на передачу персональных данных работников третьим лицам для всех вновь возникающих в организации случаев такой передачи. | P76: Заполнить | Q76: форма согласий, собираемых при трудоустройстве, а также ВНД, регламентирующий форму | T76: Не готово | U76: 0 | V76: 0 | W76: 0 | X76: =SUM(U76:W76) -> 0
A77: Нормативное соответствие | B77: ПДн | C77: ='Нормативное соответствие'!B57 -> Обеспечивается ли прекращение обработки персональных данных в случае отзыва субъектом персональных данных согласия на обработку своих персональных данных в срок, установленный законодательством РФ? | D77: ='Нормативное соответствие'!C57 -> НС.ПР.5.8.15.8 | E77: ='Нормативное соответствие'!D57 -> 5 | F77: ='Нормативное соответствие'!E57 -> 5 | G77: ='Нормативное соответствие'!F57 -> 5 | H77: ='Нормативное соответствие'!S57 -> 26.08 | I77: =IF(H77<=200,"КБ1",IF(H77<=300,"КБ2","КБ3")) -> КБ1 | J77: ='Нормативное соответствие'!K57 -> 5 | K77: ='Нормативное соответствие'!I57 -> 0 | L77: ='Нормативное соответствие'!L57 -> 0 | M77: =IF(K77=J77," ",L77-K77) -> 0 | N77: =IF(H77<100,IF(L77>=G77,0,J77-L77),IF(H77<300,IF(L77>=F77,0,J77-L77),IF(L77>=E77,0,J77-L77))) -> 5 | O77: ='Нормативное соответствие'!T57 -> - Разработать Порядок отзыва субъектом персональных данных согласия на обработку его персональных данных, определяющий процедуру и сроки прекращения обработки его персональных данных (блокирование, уничтожение) в случае невозможности обеспечения правомерности дальнейшей их обработки | P77: Заполнить | Q77: Формализованный документ, регламентирующий процедуру либо раздел в Положении об обработке ПДн о порядке отзыва согласия | T77: Не готово | U77: 0 | V77: 0 | W77: 0 | X77: =SUM(U77:W77) -> 0
A78: Нормативное соответствие | B78: ПДн | C78: ='Нормативное соответствие'!B58 -> Осуществляется ознакомление всех работников с требованием о неразглашении информации, содержащей персональные данные субъектов персональных данных третьим лицам | D78: ='Нормативное соответствие'!C58 -> НС.ПР.5.8.15.9 | E78: ='Нормативное соответствие'!D58 -> 5 | F78: ='Нормативное соответствие'!E58 -> 5 | G78: ='Нормативное соответствие'!F58 -> 5 | H78: ='Нормативное соответствие'!S58 -> 26.09 | I78: =IF(H78<=200,"КБ1",IF(H78<=300,"КБ2","КБ3")) -> КБ1 | J78: ='Нормативное соответствие'!K58 -> 5 | K78: ='Нормативное соответствие'!I58 -> 0 | L78: ='Нормативное соответствие'!L58 -> 0 | M78: =IF(K78=J78," ",L78-K78) -> 0 | N78: =IF(H78<100,IF(L78>=G78,0,J78-L78),IF(H78<300,IF(L78>=F78,0,J78-L78),IF(L78>=E78,0,J78-L78))) -> 5 | O78: ='Нормативное соответствие'!T58 -> - Разработать или получить в Блоке ИБ ПАО Ростелеком типовую форму Обязательства о неразглашении конфиденциальной информации (персональных данных); - Разработать процесс сбора Обязательств о неразглашении конфиденциальной информации (персональных данных) с вновь устроившихся работников организации, либо подтверждения их ознакомления в с требованием о неразглашении в иной форме | P78: Заполнить | Q78: Формализованная форма соглашения о конфиденциальности. Примеры заключенных соглашений | T78: Не готово | U78: 0 | V78: 0 | W78: 0 | X78: =SUM(U78:W78) -> 0
A79: Нормативное соответствие | B79: СКЗИ | C79: ='Нормативное соответствие'!B100 -> Создан орган криптографической защиты (ОКЗ), или возложены функции ОКЗ | D79: ='Нормативное соответствие'!C100 -> НС.СКЗИ.5.9.3.1 | E79: ='Нормативное соответствие'!D100 -> 5 | F79: ='Нормативное соответствие'!E100 -> 5 | G79: ='Нормативное соответствие'!F100 -> 5 | H79: ='Нормативное соответствие'!S100 -> 37.01 | I79: =IF(H79<=200, "КБ1", IF(H79<=300, "КБ2", "КБ3")) -> КБ1 | J79: ='Нормативное соответствие'!K100 -> 5 | K79: ='Нормативное соответствие'!I100 -> 0 | L79: ='Нормативное соответствие'!L100 -> 0 | M79: =IF(K79=J79," ",L79-K79) -> 0 | N79: =IF(H79<100, IF(L79>=G79,0,J79-L79), IF(H79<300, IF(L79>=F79,0,J79-L79), IF(L79>=E79,0,J79-L79))) -> 5 | O79: ='Нормативное соответствие'!T100 -> -Издать приказ о создании ОКЗ; Утверждено Положение об ОКЗ; Назначить руководителя ОКЗ и инженерно-технических работников; Утвердить состав ОКЗ. | P79: Заполнить | Q79: Приказ о создании ОКЗ. Утвержден состав ОКЗ. Утверждено Положение об ОКЗ. | T79: Не готово | U79: 0 | V79: 0 | W79: 0 | X79: =SUM(U79:W79) -> 0
A80: Нормативное соответствие | B80: СКЗИ | C80: ='Нормативное соответствие'!B109 -> Утвержден документ, регламентирующий организацию, эксплуатацию и вывод из эксплуатации СКЗИ в организации, включая формы соответствующих документов | D80: ='Нормативное соответствие'!C109 -> НС.СКЗИ.5.9.3.10 | E80: ='Нормативное соответствие'!D109 -> 5 | F80: ='Нормативное соответствие'!E109 -> 5 | G80: ='Нормативное соответствие'!F109 -> 5 | H80: ='Нормативное соответствие'!S109 -> 37.1 | I80: =IF(H80<=200, "КБ1", IF(H80<=300, "КБ2", "КБ3")) -> КБ1 | J80: ='Нормативное соответствие'!K109 -> 5 | K80: ='Нормативное соответствие'!I109 -> 0 | L80: ='Нормативное соответствие'!L109 -> 0 | M80: =IF(K80=J80," ",L80-K80) -> 0 | N80: =IF(H80<100, IF(L80>=G80,0,J80-L80), IF(H80<300, IF(L80>=F80,0,J80-L80), IF(L80>=E80,0,J80-L80))) -> 5 | O80: ='Нормативное соответствие'!T109 -> -Разработать и утвердить приказом Регламент ОКЗ с приложенями, но не органичиваясь: -Типовая форма акта повреждения упаковки; -Типовая форма лицевого счета пользователя СКЗИ; -Типовая форма журнала поэкземплярного учёта СКЗИ, эксплуатационной и технической документации к ним, ключевых документов; -Типовая форма журнала учета хранилищ ключевых документов, дистрибутивов, технической и эксплуатационной документации к СКЗИ; -Типовая форма журнала учета проверок порядка использования СКЗИ; -Типовая форма журнала поэкземплярного учета ключевых документов; -Типовая форма акта уничтожения СКЗИ, ключевой информации, эксплуатационной и технической документации СКЗИ; -Типовая форма журнала учёта Спецпомещений; -Порядок проведения расследований фактов нарушения условий использования средств криптографической защиты информации в организации; -Акт приема-передачи СКЗИ, эксплуатационной и технической документации СКЗИ, ключевых документов и ключевых носителей; -Акт установки и настройки СКЗИ. Перечень приложений может быть расширен в зависимости от потребностей организации. | P80: Заполнить | Q80: Регламент ОКЗ (с приложениями) | T80: Не готово | U80: 0 | V80: 0 | W80: 0 | X80: =SUM(U80:W80) -> 0
A81: Нормативное соответствие | B81: СКЗИ | C81: ='Нормативное соответствие'!B101 -> Ведется учет ключевой информации | D81: ='Нормативное соответствие'!C101 -> НС.СКЗИ.5.9.3.2 | E81: ='Нормативное соответствие'!D101 -> 5 | F81: ='Нормативное соответствие'!E101 -> 5 | G81: ='Нормативное соответствие'!F101 -> 5 | H81: ='Нормативное соответствие'!S101 -> 37.02 | I81: =IF(H81<=200, "КБ1", IF(H81<=300, "КБ2", "КБ3")) -> КБ1 | J81: ='Нормативное соответствие'!K101 -> 5 | K81: ='Нормативное соответствие'!I101 -> 0 | L81: ='Нормативное соответствие'!L101 -> 0 | M81: =IF(K81=J81," ",L81-K81) -> 0 | N81: =IF(H81<100, IF(L81>=G81,0,J81-L81), IF(H81<300, IF(L81>=F81,0,J81-L81), IF(L81>=E81,0,J81-L81))) -> 5 | O81: ='Нормативное соответствие'!T101 -> Организовать процесс учета ключевой информации; Присвоить ключевым документам (КД), ключевым носителям (КН) идентификаторы (в случае их отсутствия); Заполнить Журнал учета КД/КН в разрезе лиц, которым эти КД/КН выданы.. | P81: Заполнить | Q81: Заполненный Журнал поэкземплярного учета СКЗИ, ключевых документов (КД), ключевых носителей (КН). | T81: Не готово | U81: 0 | V81: 0 | W81: 0 | X81: =SUM(U81:W81) -> 0
A82: Нормативное соответствие | B82: СКЗИ | C82: ='Нормативное соответствие'!B102 -> Ведется обучение лиц, допускаемых и использующих СКЗИ, правилам их использования, оформлены заключения о допуске к самостоятельной работе с СКЗИ | D82: ='Нормативное соответствие'!C102 -> НС.СКЗИ.5.9.3.3 | E82: ='Нормативное соответствие'!D102 -> 5 | F82: ='Нормативное соответствие'!E102 -> 5 | G82: ='Нормативное соответствие'!F102 -> 5 | H82: ='Нормативное соответствие'!S102 -> 37.03 | I82: =IF(H82<=200, "КБ1", IF(H82<=300, "КБ2", "КБ3")) -> КБ1 | J82: ='Нормативное соответствие'!K102 -> 5 | K82: ='Нормативное соответствие'!I102 -> 0 | L82: ='Нормативное соответствие'!L102 -> 0 | M82: =IF(K82=J82," ",L82-K82) -> 0 | N82: =IF(H82<100, IF(L82>=G82,0,J82-L82), IF(H82<300, IF(L82>=F82,0,J82-L82), IF(L82>=E82,0,J82-L82))) -> 5 | O82: ='Нормативное соответствие'!T102 -> Разработать и утвердить инструкцию для пользователей СКЗИ. Ознакомить пользователей СКЗИ с инструкцией. Оформить заключения о допуске лиц к самостоятельной работе с СКЗИ для каждого пользователя СКЗИ. | P82: Заполнить | Q82: Инструкция для пользователей СКЗИ. Оформленные заключения о допуске лиц к самостоятельной работе с СКЗИ. | T82: Не готово | U82: 0 | V82: 0 | W82: 0 | X82: =SUM(U82:W82) -> 0
A83: Нормативное соответствие | B83: СКЗИ | C83: ='Нормативное соответствие'!B103 -> На каждого пользователя СКЗИ ведется лицевой счет | D83: ='Нормативное соответствие'!C103 -> НС.СКЗИ.5.9.3.4 | E83: ='Нормативное соответствие'!D103 -> 5 | F83: ='Нормативное соответствие'!E103 -> 5 | G83: ='Нормативное соответствие'!F103 -> 5 | H83: ='Нормативное соответствие'!S103 -> 37.04 | I83: =IF(H83<=200, "КБ1", IF(H83<=300, "КБ2", "КБ3")) -> КБ1 | J83: ='Нормативное соответствие'!K103 -> 5 | K83: ='Нормативное соответствие'!I103 -> 0 | L83: ='Нормативное соответствие'!L103 -> 0 | M83: =IF(K83=J83," ",L83-K83) -> 0 | N83: =IF(H83<100, IF(L83>=G83,0,J83-L83), IF(H83<300, IF(L83>=F83,0,J83-L83), IF(L83>=E83,0,J83-L83))) -> 5 | O83: ='Нормативное соответствие'!T103 -> - На каждого пользователя СКЗИ оформить лицевой счет в части выданных ему ключевых документов (КД) | P83: Заполнить | Q83: Заполненные лицевые счета на Пользователей СКЗИ | T83: Не готово | U83: 0 | V83: 0 | W83: 0 | X83: =SUM(U83:W83) -> 0
A84: Нормативное соответствие | B84: СКЗИ | C84: ='Нормативное соответствие'!B104 -> Ведется поэкземплярный учет используемых СКЗИ, эксплуатационной и технической документации к ним, ключевых документов | D84: ='Нормативное соответствие'!C104 -> НС.СКЗИ.5.9.3.5 | E84: ='Нормативное соответствие'!D104 -> 5 | F84: ='Нормативное соответствие'!E104 -> 5 | G84: ='Нормативное соответствие'!F104 -> 5 | H84: ='Нормативное соответствие'!S104 -> 37.05 | I84: =IF(H84<=200, "КБ1", IF(H84<=300, "КБ2", "КБ3")) -> КБ1 | J84: ='Нормативное соответствие'!K104 -> 5 | K84: ='Нормативное соответствие'!I104 -> 0 | L84: ='Нормативное соответствие'!L104 -> 0 | M84: =IF(K84=J84," ",L84-K84) -> 0 | N84: =IF(H84<100, IF(L84>=G84,0,J84-L84), IF(H84<300, IF(L84>=F84,0,J84-L84), IF(L84>=E84,0,J84-L84))) -> 5 | O84: ='Нормативное соответствие'!T104 -> Заполнить Журнал поэкземплярного учета, используемых СКЗИ, включив в него сведения об эксплуатационной и технической документации на СКЗИ. | P84: Заполнить | Q84: Заполненный Журнал поэкземплярного учета СКЗИ, ключевых документов (КД), ключевых носителей (КН). | T84: Не готово | U84: 0 | V84: 0 | W84: 0 | X84: =SUM(U84:W84) -> 0
A85: Нормативное соответствие | B85: СКЗИ | C85: ='Нормативное соответствие'!B105 -> Ведется учет хранилищ ключевых документов | D85: ='Нормативное соответствие'!C105 -> НС.СКЗИ.5.9.3.6 | E85: ='Нормативное соответствие'!D105 -> 5 | F85: ='Нормативное соответствие'!E105 -> 5 | G85: ='Нормативное соответствие'!F105 -> 5 | H85: ='Нормативное соответствие'!S105 -> 37.06 | I85: =IF(H85<=200, "КБ1", IF(H85<=300, "КБ2", "КБ3")) -> КБ1 | J85: ='Нормативное соответствие'!K105 -> 5 | K85: ='Нормативное соответствие'!I105 -> 0 | L85: ='Нормативное соответствие'!L105 -> 0 | M85: =IF(K85=J85," ",L85-K85) -> 0 | N85: =IF(H85<100, IF(L85>=G85,0,J85-L85), IF(H85<300, IF(L85>=F85,0,J85-L85), IF(L85>=E85,0,J85-L85))) -> 5 | O85: ='Нормативное соответствие'!T105 -> - Обеспечить приобретение сейфов/металлических шкафов для хранения КД для ОКЗ и для пользователей СКЗИ; - Выдать персоналу ОКЗ и пользователям СКЗИ персональные печати для опечатывания хранилищ; - Присвоить идентификаторы хранилищам, учесть их в Журнале учета хранилищ. | P85: Заполнить | Q85: Заполненный Журнал учета хранилищ | T85: Не готово | U85: 0 | V85: 0 | W85: 0 | X85: =SUM(U85:W85) -> 0
A86: Нормативное соответствие | B86: СКЗИ | C86: ='Нормативное соответствие'!B106 -> Осуществляется контроль за соблюдением условий использования (эксплуатации) СКЗИ, установленный эксплуатационной документацией на СКЗИ | D86: ='Нормативное соответствие'!C106 -> НС.СКЗИ.5.9.3.7 | E86: ='Нормативное соответствие'!D106 -> 5 | F86: ='Нормативное соответствие'!E106 -> 5 | G86: ='Нормативное соответствие'!F106 -> 5 | H86: ='Нормативное соответствие'!S106 -> 37.07 | I86: =IF(H86<=200, "КБ1", IF(H86<=300, "КБ2", "КБ3")) -> КБ1 | J86: ='Нормативное соответствие'!K106 -> 5 | K86: ='Нормативное соответствие'!I106 -> 0 | L86: ='Нормативное соответствие'!L106 -> 0 | M86: =IF(K86=J86," ",L86-K86) -> 0 | N86: =IF(H86<100, IF(L86>=G86,0,J86-L86), IF(H86<300, IF(L86>=F86,0,J86-L86), IF(L86>=E86,0,J86-L86))) -> 5 | O86: ='Нормативное соответствие'!T106 -> - Разработать план и график проведения проверок выполнения пользователями СКЗИ условий использования СКЗИ; - Организовать проверки в соответствии с планом. | P86: Заполнить | Q86: Утвержденный Руководителем ОКЗ график проверок. Отчет о преведении проверки. | T86: Не готово | U86: 0 | V86: 0 | W86: 0 | X86: =SUM(U86:W86) -> 0
A87: Нормативное соответствие | B87: СКЗИ | C87: ='Нормативное соответствие'!B107 -> Осуществляется уничтожение ключевой информации | D87: ='Нормативное соответствие'!C107 -> НС.СКЗИ.5.9.3.8 | E87: ='Нормативное соответствие'!D107 -> 5 | F87: ='Нормативное соответствие'!E107 -> 5 | G87: ='Нормативное соответствие'!F107 -> 5 | H87: ='Нормативное соответствие'!S107 -> 37.08 | I87: =IF(H87<=200, "КБ1", IF(H87<=300, "КБ2", "КБ3")) -> КБ1 | J87: ='Нормативное соответствие'!K107 -> 5 | K87: ='Нормативное соответствие'!I107 -> 0 | L87: ='Нормативное соответствие'!L107 -> 0 | M87: =IF(K87=J87," ",L87-K87) -> 0 | N87: =IF(H87<100, IF(L87>=G87,0,J87-L87), IF(H87<300, IF(L87>=F87,0,J87-L87), IF(L87>=E87,0,J87-L87))) -> 5 | O87: ='Нормативное соответствие'!T107 -> - Организовать процесс уничтожения ключевой информации в соответствии с требованиями пункта 42 Приказа ФАПСИ от 13 июня 2001 г. № 152 | P87: Заполнить | Q87: Оформленные Акты уничтожения СКЗИ, КИ, документации. | T87: Не готово | U87: 0 | V87: 0 | W87: 0 | X87: =SUM(U87:W87) -> 0
A88: Нормативное соответствие | B88: СКЗИ | C88: ='Нормативное соответствие'!B108 -> Ведется учет спецпомещений | D88: ='Нормативное соответствие'!C108 -> НС.СКЗИ.5.9.3.9 | E88: ='Нормативное соответствие'!D108 -> 5 | F88: ='Нормативное соответствие'!E108 -> 5 | G88: ='Нормативное соответствие'!F108 -> 5 | H88: ='Нормативное соответствие'!S108 -> 37.09 | I88: =IF(H88<=200, "КБ1", IF(H88<=300, "КБ2", "КБ3")) -> КБ1 | J88: ='Нормативное соответствие'!K108 -> 5 | K88: ='Нормативное соответствие'!I108 -> 0 | L88: ='Нормативное соответствие'!L108 -> 0 | M88: =IF(K88=J88," ",L88-K88) -> 0 | N88: =IF(H88<100, IF(L88>=G88,0,J88-L88), IF(H88<300, IF(L88>=F88,0,J88-L88), IF(L88>=E88,0,J88-L88))) -> 5 | O88: ='Нормативное соответствие'!T108 -> Определить, организовать, оборудовать в соответствии с требованиями Приказа ФАПСИ № 152 спецпомещения, а также обеспечить их учет | P88: Заполнить | Q88: Заполненный журнал учета спецпомещений. | T88: Не готово | U88: 0 | V88: 0 | W88: 0 | X88: =SUM(U88:W88) -> 0
A89: Реагирование | B89: Плейбуки | C89: =Реагирование!B56 -> Все предполагаемые вектора атак покрыты сценариями по реагированию | D89: =Реагирование!C56 -> РЕАГ.PB.5.9.3.1 | E89: =Реагирование!D56 -> 5 | F89: =Реагирование!E56 -> 5 | G89: =Реагирование!F56 -> 5 | H89: =Реагирование!S56 -> 27.01 | I89: =IF(H89<=200, "КБ1", IF(H89<=300, "КБ2", "КБ3")) -> КБ1 | J89: =Реагирование!K56 -> 5 | K89: =Реагирование!I56 -> 0 | L89: =Реагирование!L56 -> 0 | M89: =IF(K89=J89," ",L89-K89) -> 0 | N89: =IF(H89<100, IF(L89>=G89,0,J89-L89), IF(H89<300, IF(L89>=F89,0,J89-L89), IF(L89>=E89,0,J89-L89))) -> 5 | O89: =Реагирование!T56 -> - При разработке плейбуков учесть все имеющиеся информационные системы, каналы связи, подразделения и филиалы, категории пользователей, внешние сервисы и подрядчиков. | P89: Заполнить | Q89: Формализованные плейбуки (учитывающие известные вектора атак) | T89: Не готово | U89: 0 | V89: 0 | W89: 0 | X89: =SUM(U89:W89) -> 0
A90: Реагирование | B90: Плейбуки | C90: =Реагирование!B57 -> Наличие плейбука по реагированию на сработки АВЗ | D90: =Реагирование!C57 -> РЕАГ.PB.5.9.3.2 | E90: =Реагирование!D57 -> 5 | F90: =Реагирование!E57 -> 5 | G90: =Реагирование!F57 -> 5 | H90: =Реагирование!S57 -> 27.02 | I90: =IF(H90<=200, "КБ1", IF(H90<=300, "КБ2", "КБ3")) -> КБ1 | J90: =Реагирование!K57 -> 5 | K90: =Реагирование!I57 -> 0 | L90: =Реагирование!L57 -> 0 | M90: =IF(K90=J90," ",L90-K90) -> 0 | N90: =IF(H90<100, IF(L90>=G90,0,J90-L90), IF(H90<300, IF(L90>=F90,0,J90-L90), IF(L90>=E90,0,J90-L90))) -> 5 | O90: =Реагирование!T57 -> - Разработать и простестировать плейбуки по реагированию на сработки АВЗ | P90: Заполнить | Q90: Формализованные плейбуки Отчеты о тестировании | T90: Не готово | U90: 0 | V90: 0 | W90: 0 | X90: =SUM(U90:W90) -> 0
A91: Реагирование | B91: Плейбуки | C91: =Реагирование!B58 -> Наличие плейбука по реагированию на сработки (2FA) | D91: =Реагирование!C58 -> РЕАГ.PB.5.9.3.3 | E91: =Реагирование!D58 -> 5 | F91: =Реагирование!E58 -> 5 | G91: =Реагирование!F58 -> 5 | H91: =Реагирование!S58 -> 27.03 | I91: =IF(H91<=200, "КБ1", IF(H91<=300, "КБ2", "КБ3")) -> КБ1 | J91: =Реагирование!K58 -> 5 | K91: =Реагирование!I58 -> 0 | L91: =Реагирование!L58 -> 0 | M91: =IF(K91=J91," ",L91-K91) -> 0 | N91: =IF(H91<100, IF(L91>=G91,0,J91-L91), IF(H91<300, IF(L91>=F91,0,J91-L91), IF(L91>=E91,0,J91-L91))) -> 5 | O91: =Реагирование!T58 -> - Разработать и простестировать плейбуки по реагированию на сработки 2FA | P91: Заполнить | Q91: Формализованные плейбуки Отчеты о тестировании | T91: Не готово | U91: 0 | V91: 0 | W91: 0 | X91: =SUM(U91:W91) -> 0
A92: Реагирование | B92: Плейбуки | C92: =Реагирование!B59 -> Наличие плейбука по реагированию на сработки(RA VPN) | D92: =Реагирование!C59 -> РЕАГ.PB.5.9.3.4 | E92: =Реагирование!D59 -> 5 | F92: =Реагирование!E59 -> 5 | G92: =Реагирование!F59 -> 5 | H92: =Реагирование!S59 -> 27.04 | I92: =IF(H92<=200, "КБ1", IF(H92<=300, "КБ2", "КБ3")) -> КБ1 | J92: =Реагирование!K59 -> 5 | K92: =Реагирование!I59 -> 0 | L92: =Реагирование!L59 -> 0 | M92: =IF(K92=J92," ",L92-K92) -> 0 | N92: =IF(H92<100, IF(L92>=G92,0,J92-L92), IF(H92<300, IF(L92>=F92,0,J92-L92), IF(L92>=E92,0,J92-L92))) -> 5 | O92: =Реагирование!T59 -> - Разработать и простестировать плейбуки по реагированию на сработки RA VPN | P92: Заполнить | Q92: Формализованные плейбуки Отчеты о тестировании | T92: Не готово | U92: 0 | V92: 0 | W92: 0 | X92: =SUM(U92:W92) -> 0
A93: Реагирование | B93: Анализ и расследование | C93: =Реагирование!B51 -> Процесс расследования инцидентов | D93: =Реагирование!C51 -> РЕАГ.АНЛЗ.2 | E93: =Реагирование!D51 -> 4 | F93: =Реагирование!E51 -> 3 | G93: =Реагирование!F51 -> 1 | H93: =Реагирование!S51 -> 30.02 | I93: =IF(H93<=200, "КБ1", IF(H93<=300, "КБ2", "КБ3")) -> КБ1 | J93: =Реагирование!K51 -> 4 | K93: =Реагирование!I51 -> 0 | L93: =Реагирование!L51 -> 0 | M93: =IF(K93=J93," ",L93-K93) -> 0 | N93: =IF(H93<100, IF(L93>=G93,0,J93-L93), IF(H93<300, IF(L93>=F93,0,J93-L93), IF(L93>=E93,0,J93-L93))) -> 4 | O93: =Реагирование!T51 -> - Проводить расследование инцидентов информационной безопасности - Результаты расследований должны быть задокументированы | P93: Заполнить | Q93: Отчеты о проведенных расследованиях | T93: Не готово | U93: 0 | V93: 0 | W93: 0 | X93: =SUM(U93:W93) -> 0
A94: Реагирование | B94: Анализ и расследование | C94: =Реагирование!B52 -> Анализируются причины возникновения инцидентов | D94: =Реагирование!C52 -> РЕАГ.АНЛЗ.3 | E94: =Реагирование!D52 -> 5 | F94: =Реагирование!E52 -> 5 | G94: =Реагирование!F52 -> 3.2 | H94: =Реагирование!S52 -> 30.03 | I94: =IF(H94<=200, "КБ1", IF(H94<=300, "КБ2", "КБ3")) -> КБ1 | J94: =Реагирование!K52 -> 5 | K94: =Реагирование!I52 -> 0 | L94: =Реагирование!L52 -> 0 | M94: =IF(K94=J94," ",L94-K94) -> 0 | N94: =IF(H94<100, IF(L94>=G94,0,J94-L94), IF(H94<300, IF(L94>=F94,0,J94-L94), IF(L94>=E94,0,J94-L94))) -> 5 | O94: =Реагирование!T52 -> - Обеспечить проведение анализа причин возникновения критичных инцидентов ИБ; - По результатам анализа, разрабатывать рекомендации по предотвращению аналогичных инцидентов в будущем | P94: Заполнить | Q94: Справки/аналитические записки, материалы/служебные записки/протоколы заседаний РГ, комиссий и т.д. | T94: Не готово | U94: 0 | V94: 0 | W94: 0 | X94: =SUM(U94:W94) -> 0
A95: Реагирование | B95: Анализ и расследование | C95: =Реагирование!B53 -> Процесс пост-анализа инцидентов | D95: =Реагирование!C53 -> РЕАГ.АНЛЗ.4 | E95: =Реагирование!D53 -> 4 | F95: =Реагирование!E53 -> 3 | G95: =Реагирование!F53 -> 1 | H95: =Реагирование!S53 -> 30.04 | I95: =IF(H95<=200, "КБ1", IF(H95<=300, "КБ2", "КБ3")) -> КБ1 | J95: =Реагирование!K53 -> 4 | K95: =Реагирование!I53 -> 0 | L95: =Реагирование!L53 -> 0 | M95: =IF(K95=J95," ",L95-K95) -> 0 | N95: =IF(H95<100, IF(L95>=G95,0,J95-L95), IF(H95<300, IF(L95>=F95,0,J95-L95), IF(L95>=E95,0,J95-L95))) -> 4 | O95: =Реагирование!T53 -> Проводится анализ критичных инцидентов ИБ на ИС классов MissionCritical и BusinesCritical в режиме рабочих встреч с подразделениями ИТ, с составлением протоколов, содержащих первоочередные меры митигации | P95: Заполнить | Q95: Справки/аналитические записки, материалы/служебные записки/протоколы заседаний РГ, комиссий и т.д. | T95: Не готово | U95: 0 | V95: 0 | W95: 0 | X95: =SUM(U95:W95) -> 0
A96: Реагирование | B96: Коммуникации | C96: =Реагирование!B47 -> Определен порядок взаимодействия с регуляторами по инцидентам ИБ | D96: =Реагирование!C47 -> РЕАГ.КМНК.4 | E96: =Реагирование!D47 -> 5 | F96: =Реагирование!E47 -> 3.2 | G96: =Реагирование!F47 -> 1.6 | H96: =Реагирование!S47 -> 37.04 | I96: =IF(H96<=200, "КБ1", IF(H96<=300, "КБ2", "КБ3")) -> КБ1 | J96: =Реагирование!K47 -> 5 | K96: =Реагирование!I47 -> 0 | L96: =Реагирование!L47 -> 0 | M96: =IF(K96=J96," ",L96-K96) -> 0 | N96: =IF(H96<100, IF(L96>=G96,0,J96-L96), IF(H96<300, IF(L96>=F96,0,J96-L96), IF(L96>=E96,0,J96-L96))) -> 5 | O96: =Реагирование!T47 -> - Взаимодействовать с регуляторами по инциденту ИБ в установленных законом случаях | P96: Заполнить | Q96: Скан-копия/скриншот уведомлений регуляторов (при наличии) | T96: Не готово | U96: 0 | V96: 0 | W96: 0 | X96: =SUM(U96:W96) -> 0
A97: Реагирование | B97: Коммуникации | C97: =Реагирование!B48 -> Для значимых инцидентов подготовлены планы коммуникаций | D97: =Реагирование!C48 -> РЕАГ.КМНК.5 | E97: =Реагирование!D48 -> 5 | F97: =Реагирование!E48 -> 3.2 | G97: =Реагирование!F48 -> 1.6 | H97: =Реагирование!S48 -> 37.05 | I97: =IF(H97<=200, "КБ1", IF(H97<=300, "КБ2", "КБ3")) -> КБ1 | J97: =Реагирование!K48 -> 5 | K97: =Реагирование!I48 -> 0 | L97: =Реагирование!L48 -> 0 | M97: =IF(K97=J97," ",L97-K97) -> 0 | N97: =IF(H97<100, IF(L97>=G97,0,J97-L97), IF(H97<300, IF(L97>=F97,0,J97-L97), IF(L97>=E97,0,J97-L97))) -> 5 | O97: =Реагирование!T48 -> - Составить план коммуникаций при значимых инцидентах, довести его до всех участников | P97: Заполнить | Q97: План коммуникаций | T97: Не готово | U97: 0 | V97: 0 | W97: 0 | X97: =SUM(U97:W97) -> 0
A98: Реагирование | B98: Планирование реагирования | C98: =Реагирование!B39 -> Процесс реагирования на инциденты ИБ | D98: =Реагирование!C39 -> РЕАГ.ПЛР.1 | E98: =Реагирование!D39 -> 4 | F98: =Реагирование!E39 -> 3 | G98: =Реагирование!F39 -> 1 | H98: =Реагирование!S39 -> 7.01 | I98: =IF(H98<=200, "КБ1", IF(H98<=300, "КБ2", "КБ3")) -> КБ1 | J98: =Реагирование!K39 -> 4 | K98: =Реагирование!I39 -> 0 | L98: =Реагирование!L39 -> 0 | M98: =IF(K98=J98," ",L98-K98) -> 0 | N98: =IF(H98<100, IF(L98>=G98,0,J98-L98), IF(H98<300, IF(L98>=F98,0,J98-L98), IF(L98>=E98,0,J98-L98))) -> 4 | O98: =Реагирование!T39 -> - Определить ответственных за решение инцидентов ИБ, включая ответственного за коммуникации внутри и со сторонними компаниями; - Составить и актуализировать список заинтересованных лиц, которые должны получить уведомление об инциденте; - Для критичных инцидентов определить SLA и порядок действий по реагированию; | P98: Заполнить | Q98: Инструкции/статьи в базе знаний/письма в электронной почте | T98: Не готово | U98: 0 | V98: 0 | W98: 0 | X98: =SUM(U98:W98) -> 0
A99: Реагирование | B99: Планирование реагирования | C99: =Реагирование!B40 -> Процесс категорирования инцидентов ИБ | D99: =Реагирование!C40 -> РЕАГ.ПЛР.2 | E99: =Реагирование!D40 -> 4 | F99: =Реагирование!E40 -> 3 | G99: =Реагирование!F40 -> 1 | H99: =Реагирование!S40 -> 7.02 | I99: =IF(H99<=200, "КБ1", IF(H99<=300, "КБ2", "КБ3")) -> КБ1 | J99: =Реагирование!K40 -> 4 | K99: =Реагирование!I40 -> 0 | L99: =Реагирование!L40 -> 0 | M99: =IF(K99=J99," ",L99-K99) -> 0 | N99: =IF(H99<100, IF(L99>=G99,0,J99-L99), IF(H99<300, IF(L99>=F99,0,J99-L99), IF(L99>=E99,0,J99-L99))) -> 4 | O99: =Реагирование!T40 -> - В Обществе неформально определить категории инцидентов ИБ | P99: Заполнить | Q99: Инструкции/статьи в базе знаний/письма в электронной почте | T99: Не готово | U99: 0 | V99: 0 | W99: 0 | X99: =SUM(U99:W99) -> 0
A100: СЗИ | B100: Двухфакторная аутентификация пользователей (2FA) | C100: =СЗИ!B55 -> Процент покрытия необходимой инфраструктуры средствами 2FA (все необходимые системы используют второй фактор согласно Тех. проекта) | D100: =СЗИ!C55 -> СЗИ.2FA.1 | E100: =СЗИ!D55 -> 5 | F100: =СЗИ!E55 -> 5 | G100: =СЗИ!F55 -> 5 | H100: =СЗИ!S55 -> 2.01 | I100: =IF(H100<=200, "КБ1", IF(H100<=300, "КБ2", "КБ3")) -> КБ1 | J100: =СЗИ!K55 -> 5 | K100: =СЗИ!I55 -> 0 | L100: =СЗИ!L55 -> 0 | M100: =IF(K100=J100," ",L100-K100) -> 0 | N100: =IF(H100<100, IF(L100>=G100,0,J100-L100), IF(H100<300, IF(L100>=F100,0,J100-L100), IF(L100>=E100,0,J100-L100))) -> 5 | O100: =СЗИ!T55 -> - Выбрать и протестировать OTP решения; - Выполнить проектирование; - Провести закупку и внедрение. - Автоматизировать процесс выдачи и отзыва средств OTP | P100: Заполнить | Q100: 1. Скан-копия лицензии 2. Снимки экрана/выгрузка конфигураций консоли управления средствами 2FA 3. Снимки экрана/выгрузка конфигураций консоли управления средства удаленного доступа 4. Снимки экрана/выгрузка конфигураций пограничного сетевого оборудования | T100: Не готово | U100: 0 | V100: 0 | W100: 0 | X100: =SUM(U100:W100) -> 0
...

Sheet Управление ИБ
B1: Система управления ИБ | N1: =COUNTA(N2:N6955) -> 95
G40: =Расчет!$F$2 -> 45017 | H40: =Расчет!$H$2 -> 45444 | I40: 45657 | L40: =TODAY() -> 46038 | P40: Степень достижения КБ3 | Q40: Степень достижения КБ2 | R40: Степень достижения КБ1
B41: Категория | C41: Сокращенное наименование | D41: КБ3 | E41: КБ2 | F41: КБ1 | G41: Исторические данные | H41: Исторические данные | I41: Исторические данные | J41: 2026 | K41: Расчетный показатель 2025 | L41: Текущий показатель
B42: =B60 -> Система управления ИБ | C42: =C60 -> СУИБ | D42: =AVERAGE('Управление ИБ'!D61:D70) -> 5 | E42: =AVERAGE('Управление ИБ'!E61:E70) -> 4.64 | F42: =AVERAGE('Управление ИБ'!F61:F70) -> 2.5 | G42: =AVERAGE('Управление ИБ'!G61:G70) -> #DIV/0! | H42: =AVERAGE('Управление ИБ'!H61:H70) -> #DIV/0! | I42: =AVERAGE('Управление ИБ'!I61:I70) -> #DIV/0! | J42: =AVERAGE('Управление ИБ'!J61:J70) -> #DIV/0! | K42: =IF(ЦУКБ="КБ 1",AVERAGE('Управление ИБ'!F61:F70),IF(ЦУКБ="КБ 2",AVERAGE('Управление ИБ'!E61:E70),AVERAGE('Управление ИБ'!D61:D70))) -> 5 | L42: =AVERAGE('Управление ИБ'!L61:L70) -> 0 | P42: =AVERAGE('Управление ИБ'!P61:P70) -> 0 | Q42: =AVERAGE('Управление ИБ'!Q61:Q70) -> 0 | R42: =AVERAGE(R61:R65) -> 0
B43: =B71 -> Управление рисками | C43: УР | D43: =AVERAGE('Управление ИБ'!D72:D76) -> 4.8 | E43: =AVERAGE('Управление ИБ'!E72:E76) -> 2 | F43: =AVERAGE('Управление ИБ'!F72:F76) -> 1 | G43: =AVERAGE('Управление ИБ'!G72:G76) -> #DIV/0! | H43: =AVERAGE('Управление ИБ'!H72:H76) -> #DIV/0! | I43: =AVERAGE('Управление ИБ'!I72:I76) -> #DIV/0! | J43: =AVERAGE('Управление ИБ'!J72:J76) -> #DIV/0! | K43: =IF(ЦУКБ="КБ 1",AVERAGE('Управление ИБ'!F72:F76),IF(ЦУКБ="КБ 2",AVERAGE('Управление ИБ'!E72:E76),AVERAGE('Управление ИБ'!D72:D76))) -> 4.8 | L43: =AVERAGE('Управление ИБ'!L72:L76) -> 0 | P43: =0.5*P72+0.3*(AVERAGE(P74:P75))+0.2*(AVERAGE(P73,P76)) -> 0 | Q43: =0.7*Q72+0.3*Q74 -> 0 | R43: =R72 -> 0
B44: =B105 -> Управление рисками в цепочке поставок | C44: ЦП | D44: =AVERAGE('Управление ИБ'!D106:D108) -> 5 | E44: =AVERAGE('Управление ИБ'!E106:E108) -> 3.8 | F44: =AVERAGE('Управление ИБ'!F106:F108) -> 2.7333333 | G44: =AVERAGE('Управление ИБ'!G106:G108) -> #DIV/0! | H44: =AVERAGE('Управление ИБ'!H106:H108) -> #DIV/0! | I44: =AVERAGE('Управление ИБ'!I106:I108) -> #DIV/0! | J44: =AVERAGE('Управление ИБ'!J106:J108) -> #DIV/0! | K44: =IF(ЦУКБ="КБ 1",AVERAGE('Управление ИБ'!F106:F108),IF(ЦУКБ="КБ 2",AVERAGE('Управление ИБ'!E106:E108),AVERAGE('Управление ИБ'!D106:D108))) -> 5 | L44: =AVERAGE('Управление ИБ'!L106:L108) -> 0 | P44: =AVERAGE('Управление ИБ'!P106:P108) -> 0 | Q44: =AVERAGE('Управление ИБ'!Q106:Q108) -> 0 | R44: =AVERAGE(R106:R108) -> 0
B45: =B109 -> Инвентаризация | C45: ИН | D45: =AVERAGE('Управление ИБ'!D110:D123) -> 4.9285714 | E45: =AVERAGE('Управление ИБ'!E110:E123) -> 3.1857143 | F45: =AVERAGE('Управление ИБ'!F110:F123) -> 1.2142857 | G45: =AVERAGE('Управление ИБ'!G110:G123) -> #DIV/0! | H45: =AVERAGE('Управление ИБ'!H110:H123) -> #DIV/0! | I45: =AVERAGE('Управление ИБ'!I110:I123) -> #DIV/0! | J45: =AVERAGE('Управление ИБ'!J110:J123) -> #DIV/0! | K45: =AVERAGE('Управление ИБ'!K110:K123) -> 4.9285714 | L45: =AVERAGE('Управление ИБ'!L110:L123) -> 0 | P45: =AVERAGE('Управление ИБ'!P110:P123) -> 0 | Q45: =AVERAGE('Управление ИБ'!Q110:Q123) -> 0 | R45: =AVERAGE('Управление ИБ'!R110:R118) -> 0
B46: =B99 -> Управление активами | C46: УА | D46: =AVERAGE('Управление ИБ'!D100:D104) -> 4.8 | E46: =AVERAGE('Управление ИБ'!E100:E104) -> 3.16 | F46: =AVERAGE('Управление ИБ'!F100:F104) -> 0.52 | G46: =AVERAGE('Управление ИБ'!G100:G104) -> #DIV/0! | H46: =AVERAGE('Управление ИБ'!H100:H104) -> #DIV/0! | I46: =AVERAGE('Управление ИБ'!I100:I104) -> #DIV/0! | J46: =AVERAGE('Управление ИБ'!J100:J104) -> #DIV/0! | K46: =AVERAGE('Управление ИБ'!K100:K104) -> 4.8 | L46: =AVERAGE('Управление ИБ'!L100:L104) -> 0 | P46: =AVERAGE('Управление ИБ'!P100:P104) -> 0 | Q46: =AVERAGE('Управление ИБ'!Q100:Q104) -> 0 | R46: =AVERAGE(R100:R101) -> 0
B47: =B163 -> Управление доступом | C47: =C163 -> УД | D47: =AVERAGE(D164:D173) -> 4.46 | E47: =AVERAGE(E164:E173) -> 3.26 | F47: =AVERAGE(F164:F173) -> 2.14 | G47: =AVERAGE(G164:G173) -> #DIV/0! | H47: =AVERAGE(H164:H173) -> #DIV/0! | I47: =AVERAGE(I164:I173) -> #DIV/0! | J47: =AVERAGE(J164:J173) -> #DIV/0! | K47: =AVERAGE(K164:K173) -> 4.46 | L47: =AVERAGE(L164:L173) -> 0 | P47: =AVERAGE(P164:P173) -> 0 | Q47: =AVERAGE(Q164:Q173) -> 0 | R47: =AVERAGE(R165,R166,R169,R170,R171,R172,R173) -> 0
B48: =B174 -> Идентификация и аутентификация | C48: =C174 -> ИА | D48: =AVERAGE(D175:D183) -> 5 | E48: =AVERAGE(E175:E183) -> 4.6 | F48: =AVERAGE(F175:F183) -> 3.3111111 | G48: =AVERAGE(G175:G183) -> #DIV/0! | H48: =AVERAGE(H175:H183) -> #DIV/0! | I48: =AVERAGE(I175:I183) -> #DIV/0! | J48: =AVERAGE(J175:J183) -> #DIV/0! | K48: =AVERAGE(K175:K183) -> 5 | L48: =AVERAGE(L175:L183) -> 0 | P48: =AVERAGE(P175:P183) -> 0 | Q48: =AVERAGE(Q175:Q183) -> 0 | R48: =AVERAGE(R175:R178,R180:R182) -> 0
B49: =B184 -> Защита данных и информации | C49: =C184 -> Д | D49: =AVERAGE(D185:D188) -> 4.55 | E49: =AVERAGE(E185:E188) -> 3.7 | F49: =AVERAGE(F185:F188) -> 1.2 | G49: =AVERAGE(G185:G188) -> #DIV/0! | H49: =AVERAGE(H185:H188) -> #DIV/0! | I49: =AVERAGE(I185:I188) -> #DIV/0! | J49: =AVERAGE(J185:J188) -> #DIV/0! | K49: =AVERAGE(K185:K188) -> 4.55 | L49: =AVERAGE(L185:L188) -> 0 | P49: =AVERAGE(P185:P188) -> 0 | Q49: =AVERAGE(Q185:Q188) -> 0 | R49: =AVERAGE(R186:R187) -> 0
B50: =B124 -> Обеспечение доступности | C50: =C124 -> ОД | D50: =AVERAGE('Управление ИБ'!D125:D129) -> 5 | E50: =AVERAGE('Управление ИБ'!E125:E129) -> 2.92 | F50: =AVERAGE('Управление ИБ'!F125:F129) -> 0 | G50: =AVERAGE('Управление ИБ'!G128:G129) -> #DIV/0! | H50: =AVERAGE('Управление ИБ'!H128:H129) -> #DIV/0! | I50: =AVERAGE('Управление ИБ'!I125:I129) -> #DIV/0! | J50: =AVERAGE('Управление ИБ'!J125:J129) -> #DIV/0! | K50: =AVERAGE('Управление ИБ'!K125:K129) -> 5 | L50: =AVERAGE('Управление ИБ'!L125:L129) -> 0 | P50: =AVERAGE('Управление ИБ'!P125:P129) -> 0 | Q50: =AVERAGE('Управление ИБ'!Q125, Q126,Q128, Q129) -> 0
B51: =B142 -> Персонал | C51: =C142 -> Люди | D51: =AVERAGE(D143:D145) -> 5 | E51: =AVERAGE(E143:E145) -> 5 | F51: =AVERAGE(F143:F145) -> 5 | G51: =AVERAGE(G143:G145) -> #DIV/0! | H51: =AVERAGE(H143:H145) -> #DIV/0! | I51: =AVERAGE(I143:I145) -> #DIV/0! | J51: =AVERAGE(J143:J145) -> #DIV/0! | K51: =AVERAGE(K143:K145) -> 5 | L51: =AVERAGE(L143:L145) -> 0 | P51: =AVERAGE(P143:P145) -> 0 | Q51: =AVERAGE(Q143:Q145) -> 0 | R51: =AVERAGE(R143:R145) -> 0
B52: =B152 -> Осведомленность пользователей и обучение персонала | C52: =C152 -> AW | D52: =AVERAGE(D153:D162) -> 5 | E52: =AVERAGE(E153:E162) -> 3.2 | F52: =AVERAGE(F153:F162) -> 1.6 | G52: =AVERAGE(G153:G162) -> #DIV/0! | H52: =AVERAGE(H153:H162) -> #DIV/0! | I52: =AVERAGE(I153:I162) -> #DIV/0! | J52: =AVERAGE(J153:J162) -> #DIV/0! | K52: =AVERAGE(K153:K162) -> 5 | L52: =AVERAGE(L153:L162) -> 0 | P52: =AVERAGE(P153:P162) -> 0 | Q52: =AVERAGE(Q153:Q162) -> 0 | R52: =AVERAGE(R153:R162) -> 0
B53: =B77 -> Процессы | C53: ПР | D53: =AVERAGE(D78:D98) -> 4.1428571 | E53: =AVERAGE(E78:E98) -> 2.7904762 | F53: =AVERAGE(F78:F98) -> 0.6952381 | G53: =AVERAGE(G78:G98) -> 0 | H53: =AVERAGE(H78:H98) -> 0 | I53: =AVERAGE(I78:I98) -> 0 | J53: =AVERAGE(J78:J98) -> 0 | K53: =AVERAGE(K78:K98) -> 4.1428571 | L53: =AVERAGE(L78:L98) -> 0
B54: =B130 -> Приобретение, разработка и обслуживание систем и ПО | C54: =C130 -> ПРС | D54: =AVERAGE(D131:D141) -> 5 | E54: =AVERAGE(E131:E141) -> 3.8545455 | F54: =AVERAGE(F131:F141) -> 1.0181818 | G54: =AVERAGE(G131:G141) -> #DIV/0! | H54: =AVERAGE(H131:H141) -> #DIV/0! | I54: =AVERAGE(I131:I141) -> #DIV/0! | J54: =AVERAGE(J131:J141) -> #DIV/0! | K54: =AVERAGE(K131:K141) -> 5 | L54: =AVERAGE(L131:L141) -> 0 | P54: =AVERAGE(P131:P141) -> 0 | Q54: =AVERAGE(Q131:Q141) -> 0 | R54: =AVERAGE(R131,R133,R134,R136,R137,R138,R139) -> 0
B55: =B146 -> Физический доступ | C55: =C146 -> ФД | D55: =AVERAGE(D147:D151) -> 5 | E55: =AVERAGE(E147:E151) -> 4.64 | F55: =AVERAGE(F147:F151) -> 4.32 | G55: =AVERAGE(G147:G151) -> #DIV/0! | H55: =AVERAGE(H147:H151) -> #DIV/0! | I55: =AVERAGE(I147:I151) -> #DIV/0! | J55: =AVERAGE(J147:J151) -> #DIV/0! | K55: =AVERAGE(K147:K151) -> 5 | L55: =AVERAGE(L147:L151) -> 0 | P55: =AVERAGE(P147:P151) -> 0 | Q55: =AVERAGE(Q147:Q151) -> 0 | R55: =AVERAGE(R147:R151) -> 0
N59: Выберите ответ | O59: Комментарий | S59: Приоритет | T59: Рекомендации ПАО Ростелеком Очередь 1 (КБ1) | U59: Артефакты (КБ1) | W59: Рекомендации ПАО Ростелеком Очередь 2 (КБ2) | X59: Артефакты (КБ2) | Z59: Рекомендации ПАО Ростелеком Очередь 3 (КБ3) | AA59: Артефакты (КБ3)
B60: Система управления ИБ | C60: СУИБ | S60: =VLOOKUP(B60,Приоритет!$G$9:$K$52,5,0) -> 14 | T60: СУИБ | V60: =S60+200 -> 214 | W60: СУИБ | Y60: =S60+300 -> 314 | Z60: СУИБ
B61: Утверждена Политика информационной безопасности Общества | C61: СУИБ.УР.1 | D61: 5 | E61: 5 | F61: 5 | K61: =IF(ЦУКБ="КБ 1",F61, IF(ЦУКБ="КБ 2",E61,D61)) -> 5 | L61: =VALUE(LEFT(N61,3)) -> 0 | M61: =L61-K61 -> -5 | N61: 0 - нет | P61: =IFERROR(IF($L61>D61,1,$L61/D61),0) -> 0 | Q61: =IFERROR(IF($L61>E61,1,$L61/E61),0) -> 0 | R61: =IFERROR(IF($L61>=F61,1,$L61/F61),0) -> 0 | S61: =S60+0.01 -> 14.01 | T61: =IF(($L61-$F61)>=0,"", "- Разработать или Получить в Блоке ИБ ПАО Ростелеком типовую политику ИБ; - Утвердить в Обществе Политику ИБ") -> - Разработать или Получить в Блоке ИБ ПАО Ростелеком типовую политику ИБ; - Утвердить в Обществе Политику ИБ | U61: Утвержденная Политика ИБ | V61: =V60+0.01 -> 214.01 | W61: =IF(($L61-$E61)>=0,"","") | Y61: =Y60+0.01 -> 314.01 | Z61: =IF(($L61-$D61)>=0,"","")
B62: Назначено лицо, ответственное за обеспечение информационной безопасности | C62: СУИБ.УР.2 | D62: 5 | E62: 5 | F62: 5 | K62: =IF(ЦУКБ="КБ 1",F62, IF(ЦУКБ="КБ 2",E62,D62)) -> 5 | L62: =VALUE(LEFT(N62,3)) -> 0 | M62: =L62-K62 -> -5 | N62: 0 - нет | P62: =IFERROR(IF($L62>D62,1,$L62/D62),0) -> 0 | Q62: =IFERROR(IF($L62>E62,1,$L62/E62),0) -> 0 | R62: =IFERROR(IF($L62>=F62,1,$L62/F62),0) -> 0 | S62: =S61+0.01 -> 14.02 | T62: =IF(($L62-$F62)>=0,"","- Определить полномочия ответственного за обеспечение ИБ в Обществе."&" - Подготовить и утвердить приказ об ответственном за обеспечение ИБ в Обществе") -> - Определить полномочия ответственного за обеспечение ИБ в Обществе. - Подготовить и утвердить приказ об ответственном за обеспечение ИБ в Обществе | U62: Утвержденный приказ об ответственном за обеспечение ИБ | V62: =V61+0.01 -> 214.02 | Y62: =Y61+0.01 -> 314.02
B63: Создано подразделение по ИБ или задачи возложены на другое подразделение | C63: СУИБ.УР.3 | D63: 5 | E63: 5 | F63: 5 | K63: =IF(ЦУКБ="КБ 1",F63, IF(ЦУКБ="КБ 2",E63,D63)) -> 5 | L63: =VALUE(LEFT(N63,3)) -> 0 | M63: =L63-K63 -> -5 | N63: 0 - нет | P63: =IFERROR(IF($L63>D63,1,$L63/D63),0) -> 0 | Q63: =IFERROR(IF($L63>E63,1,$L63/E63),0) -> 0 | R63: =IFERROR(IF($L63>=F63,1,$L63/F63),0) -> 0 | S63: =S62+0.01 -> 14.03 | T63: =IF(($L63-$F63)>=0,"", " - Определить полномочия для подразделения, ответственное за ИБ (как минимум уровня отдела ИБ). - Подготовить положение о подразделении, обеспечивающим ИБ в Обществе."&" - Создать выделенное подразделение, ответственное за ИБ (как минимум уровня отдела ИБ): - Утвердить приказом по орг. структуре создание подразделения ИБ."&" - Утвердить положение о подразделении, обеспечивающим ИБ в Обществе. - Распоряжением/приказом определили подразделение ИБ, как подразделение Общества, ответственное за обеспечение ИБ") -> - Определить полномочия для подразделения, ответственное за ИБ (как минимум уровня отдела ИБ). - Подготовить положение о подразделении, обеспечивающим ИБ в Обществе. - Создать выделенное подразделение, ответственное за ИБ (как минимум уровня отдела ИБ): - Утвердить приказом по орг. структуре создание подразделения ИБ. - Утвердить положение о подразделении, обеспечивающим ИБ в Обществе. - Распоряжением/приказом определили подразделение ИБ, как подразделение Общества, ответственное за обеспечение ИБ | U63: Утвержденное положение о подразделении ИБ | V63: =V62+0.01 -> 214.03 | Y63: =Y62+0.01 -> 314.03
B64: Определены цели обеспечения ИБ | C64: СУИБ.УР.4 | D64: 5 | E64: 5 | F64: 5 | K64: =IF(ЦУКБ="КБ 1",F64, IF(ЦУКБ="КБ 2",E64,D64)) -> 5 | L64: =VALUE(LEFT(N64,3)) -> 0 | M64: =L64-K64 -> -5 | N64: 0 - нет | P64: =IFERROR(IF($L64>D64,1,$L64/D64),0) -> 0 | Q64: =IFERROR(IF($L64>E64,1,$L64/E64),0) -> 0 | R64: =IFERROR(IF($L64>=F64,1,$L64/F64),0) -> 0 | S64: =S63+0.01 -> 14.04 | T64: =IF(($L64-$F64)>=0,"","- Провести анализ целей Общества в области ИБ и отразить в Политике ИБ, стратегии развития или планах развития") -> - Провести анализ целей Общества в области ИБ и отразить в Политике ИБ, стратегии развития или планах развития | U64: Формализованные цели обеспечения ИБ | V64: =V63+0.01 -> 214.04 | W64: =IF(($L64-$E64)>=0,"", "") | Y64: =Y63+0.01 -> 314.04 | Z64: =IF(($L64-$D64)>=0,""," ")
B65: Наличие планов развития ИБ | C65: СУИБ.УР.5 | D65: 5 | E65: 5 | F65: 5 | K65: =IF(ЦУКБ="КБ 1",F65, IF(ЦУКБ="КБ 2",E65,D65)) -> 5 | L65: =VALUE(LEFT(N65,3)) -> 0 | M65: =L65-K65 -> -5 | N65: 0 - нет | P65: =IFERROR(IF($L65>D65,1,$L65/D65),0) -> 0 | Q65: =IFERROR(IF($L65>E65,1,$L65/E65),0) -> 0 | R65: =IFERROR(IF($L65>=F65,1,$L65/F65),0) -> 0 | S65: =S64+0.01 -> 14.05 | T65: =IF(($L65-$F65)>=0,"", "- Разработать планы развития ИБ или адаптировать типовые планы, предоставленные ПАО Ростелеком") -> - Разработать планы развития ИБ или адаптировать типовые планы, предоставленные ПАО Ростелеком | U65: Формализованные Планы развития ИБ | V65: =V64+0.01 -> 214.05 | W65: =IF(($L65-$E65)>=0,"","") | Y65: =Y64+0.01 -> 314.05 | Z65: =IF(($L65-$D65)>=0,"","")
B66: Статус достижения целей ИБ регулярно доводится до руководства Общества | C66: СУИБ.УР.6 | D66: 5 | E66: 3.2 | F66: 0 | K66: =IF(ЦУКБ="КБ 1",F66, IF(ЦУКБ="КБ 2",E66,D66)) -> 5 | L66: =VALUE(LEFT(N66,3)) -> 0 | M66: =L66-K66 -> -5 | N66: 0 - Не формализовано, не доводится | P66: =IFERROR(IF($L66>D66,1*IF(P64=0,0,1),$L66/D66*IF(P64=0,0,1)),0) -> 0 | Q66: =IFERROR(IF($L66>E66,1*IF(Q64=0,0,1),$L66/E66*IF(Q64=0,0,1)),0) -> 0 | S66: =S65+0.01 -> 14.06 | T66: =IF(($L66-$F66)>=0,"",) | V66: =V65+0.01 -> 214.06 | W66: =IF(($L66-$E66)>=0,""," Сформировать отчет о достижении целей ИБ. Представить отчет руководству Общества") -> Сформировать отчет о достижении целей ИБ. Представить отчет руководству Общества | X66: Копии отчетов о достижении целей ИБ | Y66: =Y65+0.01 -> 314.06 | Z66: =IF(($L66-$D66)>=0,"","Организовать процесс регулярной отчетности перед руководством по достижению целей ИБ") -> Организовать процесс регулярной отчетности перед руководством по достижению целей ИБ | AA66: Справки/аналитические записки, материалы/служебные записки/протоколы заседаний РГ, комиссий и т.д.
B67: Проводится регулярный (ежегодный) внешний аудит | C67: СУИБ.УР.7 | D67: 5 | E67: 5 | F67: 0 | K67: =IF(ЦУКБ="КБ 1",F67, IF(ЦУКБ="КБ 2",E67,D67)) -> 5 | L67: =VALUE(LEFT(N67,3)) -> 0 | M67: =L67-K67 -> -5 | N67: 0 - нет | O67: =IF((СК="Да"),"Совместная зона ответственности ДЗО и Сервисной компании", "") | P67: =IFERROR(IF($L67>D67,1,$L67/D67),0) -> 0 | Q67: =IFERROR(IF($L67>E67,1,$L67/E67),0) -> 0 | S67: =S66+0.01 -> 14.07 | T67: =IF(($L67-$F67)>=0,"",) | V67: =V66+0.01 -> 214.07 | W67: =IF(($L67-$E67)>=0,""," - Определить требования к процессу внешнего аудита - Организовать процесс регулярных внешних аудитов ИБ. - Принимать меры по повышению уровня ИБ по результатам аудита") -> - Определить требования к процессу внешнего аудита - Организовать процесс регулярных внешних аудитов ИБ. - Принимать меры по повышению уровня ИБ по результатам аудита | X67: Формализованный документ, определяющий требования к проведению внешнего аудита ИБ Отчеты\акты\заключения проведенных аудитов | Y67: =Y66+0.01 -> 314.07 | Z67: =IF(($L67-$D67)>=0,""," ")
B68: Проводятся регулярные (ежегодные) киберучения | C68: СУИБ.УР.8 | D68: 5 | E68: 5 | F68: 0 | K68: =IF(ЦУКБ="КБ 1",F68, IF(ЦУКБ="КБ 2",E68,D68)) -> 5 | L68: =VALUE(LEFT(N68,3)) -> 0 | M68: =L68-K68 -> -5 | N68: 0 - нет | O68: =IF((СК="Да"),"Совместная зона ответственности ДЗО и Сервисной компании", "") | P68: =IFERROR(IF($L68>D68,1,$L68/D68),0) -> 0 | Q68: =IFERROR(IF($L68>E68,1,$L68/E68),0) -> 0 | S68: =S67+0.01 -> 14.08 | T68: =IF(($L68-$F68)>=0,"",) | V68: =V67+0.01 -> 214.08 | W68: =IF(($L68-$E68)>=0,""," - Определить требования к процессу киберучений - Организовать процесс регулярных киберучений. - Принимать меры по повышению уровня ИБ по результатам киберучений") -> - Определить требования к процессу киберучений - Организовать процесс регулярных киберучений. - Принимать меры по повышению уровня ИБ по результатам киберучений | X68: Формализованный документ, определяющий требования к проведению киберучений Отчеты\акты\заключения проведенных киберучений | Y68: =Y67+0.01 -> 314.08 | Z68: =IF(($L68-$D68)>=0,"", "")
B69: Требования по ИБ к информационным активам (ИА) предьявляются на стадиях принятия решения о создании/приобретении ИА | C69: СУИБ.УР.9 | D69: 5 | E69: 3.2 | F69: 0 | K69: =IF(ЦУКБ="КБ 1",F69, IF(ЦУКБ="КБ 2",E69,D69)) -> 5 | L69: =VALUE(LEFT(N69,3)) -> 0 | M69: =L69-K69 -> -5 | N69: 0 - Контроль не выполняется | P69: =IFERROR(IF($L69>D69,1,$L69/D69),0) -> 0 | Q69: =IFERROR(IF($L69>E69,1,$L69/E69),0) -> 0 | S69: =S68+0.01 -> 14.09 | T69: =IF(($L69-$F69)>=0,"",) | V69: =V68+0.01 -> 214.09 | W69: =IF(($L69-$E69)>=0,"", "- Организовать процесс создания / приобретения ИА; - Определить требования к процессу; - Обеспечить участие подразделения ИБ в процессе;"&" - Обеспечить формирование требований ИБ на этапе принятия решения о создании/приобретении ИА.") -> - Организовать процесс создания / приобретения ИА; - Определить требования к процессу; - Обеспечить участие подразделения ИБ в процессе; - Обеспечить формирование требований ИБ на этапе принятия решения о создании/приобретении ИА. | X69: Формализованный документ, описывающий процесс создания\приобретения ИА Примеры ТЗ\заявок\ПМИ\иной документации к ИА | Y69: =Y68+0.01 -> 314.09 | Z69: =IF(($L69-$D69)>=0,"", "- Обеспечить формирование, коректировку, согласование, контроль исполнения требований ИБ на каждом этапе жизненного цикла ИА") -> - Обеспечить формирование, коректировку, согласование, контроль исполнения требований ИБ на каждом этапе жизненного цикла ИА | AA69: Примеры ТЗ\заявок\ПМИ\иной документации к ИА
B70: Актуализация внутренних нормативных документов в соответствии с изменениями в нормативно-правовых актах и распоряжениях регуляторов и контрольных (надзорных) ведомств в сфере ИБ | C70: СУИБ.УР.10 | D70: 5 | E70: 5 | F70: 0 | K70: =IF(ЦУКБ="КБ 1",F70, IF(ЦУКБ="КБ 2",E70,D70)) -> 5 | L70: =VALUE(LEFT(N70,3)) -> 0 | M70: =L70-K70 -> -5 | N70: 0 - нет | P70: =IFERROR(IF($L70>D70,1,$L70/D70),0) -> 0 | Q70: =IFERROR(IF($L70>E70,1,$L70/E70),0) -> 0 | S70: =S69+0.01 -> 14.1 | T70: =IF(($L70-$F70)>=0,"",) | V70: =V69+0.01 -> 214.1 | W70: =IF(($L70-$E70)>=0,"", "- Определить ответственных за мониторинг НПА и организовать процесс мониторинга; - Организовать процесс доведения информации до всех заинтересованных подразделений. Реализовать процесс выполнения требований НПА.") -> - Определить ответственных за мониторинг НПА и организовать процесс мониторинга; - Организовать процесс доведения информации до всех заинтересованных подразделений. Реализовать процесс выполнения требований НПА. | X70: Скан-копия должностной инструкции, содержащей пункт о мониторинге НПА либо формализованный документ, определяющий ответственного за мониторинг НПА Листы ознакомления с ВНД в области ИБ | Y70: =Y69+0.01 -> 314.1 | Z70: =IF(($L70-$D70)>=0,"", "")
B71: Управление рисками | C71: УР | M71: =L71-K71 -> 0 | S71: =VLOOKUP(B71,Приоритет!$G$9:$K$52,5,0) -> 41 | T71: УР | V71: =S71+200 -> 241 | W71: УР | Y71: =S71+300 -> 341 | Z71: УР
B72: Определены основные нежелательные события ИБ | C72: УИБ.УР.1 | D72: 5 | E72: 5 | F72: 5 | K72: =IF(ЦУКБ="КБ 1",F72, IF(ЦУКБ="КБ 2",E72,D72)) -> 5 | L72: =VALUE(LEFT(N72,3)) -> 0 | M72: =L72-K72 -> -5 | N72: 0 - нет | P72: =IFERROR(IF($L72>D72,1,$L72/D72),0) -> 0 | Q72: =IFERROR(IF($L72>E72,1,$L72/E72),0) -> 0 | R72: =IFERROR(IF($L72>=F72,1,$L72/F72),0) -> 0 | S72: =S71+0.01 -> 41.01 | T72: =IF(($L72-$F72)>=0,"","- Составить перечень нежелательныхх событий в ИБ. Согласовать перечень с руководством Общества и со всеми заинтересованными подразделениями. Утвердить перечень ") -> - Составить перечень нежелательныхх событий в ИБ. Согласовать перечень с руководством Общества и со всеми заинтересованными подразделениями. Утвердить перечень | U72: Утвержденный перечень нежелательных событий ИБ | V72: =V71+0.01 -> 241.01 | W72: =IF(($L72-$E72)>=0,"","") | Y72: =Y71+0.01 -> 341.01 | Z72: =IF(($L72-$D72)>=0,"","")
B73: Разработана и утверждена Политика управления рисками ИБ | C73: УИБ.УР.2 | D73: 5 | E73: 0 | F73: 0 | K73: =IF(ЦУКБ="КБ 1",F73, IF(ЦУКБ="КБ 2",E73,D73)) -> 5 | L73: =VALUE(LEFT(N73,3)) -> 0 | M73: =L73-K73 -> -5 | N73: 0 - нет | P73: =IFERROR(IF($L73>=D73,1,$L73/D73),0) -> 0 | S73: =S72+0.01 -> 41.02 | T73: =IF(($L73-$F73)>=0,"",) | V73: =V72+0.01 -> 241.02 | W73: =IF(($L73-$E73)>=0,"","") | Y73: =Y72+0.01 -> 341.02 | Z73: =IF(($L73-$D73)>=0,"", "- Разработать или Получить в Блоке ИБ ПАО Ростелеком типовую политику управления рисками; - Утвердить в Обществе политику управления рисками") -> - Разработать или Получить в Блоке ИБ ПАО Ростелеком типовую политику управления рисками; - Утвердить в Обществе политику управления рисками | AA73: Утвержденная Политика управления рисками ИБ
B74: Риски определены качественно | C74: УИБ.УР.3 | D74: 5 | E74: 5 | F74: 0 | K74: =IF(ЦУКБ="КБ 1",F74, IF(ЦУКБ="КБ 2",E74,D74)) -> 5 | L74: =VALUE(LEFT(N74,3)) -> 0 | M74: =L74-K74 -> -5 | N74: 0 - нет | P74: =IFERROR(IF($L74>D74,1,$L74/D74),0) -> 0 | Q74: =IFERROR(IF($L74>=E74,1,$L74/E74),0) -> 0 | S74: =S73+0.01 -> 41.03 | T74: =IF(($L74-$F74)>=0,"") | V74: =V73+0.01 -> 241.03 | W74: =IF(($L74-$E74)>=0,"","- Реализовать процесс качественной оценки рисков ИБ на основе экспертной оценки") -> - Реализовать процесс качественной оценки рисков ИБ на основе экспертной оценки | X74: Документы, подтверждающие процедуру качественной оценки рисков ИБ | Y74: =Y73+0.01 -> 341.03 | Z74: =IF(($L74-$D74)>=0,"","")
B75: Внедрен процесс количественной оценки рисков ИБ | C75: УИБ.УР.4 | D75: 4 | E75: 0 | F75: 0 | K75: =IF(ЦУКБ="КБ 1",F75, IF(ЦУКБ="КБ 2",E75,D75)) -> 4 | L75: =VALUE(LEFT(N75,3)) -> 0 | M75: =L75-K75 -> -4 | N75: 0 - Процесс отсутствует | P75: =IFERROR(IF($L75>D75,1,$L75/D75),0) -> 0 | S75: =S74+0.01 -> 41.04 | T75: =IF(($L75-$F75)>=0,"",) | V75: =V74+0.01 -> 241.04 | W75: =IF(($L75-$E75)>=0,"","") | Y75: =Y74+0.01 -> 341.04 | Z75: =IF(($L75-$D75)>=0,"", "- Разработать и утвердить методику количественной оценки рисков ИБ; - Реализовать процесс количественной оценки рисков ИБ на основе методологии ПАО Ростелеком - Автоматизировать систему оценки рисков ИБ"&" - разработаны и внедрены ключевые индикаторы риска (КИР), - организован мониторинг значений КИР, определены процедуры при выходе КИР в красную зону") -> - Разработать и утвердить методику количественной оценки рисков ИБ; - Реализовать процесс количественной оценки рисков ИБ на основе методологии ПАО Ростелеком - Автоматизировать систему оценки рисков ИБ - разработаны и внедрены ключевые индикаторы риска (КИР), - организован мониторинг значений КИР, определены процедуры при выходе КИР в красную зону | AA75: Формализованный документ, определяющий методику количественной оценки рисков ИБ Скрин-шот из автоматизированной системы оценки рисков ИБ Утвержденные ключевые индикаторы риска Скрин-шоты метрик процесса
B76: Процесс оценки рисков ИБ интегрирован в общую систему управления рисками Общества | C76: УИБ.УР.5 | D76: 5 | E76: 0 | F76: 0 | K76: =IF(ЦУКБ="КБ 1",F76, IF(ЦУКБ="КБ 2",E76,D76)) -> 5 | L76: =VALUE(LEFT(N76,3)) -> 0 | M76: =L76-K76 -> -5 | N76: 0 - нет | P76: =IFERROR(IF($L76>D76,1,$L76/D76),0) -> 0 | S76: =S75+0.01 -> 41.05 | T76: =IF(($L76-$F76)>=0,"",) | V76: =V75+0.01 -> 241.05 | W76: =IF(($L76-$E76)>=0,"","") | Y76: =Y75+0.01 -> 341.05 | Z76: =IF(($L76-$D76)>=0,"", "-Интегрировать риски ИБ в общую систему управления рисками Общества") -> -Интегрировать риски ИБ в общую систему управления рисками Общества | AA76: Формализованный документ, регламентирующий управление рисками
B77: Процессы | C77: ПР | M77: =L77-K77 -> 0 | S77: =VLOOKUP(B77,Приоритет!$G$9:$K$52,5,0) -> 28 | T77: ПР | V77: =S77+200 -> 228 | W77: ПР | Y77: =S77+300 -> 328 | Z77: ПР
B78: =СЗИ!B88 -> Внедрен процесс управления уязвимостями | C78: =СЗИ!C88 -> СЗИ.САЗ.3 | D78: =СЗИ!D88 -> 4 | E78: =СЗИ!E88 -> 3 | F78: =СЗИ!F88 -> 0 | G78: =СЗИ!G88 -> 0 | H78: =СЗИ!H88 -> 0 | I78: =СЗИ!I88 -> 0 | ... L78: =СЗИ!L88 -> 0 | S78: =S77+0.01 -> 28.01 | T78: =СЗИ!T88 | V78: =V77+0.01 -> 228.01 | W78: =СЗИ!W88 -> - Разработать или Получить в Блоке ИБ ПАО Ростелеком типовое описание процесса управления уязвимостями; - Реализовать процесс управления уязвимостями; - Обеспечить устранение или митигацию всех выявленных уязвимостей; - Обеспечить устранение уязвимостей критичного уровня в срок не более 3 рабочих дней при их обнаружении. | Y78: =Y77+0.01 -> 328.01 | Z78: =СЗИ!Z88 -> - Автоматизировать процесс управления уязвимостями. Обеспечить устранение уязвимостей критичного уровня в срок не более 24 часов, высокого уровня в срок не более 72 часов; - Разработать систему метрик для процесса управления уязвимостями; - Создать средство визуального мониторинга параметров процесса управления уязвимостями; - Реализовать мониторинг параметров процесса управления уязвимостями; - Реализовать реагирование на факты отклонения параметров процесса управления уязвимостями от определенных показателей.
B79: =СЗИ!B62 -> Внедрен процесс управления уязвимостями на периметре (CPT) | C79: =СЗИ!C62 -> СЗИ.CPT.3 | D79: =СЗИ!D62 -> 4 | E79: =СЗИ!E62 -> 3 | F79: =СЗИ!F62 -> 1 | G79: =СЗИ!G62 -> 0 | H79: =СЗИ!H62 -> 0 | I79: =СЗИ!I62 -> 0 | ... L79: =СЗИ!L62 -> 0 | S79: =S78+0.01 -> 28.02 | T79: =СЗИ!T62 -> - Уязвимости High и Critical устраняются | V79: =V78+0.01 -> 228.02 | W79: =СЗИ!W62 -> Разработать или Получить в Блоке ИБ ПАО Ростелеком типовое описание процесса контроля уязвимостей - Реализовать в Обществе процесс управления уязвимостями на периметре. - Автоматизировать процесс управления выявленными уязвимостями (учет, информирование, контроль устранения). | Y79: =Y78+0.01 -> 328.02 | Z79: =СЗИ!Z62 -> - Разработать систему метрик для процесса CPT; - Создать средство визуального мониторинга параметров процесса CPT; - Реализовать мониторинг параметров процесса CPT; - Реализовать реагирование на факты отклонения параметров процесса CPT
B80: =Мониторинг!B62 -> Процесс анализа информации о киберугрозах | C80: =Мониторинг!C62 -> МНТ.ПР.1 | D80: =Мониторинг!D62 -> 4 | E80: =Мониторинг!E62 -> 1 | F80: =Мониторинг!F62 -> 0 | G80: =Мониторинг!G62 -> 0 | H80: =Мониторинг!H62 -> 0 | I80: =Мониторинг!I62 -> 0 | ... L80: =Мониторинг!L62 -> 0 | S80: =S79+0.01 -> 28.03 | T80: =Мониторинг!T62 | V80: =V79+0.01 -> 228.03 | W80: =Мониторинг!W62 -> - Организовать процесс анализа информации об угрозах, направленой РТК, ФСТЭК и НКЦКИ. Выполнять проверку применимости угроз и мер защиты в Обществе. Выполнять рекомендуемые меры. | Y80: =Y79+0.01 -> 328.03 | Z80: =Мониторинг!Z62 -> - Организовать получение данных от поставщиков информации об угрозах и из открытых источников. Реализовать процесс анализа угроз и защиты от релевантных угроз.
B81: =Мониторинг!B63 -> Процесс мониторинга событий ИБ | C81: =Мониторинг!C63 -> МНТ.ПР.2 | D81: =Мониторинг!D63 -> 4 | E81: =Мониторинг!E63 -> 4 | F81: =Мониторинг!F63 -> 0 | G81: =Мониторинг!G63 -> 0 | H81: =Мониторинг!H63 -> 0 | I81: =Мониторинг!I63 -> 0 | ... L81: =Мониторинг!L63 -> 0 | S81: =S80+0.01 -> 28.04 | T81: =Мониторинг!T63 | V81: =V80+0.01 -> 228.04 | W81: =Мониторинг!W63 -> - Регламентировать процесс мониторинга событий ИБ, определить критерии определения и классификации инцидентов, Определить порядок инициации реагирования на инцидент. | Y81: =Y80+0.01 -> 328.04 | Z81: =Мониторинг!Z63
B82: =Реагирование!B40 -> Процесс категорирования инцидентов ИБ | C82: =Реагирование!C40 -> РЕАГ.ПЛР.2 | D82: =Реагирование!D40 -> 4 | E82: =Реагирование!E40 -> 3 | F82: =Реагирование!F40 -> 1 | G82: =Реагирование!G40 -> 0 | H82: =Реагирование!H40 -> 0 | I82: =Реагирование!I40 -> 0 | ... L82: =Реагирование!L40 -> 0 | S82: =S81+0.01 -> 28.05 | T82: =Реагирование!T40 -> - В Обществе неформально определить категории инцидентов ИБ | V82: =V81+0.01 -> 228.05 | W82: =Реагирование!W40 -> - Формализовать критерии определения критичности инцидентов ИБ; - Определить мандаты на действия участников процесса; - Официально сформировать ГЭР и ОКУ; - Не реже 1 раза в год проводить учения в формате штабных игр. | Y82: =Y81+0.01 -> 328.05 | Z82: =Реагирование!Z40 -> - Реализовать возможность корректировки категорий инцидента ИБ в процессе реагирования
B83: =Реагирование!B51 -> Процесс расследования инцидентов | C83: =Реагирование!C51 -> РЕАГ.АНЛЗ.2 | D83: =Реагирование!D51 -> 4 | E83: =Реагирование!E51 -> 3 | F83: =Реагирование!F51 -> 1 | G83: =Реагирование!G51 -> 0 | H83: =Реагирование!H51 -> 0 | I83: =Реагирование!I51 -> 0 | ... L83: =Реагирование!L51 -> 0 | S83: =S82+0.01 -> 28.06 | T83: =Реагирование!T51 -> - Проводить расследование инцидентов информационной безопасности - Результаты расследований должны быть задокументированы | V83: =V82+0.01 -> 228.06 | W83: =Реагирование!W51 -> - Разработать и задокументировать процесс расследования инцидентов, довести до сведения заинтересованных лиц; - Расследование инцидентов должно проводиться с использованием средств автоматизации; - Создать единую базу знаний по расследованиям. Результаты расследований и артефакты хранить в единой базе знаний. | Y83: =Y82+0.01 -> 328.06 | Z83: =Реагирование!Z51 -> - Определить метрики процесса реагирования на инциденты и расследования; - На постоянной основе проводить мониторинг процесса по утвержденным метрикам и показателям; - Интегрировать процесс расследования инцидентов в единый процесс управления инцидентами ИБ
B84: =Реагирование!B47 -> Определен порядок взаимодействия с регуляторами по инцидентам ИБ | C84: =Реагирование!C47 -> РЕАГ.КМНК.4 | D84: =Реагирование!D47 -> 5 | E84: =Реагирование!E47 -> 3.2 | F84: =Реагирование!F47 -> 1.6 | G84: =Реагирование!G47 -> 0 | H84: =Реагирование!H47 -> 0 | I84: =Реагирование!I47 -> 0 | ... L84: =Реагирование!L47 -> 0 | S84: =S83+0.01 -> 28.07 | T84: =Реагирование!T47 -> - Взаимодействовать с регуляторами по инциденту ИБ в установленных законом случаях | V84: =V83+0.01 -> 228.07 | W84: =Реагирование!W47 -> - Регламентировать процесс взаимодействия с регуляторами; - Определить ответственных за взаимодействие; - Определить состав и объем предоставляемой информации об инцидентах. | Y84: =Y83+0.01 -> 328.07 | Z84: =Реагирование!Z47 -> - Регламентировать процесс взаимодействия с регуляторами; - Определить ответственных за взаимодействие; - Определить состав и объем предоставляемой информации об инцидентах.
B85: =Реагирование!B39 -> Процесс реагирования на инциденты ИБ | C85: =Реагирование!C39 -> РЕАГ.ПЛР.1 | D85: =Реагирование!D39 -> 4 | E85: =Реагирование!E39 -> 3 | F85: =Реагирование!F39 -> 1 | G85: =Реагирование!G39 -> 0 | H85: =Реагирование!H39 -> 0 | I85: =Реагирование!I39 -> 0 | ... L85: =Реагирование!L39 -> 0 | S85: =S84+0.01 -> 28.08 | T85: =Реагирование!T39 -> - Определить ответственных за решение инцидентов ИБ, включая ответственного за коммуникации внутри и со сторонними компаниями; - Составить и актуализировать список заинтересованных лиц, которые должны получить уведомление об инциденте; - Для критичных инцидентов определить SLA и порядок действий по реагированию; | V85: =V84+0.01 -> 228.08 | W85: =Реагирование!W39 -> Разработать и/или Получить в Блоке ИБ ПАО Ростелеком типовое описание процесса реагирования на инциденты ИБ (Политика, Регламенты, процедуры реагирования на инциденты ИБ), определяющие: - Ответственность за координацию процесса работы с инцидентами и документирование результатов в процессе решения инцидента; - Список заинтересованных лиц, которые должны получить уведомление об инциденте, актуализиировать и пересматривать его не реже раза в год; - SLA по реагированию, механизмы обращения, минимальная информация для создания инцидента/Процедуру довести до всех работников Общества; - Роли и обязанности, план коммуникации по поводу инцидента; - План реагирования на инциденты, включая сценарии реагирования с привлечением юристов, специалистов по ИТ и ИБ, служб PR, HR и аналитиков; - Учебные сценарии по реагированию, включающие взаимодействие заинтересованных лиц и позволяющие тестировать постановку задач, процессы коммуникации и принятия решений; - Сценарии реагирования для разных событий безопасности: подозрительной активности, обнаруженной уязвимости, утечки информации; Для автоматизации процесса внедрить специализированное ПО: SIEM, IRP/ServiceDesk. | Y85: =Y84+0.01 -> 328.08 | Z85: =Реагирование!Z39 -> - Разработать КПЭ по процессу реагирования на инциденты ИБ для руководства ИБ; - Разработать метрики по процессу; - Назначить сервис-менеджеров процесса; - Создать средство визуального мониторинга параметров процесса; - Реализовать мониторинг параметров процесса; - Реализовать реагирование на факты отклонения параметров процесса от определенных показателей
B86: =Реагирование!B53 -> Процесс пост-анализа инцидентов | C86: =Реагирование!C53 -> РЕАГ.АНЛЗ.4 | D86: =Реагирование!D53 -> 4 | E86: =Реагирование!E53 -> 3 | F86: =Реагирование!F53 -> 1 | G86: =Реагирование!G53 -> 0 | H86: =Реагирование!H53 -> 0 | I86: =Реагирование!I53 -> 0 | ... L86: =Реагирование!L53 -> 0 | S86: =S85+0.01 -> 28.09 | T86: =Реагирование!T53 -> Проводится анализ критичных инцидентов ИБ на ИС классов MissionCritical и BusinesCritical в режиме рабочих встреч с подразделениями ИТ, с составлением протоколов, содержащих первоочередные меры митигации | V86: =V85+0.01 -> 228.09 | W86: =Реагирование!W53 -> - Формализовать и утвердить процесс пост-анализа инцидентов ИБ; - Довести процесс до заинтересованных лиц; - Обеспечить проведение пост-анализа инцидентов ИБ с применением средств автоматизации; - Создать единую базу знаний инцидентов ИБ; - Проводить оценку и анализ инцидентов ИБ; - По результатам расследования инцидентов разрабатывать рекомендации по устранению выявленных уязвимостей и предотвращению аналогичных инцидентов в будущем; - Разрабатывать рекомендации по улучшению применяемых методов и средств защиты информации - Повышать эффективность решающих правил SIEM с учетом инцидентов | Y86: =Y85+0.01 -> 328.09 | Z86: =Реагирование!Z53 -> - Обеспечить контроль за выполнением рекомендаций и оценку эффективности выполненных мероприятий; - На постоянной основе проводить мониторинг процесса по утвержденным метрикам и показателям; - Назначить ответственных за соблюдением сроков проведения утвержденных мероприятий.
B87: =Мониторинг!B64 -> Процесс создания решающих правил | C87: =Мониторинг!C64 -> МНТ.ПР.3 | D87: =Мониторинг!D64 -> 4 | E87: =Мониторинг!E64 -> 3 | F87: =Мониторинг!F64 -> 0 | G87: =Мониторинг!G64 -> 0 | H87: =Мониторинг!H64 -> 0 | I87: =Мониторинг!I64 -> 0 | ... L87: =Мониторинг!L64 -> 0 | S87: =S86+0.01 -> 28.1 | T87: =Мониторинг!T64 | V87: =V86+0.01 -> 228.1 | W87: =Мониторинг!W64 -> - Получить типовые решающие правила SIEM от разработчика SIEM и из других доступных источников. Адаптировать решающие правила для применения в инфрастурктуре организации. | Y87: =Y86+0.01 -> 328.1 | Z87: =Мониторинг!Z64 -> - Организовать процесс разработки решающих правил; - Создать базу знаний или инструкции по разработке решающих правил; - Составить план разработки решающих правил; - Организовать процесс анализа журналов событий для разработки решающих правил SIEM; - Применить результаты расследования инцидентов для разработки решающих правил.
B88: =Мониторинг!B65 -> Процесс подключения источников информации | C88: =Мониторинг!C65 -> МНТ.ПР.4 | D88: =Мониторинг!D65 -> 4 | E88: =Мониторинг!E65 -> 2 | F88: =Мониторинг!F65 -> 0 | G88: =Мониторинг!G65 -> 0 | H88: =Мониторинг!H65 -> 0 | I88: =Мониторинг!I65 -> 0 | ... L88: =Мониторинг!L65 -> 0 | S88: =S87+0.01 -> 28.11 | T88: =Мониторинг!T65 | V88: =V87+0.01 -> 228.11 | W88: =Мониторинг!W65 -> - Провести инвентаризацию источников событий и подключить их к SIEM | Y88: =Y87+0.01 -> 328.11 | Z88: =Мониторинг!Z65 -> - Регламентировать порядок подключения источников информации к SIEM; - Определить требования по обязательному подключению; - Реализовать процесс подключения источников, с инвентаризацией и контролем неподключенных источников; - Установить SLA по подключению.
B89: =Мониторинг!B66 -> Процесс контроля источников информации | C89: =Мониторинг!C66 -> МНТ.ПР.5 | D89: =Мониторинг!D66 -> 4 | E89: =Мониторинг!E66 -> 3 | F89: =Мониторинг!F66 -> 0 | G89: =Мониторинг!G66 -> 0 | H89: =Мониторинг!H66 -> 0 | I89: =Мониторинг!I66 -> 0 | ... L89: =Мониторинг!L66 -> 0 | S89: =S88+0.01 -> 28.12 | T89: =Мониторинг!T66 | V89: =V88+0.01 -> 228.12 | W89: =Мониторинг!W66 -> - Регламентировать процесс контроля источников | Y89: =Y88+0.01 -> 328.12 | Z89: =Мониторинг!Z66 -> - Проводить аудит ИС для выявления неподключенных к SIEM источников; - Проверять, что источники подключены и успешно передают события.
B90: =Мониторинг!B57 -> Внедрен процесс управления сбоями и мониторинга работоспособности SIEM | C90: =Мониторинг!C57 -> МНТ.SIEM.12 | D90: =Мониторинг!D57 -> 4 | E90: =Мониторинг!E57 -> 3 | F90: =Мониторинг!F57 -> 0 | G90: =Мониторинг!G57 -> 0 | H90: =Мониторинг!H57 -> 0 | I90: =Мониторинг!I57 -> 0 | ... L90: =Мониторинг!L57 -> 0 | S90: =S89+0.01 -> 28.13 | T90: =Мониторинг!T57 | V90: =V89+0.01 -> 228.13 | W90: =Мониторинг!W57 -> - Организовать контроль непрерывности мониторинга; - Обеспечить восстановление мониторинга при сбоях в срок не более чем 6 часов; - Обеспечить сохранность данных об инцидентах в случае сбоев; | Y90: =Y89+0.01 -> 328.13 | Z90: =Мониторинг!Z57 -> - Обеспечить переключение источников событий на резервный SIEM в случае сбоев. - Обеспечить визуализация мониторинга работоспособности SIEM
B91: Процесс эскалации инцидентов | C91: =Реагирование!C46 -> РЕАГ.КМНК.3 | D91: =Реагирование!D46 -> 5 | E91: =Реагирование!E46 -> 3.2 | F91: =Реагирование!F46 -> 0 | G91: =Реагирование!G46 -> 0 | H91: =Реагирование!H46 -> 0 | I91: =Реагирование!I46 -> 0 | J91: =Реагирование!J46 -> 0 | ... L91: =Реагирование!L46 -> 0 | S91: =S90+0.01 -> 28.14 | T91: =Реагирование!T46 | V91: =V90+0.01 -> 228.14 | W91: =Реагирование!W46 -> - Определить критерии и порядок эскалации инцидентов; - Определить маршруты эскалации; - Регламентировать процесс эскалации. | Y91: =Y90+0.01 -> 328.14 | Z91: =Реагирование!Z46 -> - Контролировать и оценивать эффективность процесса реагирования на инциденты при эскалациях.
B92: Количественная оценка рисков | C92: ='Управление ИБ'!C75 -> УИБ.УР.4 | D92: ='Управление ИБ'!D75 -> 4 | E92: ='Управление ИБ'!E75 -> 0 | F92: ='Управление ИБ'!F75 -> 0 | G92: ='Управление ИБ'!G75 -> 0 | H92: ='Управление ИБ'!H75 -> 0 | I92: ='Управление ИБ'!I75 -> 0 | J92: ='Управление ИБ'!J75 -> 0 | ... L92: ='Управление ИБ'!L75 -> 0 | S92: =S91+0.01 -> 28.15 | T92: =T75 | V92: =V91+0.01 -> 228.15 | W92: =W75 | Y92: =Y91+0.01 -> 328.15 | Z92: =Z75 -> - Разработать и утвердить методику количественной оценки рисков ИБ; - Реализовать процесс количественной оценки рисков ИБ на основе методологии ПАО Ростелеком - Автоматизировать систему оценки рисков ИБ - разработаны и внедрены ключевые индикаторы риска (КИР), - организован мониторинг значений КИР, определены процедуры при выходе КИР в красную зону
B93: ='Управление ИБ'!B104 -> Осуществляется контроль изменений конфигураций оборудования (АРМ, Серверы, Активное сетевое оборудование) | C93: ='Управление ИБ'!C104 -> УИБ.УА.5 | D93: ='Управление ИБ'!D104 -> 5 | E93: ='Управление ИБ'!E104 -> 3.2 | F93: ='Управление ИБ'!F104 -> 0 | G93: ='Управление ИБ'!G104 -> 0 | H93: ='Управление ИБ'!H104 -> 0 | I93: ='Управление ИБ'!I104 -> 0 | ... L93: ='Управление ИБ'!L104 -> 0 | S93: =S92+0.01 -> 28.16 | T93: =T104 | V93: =V92+0.01 -> 228.16 | W93: =W104 -> Определить порядок управления конфигурациями оборудования; Осуществлять автоматизированный контроль конфигураций активного сетевого оборудования и серверов | Y93: =Y92+0.01 -> 328.16 | Z93: =Z104 -> Осуществлять автоматизированный контроль конфигураций активного сетевого оборудования, серверов и конечных устройств; - Отслеживать события изменения конфигурации.
B94: =B101 -> Внедрен процесс инвентаризации и категорирования информационных активов | C94: =C101 -> УИБ.УА.2 | D94: =D101 -> 4 | E94: =E101 -> 3 | F94: =F101 -> 1 | G94: =G101 -> 0 | H94: =H101 -> 0 | I94: =I101 -> 0 | ... L94: =L101 -> 0 | S94: =S93+0.01 -> 28.17 | T94: =T101 -> - Ведется реестр информационных активов с определением уровней критичности | V94: =V93+0.01 -> 228.17 | W94: =W101 -> - Разработать формализованный докумет, устанавливающий критерии категорирования ИА на основании законодательства и внутренних требований; - Сформировать требования к обеспечению ИБ на основе категорий ИА - Провести категорирование всех ИА; - учет и инвентаризацию ИА проводить с использованием средств автоматизации | Y94: =Y93+0.01 -> 328.17 | Z94: =Z101 -> Разработаны и внедрены метрики процесса инвентаризации и категорирования ИА.
B95: =СЗИ!B51 -> Процесс контроля работоспособности САВЗ | C95: =СЗИ!C51 -> СЗИ.ВПО.6 | D95: =СЗИ!D51 -> 4 | E95: =СЗИ!E51 -> 3 | F95: =СЗИ!F51 -> 2 | G95: =СЗИ!G51 -> 0 | H95: =СЗИ!H51 -> 0 | I95: =СЗИ!I51 -> 0 | ... L95: =СЗИ!L51 -> 0 | S95: =S94+0.01 -> 28.18 | T95: =СЗИ!T51 -> - Разработать или Получить в Блоке ИБ ПАО Ростелеком типовое описание процесса контроля рабоспособности средств АВЗ _x000D_- Утвердить в Обществе ВНД, описывающий процесс контроля рабоспособности средств АВЗ | V95: =V94+0.01 -> 228.18 | W95: =СЗИ!W51 -> - Реализовать в Обществе процесс контроля рабоспособности средств АВЗ | Y95: =Y94+0.01 -> 328.18 | Z95: =СЗИ!Z51 -> - Разработать систему метрик для процесса контроля рабоспособности средств АВЗ _x000D_- Создать средство визуального мониторинга параметров процесса контроля работоспособности средств АВЗ _x000D_- Реализовать мониторинг параметров процесса контроля работоспособности средств АВЗ _x000D_- Реализовать реагирование на факты отклонения параметров процесса контроля работоспособности средств АВЗ от определенных показателей
B96: =СЗИ!B52 -> Процесс обновления антивирусных средств | C96: =СЗИ!C52 -> СЗИ.ВПО.7 | D96: =СЗИ!D52 -> 4 | E96: =СЗИ!E52 -> 3 | F96: =СЗИ!F52 -> 2 | G96: =СЗИ!G52 -> 0 | H96: =СЗИ!H52 -> 0 | I96: =СЗИ!I52 -> 0 | ... L96: =СЗИ!L52 -> 0 | S96: =S95+0.01 -> 28.19 | T96: =СЗИ!T52 -> - Разработать или Получить в Блоке ИБ ПАО Ростелеком типовое описание процесса обновления средств АВЗ _x000D_- Утвердить в Обществе ВНД, описывающий процесс обновления средств АВЗ | V96: =V95+0.01 -> 228.19 | W96: =СЗИ!W52 -> - Реализовать в Обществе процесс обновления средств АВЗ | Y96: =Y95+0.01 -> 328.19 | Z96: =СЗИ!Z52 -> - Разработать систему метрик для процесса обновления средств АВЗ _x000D_- Создать средство визуального мониторинга параметров процесса обновления средств АВЗ _x000D_- Реализовать мониторинг параметров процесса обновления средств АВЗ _x000D_- Реализовать реагирование на факты отклонения параметров процесса обновления средств АВЗ от определенных показателей
B97: =СЗИ!B53 -> Процесс реагирования на события САВЗ | C97: =СЗИ!C53 -> СЗИ.ВПО.8 | D97: =СЗИ!D53 -> 4 | E97: =СЗИ!E53 -> 3 | F97: =СЗИ!F53 -> 2 | G97: =СЗИ!G53 -> 0 | H97: =СЗИ!H53 -> 0 | I97: =СЗИ!I53 -> 0 | ... L97: =СЗИ!L53 -> 0 | S97: =S96+0.01 -> 28.2 | T97: =СЗИ!T53 -> - Разработать или Получить в Блоке ИБ ПАО Ростелеком типовое описание процесса реагирования на события средств АВЗ _x000D_- Утвердить в Обществе ВНД, описывающий процесс реагирования на события средств АВЗ | V97: =V96+0.01 -> 228.2 | W97: =СЗИ!W53 -> - Реализовать в Обществе процесс реагирования на события средств АВЗ | Y97: =Y96+0.01 -> 328.2 | Z97: =СЗИ!Z53 -> - Разработать систему метрик для процесса реагирования на события средств АВЗ _x000D_- Создать средство визуального мониторинга параметров процесса реагирования на события средств АВЗ _x000D_- Реализовать мониторинг параметров процесса реагирования на события средств АВЗ _x000D_- Реализовать реагирование на факты отклонения параметров процесса реагирования на события средств АВЗ от определенных показателей
B98: Процедура публикации внешних ресурсов | C98: =СЗИ!C102 -> СЗИ.WAF.2 | D98: =СЗИ!D102 -> 4 | E98: =СЗИ!E102 -> 3 | F98: =СЗИ!F102 -> 1 | G98: =СЗИ!G102 -> 0 | H98: =СЗИ!H102 -> 0 | I98: =СЗИ!I102 -> 0 | J98: =СЗИ!J102 -> 0 | ... L98: =СЗИ!L102 -> 0 | S98: =S97+0.01 -> 28.21 | T98: =СЗИ!T102 | V98: =V97+0.01 -> 228.21 | W98: =СЗИ!W102 | Y98: =Y97+0.01 -> 328.21 | Z98: =СЗИ!Z102
B99: Управление активами | C99: УА | S99: =VLOOKUP(B99,Приоритет!$G$9:$K$48,5,0) -> 29 | T99: УА | V99: =S99+200 -> 229 | W99: УА | Y99: =S99+300 -> 329 | Z99: УА
B100: Информационные системы Общества соотнесены с ИТ-инфраструктурой, на которой они функциониуют, а также с информационными ресурсами, относящимися к данным ИС | C100: УИБ.УА.1 | D100: 5 | E100: 3.2 | F100: 1.6 | K100: =IF(ЦУКБ="КБ 1",F100, IF(ЦУКБ="КБ 2",E100,D100)) -> 5 | L100: =IF((СК="Да"), D100, VALUE(LEFT(N100,3))) -> 0 | M100: =L100-K100 -> -5 | N100: 0 - Контроль не выполняется | O100: =IF((СК="Да"),"Зона ответственности Сервисной компании", "") | P100: =IFERROR(IF($L100>D100,1,$L100/D100),0) -> 0 | Q100: =IFERROR(IF($L100>E100,1,$L100/E100),0) -> 0 | R100: =IFERROR(IF($L100>=F100,1,$L100/F100),0) -> 0 | S100: =S99+0.01 -> 29.01 | T100: =IF(($L100-$F100)>=0,"", " - Выполнить инвентаризацию ИС и информационных ресурсов. - Установить принадлежность ресурсов к ИС - Установить принадлежность ИС к инфраструктуре") -> - Выполнить инвентаризацию ИС и информационных ресурсов. - Установить принадлежность ресурсов к ИС - Установить принадлежность ИС к инфраструктуре | U100: Копия\выгрузка реестра инвентаризации | V100: =V99+0.01 -> 229.01 | W100: =IF(($L100-$E100)>=0,""," - Автоматизировать учет ИС и информационных ресурсов и сформировать единую базу данных.") -> - Автоматизировать учет ИС и информационных ресурсов и сформировать единую базу данных. | X100: Скрин-шот\выгрузка из средств автоматизации | Y100: =Y99+0.01 -> 329.01 | Z100: =IF(($L100-$D100)>=0,"", " - Обеспечить непрерывный учет и актуальность данных об ИС и их ресурсах.") -> - Обеспечить непрерывный учет и актуальность данных об ИС и их ресурсах. | AA100: Скрин-шот\выгрузка из средств автоматизации
B101: Внедрен процесс инвентаризации и категорирования информационных активов | C101: УИБ.УА.2 | D101: 4 | E101: 3 | F101: 1 | K101: =IF(ЦУКБ="КБ 1",F101, IF(ЦУКБ="КБ 2",E101,D101)) -> 4 | L101: =IF((СК="Да"), F101, VALUE(LEFT(N101,3))) -> 0 | M101: =L101-K101 -> -4 | N101: 0 - Процесс отсутствует | P101: =IFERROR(IF($L101>D101,1,$L101/D101),0) -> 0 | Q101: =IFERROR(IF($L101>E101,1,$L101/E101),0) -> 0 | R101: =IFERROR(IF($L101>=F101,1,$L101/F101),0) -> 0 | S101: =S100+0.01 -> 29.02 | T101: =IF(($L101-$F101)>=0,"", "- Ведется реестр информационных активов с определением уровней критичности ") -> - Ведется реестр информационных активов с определением уровней критичности | U101: Скриншот\выгрузка реестра информационных активов | V101: =V100+0.01 -> 229.02 | W101: =IF(($L101-$E101)>=0,"", " - Разработать формализованный докумет, устанавливающий критерии категорирования ИА на основании законодательства и внутренних требований; - Сформировать требования к обеспечению ИБ на основе категорий ИА"&" - Провести категорирование всех ИА; - учет и инвентаризацию ИА проводить с использованием средств автоматизации") -> - Разработать формализованный докумет, устанавливающий критерии категорирования ИА на основании законодательства и внутренних требований; - Сформировать требования к обеспечению ИБ на основе категорий ИА - Провести категорирование всех ИА; - учет и инвентаризацию ИА проводить с использованием средств автоматизации | X101: Формалиованный документ, устанавливающий критерии категорирования ИА; Скриншот\выгрузка из средств автоматизации | Y101: =Y100+0.01 -> 329.02 | Z101: =IF(($L101-$D101)>=0,"", " Разработаны и внедрены метрики процесса инвентаризации и категорирования ИА.") -> Разработаны и внедрены метрики процесса инвентаризации и категорирования ИА. | AA101: Скриншот\выгрузка метрик
B102: Описаны все сетевые взаимодействия между компонентами инфраструктуры и информационными системами | C102: УИБ.УА.3 | D102: 5 | E102: 3.2 | F102: 0 | K102: =IF(ЦУКБ="КБ 1",F102, IF(ЦУКБ="КБ 2",E102,D102)) -> 5 | L102: =IF((СК="Да"), D102, VALUE(LEFT(N102,3))) -> 0 | M102: =L102-K102 -> -5 | N102: 0 - Контроль не выполняется | O102: =IF((СК="Да"),"Зона ответственности Сервисной компании", "") | P102: =IFERROR(IF($L102>D102,1,$L102/D102),0) -> 0 | Q102: =IFERROR(IF($L102>E102,1,$L102/E102),0) -> 0 | S102: =S101+0.01 -> 29.03 | T102: =IF(($L102-$F102)>=0,"",) | V102: =V101+0.01 -> 229.03 | W102: =IF(($L102-$E102)>=0,"", " - Регламентировать порядок описания сетевых взаимодействий;"&" - Документировать перечень разрешенных сетевых взаимодействий для компонентов инфраструктуры и не менее чем для 30% ИС;"&" - По результатам документирования привести в соответствие правила межсетевых экранов.") -> - Регламентировать порядок описания сетевых взаимодействий; - Документировать перечень разрешенных сетевых взаимодействий для компонентов инфраструктуры и не менее чем для 30% ИС; - По результатам документирования привести в соответствие правила межсетевых экранов. | X102: Формализованный документ, определяющий правила сетевых взаимодействий между компонентами инфраструктуры и ИС Сетевые схемы взаимодействия Выгрузка правил сетевого оборудования | Y102: =Y101+0.01 -> 329.03 | Z102: =IF(($L102-$D102)>=0,"", " - Документировать перечень разрешенных сетевых взаимодействий для всех ИС;"&" - Документировать конфигурацию сети (состав сетевых сегментов, сетевые маршруты, правила межсетевых экранов);"&" - Для каждого сетевого правила определить владельца и врям жизни - Регламентировать и реализовать процесс согласования и изменения конфигурации сети.") -> - Документировать перечень разрешенных сетевых взаимодействий для всех ИС; - Документировать конфигурацию сети (состав сетевых сегментов, сетевые маршруты, правила межсетевых экранов); - Для каждого сетевого правила определить владельца и врям жизни - Регламентировать и реализовать процесс согласования и изменения конфигурации сети. | AA102: Формализованный документ, определяющий правила сетевых взаимодействий между компонентами инфраструктуры и ИС Формализованный документ, регламентирующий процесс согласования и изменения конфигурации сети Сетевые схемы взаимодействия Выгрузка правил сетевого оборудования
B103: Определены правила конфигурирования ативов (Харденинг) | C103: УИБ.УА.4 | D103: 5 | E103: 3.2 | F103: 0 | K103: =IF(ЦУКБ="КБ 1",F103, IF(ЦУКБ="КБ 2",E103,D103)) -> 5 | L103: =IF((СК="Да"), D103, VALUE(LEFT(N103,3))) -> 0 | M103: =L103-K103 -> -5 | N103: 0 - Контроль не выполняется | O103: =IF((СК="Да"),"Зона ответственности Сервисной компании", "") | P103: =IFERROR(IF($L103>D103,1,$L103/D103),0) -> 0 | Q103: =IFERROR(IF($L103>E103,1,$L103/E103),0) -> 0 | S103: =S102+0.01 -> 29.04 | T103: =IF(($L103-$F103)>=0,"",) | V103: =V102+0.01 -> 229.04 | W103: =IF(($L103-$E103)>=0,"", " - Разработать или Получить в Блоке ИБ ПАО Ростелеком типовые защищенные конфигурации;"&" - Обеспечить применение безопасных конфигураций на не менее чем 50% хостов.") -> - Разработать или Получить в Блоке ИБ ПАО Ростелеком типовые защищенные конфигурации; - Обеспечить применение безопасных конфигураций на не менее чем 50% хостов. | X103: Формализованный документ, определяющий правила конфигурирования активов | Y103: =Y102+0.01 -> 329.04 | Z103: =IF(($L103-$D103)>=0,"", " - Обеспечить применение безопасных конфигураций на 100% хостов; - Разработать безопасные конфигурации для видов ПО, применяемых в Обществе.") -> - Обеспечить применение безопасных конфигураций на 100% хостов; - Разработать безопасные конфигурации для видов ПО, применяемых в Обществе. | AA103: Формализованный документ, определяющий правила конфигурирования активов
B104: Осуществляется контроль изменений конфигураций оборудования (АРМ, Серверы, Активное сетевое оборудование) | C104: УИБ.УА.5 | D104: 5 | E104: 3.2 | F104: 0 | K104: =IF(ЦУКБ="КБ 1",F104, IF(ЦУКБ="КБ 2",E104,D104)) -> 5 | L104: =IF((СК="Да"), D104, VALUE(LEFT(N104,3))) -> 0 | M104: =L104-K104 -> -5 | N104: 0 - Контроль не выполняется | O104: =IF((СК="Да"),"Зона ответственности Сервисной компании", "") | P104: =IFERROR(IF($L104>D104,1,$L104/D104),0) -> 0 | Q104: =IFERROR(IF($L104>E104,1,$L104/E104),0) -> 0 | S104: =S103+0.01 -> 29.05 | T104: =IF(($L104-$F104)>=0,"",) | V104: =V103+0.01 -> 229.05 | W104: =IF(($L104-$E104)>=0,"", "Определить порядок управления конфигурациями оборудования; Осуществлять автоматизированный контроль конфигураций активного сетевого оборудования и серверов") -> Определить порядок управления конфигурациями оборудования; Осуществлять автоматизированный контроль конфигураций активного сетевого оборудования и серверов | X104: Формализованный документ, определяющий порядок управления конфигурациями оборудования Скрин-шот/выгрузка настроек автоматизированного средства управления конфигурациями выгрузка файлов конфигураций | Y104: =Y103+0.01 -> 329.05 | Z104: =IF(($L104-$D104)>=0,"", " Осуществлять автоматизированный контроль конфигураций активного сетевого оборудования, серверов и конечных устройств; - Отслеживать события изменения конфигурации.") -> Осуществлять автоматизированный контроль конфигураций активного сетевого оборудования, серверов и конечных устройств; - Отслеживать события изменения конфигурации. | AA104: Формализованный документ, определяющий порядок управления конфигурациями оборудования Скрин-шот/выгрузка настроек автоматизированного средства управления конфигурациями выгрузка файлов конфигураций
B105: Управление рисками в цепочке поставок | C105: ЦП | S105: =VLOOKUP(B105,Приоритет!$G$9:$K$48,5,0) -> 35 | T105: ЦП | V105: =S105+200 -> 235 | W105: ЦП | Y105: =S105+300 -> 335 | Z105: ЦП
B106: Процессы взаимодействия в ИТ цепочке c участниками цепочки поставок определены, управляются и согласовываются заинтересованными сторонами Общества | C106: УИБ.ЦП.1 | D106: 5 | E106: 3.2 | F106: 1.6 | K106: =IF(ЦУКБ="КБ 1",F106, IF(ЦУКБ="КБ 2",E106,D106)) -> 5 | L106: =VALUE(LEFT(N106,3)) -> 0 | M106: =L106-K106 -> -5 | N106: 0 - Контроль не выполняется | P106: =IFERROR(IF($L106>D106,1,$L106/D106),0) -> 0 | Q106: =IFERROR(IF($L106>E106,1,$L106/E106),0) -> 0 | R106: =IFERROR(IF($L106>=F106,1,$L106/F106),0) -> 0 | S106: =S105+0.01 -> 35.01 | T106: =IF(($L106-$F106)>=0,"", " - Включить подразделение ИБ в согласование договоров с ИТ/ИБ составляющей.") -> - Включить подразделение ИБ в согласование договоров с ИТ/ИБ составляющей. | U106: Примеры заключенных договоров за последний год | V106: =V105+0.01 -> 235.01 | W106: =IF(($L106-$E106)>=0,"","Роль ИБ в согласовании договоров с ИТ/ИБ составляющей закреплена в ВНД") -> Роль ИБ в согласовании договоров с ИТ/ИБ составляющей закреплена в ВНД | X106: Формализованный документ, в котором закреплена роль подразделений ИБ в согласовании договоров | Y106: =Y105+0.01 -> 335.01 | Z106: =IF(($L106-$D106)>=0,"", "Для договоров, подразумевающих интеграцию\сетевые взаимодействие, обязательно наличие утвержденных схем") -> Для договоров, подразумевающих интеграцию\сетевые взаимодействие, обязательно наличие утвержденных схем | AA106: Утвержденные схемы интеграции
