Workbook
Name БР: ИТОГ!$AA$34
Name ГИС: ИТОГ!$V$35
Name КИИ: ИТОГ!$V$36
Name КТ: ИТОГ!$V$40
Name ЛИЦ: ИТОГ!$V$34
Name Лицензия: ИТОГ!$V$34
Name ПДН: ИТОГ!$V$37
Name СКЗИ: ИТОГ!$AA$35
Name СКПДН: ИТОГ!$V$38
Name СТОРПДН: ИТОГ!$V$37
Name СУДПДН: ИТОГ!$V$39
Name ЦУКБ: ИТОГ!$L$3

Sheet Описание
D2: Индекс кибербезопаности
B10: Данный файл предназначен для проведения саммоценки состояния информационной безопасности и расчета итогового "Индекса кибербезопасности".
B13: Для работы с файлом необходимо заполнить данные в ячейках с желтым фоном на листах с зелеными ярлычками.
B14: На вкладке "ИТОГ" отображается сводный график достижения целевого уровня кибербезопасности.
B15: Лист "Расчет" - это итоговая служебная таблица, на которой осуществляется промежуточный расчет, он не предназначен для редактирования
B18: Рассчет индекса ведется как некоторая усредненная величина показателей по отдельным доменам кибербезопасности.
B19: В каждой отдельной вкладке доменеа строится своя диаграмма и рассчитывается свой локальный индекс.

Sheet ИТОГ
D2: Итоговый рассчетный индекс кибербезопасности и диаграмма достижения целевых показателей в различных доменах информационной безопасности | L2: Целевой уровень | O2: =Расчет!M3 -> 0.35251776 | U2: КБ1 | X2: КБ2 | AA2: КБ3
L3: КБ1 | O3: на | P3: =Расчет!M2 -> 46038 | R3: тренд | U3: =Расчет!T3 -> 0.28957767 | X3: =Расчет!S3 -> 0.093196018 | AA3: =Расчет!R3 -> 0.071458828
V8: =Светофор!F20 -> 0.15479231 | X8: - Предварительное значение оценки показателя состояния ТЗИ и обеспечения безопасности ЗОКИИ РФ в соответствии с Методикой ФСТЭК России
V12: =Светофор!J33 -> 0 | X12: - Отраслевой стандарт защиты данных
V34: нет | W34: Лицензиат ФСТЭК/ФСБ | AA34: да | AB34: Безопасная разработка
V35: да | W35: Наличие ГИС | AA35: да | AB35: СКЗИ ГОСТ
V36: нет | W36: Субьект КИИ
V37: нет | W37: Обработка сторонних ПДН
V38: нет | W38: Спец. Категории ПДН
V39: нет | W39: ПДН о судимости
V40: да | W40: Наличие Коммерческой тайны

Sheet Расчет
C1: КБ3 | D1: КБ2 | E1: КБ1 | F1: Исторические данные | H1: Исторические данные середину 2024 г. | I1: Исторические данные на конец 2024 г. | J1: Архивные расчетные данные на 31.12.2024 | K1: Расчетные данные на 31.12.2026 | L1: Расчетные данные на 31.12.2025 | M1: Текущий показатель | P1: Степень выполнения расчетного показателя | R1: Степень достижения КБ3 | S1: Степень достижения КБ2 | T1: Степень достижения КБ1
B2: Дата заполнения | F2: 45017 | G2: 45291 | H2: 45444 | M2: =TODAY() -> 46038
B3: ИНДЕКС КИБЕРБЕЗОПАСНОСТИ | C3: =0.3*( SUM(C23+C24+C25+C26+C27*IF(СКЗИ="да",1,0)) / (1+1+1+1+1*IF(СКЗИ="да",1,0)) ) +0.2*(SUM(C18+C19*IF(СКЗИ="да",1,0)+(C20+C21)*IF(КИИ="да",1,0)+C22*IF(КТ="да",1,0)) / (1+1*IF(СКЗИ="да",1,0)+(2)*IF(КИИ="да",1,0)+1*IF(КТ="да",1,0)) ) +0.3*(SUM(C4,C6,C28,C37,C38,C39)/6) +0.2*(SUM(C40:C45,C29:C36,C7:C15,C17,C5, C16*IF(БР="да",1,0)) / (25+1*IF(БР="да",1,0))) -> 4.8446459 | D3: =0.3*( SUM(D23+D24+D25+D26+D27*IF(СКЗИ="да",1,0)) / (1+1+1+1+1*IF(СКЗИ="да",1,0)) ) +0.2*(SUM(D18+D19*IF(СКЗИ="да",1,0)+(D20+D21)*IF(КИИ="да",1,0)+D22*IF(КТ="да",1,0)) / (1+1*IF(СКЗИ="да",1,0)+(2)*IF(КИИ="да",1,0)+1*IF(КТ="да",1,0)) ) +0.3*(SUM(D4,D6,D28,D37,D38,D39)/6) +0.2*(SUM(D40:D45,D29:D36,D7:D15,D17,D5, D16*IF(БР="да",1,0)) / (25+1*IF(БР="да",1,0))) -> 4.1010903 | E3: =0.3*( SUM(E23+E24+E25+E26+E27*IF(СКЗИ="да",1,0)) / (1+1+1+1+1*IF(СКЗИ="да",1,0)) ) +0.2*(SUM(E18+E19*IF(СКЗИ="да",1,0)+(E20+E21)*IF(КИИ="да",1,0)+E22*IF(КТ="да",1,0)) / (1+1*IF(СКЗИ="да",1,0)+(2)*IF(КИИ="да",1,0)+1*IF(КТ="да",1,0)) ) +0.3*(SUM(E4,E6,E28,E37,E38,E39)/6) +0.2*(SUM(E40:E45,E29:E36,E7:E15,E17,E5, E16*IF(БР="да",1,0)) / (25+1*IF(БР="да",1,0))) -> 2.5051598 | F3: =0.3*( SUM(F23+F24+F25+F26+F27*IF(СКЗИ="да",1,0)) / (1+1+1+1+1*IF(СКЗИ="да",1,0)) ) +0.2*(SUM(F18+F19*IF(СКЗИ="да",1,0)+(F20+F21)*IF(КИИ="да",1,0)+F22*IF(КТ="да",1,0)) / (1+1*IF(СКЗИ="да",1,0)+(2)*IF(КИИ="да",1,0)+1*IF(КТ="да",1,0)) ) +0.3*(SUM(F4,F6,F28,F37,F38,F39)/6) +0.2*(SUM(F40:F45,F29:F36,F7:F15,F17,F5, F16*IF(БР="да",1,0)) / (25+1*IF(БР="да",1,0))) -> 0 | G3: =0.3*( SUM(G23+G24+G25+G26+G27*IF(СКЗИ="да",1,0)) / (1+1+1+1+1*IF(СКЗИ="да",1,0)) ) +0.2*(SUM(G18+G19*IF(СКЗИ="да",1,0)+(G20+G21)*IF(КИИ="да",1,0)+G22*IF(КТ="да",1,0)) / (1+1*IF(СКЗИ="да",1,0)+(2)*IF(КИИ="да",1,0)+1*IF(КТ="да",1,0)) ) +0.3*(SUM(G4,G6,G28,G37,G38,G39)/6) +0.2*(SUM(G40:G45,G29:G36,G7:G15,G17,G5, G16*IF(БР="да",1,0)) / (25+1*IF(БР="да",1,0))) -> 0 | H3: =0.3*( SUM(H23+H24+H25+H26+H27*IF(СКЗИ="да",1,0)) / (1+1+1+1+1*IF(СКЗИ="да",1,0)) ) +0.2*(SUM(H18+H19*IF(СКЗИ="да",1,0)+(H20+H21)*IF(КИИ="да",1,0)+H22*IF(КТ="да",1,0)) / (1+1*IF(СКЗИ="да",1,0)+(2)*IF(КИИ="да",1,0)+1*IF(КТ="да",1,0)) ) +0.3*(SUM(H4,H6,H28,H37,H38,H39)/6) +0.2*(SUM(H40:H45,H29:H36,H7:H15,H17,H5, H16*IF(БР="да",1,0)) / (25+1*IF(БР="да",1,0))) -> 0 | I3: =0.3*( SUM(I23+I24+I25+I26+I27*IF(СКЗИ="да",1,0)) / (1+1+1+1+1*IF(СКЗИ="да",1,0)) ) +0.2*(SUM(I18+I19*IF(СКЗИ="да",1,0)+(I20+I21)*IF(КИИ="да",1,0)+I22*IF(КТ="да",1,0)) / (1+1*IF(СКЗИ="да",1,0)+(2)*IF(КИИ="да",1,0)+1*IF(КТ="да",1,0)) ) +0.3*(SUM(I4,I6,I28,I37,I38,I39)/6) +0.2*(SUM(I40:I45,I29:I36,I7:I15,I17,I5, I16*IF(БР="да",1,0)) / (25+1*IF(БР="да",1,0))) -> 0 | J3: =0.3*( SUM(J23+J24+J25+J26+J27*IF(СКЗИ="да",1,0)) / (1+1+1+1+1*IF(СКЗИ="да",1,0)) ) +0.2*(SUM(J18+J19*IF(СКЗИ="да",1,0)+(J20+J21)*IF(КИИ="да",1,0)+J22*IF(КТ="да",1,0)) / (1+1*IF(СКЗИ="да",1,0)+(2)*IF(КИИ="да",1,0)+1*IF(КТ="да",1,0)) ) +0.3*(SUM(J4,J6,J28,J37,J38,J39)/6) +0.2*(SUM(J40:J45,J29:J36,J7:J15,J17,J5, J16*IF(БР="да",1,0)) / (25+1*IF(БР="да",1,0))) -> 0 | ... M3: =0.3*( SUM(M23+M24+M25+M26+M27*IF(СКЗИ="да",1,0)) / (1+1+1+1+1*IF(СКЗИ="да",1,0)) ) +0.2*(SUM(M18+M19*IF(СКЗИ="да",1,0)+(M20+M21)*IF(КИИ="да",1,0)+M22*IF(КТ="да",1,0)) / (1+1*IF(СКЗИ="да",1,0)+(2)*IF(КИИ="да",1,0)+1*IF(КТ="да",1,0)) ) +0.3*(SUM(M4,M6,M28,M37,M38,M39)/6) +0.2*(SUM(M40:M45,M29:M36,M7:M15,M17,M5, M16*IF(БР="да",1,0)) / (25+1*IF(БР="да",1,0))) -> 0.35251776 | O3: прирост (дек.24- т.вр) | P3: =1-(0.3*( SUM(P23+P24+P25+P26+P27*IF(СКЗИ="да",1,0)) / (1+1+1+1+1*IF(СКЗИ="да",1,0)) ) +0.2*(SUM(P18+P19*IF(СКЗИ="да",1,0)+(P20+P21)*IF(КИИ="да",1,0)+P22*IF(КТ="да",1,0)) / (1+1*IF(СКЗИ="да",1,0)+(2)*IF(КИИ="да",1,0)+1*IF(КТ="да",1,0)) ) +0.3*(SUM(P4,P6,P28,P37,P38,P39)/6) +0.2*(SUM(P40:P45,P29:P36,P7:P15,P17,P5, P16*IF(БР="да",1,0)) / (25+1*IF(БР="да",1,0)))) -> 0.28188536 | R3: =1-(0.3*( SUM(R23+R24+R25+R26+R27*IF(СКЗИ="да",1,0)) / (1+1+1+1+1*IF(СКЗИ="да",1,0)) ) +0.2*(SUM(R18+R19*IF(СКЗИ="да",1,0)+(R20+R21)*IF(КИИ="да",1,0)+R22*IF(КТ="да",1,0)) / (1+1*IF(СКЗИ="да",1,0)+(2)*IF(КИИ="да",1,0)+1*IF(КТ="да",1,0)) ) +0.3*(SUM(R4,R6,R28,R37,R38,R39)/6) +0.2*(SUM(R40:R45,R29:R36,R7:R15,R17,R5, R16*IF(БР="да",1,0)) / (25+1*IF(БР="да",1,0)))) -> 0.071458828 | S3: =1-(0.3*( SUM(S23+S24+S25+S26+S27*IF(СКЗИ="да",1,0)) / (1+1+1+1+1*IF(СКЗИ="да",1,0)) ) +0.2*(SUM(S18+S19*IF(СКЗИ="да",1,0)+(S20+S21)*IF(КИИ="да",1,0)+S22*IF(КТ="да",1,0)) / (1+1*IF(СКЗИ="да",1,0)+(2)*IF(КИИ="да",1,0)+1*IF(КТ="да",1,0)) ) +0.3*(SUM(S4,S6,S28,S37,S38,S39)/6) +0.2*(SUM(S40:S45,S29:S36,S7:S15,S17,S5, S16*IF(БР="да",1,0)) / (25+1*IF(БР="да",1,0)))) -> 0.093196018 | T3: =1-(0.3*( SUM(T23+T24+T25+T26+T27*IF(СКЗИ="да",1,0)) / (1+1+1+1+1*IF(СКЗИ="да",1,0)) ) +0.2*(SUM(T18+T19*IF(СКЗИ="да",1,0)+(T20+T21)*IF(КИИ="да",1,0)+T22*IF(КТ="да",1,0)) / (1+1*IF(СКЗИ="да",1,0)+(2)*IF(КИИ="да",1,0)+1*IF(КТ="да",1,0)) ) +0.3*(SUM(T4,T6,T28,T37,T38,T39)/6) +0.2*(SUM(T40:T45,T29:T36,T7:T15,T17,T5, T16*IF(БР="да",1,0)) / (25+1*IF(БР="да",1,0)))) -> 0.28957767
A4: СУИБ | B4: ='Управление ИБ'!B42 -> Система управления ИБ | C4: ='Управление ИБ'!D42 -> 5 | D4: ='Управление ИБ'!E42 -> 4.64 | E4: ='Управление ИБ'!F42 -> 2 | F4: 0 | G4: 0 | H4: 0 | I4: 0 | J4: 0 | K4: ='Управление ИБ'!J42 -> #DIV/0! | L4: ='Управление ИБ'!K42 -> 2 | M4: ='Управление ИБ'!L42 -> 3.32 | N4: =L4-M4 -> -1.32 | O4: =I4-M4 -> -3.32 | P4: =IF((M4-L4)>=0,0,(M4-L4)*(-1)/L4) -> 0 | R4: =IF(($M4-C4)>=0,0,($M4-C4)*(-1)/C4) -> 0.336 | S4: =IF(($M4-D4)>=0,0,($M4-D4)*(-1)/D4) -> 0.28448276 | T4: =IF(($M4-E4)>=0,0,($M4-E4)*(-1)/E4) -> 0
B5: ='Управление ИБ'!B43 -> Управление рисками | C5: ='Управление ИБ'!D43 -> 4.8 | D5: ='Управление ИБ'!E43 -> 2 | E5: ='Управление ИБ'!F43 -> 1 | F5: 0 | G5: 0 | H5: 0 | I5: 0 | J5: 0 | K5: ='Управление ИБ'!J43 -> #DIV/0! | L5: ='Управление ИБ'!K43 -> 1 | M5: ='Управление ИБ'!L43 -> 0 | N5: =L5-M5 -> 1 | O5: =I5-M5 -> 0 | P5: =IF((M5-L5)>=0,0,(M5-L5)*(-1)/L5) -> 1 | R5: =IF(($M5-C5)>=0,0,($M5-C5)*(-1)/C5) -> 1 | S5: =IF(($M5-D5)>=0,0,($M5-D5)*(-1)/D5) -> 1 | T5: =IF(($M5-E5)>=0,0,($M5-E5)*(-1)/E5) -> 1
B6: ='Управление ИБ'!B44 -> Управление рисками в цепочке поставок | C6: ='Управление ИБ'!D44 -> 5 | D6: ='Управление ИБ'!E44 -> 3.2 | E6: ='Управление ИБ'!F44 -> 1.6 | F6: 0 | G6: 0 | H6: 0 | I6: 0 | J6: 0 | K6: ='Управление ИБ'!J44 -> #DIV/0! | L6: ='Управление ИБ'!K44 -> 1.6 | M6: ='Управление ИБ'!L44 -> 0 | N6: =L6-M6 -> 1.6 | O6: =I6-M6 -> 0 | P6: =IF((M6-L6)>=0,0,(M6-L6)*(-1)/L6) -> 1 | R6: =IF(($M6-C6)>=0,0,($M6-C6)*(-1)/C6) -> 1 | S6: =IF(($M6-D6)>=0,0,($M6-D6)*(-1)/D6) -> 1 | T6: =IF(($M6-E6)>=0,0,($M6-E6)*(-1)/E6) -> 1
B7: ='Управление ИБ'!B45 -> Инвентаризация | C7: ='Управление ИБ'!D45 -> 5 | D7: ='Управление ИБ'!E45 -> 3.2 | E7: ='Управление ИБ'!F45 -> 1.2307692 | F7: 0 | G7: 0 | H7: 0 | I7: 0 | J7: 0 | K7: ='Управление ИБ'!J45 -> #DIV/0! | L7: ='Управление ИБ'!K45 -> 1.2307692 | M7: ='Управление ИБ'!L45 -> 0.24615385 | N7: =L7-M7 -> 0.98461538 | O7: =I7-M7 -> -0.24615385 | P7: =IF((M7-L7)>=0,0,(M7-L7)*(-1)/L7) -> 0.8 | R7: =IF(($M7-C7)>=0,0,($M7-C7)*(-1)/C7) -> 0.95076923 | S7: =IF(($M7-D7)>=0,0,($M7-D7)*(-1)/D7) -> 0.92307692 | T7: =IF(($M7-E7)>=0,0,($M7-E7)*(-1)/E7) -> 0.8
B8: ='Управление ИБ'!B46 -> Управление активами | C8: ='Управление ИБ'!D46 -> 4.6 | D8: ='Управление ИБ'!E46 -> 3.12 | E8: ='Управление ИБ'!F46 -> 0.52 | F8: 0 | G8: 0 | H8: 0 | I8: 0 | J8: 0 | K8: ='Управление ИБ'!J46 -> #DIV/0! | L8: ='Управление ИБ'!K46 -> 0.52 | M8: ='Управление ИБ'!L46 -> 0.84 | N8: =L8-M8 -> -0.32 | O8: =I8-M8 -> -0.84 | P8: =IF((M8-L8)>=0,0,(M8-L8)*(-1)/L8) -> 0 | R8: =IF(($M8-C8)>=0,0,($M8-C8)*(-1)/C8) -> 0.8173913 | S8: =IF(($M8-D8)>=0,0,($M8-D8)*(-1)/D8) -> 0.73076923 | T8: =IF(($M8-E8)>=0,0,($M8-E8)*(-1)/E8) -> 0
B9: ='Управление ИБ'!B47 -> Управление доступом | C9: ='Управление ИБ'!D47 -> 4.46 | D9: ='Управление ИБ'!E47 -> 3.26 | E9: ='Управление ИБ'!F47 -> 2.14 | F9: 0 | G9: 0 | H9: 0 | I9: 0 | J9: 0 | K9: ='Управление ИБ'!J47 -> #DIV/0! | L9: ='Управление ИБ'!K47 -> 2.14 | M9: ='Управление ИБ'!L47 -> 1.32 | N9: =L9-M9 -> 0.82 | O9: =I9-M9 -> -1.32 | P9: =IF((M9-L9)>=0,0,(M9-L9)*(-1)/L9) -> 0.38317757 | R9: =IF(($M9-C9)>=0,0,($M9-C9)*(-1)/C9) -> 0.70403587 | S9: =IF(($M9-D9)>=0,0,($M9-D9)*(-1)/D9) -> 0.59509202 | T9: =IF(($M9-E9)>=0,0,($M9-E9)*(-1)/E9) -> 0.38317757
B10: ='Управление ИБ'!B48 -> Идентификация и аутентификация | C10: ='Управление ИБ'!D48 -> 5 | D10: ='Управление ИБ'!E48 -> 4.6 | E10: ='Управление ИБ'!F48 -> 3.3111111 | F10: 0 | G10: 0 | H10: 0 | I10: 0 | J10: 0 | K10: ='Управление ИБ'!J48 -> #DIV/0! | L10: ='Управление ИБ'!K48 -> 3.3111111 | M10: ='Управление ИБ'!L48 -> 0 | N10: =L10-M10 -> 3.3111111 | O10: =I10-M10 -> 0 | P10: =IF((M10-L10)>=0,0,(M10-L10)*(-1)/L10) -> 1 | R10: =IF(($M10-C10)>=0,0,($M10-C10)*(-1)/C10) -> 1 | S10: =IF(($M10-D10)>=0,0,($M10-D10)*(-1)/D10) -> 1 | T10: =IF(($M10-E10)>=0,0,($M10-E10)*(-1)/E10) -> 1
B11: ='Управление ИБ'!B49 -> Защита данных и информации | C11: ='Управление ИБ'!D49 -> 4.55 | D11: ='Управление ИБ'!E49 -> 3.7 | E11: ='Управление ИБ'!F49 -> 0.8 | F11: 0 | G11: 0 | H11: 0 | I11: 0 | J11: 0 | K11: ='Управление ИБ'!J49 -> #DIV/0! | L11: ='Управление ИБ'!K49 -> 0.8 | M11: ='Управление ИБ'!L49 -> 2.5 | N11: =L11-M11 -> -1.7 | O11: =I11-M11 -> -2.5 | P11: =IF((M11-L11)>=0,0,(M11-L11)*(-1)/L11) -> 0 | R11: =IF(($M11-C11)>=0,0,($M11-C11)*(-1)/C11) -> 0.45054945 | S11: =IF(($M11-D11)>=0,0,($M11-D11)*(-1)/D11) -> 0.32432432 | T11: =IF(($M11-E11)>=0,0,($M11-E11)*(-1)/E11) -> 0
B12: ='Управление ИБ'!B50 -> Обеспечение доступности | C12: ='Управление ИБ'!D50 -> 5 | D12: ='Управление ИБ'!E50 -> 3.92 | E12: ='Управление ИБ'!F50 -> 0 | F12: 0 | G12: 0 | H12: 0 | I12: 0 | J12: 0 | K12: ='Управление ИБ'!J50 -> #DIV/0! | L12: ='Управление ИБ'!K50 -> 0 | M12: ='Управление ИБ'!L50 -> 0 | N12: =L12-M12 -> 0 | O12: =I12-M12 -> 0 | P12: =IF((M12-L12)>=0,0,(M12-L12)*(-1)/L12) -> 0 | R12: =IF(($M12-C12)>=0,0,($M12-C12)*(-1)/C12) -> 1 | S12: =IF(($M12-D12)>=0,0,($M12-D12)*(-1)/D12) -> 1 | T12: =IF(($M12-E12)>=0,0,($M12-E12)*(-1)/E12) -> 0
B13: ='Управление ИБ'!B51 -> Персонал | C13: ='Управление ИБ'!D51 -> 5 | D13: ='Управление ИБ'!E51 -> 5 | E13: ='Управление ИБ'!F51 -> 5 | F13: 0 | G13: 0 | H13: 0 | I13: 0 | J13: 0 | K13: ='Управление ИБ'!J51 -> #DIV/0! | L13: ='Управление ИБ'!K51 -> 5 | M13: ='Управление ИБ'!L51 -> 0 | N13: =L13-M13 -> 5 | O13: =I13-M13 -> 0 | P13: =IF((M13-L13)>=0,0,(M13-L13)*(-1)/L13) -> 1 | R13: =IF(($M13-C13)>=0,0,($M13-C13)*(-1)/C13) -> 1 | S13: =IF(($M13-D13)>=0,0,($M13-D13)*(-1)/D13) -> 1 | T13: =IF(($M13-E13)>=0,0,($M13-E13)*(-1)/E13) -> 1
B14: ='Управление ИБ'!B52 -> Осведомленность пользователей и обучение персонала | C14: ='Управление ИБ'!D52 -> 5 | D14: ='Управление ИБ'!E52 -> 3.2 | E14: ='Управление ИБ'!F52 -> 1.6 | F14: 0 | G14: 0 | H14: 0 | I14: 0 | J14: 0 | K14: ='Управление ИБ'!J52 -> #DIV/0! | L14: ='Управление ИБ'!K52 -> 1.6 | M14: ='Управление ИБ'!L52 -> 0.14545455 | N14: =L14-M14 -> 1.4545455 | O14: =I14-M14 -> -0.14545455 | P14: =IF((M14-L14)>=0,0,(M14-L14)*(-1)/L14) -> 0.90909091 | R14: =IF(($M14-C14)>=0,0,($M14-C14)*(-1)/C14) -> 0.97090909 | S14: =IF(($M14-D14)>=0,0,($M14-D14)*(-1)/D14) -> 0.95454545 | T14: =IF(($M14-E14)>=0,0,($M14-E14)*(-1)/E14) -> 0.90909091
B15: ='Управление ИБ'!B53 -> Процессы | C15: ='Управление ИБ'!D53 -> 4.0869565 | D15: ='Управление ИБ'!E53 -> 2.8 | E15: ='Управление ИБ'!F53 -> 0.67826087 | F15: 0 | G15: 0 | H15: 0 | I15: 0 | J15: 0 | K15: ='Управление ИБ'!J53 -> 0 | L15: ='Управление ИБ'!K53 -> 0.67826087 | M15: ='Управление ИБ'!L53 -> 0.24347826 | N15: =L15-M15 -> 0.43478261 | O15: =I15-M15 -> -0.24347826 | P15: =IF((M15-L15)>=0,0,(M15-L15)*(-1)/L15) -> 0.64102564 | R15: =IF(($M15-C15)>=0,0,($M15-C15)*(-1)/C15) -> 0.94042553 | S15: =IF(($M15-D15)>=0,0,($M15-D15)*(-1)/D15) -> 0.91304348 | T15: =IF(($M15-E15)>=0,0,($M15-E15)*(-1)/E15) -> 0.64102564
B16: ='Управление ИБ'!B54 -> Безопасная разработка | C16: ='Управление ИБ'!D54 -> 4.9285714 | D16: ='Управление ИБ'!E54 -> 3.8285714 | E16: ='Управление ИБ'!F54 -> 0.98571429 | F16: 0 | G16: 0 | H16: 0 | I16: 0 | J16: 0 | K16: ='Управление ИБ'!J54 -> #DIV/0! | L16: ='Управление ИБ'!K54 -> 0.98571429 | M16: ='Управление ИБ'!L54 -> 0 | N16: =L16-M16 -> 0.98571429 | O16: =I16-M16 -> 0 | P16: =IF((M16-L16)>=0,0,(M16-L16)*(-1)/L16) -> 1 | R16: =IF(($M16-C16)>=0,0,($M16-C16)*(-1)/C16) -> 1 | S16: =IF(($M16-D16)>=0,0,($M16-D16)*(-1)/D16) -> 1 | T16: =IF(($M16-E16)>=0,0,($M16-E16)*(-1)/E16) -> 1
B17: ='Управление ИБ'!B55 -> Физический доступ | C17: ='Управление ИБ'!D55 -> 5 | D17: ='Управление ИБ'!E55 -> 4.64 | E17: ='Управление ИБ'!F55 -> 4.32 | F17: 0 | G17: 0 | H17: 0 | I17: 0 | J17: 0 | K17: ='Управление ИБ'!J55 -> #DIV/0! | L17: ='Управление ИБ'!K55 -> 4.32 | M17: ='Управление ИБ'!L55 -> 0 | N17: =L17-M17 -> 4.32 | O17: =I17-M17 -> 0 | P17: =IF((M17-L17)>=0,0,(M17-L17)*(-1)/L17) -> 1 | R17: =IF(($M17-C17)>=0,0,($M17-C17)*(-1)/C17) -> 1 | S17: =IF(($M17-D17)>=0,0,($M17-D17)*(-1)/D17) -> 1 | T17: =IF(($M17-E17)>=0,0,($M17-E17)*(-1)/E17) -> 1
A18: ='Нормативное соответствие'!B1 -> Нормативное соответствие | B18: ='Нормативное соответствие'!B42 -> Персональные данные | C18: ='Нормативное соответствие'!D42 -> 5 | D18: ='Нормативное соответствие'!E42 -> 5 | E18: ='Нормативное соответствие'!F42 -> 5 | F18: 0 | G18: 0 | H18: 0 | I18: 0 | J18: 0 | K18: ='Нормативное соответствие'!J42 -> #DIV/0! | L18: ='Нормативное соответствие'!K42 -> 5 | M18: ='Нормативное соответствие'!L42 -> 0.20833333 | N18: =L18-M18 -> 4.7916667 | O18: =I18-M18 -> -0.20833333 | P18: =IF((M18-L18)>=0,0,(M18-L18)*(-1)/L18) -> 0.95833333 | R18: =IF(($M18-C18)>=0,0,($M18-C18)*(-1)/C18) -> 0.95833333 | S18: =IF(($M18-D18)>=0,0,($M18-D18)*(-1)/D18) -> 0.95833333 | T18: =IF(($M18-E18)>=0,0,($M18-E18)*(-1)/E18) -> 0.95833333
B19: ='Нормативное соответствие'!B45 -> Средства криптографической защиты информации (СКЗИ ГОСТ) | C19: ='Нормативное соответствие'!D45 -> 5 | D19: ='Нормативное соответствие'!E45 -> 4.82 | E19: ='Нормативное соответствие'!F45 -> 4.66 | F19: 0 | G19: 0 | H19: 0 | I19: 0 | J19: 0 | K19: ='Нормативное соответствие'!J45 -> #DIV/0! | L19: ='Нормативное соответствие'!K45 -> 4.66 | M19: ='Нормативное соответствие'!L45 -> 0 | N19: =L19-M19 -> 4.66 | O19: =I19-M19 -> 0 | P19: =IF((M19-L19)>=0,0,(M19-L19)*(-1)/L19) -> 1 | R19: =IF(($M19-C19)>=0,0,($M19-C19)*(-1)/C19) -> 1 | S19: =IF(($M19-D19)>=0,0,($M19-D19)*(-1)/D19) -> 1 | T19: =IF(($M19-E19)>=0,0,($M19-E19)*(-1)/E19) -> 1
B20: ='Нормативное соответствие'!B43 -> КИИ | C20: ='Нормативное соответствие'!D43 -> 0 | D20: ='Нормативное соответствие'!E43 -> 0 | E20: ='Нормативное соответствие'!F43 -> 0 | F20: 0 | G20: 0 | H20: 0 | I20: 0 | J20: 0 | K20: ='Нормативное соответствие'!J43 -> #DIV/0! | L20: ='Нормативное соответствие'!K43 -> 0 | M20: ='Нормативное соответствие'!L43 -> 0 | N20: =L20-M20 -> 0 | O20: =I20-M20 -> 0 | P20: =IF((M20-L20)>=0,0,(M20-L20)*(-1)/L20) -> 0 | R20: =IF(($M20-C20)>=0,0,($M20-C20)*(-1)/C20) -> 0 | S20: =IF(($M20-D20)>=0,0,($M20-D20)*(-1)/D20) -> 0 | T20: =IF(($M20-E20)>=0,0,($M20-E20)*(-1)/E20) -> 0
B21: ='Нормативное соответствие'!B46 -> 250 указ | C21: ='Нормативное соответствие'!D46 -> 0 | D21: ='Нормативное соответствие'!E46 -> 0 | E21: ='Нормативное соответствие'!F46 -> 0 | F21: 0 | G21: 0 | H21: 0 | I21: 0 | J21: 0 | K21: ='Нормативное соответствие'!J46 -> #DIV/0! | L21: ='Нормативное соответствие'!K46 -> 0.43402778 | M21: ='Нормативное соответствие'!L46 -> 0.48611111 | N21: =L21-M21 -> -0.052083333 | O21: =I21-M21 -> -0.48611111 | P21: =IF((M21-L21)>=0,0,(M21-L21)*(-1)/L21) -> 0 | R21: =IF(($M21-C21)>=0,0,($M21-C21)*(-1)/C21) -> 0 | S21: =IF(($M21-D21)>=0,0,($M21-D21)*(-1)/D21) -> 0 | T21: =IF(($M21-E21)>=0,0,($M21-E21)*(-1)/E21) -> 0
B22: ='Нормативное соответствие'!B44 -> Коммерческая тайна | C22: ='Нормативное соответствие'!D44 -> 5 | D22: ='Нормативное соответствие'!E44 -> 5 | E22: ='Нормативное соответствие'!F44 -> 5 | F22: 0 | G22: 0 | H22: 0 | I22: 0 | J22: 0 | K22: ='Нормативное соответствие'!J44 -> #DIV/0! | L22: ='Нормативное соответствие'!K44 -> 5 | M22: ='Нормативное соответствие'!L44 -> 1 | N22: =L22-M22 -> 4 | O22: =I22-M22 -> -1 | P22: =IF((M22-L22)>=0,0,(M22-L22)*(-1)/L22) -> 0.8 | R22: =IF(($M22-C22)>=0,0,($M22-C22)*(-1)/C22) -> 0.8 | S22: =IF(($M22-D22)>=0,0,($M22-D22)*(-1)/D22) -> 0.8 | T22: =IF(($M22-E22)>=0,0,($M22-E22)*(-1)/E22) -> 0.8
A23: СЗИ | B23: =СЗИ!B29 -> Защита от ВПО | C23: =СЗИ!D29 -> 4.59375 | D23: =СЗИ!E29 -> 4.1875 | E23: =СЗИ!F29 -> 3.49375 | F23: 0 | G23: 0 | H23: 0 | I23: 0 | J23: 0 | K23: =СЗИ!J29 -> #DIV/0! | L23: =СЗИ!K29 -> 3.49375 | M23: =СЗИ!L29 -> 0 | N23: =L23-M23 -> 3.49375 | O23: =I23-M23 -> 0 | P23: =IF((M23-L23)>=0,0,(M23-L23)*(-1)/L23) -> 1 | R23: =IF(($M23-C23)>=0,0,($M23-C23)*(-1)/C23) -> 1 | S23: =IF(($M23-D23)>=0,0,($M23-D23)*(-1)/D23) -> 1 | T23: =IF(($M23-E23)>=0,0,($M23-E23)*(-1)/E23) -> 1
B24: =СЗИ!B30 -> Двухфакторная аутентификация пользователей (2FA) | C24: =СЗИ!D30 -> 5 | D24: =СЗИ!E30 -> 5 | E24: =СЗИ!F30 -> 3.65 | F24: 0 | G24: 0 | H24: 0 | I24: 0 | J24: 0 | K24: =СЗИ!J30 -> #DIV/0! | L24: =СЗИ!K30 -> 3.65 | M24: =СЗИ!L30 -> 0 | N24: =L24-M24 -> 3.65 | O24: =I24-M24 -> 0 | P24: =IF((M24-L24)>=0,0,(M24-L24)*(-1)/L24) -> 1 | R24: =IF(($M24-C24)>=0,0,($M24-C24)*(-1)/C24) -> 1 | S24: =IF(($M24-D24)>=0,0,($M24-D24)*(-1)/D24) -> 1 | T24: =IF(($M24-E24)>=0,0,($M24-E24)*(-1)/E24) -> 1
B25: =СЗИ!B31 -> Защита внешнего инфраструктурного периметра (CPT) | C25: =СЗИ!D31 -> 4.5833333 | D25: =СЗИ!E31 -> 4.1666667 | E25: =СЗИ!F31 -> 3.25 | F25: 0 | G25: 0 | H25: 0 | I25: 0 | J25: 0 | K25: =СЗИ!J31 -> #DIV/0! | L25: =СЗИ!K31 -> 3.25 | M25: =СЗИ!L31 -> 0 | N25: =L25-M25 -> 3.25 | O25: =I25-M25 -> 0 | P25: =IF((M25-L25)>=0,0,(M25-L25)*(-1)/L25) -> 1 | R25: =IF(($M25-C25)>=0,0,($M25-C25)*(-1)/C25) -> 1 | S25: =IF(($M25-D25)>=0,0,($M25-D25)*(-1)/D25) -> 1 | T25: =IF(($M25-E25)>=0,0,($M25-E25)*(-1)/E25) -> 1
B26: =СЗИ!B32 -> Защита удаленного доступа (RA VPN) | C26: =СЗИ!D32 -> 5 | D26: =СЗИ!E32 -> 4.55 | E26: =СЗИ!F32 -> 4.1 | F26: 0 | G26: 0 | H26: 0 | I26: 0 | J26: 0 | K26: =СЗИ!J32 -> #DIV/0! | L26: =СЗИ!K32 -> 4.1 | M26: =СЗИ!L32 -> 0 | N26: =L26-M26 -> 4.1 | O26: =I26-M26 -> 0 | P26: =IF((M26-L26)>=0,0,(M26-L26)*(-1)/L26) -> 1 | R26: =IF(($M26-C26)>=0,0,($M26-C26)*(-1)/C26) -> 1 | S26: =IF(($M26-D26)>=0,0,($M26-D26)*(-1)/D26) -> 1 | T26: =IF(($M26-E26)>=0,0,($M26-E26)*(-1)/E26) -> 1
B27: =СЗИ!B33 -> Средства криптографической защиты информации (СКЗИ ГОСТ) | C27: =СЗИ!D33 -> 5 | D27: =СЗИ!E33 -> 4.955 | E27: =СЗИ!F33 -> 4.465 | F27: 0 | G27: 0 | H27: 0 | I27: 0 | J27: 0 | K27: =СЗИ!J33 -> #DIV/0! | L27: =СЗИ!K33 -> 4.465 | M27: =СЗИ!L33 -> 0.91111111 | N27: =L27-M27 -> 3.5538889 | O27: =I27-M27 -> -0.91111111 | P27: =IF((M27-L27)>=0,0,(M27-L27)*(-1)/L27) -> 0.79594376 | R27: =IF(($M27-C27)>=0,0,($M27-C27)*(-1)/C27) -> 0.81777778 | S27: =IF(($M27-D27)>=0,0,($M27-D27)*(-1)/D27) -> 0.81612288 | T27: =IF(($M27-E27)>=0,0,($M27-E27)*(-1)/E27) -> 0.79594376
B28: =СЗИ!B34 -> Мониторинг, обнаружение, анализ и реагирование на инциденты в информационных системах (SOC) | C28: =СЗИ!D34 -> 4.6346154 | D28: =СЗИ!E34 -> 3.7205128 | E28: =СЗИ!F34 -> 0.041025641 | F28: 0 | G28: 0 | H28: 0 | I28: 0 | J28: 0 | K28: =СЗИ!J34 -> #DIV/0! | L28: =СЗИ!K34 -> 0.041025641 | M28: =СЗИ!L34 -> 0 | N28: =L28-M28 -> 0.041025641 | O28: =I28-M28 -> 0 | P28: =IF((M28-L28)>=0,0,(M28-L28)*(-1)/L28) -> 1 | R28: =IF(($M28-C28)>=0,0,($M28-C28)*(-1)/C28) -> 1 | S28: =IF(($M28-D28)>=0,0,($M28-D28)*(-1)/D28) -> 1 | T28: =IF(($M28-E28)>=0,0,($M28-E28)*(-1)/E28) -> 1
B29: =СЗИ!B35 -> Сетевая безопасность (МСЭ\NGFW) | C29: =СЗИ!D35 -> 5 | D29: =СЗИ!E35 -> 4.1 | E29: =СЗИ!F35 -> 0 | F29: 0 | G29: 0 | H29: 0 | I29: 0 | J29: 0 | K29: =СЗИ!J35 -> #DIV/0! | L29: =СЗИ!K35 -> 0 | M29: =СЗИ!L35 -> 0 | N29: =L29-M29 -> 0 | O29: =I29-M29 -> 0 | P29: =IF((M29-L29)>=0,0,(M29-L29)*(-1)/L29) -> 0 | R29: =IF(($M29-C29)>=0,0,($M29-C29)*(-1)/C29) -> 1 | S29: =IF(($M29-D29)>=0,0,($M29-D29)*(-1)/D29) -> 1 | T29: =IF(($M29-E29)>=0,0,($M29-E29)*(-1)/E29) -> 0
B30: =СЗИ!B36 -> Защита и фильтрация сетевого трафика (Прокси-сервер) | C30: =СЗИ!D36 -> 5 | D30: =СЗИ!E36 -> 3.025 | E30: =СЗИ!F36 -> 0 | F30: 0 | G30: 0 | H30: 0 | I30: 0 | J30: 0 | K30: =СЗИ!J36 -> #DIV/0! | L30: =СЗИ!K36 -> 0 | M30: =СЗИ!L36 -> 0 | N30: =L30-M30 -> 0 | O30: =I30-M30 -> 0 | P30: =IF((M30-L30)>=0,0,(M30-L30)*(-1)/L30) -> 0 | R30: =IF(($M30-C30)>=0,0,($M30-C30)*(-1)/C30) -> 1 | S30: =IF(($M30-D30)>=0,0,($M30-D30)*(-1)/D30) -> 1 | T30: =IF(($M30-E30)>=0,0,($M30-E30)*(-1)/E30) -> 0
B31: =СЗИ!B37 -> Сканер уязвимостей | C31: =СЗИ!D37 -> 4.6666667 | D31: =СЗИ!E37 -> 3.7333333 | E31: =СЗИ!F37 -> 0 | F31: 0 | G31: 0 | H31: 0 | I31: 0 | J31: 0 | K31: =СЗИ!J37 -> #DIV/0! | L31: =СЗИ!K37 -> 0 | M31: =СЗИ!L37 -> 0.33333333 | N31: =L31-M31 -> -0.33333333 | O31: =I31-M31 -> -0.33333333 | P31: =IF((M31-L31)>=0,0,(M31-L31)*(-1)/L31) -> 0 | R31: =IF(($M31-C31)>=0,0,($M31-C31)*(-1)/C31) -> 0.92857143 | S31: =IF(($M31-D31)>=0,0,($M31-D31)*(-1)/D31) -> 0.91071429 | T31: =IF(($M31-E31)>=0,0,($M31-E31)*(-1)/E31) -> 0
B32: =СЗИ!B38 -> Защита от вредоносного трафика (Anti-DDoS) | C32: =СЗИ!D38 -> 5 | D32: =СЗИ!E38 -> 4.2 | E32: =СЗИ!F38 -> 0 | F32: 0 | G32: 0 | H32: 0 | I32: 0 | J32: 0 | K32: =СЗИ!J38 -> #DIV/0! | L32: =СЗИ!K38 -> 0 | M32: =СЗИ!L38 -> 0 | N32: =L32-M32 -> 0 | O32: =I32-M32 -> 0 | P32: =IF((M32-L32)>=0,0,(M32-L32)*(-1)/L32) -> 0 | R32: =IF(($M32-C32)>=0,0,($M32-C32)*(-1)/C32) -> 1 | S32: =IF(($M32-D32)>=0,0,($M32-D32)*(-1)/D32) -> 1 | T32: =IF(($M32-E32)>=0,0,($M32-E32)*(-1)/E32) -> 0
B33: =СЗИ!B39 -> Фильтрация нежелательных и вредоносных сообщений (Антиспам) | C33: =СЗИ!D39 -> 5 | D33: =СЗИ!E39 -> 1 | E33: =СЗИ!F39 -> 0 | F33: 0 | G33: 0 | H33: 0 | I33: 0 | J33: 0 | K33: =СЗИ!J39 -> #DIV/0! | L33: =СЗИ!K39 -> 0 | M33: =СЗИ!L39 -> 0 | N33: =L33-M33 -> 0 | O33: =I33-M33 -> 0 | P33: =IF((M33-L33)>=0,0,(M33-L33)*(-1)/L33) -> 0 | R33: =IF(($M33-C33)>=0,0,($M33-C33)*(-1)/C33) -> 1 | S33: =IF(($M33-D33)>=0,0,($M33-D33)*(-1)/D33) -> 1 | T33: =IF(($M33-E33)>=0,0,($M33-E33)*(-1)/E33) -> 0
B34: =СЗИ!B40 -> Обнаружение и блокирование сетевых атак на web-приложении (WAF) | C34: =СЗИ!D40 -> 4.8 | D34: =СЗИ!E40 -> 1.24 | E34: =СЗИ!F40 -> 0.84 | F34: 0 | G34: 0 | H34: 0 | I34: 0 | J34: 0 | K34: =СЗИ!J40 -> #DIV/0! | L34: =СЗИ!K40 -> 0.84 | M34: =СЗИ!L40 -> 0 | N34: =L34-M34 -> 0.84 | O34: =I34-M34 -> 0 | P34: =IF((M34-L34)>=0,0,(M34-L34)*(-1)/L34) -> 1 | R34: =IF(($M34-C34)>=0,0,($M34-C34)*(-1)/C34) -> 1 | S34: =IF(($M34-D34)>=0,0,($M34-D34)*(-1)/D34) -> 1 | T34: =IF(($M34-E34)>=0,0,($M34-E34)*(-1)/E34) -> 1
B35: =СЗИ!B41 -> Контроль учетных записей (PAM) | C35: =СЗИ!D41 -> 5 | D35: =СЗИ!E41 -> 0 | E35: =СЗИ!F41 -> 0 | F35: 0 | G35: 0 | H35: 0 | I35: 0 | J35: 0 | K35: =СЗИ!J41 -> 0 | L35: =СЗИ!K41 -> 0 | M35: =СЗИ!L41 -> 0 | N35: =L35-M35 -> 0 | O35: =I35-M35 -> 0 | P35: =IF((M35-L35)>=0,0,(M35-L35)*(-1)/L35) -> 0 | R35: =IF(($M35-C35)>=0,0,($M35-C35)*(-1)/C35) -> 1 | S35: =IF(($M35-D35)>=0,0,($M35-D35)*(-1)/D35) -> 0 | T35: =IF(($M35-E35)>=0,0,($M35-E35)*(-1)/E35) -> 0
B36: =СЗИ!B42 -> Предотвращение утечки данных (Data Loss Prevention (DLP) | C36: =СЗИ!D42 -> 4.8214286 | D36: =СЗИ!E42 -> 0 | E36: =СЗИ!F42 -> 0 | F36: 0 | G36: 0 | H36: 0 | I36: 0 | J36: 0 | K36: =СЗИ!J42 -> 0 | L36: =СЗИ!K42 -> 0 | M36: =СЗИ!L42 -> 0 | N36: =L36-M36 -> 0 | O36: =I36-M36 -> 0 | P36: =IF((M36-L36)>=0,0,(M36-L36)*(-1)/L36) -> 0 | R36: =IF(($M36-C36)>=0,0,($M36-C36)*(-1)/C36) -> 1 | S36: =IF(($M36-D36)>=0,0,($M36-D36)*(-1)/D36) -> 0 | T36: =IF(($M36-E36)>=0,0,($M36-E36)*(-1)/E36) -> 0
A37: Мониторинг | B37: =Мониторинг!B39 -> SIEM (внедрение системы как СЗИ) | C37: =Мониторинг!D39 -> 4.9038462 | D37: =Мониторинг!E39 -> 3.5615385 | E37: =Мониторинг!F39 -> 0.12307692 | F37: 0 | G37: 0 | H37: 0 | I37: 0 | J37: 0 | K37: =Мониторинг!J39 -> #DIV/0! | L37: =Мониторинг!K39 -> 0.12307692 | M37: =Мониторинг!L39 -> 0 | N37: =L37-M37 -> 0.12307692 | O37: =I37-M37 -> 0 | P37: =IF((M37-L37)>=0,0,(M37-L37)*(-1)/L37) -> 1 | R37: =IF(($M37-C37)>=0,0,($M37-C37)*(-1)/C37) -> 1 | S37: =IF(($M37-D37)>=0,0,($M37-D37)*(-1)/D37) -> 1 | T37: =IF(($M37-E37)>=0,0,($M37-E37)*(-1)/E37) -> 1
B38: =Мониторинг!B38 -> Аномалии и события (Хранение информации о событиях) | C38: =Мониторинг!D38 -> 5 | D38: =Мониторинг!E38 -> 5 | E38: =Мониторинг!F38 -> 0 | F38: 0 | G38: 0 | H38: 0 | I38: 0 | J38: 0 | K38: =Мониторинг!J38 -> #DIV/0! | L38: =Мониторинг!K38 -> 0 | M38: =Мониторинг!L38 -> 0 | N38: =L38-M38 -> 0 | O38: =I38-M38 -> 0 | P38: =IF((M38-L38)>=0,0,(M38-L38)*(-1)/L38) -> 0 | R38: =IF(($M38-C38)>=0,0,($M38-C38)*(-1)/C38) -> 1 | S38: =IF(($M38-D38)>=0,0,($M38-D38)*(-1)/D38) -> 1 | T38: =IF(($M38-E38)>=0,0,($M38-E38)*(-1)/E38) -> 0
B39: =Мониторинг!B40 -> Мониторинг - Процессы | C39: =Мониторинг!D40 -> 4 | D39: =Мониторинг!E40 -> 2.6 | E39: =Мониторинг!F40 -> 0 | F39: 0 | G39: 0 | H39: 0 | I39: 0 | J39: 0 | K39: =Мониторинг!J40 -> #DIV/0! | L39: =Мониторинг!K40 -> 0 | M39: =Мониторинг!L40 -> 0 | N39: =L39-M39 -> 0 | O39: =I39-M39 -> 0 | P39: =IF((M39-L39)>=0,0,(M39-L39)*(-1)/L39) -> 0 | R39: =IF(($M39-C39)>=0,0,($M39-C39)*(-1)/C39) -> 1 | S39: =IF(($M39-D39)>=0,0,($M39-D39)*(-1)/D39) -> 1 | T39: =IF(($M39-E39)>=0,0,($M39-E39)*(-1)/E39) -> 0
A40: Реагирование | B40: =Реагирование!B30 -> Планирование реагирования | C40: =Реагирование!D30 -> 4.5 | D40: =Реагирование!E30 -> 3.1 | E40: =Реагирование!F30 -> 0.5 | F40: 0 | G40: 0 | H40: 0 | I40: 0 | J40: 0 | K40: =Реагирование!J30 -> #DIV/0! | L40: =Реагирование!K30 -> 0.5 | M40: =Реагирование!L30 -> 0 | N40: =L40-M40 -> 0.5 | O40: =I40-M40 -> 0 | P40: =IF((M40-L40)>=0,0,(M40-L40)*(-1)/L40) -> 1 | R40: =IF(($M40-C40)>=0,0,($M40-C40)*(-1)/C40) -> 1 | S40: =IF(($M40-D40)>=0,0,($M40-D40)*(-1)/D40) -> 1 | T40: =IF(($M40-E40)>=0,0,($M40-E40)*(-1)/E40) -> 1
B41: =Реагирование!B31 -> Коммуникации (реагирование на инциденты) | C41: =Реагирование!D31 -> 5 | D41: =Реагирование!E31 -> 3.2 | E41: =Реагирование!F31 -> 0.64 | F41: 0 | G41: 0 | H41: 0 | I41: 0 | J41: 0 | K41: =Реагирование!J31 -> #DIV/0! | L41: =Реагирование!K31 -> 0.64 | M41: =Реагирование!L31 -> 0.32 | N41: =L41-M41 -> 0.32 | O41: =I41-M41 -> -0.32 | P41: =IF((M41-L41)>=0,0,(M41-L41)*(-1)/L41) -> 0.5 | R41: =IF(($M41-C41)>=0,0,($M41-C41)*(-1)/C41) -> 0.936 | S41: =IF(($M41-D41)>=0,0,($M41-D41)*(-1)/D41) -> 0.9 | T41: =IF(($M41-E41)>=0,0,($M41-E41)*(-1)/E41) -> 0.5
B42: =Реагирование!B33 -> Плейбуки по реагированию | C42: =Реагирование!D33 -> 4.9090909 | D42: =Реагирование!E33 -> 3.2 | E42: =Реагирование!F33 -> 1.6666667 | F42: 0 | G42: 0 | H42: 0 | I42: 0 | J42: 0 | K42: =Реагирование!J33 -> #DIV/0! | L42: =Реагирование!K33 -> 1.6666667 | M42: =Реагирование!L33 -> 0 | N42: =L42-M42 -> 1.6666667 | O42: =I42-M42 -> 0 | P42: =IF((M42-L42)>=0,0,(M42-L42)*(-1)/L42) -> 1 | R42: =IF(($M42-C42)>=0,0,($M42-C42)*(-1)/C42) -> 1 | S42: =IF(($M42-D42)>=0,0,($M42-D42)*(-1)/D42) -> 1 | T42: =IF(($M42-E42)>=0,0,($M42-E42)*(-1)/E42) -> 1
B43: =Реагирование!B32 -> Анализ и расследование | C43: =Реагирование!D32 -> 4.6 | D43: =Реагирование!E32 -> 3.84 | E43: =Реагирование!F32 -> 1.04 | F43: 0 | G43: 0 | H43: 0 | I43: 0 | J43: 0 | K43: =Реагирование!J32 -> #DIV/0! | L43: =Реагирование!K32 -> 1.04 | M43: =Реагирование!L32 -> 0.72 | N43: =L43-M43 -> 0.32 | O43: =I43-M43 -> -0.72 | P43: =IF((M43-L43)>=0,0,(M43-L43)*(-1)/L43) -> 0.30769231 | R43: =IF(($M43-C43)>=0,0,($M43-C43)*(-1)/C43) -> 0.84347826 | S43: =IF(($M43-D43)>=0,0,($M43-D43)*(-1)/D43) -> 0.8125 | T43: =IF(($M43-E43)>=0,0,($M43-E43)*(-1)/E43) -> 0.30769231
A44: Восстановление | B44: =Восстановление!B31 -> Планирование восстановления | C44: =Восстановление!D27 -> 5 | D44: =Восстановление!E27 -> 3.2 | E44: =Восстановление!F27 -> 0 | F44: 0 | G44: 0 | H44: 0 | I44: 0 | J44: 0 | K44: =Восстановление!J27 -> #DIV/0! | L44: =Восстановление!K27 -> 1.0666667 | M44: =Восстановление!L27 -> 0 | N44: =L44-M44 -> 1.0666667 | O44: =I44-M44 -> 0 | P44: =IF((M44-L44)>=0,0,(M44-L44)*(-1)/L44) -> 1 | R44: =IF(($M44-C44)>=0,0,($M44-C44)*(-1)/C44) -> 1 | S44: =IF(($M44-D44)>=0,0,($M44-D44)*(-1)/D44) -> 1 | T44: =IF(($M44-E44)>=0,0,($M44-E44)*(-1)/E44) -> 0
B45: =Восстановление!B41 -> Восстановление - Коммуникации | C45: =Восстановление!D28 -> 5 | D45: =Восстановление!E28 -> 1.6 | E45: =Восстановление!F28 -> 0 | F45: 0 | G45: 0 | H45: 0 | I45: 0 | J45: 0 | K45: =Восстановление!J28 -> #DIV/0! | L45: =Восстановление!K28 -> 0 | M45: =Восстановление!L28 -> 0 | N45: =L45-M45 -> 0 | O45: =I45-M45 -> 0 | P45: =IF((M45-L45)>=0,0,(M45-L45)*(-1)/L45) -> 0 | R45: =IF(($M45-C45)>=0,0,($M45-C45)*(-1)/C45) -> 1 | S45: =IF(($M45-D45)>=0,0,($M45-D45)*(-1)/D45) -> 1 | T45: =IF(($M45-E45)>=0,0,($M45-E45)*(-1)/E45) -> 0
R46: =1-SUM(Расчет!R23:R36)/COUNTA(Расчет!R23:R36) -> 0.018117914 | S46: =1-SUM(Расчет!S23:S36)/COUNTA(Расчет!S23:S36) -> 0.16236877 | T46: =1-SUM(Расчет!T23:T36)/COUNTA(Расчет!T23:T36) -> 0.51457545 | U46: Реализация технических мер
R47: =1-SUM(R4:R17,R18:R22,R39:R45)/COUNTA(R4:R17,R18:R22,R39:R45) -> 0.16508107 | S47: =1-SUM(S4:S17,S18:S22,S39:S45)/COUNTA(S4:S17,S18:S22,S39:S45) -> 0.18476279 | U47: ОРГ
C53: КБ3 | D53: КБ2 | E53: КБ1 | F53: Исторические данные | J53: Расчетные данные на 31.12.2025 | L53: =L1 -> Расчетные данные на 31.12.2025 | M53: Текущий показатель
B54: Дата заполнения | F54: 45017 | G54: 45291 | J54: 46022 | L54: 46022 | M54: 46022
A55: ='Управление ИБ'!B1 -> Система управления ИБ | C55: =AVERAGE(C4:C17) -> 4.8161091 | D55: =AVERAGE(D4:D17) -> 3.6506122 | E55: =AVERAGE(E4:E17) -> 1.7989897 | L55: =AVERAGE(L4:L17) -> 1.7989897 | M55: =AVERAGE(M4:M17) -> 0.61536333
A56: Нормативное соответствие | C56: =AVERAGE(C18:C22) -> 3 | D56: =AVERAGE(D18:D22) -> 2.964 | E56: =AVERAGE(E18:E22) -> 2.932 | L56: =AVERAGE(L18:L22) -> 3.0188056 | M56: =AVERAGE(M18:M22) -> 0.33888889
A57: СЗИ | C57: =AVERAGE(C23:C36) -> 4.864271 | D57: =AVERAGE(D23:D36) -> 3.1341438 | E57: =AVERAGE(E23:E36) -> 1.4171268 | L57: =AVERAGE(L23:L36) -> 1.4171268 | M57: =AVERAGE(M23:M36) -> 0.088888889
A58: Мониторинг | C58: =AVERAGE(C38:C39) -> 4.5 | D58: =AVERAGE(D38:D39) -> 3.8 | E58: =AVERAGE(E38:E39) -> 0 | L58: =AVERAGE(L38:L39) -> 0 | M58: =AVERAGE(M38:M39) -> 0
A59: Реагирование | C59: =AVERAGE(C40:C43) -> 4.7522727 | D59: =AVERAGE(D40:D43) -> 3.335 | E59: =AVERAGE(E40:E43) -> 0.96166667 | L59: =AVERAGE(L40:L43) -> 0.96166667 | M59: =AVERAGE(M40:M43) -> 0.26
A60: Восстановление | C60: =AVERAGE(C44:C45) -> 5 | D60: =AVERAGE(D44:D45) -> 2.4 | E60: =AVERAGE(E44:E45) -> 0 | L60: =AVERAGE(L44:L45) -> 0.53333333 | M60: =AVERAGE(M44:M45) -> 0

Sheet Программа
K1: =SUBTOTAL(3,K3:K9672) -> 611 | M1: =SUBTOTAL(3,M3:M9672) -> 611 | N1: =SUBTOTAL(3,N3:N9672) -> 609 | O1: =SUBTOTAL(3,O3:O9672) -> 3 | P1: =SUBTOTAL(3,P3:P9672) -> 0
A2: Тематика | B2: Домен | C2: Наименование показателя | D2: Сокращенное наименование | E2: КБ3 | F2: КБ2 | G2: КБ1 | H2: Приоритет | I2: Расчетный показатель 2025 | J2: Начальный показатель (на 01.25) | K2: Текущий показатель | L2: Динамика | M2: Индикатор | N2: Пункт плана | O2: Артефакты достижения | P2: Методика проверки
A3: СЗИ | B3: Защита от ВПО | C3: =СЗИ!B46 -> Процент покрытия инфраструктуры лицензиями на антивирусное ПО | D3: =СЗИ!C46 -> СЗИ.ВПО.1 | E3: =СЗИ!D46 -> 5 | F3: =СЗИ!E46 -> 5 | G3: =СЗИ!F46 -> 5 | H3: =СЗИ!P46 -> 1.01 | I3: =СЗИ!K46 -> 5 | J3: =СЗИ!I46 -> 0 | K3: =СЗИ!L46 -> 0 | L3: =IF(J3=I3," ",K3-J3) -> 0 | M3: =IF(H3<100, IF(K3>=G3,0,I3-K3), IF(H3<300, IF(K3>=F3,0,I3-K3), IF(K3>=E3,0,I3-K3))) -> 5 | N3: =СЗИ!Q46 -> - Закупить средства АВЗ в объеме, достаточном для охвата инфраструктуры Общества
A4: СЗИ | B4: Защита от ВПО | C4: =СЗИ!B47 -> Процент покрытия инфраструктуры средствами антивирусного ПО | D4: =СЗИ!C47 -> СЗИ.ВПО.2 | E4: =СЗИ!D47 -> 4.75 | F4: =СЗИ!E47 -> 4.5 | G4: =СЗИ!F47 -> 3.75 | H4: =СЗИ!P47 -> 1.02 | I4: =СЗИ!K47 -> 3.75 | J4: =СЗИ!I47 -> 0 | K4: =СЗИ!L47 -> 0 | L4: =IF(J4=I4," ",K4-J4) -> 0 | M4: =IF(H4<100, IF(K4>=G4,0,I4-K4), IF(H4<300, IF(K4>=F4,0,I4-K4), IF(K4>=E4,0,I4-K4))) -> 3.75 | N4: =СЗИ!Q47 -> - Обеспечить установку средств АВЗ не менее чем на 75% хостов инфраструктуры Общества
A5: СЗИ | B5: Защита от ВПО | C5: =СЗИ!B48 -> Осуществляется централизованное управление средствами антивирусной защиты (САВЗ) | D5: =СЗИ!C48 -> СЗИ.ВПО.3 | E5: =СЗИ!D48 -> 5 | F5: =СЗИ!E48 -> 5 | G5: =СЗИ!F48 -> 3.2 | H5: =СЗИ!P48 -> 1.03 | I5: =СЗИ!K48 -> 3.2 | J5: =СЗИ!I48 -> 0 | K5: =СЗИ!L48 -> 0 | L5: =IF(J5=I5," ",K5-J5) -> 0 | M5: =IF(H5<100, IF(K5>=G5,0,I5-K5), IF(H5<300, IF(K5>=F5,0,I5-K5), IF(K5>=E5,0,I5-K5))) -> 3.2 | N5: =СЗИ!Q48 -> - Создать систему централизованного управления средствами АВЗ и обеспечить подключение к ней основных элементов инфраструктуры
A6: СЗИ | B6: Защита от ВПО | C6: =СЗИ!B49 -> Настроены и применены централизованные политики АВЗ, рекомендованые ПАО "Ростелеком" | D6: =СЗИ!C49 -> СЗИ.ВПО.4 | E6: =СЗИ!D49 -> 5 | F6: =СЗИ!E49 -> 5 | G6: =СЗИ!F49 -> 5 | H6: =СЗИ!P49 -> 1.04 | I6: =СЗИ!K49 -> 5 | J6: =СЗИ!I49 -> 0 | K6: =СЗИ!L49 -> 0 | L6: =IF(J6=I6," ",K6-J6) -> 0 | M6: =IF(H6<100, IF(K6>=G6,0,I6-K6), IF(H6<300, IF(K6>=F6,0,I6-K6), IF(K6>=E6,0,I6-K6))) -> 5 | N6: =СЗИ!Q49 -> - Получить в Блоке ИБ ПАО Ростелеком конфигурационные решения (КР) по настройке средств АВЗ _x000D_- Применить настройки средств АВЗ для рабочих станций _x000D_- Применить настройки средств АВЗ для серверов _x000D_- Применить настройки средств АВЗ для серверов СУБД _x000D_- Применить настройки средств АВЗ для платформ виртуализации _x000D_- Применить настройки средств АВЗ для прокси-серверов _x000D_- Применить настройки средств АВЗ для почтовых серверов
A7: СЗИ | B7: Защита от ВПО | C7: =СЗИ!B50 -> Архитектура решения соответствует ТТР Блока ИБ | D7: =СЗИ!C50 -> СЗИ.ВПО.5 | E7: =СЗИ!D50 -> 5 | F7: =СЗИ!E50 -> 5 | G7: =СЗИ!F50 -> 5 | H7: =СЗИ!P50 -> 1.05 | I7: =СЗИ!K50 -> 5 | J7: =СЗИ!I50 -> 0 | K7: =СЗИ!L50 -> 0 | L7: =IF(J7=I7," ",K7-J7) -> 0 | M7: =IF(H7<100, IF(K7>=G7,0,I7-K7), IF(H7<300, IF(K7>=F7,0,I7-K7), IF(K7>=E7,0,I7-K7))) -> 5 | N7: =СЗИ!Q50 -> - Получить в Блоке ИБ ПАО Ростелеком конфигурационные решения (КР) по архитектуре средств АВЗ _x000D_- Организовать средства централизованного управления АВЗ в соответствии с КР
A8: СЗИ | B8: Защита от ВПО | C8: =СЗИ!B51 -> Процесс контроля работоспособности САВЗ | D8: =СЗИ!C51 -> СЗИ.ВПО.6 | E8: =СЗИ!D51 -> 4 | F8: =СЗИ!E51 -> 3 | G8: =СЗИ!F51 -> 2 | H8: =СЗИ!P51 -> 1.06 | I8: =СЗИ!K51 -> 2 | J8: =СЗИ!I51 -> 0 | K8: =СЗИ!L51 -> 0 | L8: =IF(J8=I8," ",K8-J8) -> 0 | M8: =IF(H8<100, IF(K8>=G8,0,I8-K8), IF(H8<300, IF(K8>=F8,0,I8-K8), IF(K8>=E8,0,I8-K8))) -> 2 | N8: =СЗИ!Q51 -> - Разработать или Получить в Блоке ИБ ПАО Ростелеком типовое описание процесса контроля рабоспособности средств АВЗ _x000D_- Утвердить в Обществе ВНД, описывающий процесс контроля рабоспособности средств АВЗ
A9: СЗИ | B9: Защита от ВПО | C9: =СЗИ!B52 -> Процесс обновления антивирусных средств | D9: =СЗИ!C52 -> СЗИ.ВПО.7 | E9: =СЗИ!D52 -> 4 | F9: =СЗИ!E52 -> 3 | G9: =СЗИ!F52 -> 2 | H9: =СЗИ!P52 -> 1.07 | I9: =СЗИ!K52 -> 2 | J9: =СЗИ!I52 -> 0 | K9: =СЗИ!L52 -> 0 | L9: =IF(J9=I9," ",K9-J9) -> 0 | M9: =IF(H9<100, IF(K9>=G9,0,I9-K9), IF(H9<300, IF(K9>=F9,0,I9-K9), IF(K9>=E9,0,I9-K9))) -> 2 | N9: =СЗИ!Q52 -> - Разработать или Получить в Блоке ИБ ПАО Ростелеком типовое описание процесса обновления средств АВЗ _x000D_- Утвердить в Обществе ВНД, описывающий процесс обновления средств АВЗ
A10: СЗИ | B10: Защита от ВПО | C10: =СЗИ!B53 -> Процесс реагирования на события САВЗ | D10: =СЗИ!C53 -> СЗИ.ВПО.8 | E10: =СЗИ!D53 -> 4 | F10: =СЗИ!E53 -> 3 | G10: =СЗИ!F53 -> 2 | H10: =СЗИ!P53 -> 1.08 | I10: =СЗИ!K53 -> 2 | J10: =СЗИ!I53 -> 0 | K10: =СЗИ!L53 -> 0 | L10: =IF(J10=I10," ",K10-J10) -> 0 | M10: =IF(H10<100, IF(K10>=G10,0,I10-K10), IF(H10<300, IF(K10>=F10,0,I10-K10), IF(K10>=E10,0,I10-K10))) -> 2 | N10: =СЗИ!Q53 -> - Разработать или Получить в Блоке ИБ ПАО Ростелеком типовое описание процесса реагирования на события средств АВЗ _x000D_- Утвердить в Обществе ВНД, описывающий процесс реагирования на события средств АВЗ
A11: СЗИ | B11: Двухфакторная аутентификация пользователей (2FA) | C11: =СЗИ!B55 -> Использование OTP | D11: =СЗИ!C55 -> СЗИ.2FA.1 | E11: =СЗИ!D55 -> 5 | F11: =СЗИ!E55 -> 5 | G11: =СЗИ!F55 -> 3.2 | H11: =СЗИ!P55 -> 2.01 | I11: =СЗИ!K55 -> 3.2 | J11: =СЗИ!I55 -> 0 | K11: =СЗИ!L55 -> 0 | L11: =IF(J11=I11," ",K11-J11) -> 0 | M11: =IF(H11<100, IF(K11>=G11,0,I11-K11), IF(H11<300, IF(K11>=F11,0,I11-K11), IF(K11>=E11,0,I11-K11))) -> 3.2 | N11: =СЗИ!Q55 -> - Выбрать и протестировать OTP решения; - Выполнить проектирование; - Провести закупку и внедрение.
A12: СЗИ | B12: Двухфакторная аутентификация пользователей (2FA) | C12: =СЗИ!B56 -> Двухфакторная аутентификация используется для удаленного доступа работников к ресурсам Общества | D12: =СЗИ!C56 -> СЗИ.2FA.2 | E12: =СЗИ!D56 -> 5 | F12: =СЗИ!E56 -> 5 | G12: =СЗИ!F56 -> 5 | H12: =СЗИ!P56 -> 2.02 | I12: =СЗИ!K56 -> 5 | J12: =СЗИ!I56 -> 0 | K12: =СЗИ!L56 -> 0 | L12: =IF(J12=I12," ",K12-J12) -> 0 | M12: =IF(H12<100, IF(K12>=G12,0,I12-K12), IF(H12<300, IF(K12>=F12,0,I12-K12), IF(K12>=E12,0,I12-K12))) -> 5 | N12: =СЗИ!Q56 -> - Внедрить OTP для системы удаленного доступа
A13: СЗИ | B13: Двухфакторная аутентификация пользователей (2FA) | C13: =СЗИ!B57 -> Двухфакторная аутентификация используется для удаленного доступа подрядчиков к ресурсам Общества | D13: =СЗИ!C57 -> СЗИ.2FA.3 | E13: =СЗИ!D57 -> 5 | F13: =СЗИ!E57 -> 5 | G13: =СЗИ!F57 -> 3.2 | H13: =СЗИ!P57 -> 2.03 | I13: =СЗИ!K57 -> 3.2 | J13: =СЗИ!I57 -> 0 | K13: =СЗИ!L57 -> 0 | L13: =IF(J13=I13," ",K13-J13) -> 0 | M13: =IF(H13<100, IF(K13>=G13,0,I13-K13), IF(H13<300, IF(K13>=F13,0,I13-K13), IF(K13>=E13,0,I13-K13))) -> 3.2 | N13: =СЗИ!Q57 -> - Внедрить OTP для подрядчиков, выполняющих администрирование ИС Общества
A14: СЗИ | B14: Двухфакторная аутентификация пользователей (2FA) | C14: =СЗИ!B58 -> Двухфакторная аутентификация используется для привелигированных УЗ | D14: =СЗИ!C58 -> СЗИ.2FA.4 | E14: =СЗИ!D58 -> 5 | F14: =СЗИ!E58 -> 5 | G14: =СЗИ!F58 -> 3.2 | H14: =СЗИ!P58 -> 2.04 | I14: =СЗИ!K58 -> 3.2 | J14: =СЗИ!I58 -> 0 | K14: =СЗИ!L58 -> 0 | L14: =IF(J14=I14," ",K14-J14) -> 0 | M14: =IF(H14<100, IF(K14>=G14,0,I14-K14), IF(H14<300, IF(K14>=F14,0,I14-K14), IF(K14>=E14,0,I14-K14))) -> 3.2 | N14: =СЗИ!Q58 -> - Внедрить OTP для административного доступа к серверам ИС
A15: СЗИ | B15: Защита внешнего инфраструктурного периметра (CPT) | C15: =СЗИ!B60 -> Процент покрытия активов на внешнем периметре лицензиями/договорами | D15: =СЗИ!C60 -> СЗИ.CPT.1 | E15: =СЗИ!D60 -> 5 | F15: =СЗИ!E60 -> 5 | G15: =СЗИ!F60 -> 5 | H15: =СЗИ!P60 -> 3.01 | I15: =СЗИ!K60 -> 5 | J15: =СЗИ!I60 -> 0 | K15: =СЗИ!L60 -> 0 | L15: =IF(J15=I15," ",K15-J15) -> 0 | M15: =IF(H15<100, IF(K15>=G15,0,I15-K15), IF(H15<300, IF(K15>=F15,0,I15-K15), IF(K15>=E15,0,I15-K15))) -> 5 | N15: =СЗИ!Q60 -> - Приобрести средства CPT в достаточном объеме для контроля всех активов, опубликованных на периметре
A16: СЗИ | B16: Защита внешнего инфраструктурного периметра (CPT) | C16: =СЗИ!B61 -> Процент охваченных регулярным сканированием активов | D16: =СЗИ!C61 -> СЗИ.CPT.2 | E16: =СЗИ!D61 -> 4.75 | F16: =СЗИ!E61 -> 4.5 | G16: =СЗИ!F61 -> 3.75 | H16: =СЗИ!P61 -> 3.02 | I16: =СЗИ!K61 -> 3.75 | J16: =СЗИ!I61 -> 0 | K16: =СЗИ!L61 -> 0 | L16: =IF(J16=I16," ",K16-J16) -> 0 | M16: =IF(H16<100, IF(K16>=G16,0,I16-K16), IF(H16<300, IF(K16>=F16,0,I16-K16), IF(K16>=E16,0,I16-K16))) -> 3.75 | N16: =СЗИ!Q61 -> - Поставить периметр на контроль CPT, всего активов не менее: 75%
A17: СЗИ | B17: Защита внешнего инфраструктурного периметра (CPT) | C17: =СЗИ!B62 -> Внедрен процесс управления уязвимостями на периметре (CPT) | D17: =СЗИ!C62 -> СЗИ.CPT.3 | E17: =СЗИ!D62 -> 4 | F17: =СЗИ!E62 -> 3 | G17: =СЗИ!F62 -> 1 | H17: =СЗИ!P62 -> 3.03 | I17: =СЗИ!K62 -> 1 | J17: =СЗИ!I62 -> 0 | K17: =СЗИ!L62 -> 0 | L17: =IF(J17=I17," ",K17-J17) -> 0 | M17: =IF(H17<100, IF(K17>=G17,0,I17-K17), IF(H17<300, IF(K17>=F17,0,I17-K17), IF(K17>=E17,0,I17-K17))) -> 1 | N17: =СЗИ!Q62 -> - Разработать или Получить в Блоке ИБ ПАО Ростелеком типовое описание процесса контроля уязвимостей
A18: СЗИ | B18: Защита удаленного доступа (RA VPN) | C18: =СЗИ!B64 -> Наличие средств RA VPN | D18: =СЗИ!C64 -> СЗИ.RA-VPN.1 | E18: =СЗИ!D64 -> 5 | F18: =СЗИ!E64 -> 5 | G18: =СЗИ!F64 -> 5 | H18: =СЗИ!P64 -> 4.01 | I18: =СЗИ!K64 -> 5 | J18: =СЗИ!I64 -> 0 | K18: =СЗИ!L64 -> 0 | L18: =IF(J18=I18," ",K18-J18) -> 0 | M18: =IF(H18<100, IF(K18>=G18,0,I18-K18), IF(H18<300, IF(K18>=F18,0,I18-K18), IF(K18>=E18,0,I18-K18))) -> 5 | N18: =СЗИ!Q64 -> - Выбрать и протестировать решения RA VPN; - Выполнить проектирование; - Провести закупку и внедрение.
A19: СЗИ | B19: Защита удаленного доступа (RA VPN) | C19: =СЗИ!B65 -> Покрытие инфраструктуры средствами защищенного удаленного доступа | D19: =СЗИ!C65 -> СЗИ.RA-VPN.2 | E19: =СЗИ!D65 -> 5 | F19: =СЗИ!E65 -> 3.2 | G19: =СЗИ!F65 -> 3.2 | H19: =СЗИ!P65 -> 4.02 | I19: =СЗИ!K65 -> 3.2 | J19: =СЗИ!I65 -> 0 | K19: =СЗИ!L65 -> 0 | L19: =IF(J19=I19," ",K19-J19) -> 0 | M19: =IF(H19<100, IF(K19>=G19,0,I19-K19), IF(H19<300, IF(K19>=F19,0,I19-K19), IF(K19>=E19,0,I19-K19))) -> 3.2 | N19: =СЗИ!Q65 -> - Обеспечить возможность удаленного подключения к инфраструктуре Общества только с использованием RA VPN; - VPN должны требовать двухфакторной аутентификации.
A20: СЗИ | B20: Защита удаленного доступа (RA VPN) | C20: =СЗИ!B66 -> Осуществляется централизованное управление удаленным доступом | D20: =СЗИ!C66 -> СЗИ.RA-VPN.3 | E20: =СЗИ!D66 -> 5 | F20: =СЗИ!E66 -> 5 | G20: =СЗИ!F66 -> 3.2 | H20: =СЗИ!P66 -> 4.03 | I20: =СЗИ!K66 -> 3.2 | J20: =СЗИ!I66 -> 0 | K20: =СЗИ!L66 -> 0 | L20: =IF(J20=I20," ",K20-J20) -> 0 | M20: =IF(H20<100, IF(K20>=G20,0,I20-K20), IF(H20<300, IF(K20>=F20,0,I20-K20), IF(K20>=E20,0,I20-K20))) -> 3.2 | N20: =СЗИ!Q66 -> - Создать систему централизованного управления средствами VPN и обеспечить подключение к ней всех средств VPN
A21: СЗИ | B21: Защита удаленного доступа (RA VPN) | C21: =СЗИ!B67 -> Наличие действующего сертификата ФСБ России на этапе проведения аудита | D21: =СЗИ!C67 -> СЗИ.RA-VPN.4 | E21: =СЗИ!D67 -> 5 | F21: =СЗИ!E67 -> 5 | G21: =СЗИ!F67 -> 5 | H21: =СЗИ!P67 -> 4.04 | I21: =СЗИ!K67 -> 5 | J21: =СЗИ!I67 -> 0 | K21: =СЗИ!L67 -> 0 | L21: =IF(J21=I21," ",K21-J21) -> 0 | M21: =IF(H21<100, IF(K21>=G21,0,I21-K21), IF(H21<300, IF(K21>=F21,0,I21-K21), IF(K21>=E21,0,I21-K21))) -> 5 | N21: =СЗИ!Q67 -> - Если требования законодательства применимы, необходимо использовать только сертифицированные VPN
A22: СЗИ | B22: СКЗИ ГОСТ | C22: =СЗИ!B69 -> Защищены взаимодействия между площадками и ЦОД | D22: =СЗИ!C69 -> СЗИ.СКЗИ.1 | E22: =СЗИ!D69 -> 5 | F22: =СЗИ!E69 -> 5 | G22: =СЗИ!F69 -> 5 | H22: =СЗИ!P69 -> 5.01 | I22: =СЗИ!K69 -> 5 | J22: =СЗИ!I69 -> 0 | K22: =СЗИ!L69 -> 5 | L22: =IF(J22=I22," ",K22-J22) -> 5 | M22: =IF(H22<100, IF(K22>=G22,0,I22-K22), IF(H22<300, IF(K22>=F22,0,I22-K22), IF(K22>=E22,0,I22-K22))) -> 0 | N22: =СЗИ!Q69
A23: СЗИ | B23: СКЗИ ГОСТ | C23: =СЗИ!B70 -> Осуществляется централизованное управление СКЗИ | D23: =СЗИ!C70 -> СЗИ.СКЗИ.2 | E23: =СЗИ!D70 -> 5 | F23: =СЗИ!E70 -> 5 | G23: =СЗИ!F70 -> 3.2 | H23: =СЗИ!P70 -> 5.02 | I23: =СЗИ!K70 -> 3.2 | J23: =СЗИ!I70 -> 0 | K23: =СЗИ!L70 -> 3.2 | L23: =IF(J23=I23," ",K23-J23) -> 3.2 | M23: =IF(H23<100, IF(K23>=G23,0,I23-K23), IF(H23<300, IF(K23>=F23,0,I23-K23), IF(K23>=E23,0,I23-K23))) -> 0 | N23: =СЗИ!Q70
A24: СЗИ | B24: СКЗИ ГОСТ | C24: =СЗИ!B72 -> Наличие действующего сертификата ФСБ на этапе проведения аудита | D24: =СЗИ!C72 -> СЗИ.СКЗИ.4 | E24: =СЗИ!D72 -> 5 | F24: =СЗИ!E72 -> 5 | G24: =СЗИ!F72 -> 5 | H24: =СЗИ!P72 -> 5.04 | I24: =СЗИ!K72 -> 5 | J24: =СЗИ!I72 -> 0 | K24: =СЗИ!L72 -> 0 | L24: =IF(J24=I24," ",K24-J24) -> 0 | M24: =IF(H24<100, IF(K24>=G24,0,I24-K24), IF(H24<300, IF(K24>=F24,0,I24-K24), IF(K24>=E24,0,I24-K24))) -> 5 | N24: =СЗИ!Q72 -> - Если требования законодательства применимы, необходимо использовать только сертифицированные СКЗИ
A25: Мониторинг | B25: SIEM | C25: =Мониторинг!B45 -> Процент покрытия инфраструктуры лицензиями на мониторинг | D25: =Мониторинг!C45 -> МНТ.SIEM.1 | E25: =Мониторинг!D45 -> 5 | F25: =Мониторинг!E45 -> 5 | G25: =Мониторинг!F45 -> 0 | H25: =Мониторинг!P45 -> 6.01 | I25: =Мониторинг!K45 -> 0 | J25: =Мониторинг!I45 -> 0 | K25: =Мониторинг!L45 -> 0 | L25: =IF(J25=I25," ",K25-J25) | M25: =IF(H25<100, IF(K25>=G25,0,I25-K25), IF(H25<300, IF(K25>=F25,0,I25-K25), IF(K25>=E25,0,I25-K25))) -> 0 | N25: =Мониторинг!Q45
A26: Мониторинг | B26: SIEM | C26: =Мониторинг!B46 -> Процент покрытия инфраструктуры мониторингом | D26: =Мониторинг!C46 -> МНТ.SIEM.2 | E26: =Мониторинг!D46 -> 4.75 | F26: =Мониторинг!E46 -> 4.5 | G26: =Мониторинг!F46 -> 0 | H26: =Мониторинг!P46 -> 6.02 | I26: =Мониторинг!K46 -> 0 | J26: =Мониторинг!I46 -> 0 | K26: =Мониторинг!L46 -> 0 | L26: =IF(J26=I26," ",K26-J26) | M26: =IF(H26<100, IF(K26>=G26,0,I26-K26), IF(H26<300, IF(K26>=F26,0,I26-K26), IF(K26>=E26,0,I26-K26))) -> 0 | N26: =Мониторинг!Q46
A27: Мониторинг | B27: SIEM | C27: =Мониторинг!B47 -> Определен набор решающих правил и пороги страбатывания | D27: =Мониторинг!C47 -> МНТ.SIEM.3 | E27: =Мониторинг!D47 -> 5 | F27: =Мониторинг!E47 -> 3.2 | G27: =Мониторинг!F47 -> 0 | H27: =Мониторинг!P47 -> 6.03 | I27: =Мониторинг!K47 -> 0 | J27: =Мониторинг!I47 -> 0 | K27: =Мониторинг!L47 -> 0 | L27: =IF(J27=I27," ",K27-J27) | M27: =IF(H27<100, IF(K27>=G27,0,I27-K27), IF(H27<300, IF(K27>=F27,0,I27-K27), IF(K27>=E27,0,I27-K27))) -> 0 | N27: =Мониторинг!Q47
A28: Мониторинг | B28: SIEM | C28: =Мониторинг!B48 -> Осуществляется сбор событий, необходимых для детекта и обогащения в объеме, достаточном для решения задач (- создания, изменения, удаления субъектов и объектов доступа; - аутентификации (вход и выход субъектов); - авторизации (доступа субъектов к объектам); - запуска и остановки, удаления и остановки служб (ПО); - изменения настроек ПО и средств защиты информации; - обработки сетевого трафика (netflow)) | D28: =Мониторинг!C48 -> МНТ.SIEM.4 | E28: =Мониторинг!D48 -> 5 | F28: =Мониторинг!E48 -> 3.2 | G28: =Мониторинг!F48 -> 0 | H28: =Мониторинг!P48 -> 6.04 | I28: =Мониторинг!K48 -> 0 | J28: =Мониторинг!I48 -> 0 | K28: =Мониторинг!L48 -> 0 | L28: =IF(J28=I28," ",K28-J28) | M28: =IF(H28<100, IF(K28>=G28,0,I28-K28), IF(H28<300, IF(K28>=F28,0,I28-K28), IF(K28>=E28,0,I28-K28))) -> 0 | N28: =Мониторинг!Q48
A29: Мониторинг | B29: SIEM | C29: =Мониторинг!B49 -> Настроенные решающие правила соответствуют ТТР Блока ИБ | D29: =Мониторинг!C49 -> МНТ.SIEM.5 | E29: =Мониторинг!D49 -> 5 | F29: =Мониторинг!E49 -> 3.2 | G29: =Мониторинг!F49 -> 0 | H29: =Мониторинг!P49 -> 6.05 | I29: =Мониторинг!K49 -> 0 | J29: =Мониторинг!I49 -> 0 | K29: =Мониторинг!L49 -> 0 | L29: =IF(J29=I29," ",K29-J29) | M29: =IF(H29<100, IF(K29>=G29,0,I29-K29), IF(H29<300, IF(K29>=F29,0,I29-K29), IF(K29>=E29,0,I29-K29))) -> 0 | N29: =Мониторинг!Q49
A30: Мониторинг | B30: SIEM | C30: =Мониторинг!B50 -> Контролируются сетевые события | D30: =Мониторинг!C50 -> МНТ.SIEM.6 | E30: =Мониторинг!D50 -> 5 | F30: =Мониторинг!E50 -> 3.2 | G30: =Мониторинг!F50 -> 0 | H30: =Мониторинг!P50 -> 6.06 | I30: =Мониторинг!K50 -> 0 | J30: =Мониторинг!I50 -> 0 | K30: =Мониторинг!L50 -> 0 | L30: =IF(J30=I30," ",K30-J30) | M30: =IF(H30<100, IF(K30>=G30,0,I30-K30), IF(H30<300, IF(K30>=F30,0,I30-K30), IF(K30>=E30,0,I30-K30))) -> 0 | N30: =Мониторинг!Q50
A31: Мониторинг | B31: SIEM | C31: =Мониторинг!B51 -> Контролируются события ОС | D31: =Мониторинг!C51 -> МНТ.SIEM.7 | E31: =Мониторинг!D51 -> 5 | F31: =Мониторинг!E51 -> 3.2 | G31: =Мониторинг!F51 -> 0 | H31: =Мониторинг!P51 -> 6.07 | I31: =Мониторинг!K51 -> 0 | J31: =Мониторинг!I51 -> 0 | K31: =Мониторинг!L51 -> 0 | L31: =IF(J31=I31," ",K31-J31) | M31: =IF(H31<100, IF(K31>=G31,0,I31-K31), IF(H31<300, IF(K31>=F31,0,I31-K31), IF(K31>=E31,0,I31-K31))) -> 0 | N31: =Мониторинг!Q51
A32: Мониторинг | B32: SIEM | C32: =Мониторинг!B52 -> Контролируются события СУБД | D32: =Мониторинг!C52 -> МНТ.SIEM.8 | E32: =Мониторинг!D52 -> 5 | F32: =Мониторинг!E52 -> 3.2 | G32: =Мониторинг!F52 -> 0 | H32: =Мониторинг!P52 -> 6.08 | I32: =Мониторинг!K52 -> 0 | J32: =Мониторинг!I52 -> 0 | K32: =Мониторинг!L52 -> 0 | L32: =IF(J32=I32," ",K32-J32) | M32: =IF(H32<100, IF(K32>=G32,0,I32-K32), IF(H32<300, IF(K32>=F32,0,I32-K32), IF(K32>=E32,0,I32-K32))) -> 0 | N32: =Мониторинг!Q52
A33: Мониторинг | B33: SIEM | C33: =Мониторинг!B53 -> Контролируются события прикладных ИС | D33: =Мониторинг!C53 -> МНТ.SIEM.9 | E33: =Мониторинг!D53 -> 5 | F33: =Мониторинг!E53 -> 3.2 | G33: =Мониторинг!F53 -> 0 | H33: =Мониторинг!P53 -> 6.09 | I33: =Мониторинг!K53 -> 0 | J33: =Мониторинг!I53 -> 0 | K33: =Мониторинг!L53 -> 0 | L33: =IF(J33=I33," ",K33-J33) | M33: =IF(H33<100, IF(K33>=G33,0,I33-K33), IF(H33<300, IF(K33>=F33,0,I33-K33), IF(K33>=E33,0,I33-K33))) -> 0 | N33: =Мониторинг!Q53
A34: Мониторинг | B34: SIEM | C34: =Мониторинг!B54 -> Контроль событий СЗИ | D34: =Мониторинг!C54 -> МНТ.SIEM.10 | E34: =Мониторинг!D54 -> 5 | F34: =Мониторинг!E54 -> 3.2 | G34: =Мониторинг!F54 -> 0 | H34: =Мониторинг!P54 -> 6.1 | I34: =Мониторинг!K54 -> 0 | J34: =Мониторинг!I54 -> 0 | K34: =Мониторинг!L54 -> 0 | L34: =IF(J34=I34," ",K34-J34) | M34: =IF(H34<100, IF(K34>=G34,0,I34-K34), IF(H34<300, IF(K34>=F34,0,I34-K34), IF(K34>=E34,0,I34-K34))) -> 0 | N34: =Мониторинг!Q54
A35: Мониторинг | B35: SIEM | C35: =Мониторинг!B55 -> Контроль событий о действиях привелигированных пользователей | D35: =Мониторинг!C55 -> МНТ.SIEM.11 | E35: =Мониторинг!D55 -> 5 | F35: =Мониторинг!E55 -> 3.2 | G35: =Мониторинг!F55 -> 1.6 | H35: =Мониторинг!P55 -> 6.11 | I35: =Мониторинг!K55 -> 1.6 | J35: =Мониторинг!I55 -> 0 | K35: =Мониторинг!L55 -> 0 | L35: =IF(J35=I35," ",K35-J35) -> 0 | M35: =IF(H35<100, IF(K35>=G35,0,I35-K35), IF(H35<300, IF(K35>=F35,0,I35-K35), IF(K35>=E35,0,I35-K35))) -> 1.6 | N35: =Мониторинг!Q55 -> - Составить перчень привилегированных пользователей и групп; - Разработать решающие правила SIEM для выявления действий привилегированных пользователей; - Контролировать действия привилегированных пользователей в критичных ИС
A36: Мониторинг | B36: SIEM | C36: =Мониторинг!B56 -> Внедрен процесс управления сбоями и мониторинга работоспособности SIEM | D36: =Мониторинг!C56 -> МНТ.SIEM.12 | E36: =Мониторинг!D56 -> 4 | F36: =Мониторинг!E56 -> 3 | G36: =Мониторинг!F56 -> 0 | H36: =Мониторинг!P56 -> 6.12 | I36: =Мониторинг!K56 -> 0 | J36: =Мониторинг!I56 -> 0 | K36: =Мониторинг!L56 -> 0 | L36: =IF(J36=I36," ",K36-J36) | M36: =IF(H36<100, IF(K36>=G36,0,I36-K36), IF(H36<300, IF(K36>=F36,0,I36-K36), IF(K36>=E36,0,I36-K36))) -> 0 | N36: =Мониторинг!Q56
A37: Реагирование | B37: Планирование реагирования | C37: =Реагирование!B39 -> Процесс реагирования на инциденты ИБ | D37: =Реагирование!C39 -> РЕАГ.ПЛР.1 | E37: =Реагирование!D39 -> 4 | F37: =Реагирование!E39 -> 3 | G37: =Реагирование!F39 -> 1 | H37: =Реагирование!P39 -> 7.01 | I37: =Реагирование!K39 -> 1 | J37: =Реагирование!I39 -> 0 | K37: =Реагирование!L39 -> 0 | L37: =IF(J37=I37," ",K37-J37) -> 0 | M37: =IF(H37<100, IF(K37>=G37,0,I37-K37), IF(H37<300, IF(K37>=F37,0,I37-K37), IF(K37>=E37,0,I37-K37))) -> 1 | N37: =Реагирование!Q39 -> - Назначить ответственных за решение инцидентов ИБ, включая ответственного за коммуникации внутри и со сторонними компаниями; - Составить и актуализировать список заинтересованных лиц, которые должны получить уведомление об инциденте; - Для критичных инцидентов определить SLA и порядок действий по реагированию; - Автоматизировать процесс реагирования на инциденты ИБ с применением не специализированных средств.
A38: Реагирование | B38: Планирование реагирования | C38: =Реагирование!B40 -> Процесс категорирования инцидентов ИБ | D38: =Реагирование!C40 -> РЕАГ.ПЛР.2 | E38: =Реагирование!D40 -> 4 | F38: =Реагирование!E40 -> 3 | G38: =Реагирование!F40 -> 1 | H38: =Реагирование!P40 -> 7.02 | I38: =Реагирование!K40 -> 1 | J38: =Реагирование!I40 -> 0 | K38: =Реагирование!L40 -> 0 | L38: =IF(J38=I38," ",K38-J38) -> 0 | M38: =IF(H38<100, IF(K38>=G38,0,I38-K38), IF(H38<300, IF(K38>=F38,0,I38-K38), IF(K38>=E38,0,I38-K38))) -> 1 | N38: =Реагирование!Q40 -> - В Обществе неформально определить категории инцидентов ИБ
A39: Реагирование | B39: Планирование реагирования | C39: =Реагирование!B41 -> Определен мандат на действие в ходе реагирования на инцидент | D39: =Реагирование!C41 -> РЕАГ.ПЛР.3 | E39: =Реагирование!D41 -> 5 | F39: =Реагирование!E41 -> 3.2 | G39: =Реагирование!F41 -> 0 | H39: =Реагирование!P41 -> 7.03 | I39: =Реагирование!K41 -> 0 | J39: =Реагирование!I41 -> 0 | K39: =Реагирование!L41 -> 0 | L39: =IF(J39=I39," ",K39-J39) | M39: =IF(H39<100, IF(K39>=G39,0,I39-K39), IF(H39<300, IF(K39>=F39,0,I39-K39), IF(K39>=E39,0,I39-K39))) -> 0 | N39: =Реагирование!Q41
A40: Реагирование | B40: Планирование реагирования | C40: =Реагирование!B42 -> Планы реагирования совершенствуются по результатам тестирования и пост-анализа | D40: =Реагирование!C42 -> РЕАГ.ПЛР.4 | E40: =Реагирование!D42 -> 5 | F40: =Реагирование!E42 -> 3.2 | G40: =Реагирование!F42 -> 0 | H40: =Реагирование!P42 -> 7.04 | I40: =Реагирование!K42 -> 0 | J40: =Реагирование!I42 -> 0 | K40: =Реагирование!L42 -> 0 | L40: =IF(J40=I40," ",K40-J40) | M40: =IF(H40<100, IF(K40>=G40,0,I40-K40), IF(H40<300, IF(K40>=F40,0,I40-K40), IF(K40>=E40,0,I40-K40))) -> 0 | N40: =Реагирование!Q42
A41: Нормативное соответствие | B41: КИИ | C41: ='Нормативное соответствие'!B75 -> Полномочия по обеспечению ИБ возложены на заместителя руководителя Общества | D41: ='Нормативное соответствие'!C75 -> НС.КИИ.1 | E41: ='Нормативное соответствие'!D75 -> 0 | F41: ='Нормативное соответствие'!E75 -> 0 | G41: ='Нормативное соответствие'!F75 -> 0 | H41: ='Нормативное соответствие'!P75 -> 8.01 | I41: ='Нормативное соответствие'!K75 -> 0 | J41: ='Нормативное соответствие'!I75 -> 0 | K41: ='Нормативное соответствие'!L75 -> 0 | L41: =IF(J41=I41," ",K41-J41) | M41: =IF(H41<100, IF(K41>=G41,0,I41-K41), IF(H41<300, IF(K41>=F41,0,I41-K41), IF(K41>=E41,0,I41-K41))) -> 0 | N41: ='Нормативное соответствие'!Q75
A42: Нормативное соответствие | B42: КИИ | C42: ='Нормативное соответствие'!B76 -> Функции по обеспечению Иб возложены на структурное подразделение | D42: ='Нормативное соответствие'!C76 -> НС.КИИ.2 | E42: ='Нормативное соответствие'!D76 -> 0 | F42: ='Нормативное соответствие'!E76 -> 0 | G42: ='Нормативное соответствие'!F76 -> 0 | H42: ='Нормативное соответствие'!P76 -> 8.02 | I42: ='Нормативное соответствие'!K76 -> 0 | J42: ='Нормативное соответствие'!I76 -> 0 | K42: ='Нормативное соответствие'!L76 -> 0 | L42: =IF(J42=I42," ",K42-J42) | M42: =IF(H42<100, IF(K42>=G42,0,I42-K42), IF(H42<300, IF(K42>=F42,0,I42-K42), IF(K42>=E42,0,I42-K42))) -> 0 | N42: ='Нормативное соответствие'!Q76
A43: Нормативное соответствие | B43: КИИ | C43: ='Нормативное соответствие'!B77 -> Создана Комиссия по категорированию объектов КИИ | D43: ='Нормативное соответствие'!C77 -> НС.КИИ.3 | E43: ='Нормативное соответствие'!D77 -> 0 | F43: ='Нормативное соответствие'!E77 -> 0 | G43: ='Нормативное соответствие'!F77 -> 0 | H43: ='Нормативное соответствие'!P77 -> 8.03 | I43: ='Нормативное соответствие'!K77 -> 0 | J43: ='Нормативное соответствие'!I77 -> 0 | K43: ='Нормативное соответствие'!L77 -> 0 | L43: =IF(J43=I43," ",K43-J43) | M43: =IF(H43<100, IF(K43>=G43,0,I43-K43), IF(H43<300, IF(K43>=F43,0,I43-K43), IF(K43>=E43,0,I43-K43))) -> 0 | N43: ='Нормативное соответствие'!Q77
A44: Нормативное соответствие | B44: КИИ | C44: ='Нормативное соответствие'!B78 -> Проведен анализ критичных процессов, сформирован перечень систем, подлежащих категорированию (ИС, ИТКС, АСУ) | D44: ='Нормативное соответствие'!C78 -> НС.КИИ.4 | E44: ='Нормативное соответствие'!D78 -> 0 | F44: ='Нормативное соответствие'!E78 -> 0 | G44: ='Нормативное соответствие'!F78 -> 0 | H44: ='Нормативное соответствие'!P78 -> 8.04 | I44: ='Нормативное соответствие'!K78 -> 0 | J44: ='Нормативное соответствие'!I78 -> 0 | K44: ='Нормативное соответствие'!L78 -> 0 | L44: =IF(J44=I44," ",K44-J44) | M44: =IF(H44<100, IF(K44>=G44,0,I44-K44), IF(H44<300, IF(K44>=F44,0,I44-K44), IF(K44>=E44,0,I44-K44))) -> 0 | N44: ='Нормативное соответствие'!Q78
A45: Нормативное соответствие | B45: КИИ | C45: ='Нормативное соответствие'!B79 -> Проведено категорирование объктов КИИ | D45: ='Нормативное соответствие'!C79 -> НС.КИИ.5 | E45: ='Нормативное соответствие'!D79 -> 0 | F45: ='Нормативное соответствие'!E79 -> 0 | G45: ='Нормативное соответствие'!F79 -> 0 | H45: ='Нормативное соответствие'!P79 -> 8.05 | I45: ='Нормативное соответствие'!K79 -> 0 | J45: ='Нормативное соответствие'!I79 -> 0 | K45: ='Нормативное соответствие'!L79 -> 0 | L45: =IF(J45=I45," ",K45-J45) | M45: =IF(H45<100, IF(K45>=G45,0,I45-K45), IF(H45<300, IF(K45>=F45,0,I45-K45), IF(K45>=E45,0,I45-K45))) -> 0 | N45: ='Нормативное соответствие'!Q79
A46: Нормативное соответствие | B46: КИИ | C46: ='Нормативное соответствие'!B80 -> Сведения о системах передаются в ФСТЭК России | D46: ='Нормативное соответствие'!C80 -> НС.КИИ.6 | E46: ='Нормативное соответствие'!D80 -> 0 | F46: ='Нормативное соответствие'!E80 -> 0 | G46: ='Нормативное соответствие'!F80 -> 0 | H46: ='Нормативное соответствие'!P80 -> 8.06 | I46: ='Нормативное соответствие'!K80 -> 0 | J46: ='Нормативное соответствие'!I80 -> 0 | K46: ='Нормативное соответствие'!L80 -> 0 | L46: =IF(J46=I46," ",K46-J46) | M46: =IF(H46<100, IF(K46>=G46,0,I46-K46), IF(H46<300, IF(K46>=F46,0,I46-K46), IF(K46>=E46,0,I46-K46))) -> 0 | N46: ='Нормативное соответствие'!Q80
A47: Нормативное соответствие | B47: КИИ | C47: ='Нормативное соответствие'!B81 -> Реализованы организационные меры для обеспечения информационной безопаности значимых объектов КИИ (ЗОКИИ) | D47: ='Нормативное соответствие'!C81 -> НС.КИИ.7 | E47: ='Нормативное соответствие'!D81 -> 0 | F47: ='Нормативное соответствие'!E81 -> 0 | G47: ='Нормативное соответствие'!F81 -> 0 | H47: ='Нормативное соответствие'!P81 -> 8.07 | I47: ='Нормативное соответствие'!K81 -> 0 | J47: ='Нормативное соответствие'!I81 -> 0 | K47: ='Нормативное соответствие'!L81 -> 0 | L47: =IF(J47=I47," ",K47-J47) | M47: =IF(H47<100, IF(K47>=G47,0,I47-K47), IF(H47<300, IF(K47>=F47,0,I47-K47), IF(K47>=E47,0,I47-K47))) -> 0 | N47: ='Нормативное соответствие'!Q81
A48: Нормативное соответствие | B48: КИИ | C48: ='Нормативное соответствие'!B82 -> Реализованы технические меры для обеспечения информационной безопаности значимых объектов КИИ (ЗОКИИ) | D48: ='Нормативное соответствие'!C82 -> НС.КИИ.8 | E48: ='Нормативное соответствие'!D82 -> 0 | F48: ='Нормативное соответствие'!E82 -> 0 | G48: ='Нормативное соответствие'!F82 -> 0 | H48: ='Нормативное соответствие'!P82 -> 8.08 | I48: ='Нормативное соответствие'!K82 -> 0 | J48: ='Нормативное соответствие'!I82 -> 0 | K48: ='Нормативное соответствие'!L82 -> 0 | L48: =IF(J48=I48," ",K48-J48) | M48: =IF(H48<100, IF(K48>=G48,0,I48-K48), IF(H48<300, IF(K48>=F48,0,I48-K48), IF(K48>=E48,0,I48-K48))) -> 0 | N48: ='Нормативное соответствие'!Q82
A49: Нормативное соответствие | B49: КИИ | C49: ='Нормативное соответствие'!B83 -> Проведены мероприятия по оценке уровня защищенности информационных систем с привлечением организаций, имеющих соответствующие лицензии ФСБ России и ФСТЭК России | D49: ='Нормативное соответствие'!C83 -> НС.КИИ.9 | E49: ='Нормативное соответствие'!D83 -> 0 | F49: ='Нормативное соответствие'!E83 -> 0 | G49: ='Нормативное соответствие'!F83 -> 0 | H49: ='Нормативное соответствие'!P83 -> 8.09 | I49: ='Нормативное соответствие'!K83 -> 0 | J49: ='Нормативное соответствие'!I83 -> 0 | K49: ='Нормативное соответствие'!L83 -> 0 | L49: =IF(J49=I49," ",K49-J49) | M49: =IF(H49<100, IF(K49>=G49,0,I49-K49), IF(H49<300, IF(K49>=F49,0,I49-K49), IF(K49>=E49,0,I49-K49))) -> 0 | N49: ='Нормативное соответствие'!Q83
A50: Нормативное соответствие | B50: КИИ | C50: ='Нормативное соответствие'!B84 -> Подготовка к импортозамещению (до 1 января 2025г.) иностранного ПО на значимых объектах КИИ: в части общесистемного (ОС) и прикладного ПО | D50: ='Нормативное соответствие'!C84 -> НС.КИИ.10 | E50: ='Нормативное соответствие'!D84 -> 0 | F50: ='Нормативное соответствие'!E84 -> 0 | G50: ='Нормативное соответствие'!F84 -> 0 | H50: ='Нормативное соответствие'!P84 -> 8.1 | I50: ='Нормативное соответствие'!K84 -> 0 | J50: ='Нормативное соответствие'!I84 -> 0 | K50: ='Нормативное соответствие'!L84 -> 0 | L50: =IF(J50=I50," ",K50-J50) | M50: =IF(H50<100, IF(K50>=G50,0,I50-K50), IF(H50<300, IF(K50>=F50,0,I50-K50), IF(K50>=E50,0,I50-K50))) -> 0 | N50: ='Нормативное соответствие'!Q84
A51: Нормативное соответствие | B51: КИИ | C51: ='Нормативное соответствие'!B85 -> Подготовка к импортозамещению (до 1 января 2025г.) иностранного ПО на значимых объектах КИИ: в части ПО входящего в состав средств (систем) обеспечения ИБ | D51: ='Нормативное соответствие'!C85 -> НС.КИИ.11 | E51: ='Нормативное соответствие'!D85 -> 0 | F51: ='Нормативное соответствие'!E85 -> 0 | G51: ='Нормативное соответствие'!F85 -> 0 | H51: ='Нормативное соответствие'!P85 -> 8.11 | I51: ='Нормативное соответствие'!K85 -> 0 | J51: ='Нормативное соответствие'!I85 -> 0 | K51: ='Нормативное соответствие'!L85 -> 0 | L51: =IF(J51=I51," ",K51-J51) | M51: =IF(H51<100, IF(K51>=G51,0,I51-K51), IF(H51<300, IF(K51>=F51,0,I51-K51), IF(K51>=E51,0,I51-K51))) -> 0 | N51: ='Нормативное соответствие'!Q85
A52: Нормативное соответствие | B52: КИИ | C52: ='Нормативное соответствие'!B86 -> Подготовка к импортозамещению (до 1 января 2025г.) ПАК на значимых объектах КИИ | D52: ='Нормативное соответствие'!C86 -> НС.КИИ.12 | E52: ='Нормативное соответствие'!D86 -> 0 | F52: ='Нормативное соответствие'!E86 -> 0 | G52: ='Нормативное соответствие'!F86 -> 0 | H52: ='Нормативное соответствие'!P86 -> 8.12 | I52: ='Нормативное соответствие'!K86 -> 0 | K52: ='Нормативное соответствие'!L86 -> 0 | L52: =IF(J52=I52," ",K52-J52) | M52: =IF(H52<100, IF(K52>=G52,0,I52-K52), IF(H52<300, IF(K52>=F52,0,I52-K52), IF(K52>=E52,0,I52-K52))) -> 0 | N52: ='Нормативное соответствие'!Q86
A53: Нормативное соответствие | B53: КИИ | C53: ='Нормативное соответствие'!B87 -> Информирование и обучение персонала | D53: ='Нормативное соответствие'!C87 -> НС.КИИ.13 | E53: ='Нормативное соответствие'!D87 -> 0 | F53: ='Нормативное соответствие'!E87 -> 0 | G53: ='Нормативное соответствие'!F87 -> 0 | H53: ='Нормативное соответствие'!P87 -> 8.13 | I53: ='Нормативное соответствие'!K87 -> 0 | J53: ='Нормативное соответствие'!I87 -> 0 | K53: ='Нормативное соответствие'!L87 -> 0 | L53: =IF(J53=I53," ",K53-J53) | M53: =IF(H53<100, IF(K53>=G53,0,I53-K53), IF(H53<300, IF(K53>=F53,0,I53-K53), IF(K53>=E53,0,I53-K53))) -> 0 | N53: ='Нормативное соответствие'!Q87
A54: Нормативное соответствие | B54: КИИ | C54: ='Нормативное соответствие'!B88 -> Взаимодействие с ГОССОПКА | D54: ='Нормативное соответствие'!C88 -> НС.КИИ.14 | E54: ='Нормативное соответствие'!D88 -> 0 | F54: ='Нормативное соответствие'!E88 -> 0 | G54: ='Нормативное соответствие'!F88 -> 0 | H54: ='Нормативное соответствие'!P88 -> 8.14 | I54: ='Нормативное соответствие'!K88 -> 0 | K54: ='Нормативное соответствие'!L88 -> 0 | L54: =IF(J54=I54," ",K54-J54) | M54: =IF(H54<100, IF(K54>=G54,0,I54-K54), IF(H54<300, IF(K54>=F54,0,I54-K54), IF(K54>=E54,0,I54-K54))) -> 0
A55: Нормативное соответствие | B55: КИИ | C55: ='Нормативное соответствие'!B89 -> Предоставлены своевременные ответы на запросы ФСТЭК России о выполнении мер по защите информации, рекомендованных к реализации (ответы предоставлены на более чем 95% запросов) | D55: ='Нормативное соответствие'!C89 -> НС.КИИ.15 | E55: ='Нормативное соответствие'!D89 -> 0 | F55: ='Нормативное соответствие'!E89 -> 0 | G55: ='Нормативное соответствие'!F89 -> 0 | H55: ='Нормативное соответствие'!P89 -> 8.15 | I55: ='Нормативное соответствие'!K89 -> 0 | K55: ='Нормативное соответствие'!L89 -> 0 | L55: =IF(J55=I55," ",K55-J55) | M55: =IF(H55<100, IF(K55>=G55,0,I55-K55), IF(H55<300, IF(K55>=F55,0,I55-K55), IF(K55>=E55,0,I55-K55))) -> 0 | N55: ='Нормативное соответствие'!Q89
A56: Нормативное соответствие | B56: 250 Указ | C56: ='Нормативное соответствие'!B108 -> Созданы органы управления | D56: ='Нормативное соответствие'!C108 -> НС.250.1 | E56: ='Нормативное соответствие'!D108 -> 0.625 | F56: ='Нормативное соответствие'!E108 -> 0.625 | G56: ='Нормативное соответствие'!F108 -> 0.625 | H56: ='Нормативное соответствие'!P108 -> 9.01 | I56: ='Нормативное соответствие'!K108 -> 0.625 | J56: ='Нормативное соответствие'!I108 -> 0 | K56: ='Нормативное соответствие'!L108 -> 0.625 | L56: =IF(J56=I56," ",K56-J56) -> 0.625 | M56: =IF(H56<100, IF(K56>=G56,0,I56-K56), IF(H56<300, IF(K56>=F56,0,I56-K56), IF(K56>=E56,0,I56-K56))) -> 0 | N56: ='Нормативное соответствие'!Q108
A57: Нормативное соответствие | B57: 250 Указ | C57: ='Нормативное соответствие'!B109 -> Подразделение по ИБ | D57: ='Нормативное соответствие'!C109 -> НС.250.2 | E57: ='Нормативное соответствие'!D109 -> 1.6666667 | F57: ='Нормативное соответствие'!E109 -> 1.6666667 | G57: ='Нормативное соответствие'!F109 -> 1.6666667 | H57: ='Нормативное соответствие'!P109 -> 9.02 | I57: ='Нормативное соответствие'!K109 -> 1.6666667 | J57: ='Нормативное соответствие'!I109 -> 0 | K57: ='Нормативное соответствие'!L109 -> 1.6666667 | L57: =IF(J57=I57," ",K57-J57) -> 1.6666667 | M57: =IF(H57<100, IF(K57>=G57,0,I57-K57), IF(H57<300, IF(K57>=F57,0,I57-K57), IF(K57>=E57,0,I57-K57))) -> 0 | N57: ='Нормативное соответствие'!Q109
A58: Нормативное соответствие | B58: 250 Указ | C58: ='Нормативное соответствие'!B110 -> Организованно взаимодействие с подрядчиками | D58: ='Нормативное соответствие'!C110 -> НС.250.3 | E58: ='Нормативное соответствие'!D110 -> 0 | F58: ='Нормативное соответствие'!E110 -> 0 | G58: ='Нормативное соответствие'!F110 -> 0 | H58: ='Нормативное соответствие'!P110 -> 9.03 | I58: ='Нормативное соответствие'!K110 -> 0 | J58: ='Нормативное соответствие'!I110 -> 0 | K58: ='Нормативное соответствие'!L110 -> 0 | L58: =IF(J58=I58," ",K58-J58) | M58: =IF(H58<100, IF(K58>=G58,0,I58-K58), IF(H58<300, IF(K58>=F58,0,I58-K58), IF(K58>=E58,0,I58-K58))) -> 0 | N58: ='Нормативное соответствие'!Q110
A59: Нормативное соответствие | B59: 250 Указ | C59: ='Нормативное соответствие'!B112 -> Использование СЗИ | D59: ='Нормативное соответствие'!C112 -> НС.250.5 | E59: ='Нормативное соответствие'!D112 -> 0 | F59: ='Нормативное соответствие'!E112 -> 0 | G59: ='Нормативное соответствие'!F112 -> 0 | H59: ='Нормативное соответствие'!P112 -> 9.05 | I59: ='Нормативное соответствие'!K112 -> 0 | J59: ='Нормативное соответствие'!I112 -> 0 | K59: ='Нормативное соответствие'!L112 -> 0 | L59: =IF(J59=I59," ",K59-J59) | M59: =IF(H59<100, IF(K59>=G59,0,I59-K59), IF(H59<300, IF(K59>=F59,0,I59-K59), IF(K59>=E59,0,I59-K59))) -> 0 | N59: ='Нормативное соответствие'!Q112
A60: Нормативное соответствие | B60: 250 Указ | C60: ='Нормативное соответствие'!B113 -> Взаимодействие с ГОССОПКА | D60: ='Нормативное соответствие'!C113 -> НС.250.6 | E60: ='Нормативное соответствие'!D113 -> 0 | F60: ='Нормативное соответствие'!E113 -> 0 | G60: ='Нормативное соответствие'!F113 -> 0 | H60: ='Нормативное соответствие'!P113 -> 9.06 | I60: ='Нормативное соответствие'!K113 -> 0 | J60: ='Нормативное соответствие'!I113 -> 0 | K60: ='Нормативное соответствие'!L113 -> 0 | L60: =IF(J60=I60," ",K60-J60) | M60: =IF(H60<100, IF(K60>=G60,0,I60-K60), IF(H60<300, IF(K60>=F60,0,I60-K60), IF(K60>=E60,0,I60-K60))) -> 0 | N60: ='Нормативное соответствие'!Q113
A61: СЗИ | B61: Сканер уязвимостей | C61: =СЗИ!B86 -> Процент покрытия активов лицензиями | D61: =СЗИ!C86 -> СЗИ.САЗ.1 | E61: =СЗИ!D86 -> 5 | F61: =СЗИ!E86 -> 5 | G61: =СЗИ!F86 -> 0 | H61: =СЗИ!P86 -> 10.01 | I61: =СЗИ!K86 -> 0 | J61: =СЗИ!I86 -> 0 | K61: =СЗИ!L86 -> 0 | L61: =IF(J61=I61," ",K61-J61) | M61: =IF(H61<100, IF(K61>=G61,0,I61-K61), IF(H61<300, IF(K61>=F61,0,I61-K61), IF(K61>=E61,0,I61-K61))) -> 0 | N61: =СЗИ!Q86
A62: СЗИ | B62: Сканер уязвимостей | C62: =СЗИ!B87 -> Процент охваченных регулярным сканированием активов | D62: =СЗИ!C87 -> СЗИ.САЗ.2 | E62: =СЗИ!D87 -> 5 | F62: =СЗИ!E87 -> 3.2 | G62: =СЗИ!F87 -> 0 | H62: =СЗИ!P87 -> 10.02 | I62: =СЗИ!K87 -> 0 | J62: =СЗИ!I87 -> 0 | K62: =СЗИ!L87 -> 0 | L62: =IF(J62=I62," ",K62-J62) | M62: =IF(H62<100, IF(K62>=G62,0,I62-K62), IF(H62<300, IF(K62>=F62,0,I62-K62), IF(K62>=E62,0,I62-K62))) -> 0 | N62: =СЗИ!Q87
A63: СЗИ | B63: Сканер уязвимостей | C63: =СЗИ!B88 -> Внедрен процесс управления уязвимостями | D63: =СЗИ!C88 -> СЗИ.САЗ.3 | E63: =СЗИ!D88 -> 4 | F63: =СЗИ!E88 -> 3 | G63: =СЗИ!F88 -> 0 | H63: =СЗИ!P88 -> 10.03 | I63: =СЗИ!K88 -> 0 | J63: =СЗИ!I88 -> 0 | K63: =СЗИ!L88 -> 1 | L63: =IF(J63=I63," ",K63-J63) | M63: =IF(H63<100, IF(K63>=G63,0,I63-K63), IF(H63<300, IF(K63>=F63,0,I63-K63), IF(K63>=E63,0,I63-K63))) -> 0 | N63: =СЗИ!Q88
A64: СЗИ | B64: Сетевая безопасность (NGFW) | C64: =СЗИ!B76 -> Защита периметра и DMZ реализована с использованием аппаратных NGFW | D64: =СЗИ!C76 -> СЗИ.NGFW.1 | E64: =СЗИ!D76 -> 5 | F64: =СЗИ!E76 -> 5 | G64: =СЗИ!F76 -> 0 | H64: =СЗИ!P76 -> 11.01 | I64: =СЗИ!K76 -> 0 | J64: =СЗИ!I76 -> 0 | K64: =СЗИ!L76 -> 0 | L64: =IF(J64=I64," ",K64-J64) | M64: =IF(H64<100, IF(K64>=G64,0,I64-K64), IF(H64<300, IF(K64>=F64,0,I64-K64), IF(K64>=E64,0,I64-K64))) -> 0 | N64: =СЗИ!Q76
A65: СЗИ | B65: Сетевая безопасность (NGFW) | C65: =СЗИ!B77 -> Межсегментное взаимодействие реализовано с учетом критичности этих сегментов | D65: =СЗИ!C77 -> СЗИ.NGFW.2 | E65: =СЗИ!D77 -> 5 | F65: =СЗИ!E77 -> 5 | G65: =СЗИ!F77 -> 0 | H65: =СЗИ!P77 -> 11.02 | I65: =СЗИ!K77 -> 0 | J65: =СЗИ!I77 -> 0 | K65: =СЗИ!L77 -> 0 | L65: =IF(J65=I65," ",K65-J65) | M65: =IF(H65<100, IF(K65>=G65,0,I65-K65), IF(H65<300, IF(K65>=F65,0,I65-K65), IF(K65>=E65,0,I65-K65))) -> 0 | N65: =СЗИ!Q77
A66: СЗИ | B66: Сетевая безопасность (NGFW) | C66: =СЗИ!B78 -> Осуществляется централизованное управление и контроль настроек | D66: =СЗИ!C78 -> СЗИ.NGFW.3 | E66: =СЗИ!D78 -> 5 | F66: =СЗИ!E78 -> 3.2 | G66: =СЗИ!F78 -> 0 | H66: =СЗИ!P78 -> 11.03 | I66: =СЗИ!K78 -> 0 | J66: =СЗИ!I78 -> 0 | K66: =СЗИ!L78 -> 0 | L66: =IF(J66=I66," ",K66-J66) | M66: =IF(H66<100, IF(K66>=G66,0,I66-K66), IF(H66<300, IF(K66>=F66,0,I66-K66), IF(K66>=E66,0,I66-K66))) -> 0 | N66: =СЗИ!Q78
A67: СЗИ | B67: Сетевая безопасность (NGFW) | C67: =СЗИ!B79 -> Настроенные политики соответствуют ТТР Блока ИБ | D67: =СЗИ!C79 -> СЗИ.NGFW.4 | E67: =СЗИ!D79 -> 5 | F67: =СЗИ!E79 -> 3.2 | G67: =СЗИ!F79 -> 0 | H67: =СЗИ!P79 -> 11.04 | I67: =СЗИ!K79 -> 0 | J67: =СЗИ!I79 -> 0 | K67: =СЗИ!L79 -> 0 | L67: =IF(J67=I67," ",K67-J67) | M67: =IF(H67<100, IF(K67>=G67,0,I67-K67), IF(H67<300, IF(K67>=F67,0,I67-K67), IF(K67>=E67,0,I67-K67))) -> 0 | N67: =СЗИ!Q79
A68: СЗИ | B68: Защита и фильтрация сетевого трафика (Прокси-сервер) | C68: =СЗИ!B81 -> Доступ пользователей в интернет организован через PROXY | D68: =СЗИ!C81 -> СЗИ.PROXY.1 | E68: =СЗИ!D81 -> 5 | F68: =СЗИ!E81 -> 3.2 | G68: =СЗИ!F81 -> 0 | H68: =СЗИ!P81 -> 12.01 | I68: =СЗИ!K81 -> 0 | J68: =СЗИ!I81 -> 0 | K68: =СЗИ!L81 -> 0 | L68: =IF(J68=I68," ",K68-J68) | M68: =IF(H68<100, IF(K68>=G68,0,I68-K68), IF(H68<300, IF(K68>=F68,0,I68-K68), IF(K68>=E68,0,I68-K68))) -> 0 | N68: =СЗИ!Q81
A69: СЗИ | B69: Защита и фильтрация сетевого трафика (Прокси-сервер) | C69: =СЗИ!B82 -> Настроены политики разграничения доступа | D69: =СЗИ!C82 -> СЗИ.PROXY.2 | E69: =СЗИ!D82 -> 5 | F69: =СЗИ!E82 -> 3.2 | G69: =СЗИ!F82 -> 0 | H69: =СЗИ!P82 -> 12.02 | I69: =СЗИ!K82 -> 0 | J69: =СЗИ!I82 -> 0 | K69: =СЗИ!L82 -> 0 | L69: =IF(J69=I69," ",K69-J69) | M69: =IF(H69<100, IF(K69>=G69,0,I69-K69), IF(H69<300, IF(K69>=F69,0,I69-K69), IF(K69>=E69,0,I69-K69))) -> 0 | N69: =СЗИ!Q82
A70: СЗИ | B70: Защита и фильтрация сетевого трафика (Прокси-сервер) | C70: =СЗИ!B83 -> Проведена интеграция со средствами защиты от ВПО и AD | D70: =СЗИ!C83 -> СЗИ.PROXY.3 | E70: =СЗИ!D83 -> 5 | F70: =СЗИ!E83 -> 2.5 | G70: =СЗИ!F83 -> 0 | H70: =СЗИ!P83 -> 12.03 | I70: =СЗИ!K83 -> 0 | J70: =СЗИ!I83 -> 0 | K70: =СЗИ!L83 -> 0 | L70: =IF(J70=I70," ",K70-J70) | M70: =IF(H70<100, IF(K70>=G70,0,I70-K70), IF(H70<300, IF(K70>=F70,0,I70-K70), IF(K70>=E70,0,I70-K70))) -> 0 | N70: =СЗИ!Q83
A71: СЗИ | B71: Защита и фильтрация сетевого трафика (Прокси-сервер) | C71: =СЗИ!B84 -> Настроенные политики соответствуют ТТР Блока ИБ | D71: =СЗИ!C84 -> СЗИ.PROXY.4 | E71: =СЗИ!D84 -> 5 | F71: =СЗИ!E84 -> 3.2 | G71: =СЗИ!F84 -> 0 | H71: =СЗИ!P84 -> 12.04 | I71: =СЗИ!K84 -> 0 | J71: =СЗИ!I84 -> 0 | K71: =СЗИ!L84 -> 0 | L71: =IF(J71=I71," ",K71-J71) | M71: =IF(H71<100, IF(K71>=G71,0,I71-K71), IF(H71<300, IF(K71>=F71,0,I71-K71), IF(K71>=E71,0,I71-K71))) -> 0 | N71: =СЗИ!Q84
A72: Управление ИБ | B72: Система управления ИБ | C72: ='Управление ИБ'!B61 -> Утверждена Политика информационной безопасности Общества | D72: ='Управление ИБ'!C61 -> СУИБ.УР.1 | E72: ='Управление ИБ'!D61 -> 5 | F72: ='Управление ИБ'!E61 -> 5 | G72: ='Управление ИБ'!F61 -> 5 | H72: ='Управление ИБ'!P61 -> 14.01 | I72: ='Управление ИБ'!K61 -> 5 | J72: ='Управление ИБ'!I61 -> 0 | K72: ='Управление ИБ'!L61 -> 5 | L72: =IF(J72=I72," ",K72-J72) -> 5 | M72: =IF(H72<100, IF(K72>=G72,0,I72-K72), IF(H72<300, IF(K72>=F72,0,I72-K72), IF(K72>=E72,0,I72-K72))) -> 0 | N72: ='Управление ИБ'!Q61
A73: Управление ИБ | B73: Система управления ИБ | C73: ='Управление ИБ'!B62 -> Назначено лицо, ответственное за обеспечение информационной безопасности | D73: ='Управление ИБ'!C62 -> СУИБ.УР.10 | E73: ='Управление ИБ'!D62 -> 5 | F73: ='Управление ИБ'!E62 -> 5 | G73: ='Управление ИБ'!F62 -> 5 | H73: ='Управление ИБ'!P62 -> 14.02 | I73: ='Управление ИБ'!K62 -> 5 | J73: ='Управление ИБ'!I62 -> 0 | K73: ='Управление ИБ'!L62 -> 5 | L73: =IF(J73=I73," ",K73-J73) -> 5 | M73: =IF(H73<100, IF(K73>=G73,0,I73-K73), IF(H73<300, IF(K73>=F73,0,I73-K73), IF(K73>=E73,0,I73-K73))) -> 0 | N73: ='Управление ИБ'!Q62
A74: Управление ИБ | B74: Система управления ИБ | C74: ='Управление ИБ'!B63 -> Создано подразделение по ИБ или задачи возложены на подразделение | D74: ='Управление ИБ'!C63 -> СУИБ.УР.11 | E74: ='Управление ИБ'!D63 -> 5 | F74: ='Управление ИБ'!E63 -> 5 | G74: ='Управление ИБ'!F63 -> 5 | H74: ='Управление ИБ'!P63 -> 14.03 | I74: ='Управление ИБ'!K63 -> 5 | J74: ='Управление ИБ'!I63 -> 0 | K74: ='Управление ИБ'!L63 -> 5 | L74: =IF(J74=I74," ",K74-J74) -> 5 | M74: =IF(H74<100, IF(K74>=G74,0,I74-K74), IF(H74<300, IF(K74>=F74,0,I74-K74), IF(K74>=E74,0,I74-K74))) -> 0 | N74: ='Управление ИБ'!Q63
A75: Управление ИБ | B75: Система управления ИБ | C75: ='Управление ИБ'!B64 -> Определены цели обеспечения ИБ | D75: ='Управление ИБ'!C64 -> СУИБ.УР.2 | E75: ='Управление ИБ'!D64 -> 5 | F75: ='Управление ИБ'!E64 -> 5 | G75: ='Управление ИБ'!F64 -> 0 | H75: ='Управление ИБ'!P64 -> 14.04 | I75: ='Управление ИБ'!K64 -> 0 | J75: ='Управление ИБ'!I64 -> 0 | K75: ='Управление ИБ'!L64 -> 5 | L75: =IF(J75=I75," ",K75-J75) | M75: =IF(H75<100, IF(K75>=G75,0,I75-K75), IF(H75<300, IF(K75>=F75,0,I75-K75), IF(K75>=E75,0,I75-K75))) -> 0 | N75: ='Управление ИБ'!Q64
A76: Управление ИБ | B76: Система управления ИБ | C76: ='Управление ИБ'!B65 -> Наличие планов развития ИБ | D76: ='Управление ИБ'!C65 -> СУИБ.УР.3 | E76: ='Управление ИБ'!D65 -> 5 | F76: ='Управление ИБ'!E65 -> 5 | G76: ='Управление ИБ'!F65 -> 5 | H76: ='Управление ИБ'!P65 -> 14.05 | I76: ='Управление ИБ'!K65 -> 5 | J76: ='Управление ИБ'!I65 -> 0 | K76: ='Управление ИБ'!L65 -> 5 | L76: =IF(J76=I76," ",K76-J76) -> 5 | M76: =IF(H76<100, IF(K76>=G76,0,I76-K76), IF(H76<300, IF(K76>=F76,0,I76-K76), IF(K76>=E76,0,I76-K76))) -> 0 | N76: ='Управление ИБ'!Q65
A77: Управление ИБ | B77: Система управления ИБ | C77: ='Управление ИБ'!B66 -> Статус достижения целей ИБ регулярно доводится до руководства Общества | D77: ='Управление ИБ'!C66 -> СУИБ.УР.4 | E77: ='Управление ИБ'!D66 -> 5 | F77: ='Управление ИБ'!E66 -> 3.2 | G77: ='Управление ИБ'!F66 -> 0 | H77: ='Управление ИБ'!P66 -> 14.06 | I77: ='Управление ИБ'!K66 -> 0 | J77: ='Управление ИБ'!I66 -> 0 | K77: ='Управление ИБ'!L66 -> 1.6 | L77: =IF(J77=I77," ",K77-J77) | M77: =IF(H77<100, IF(K77>=G77,0,I77-K77), IF(H77<300, IF(K77>=F77,0,I77-K77), IF(K77>=E77,0,I77-K77))) -> 0 | N77: ='Управление ИБ'!Q66
A78: Управление ИБ | B78: Система управления ИБ | C78: ='Управление ИБ'!B67 -> Проводится регулярный (ежегодный) внешний аудит | D78: ='Управление ИБ'!C67 -> СУИБ.УР.5 | E78: ='Управление ИБ'!D67 -> 5 | F78: ='Управление ИБ'!E67 -> 5 | G78: ='Управление ИБ'!F67 -> 0 | H78: ='Управление ИБ'!P67 -> 14.07 | I78: ='Управление ИБ'!K67 -> 0 | J78: ='Управление ИБ'!I67 -> 0 | K78: ='Управление ИБ'!L67 -> 0 | L78: =IF(J78=I78," ",K78-J78) | M78: =IF(H78<100, IF(K78>=G78,0,I78-K78), IF(H78<300, IF(K78>=F78,0,I78-K78), IF(K78>=E78,0,I78-K78))) -> 0 | N78: ='Управление ИБ'!Q67
A79: Управление ИБ | B79: Система управления ИБ | C79: ='Управление ИБ'!B68 -> Проводятся регулярные (ежегодные) киберучения | D79: ='Управление ИБ'!C68 -> СУИБ.УР.6 | E79: ='Управление ИБ'!D68 -> 5 | F79: ='Управление ИБ'!E68 -> 5 | G79: ='Управление ИБ'!F68 -> 0 | H79: ='Управление ИБ'!P68 -> 14.08 | I79: ='Управление ИБ'!K68 -> 0 | J79: ='Управление ИБ'!I68 -> 0 | K79: ='Управление ИБ'!L68 -> 0 | L79: =IF(J79=I79," ",K79-J79) | M79: =IF(H79<100, IF(K79>=G79,0,I79-K79), IF(H79<300, IF(K79>=F79,0,I79-K79), IF(K79>=E79,0,I79-K79))) -> 0 | N79: ='Управление ИБ'!Q68
A80: Управление ИБ | B80: Система управления ИБ | C80: ='Управление ИБ'!B69 -> Требования по ИБ к информационным активам (ИА) предьявляются на стадиях принятия решения о создании/приобретении ИА | D80: ='Управление ИБ'!C69 -> СУИБ.УР.7 | E80: ='Управление ИБ'!D69 -> 5 | F80: ='Управление ИБ'!E69 -> 3.2 | G80: ='Управление ИБ'!F69 -> 0 | H80: ='Управление ИБ'!P69 -> 14.09 | I80: ='Управление ИБ'!K69 -> 0 | J80: ='Управление ИБ'!I69 -> 0 | K80: ='Управление ИБ'!L69 -> 1.6 | L80: =IF(J80=I80," ",K80-J80) | M80: =IF(H80<100, IF(K80>=G80,0,I80-K80), IF(H80<300, IF(K80>=F80,0,I80-K80), IF(K80>=E80,0,I80-K80))) -> 0 | N80: ='Управление ИБ'!Q69
A81: Управление ИБ | B81: Система управления ИБ | C81: ='Управление ИБ'!B70 -> Актуализация внутренних нормативных документов в соответствии с изменениями в нормативно-правовых актах и распоряжениях регуляторов и контрольных (надзорных) ведомств в сфере ИБ | D81: ='Управление ИБ'!C70 -> СУИБ.УР.8 | E81: ='Управление ИБ'!D70 -> 5 | F81: ='Управление ИБ'!E70 -> 5 | G81: ='Управление ИБ'!F70 -> 0 | H81: ='Управление ИБ'!P70 -> 14.1 | I81: ='Управление ИБ'!K70 -> 0 | J81: ='Управление ИБ'!I70 -> 0 | K81: ='Управление ИБ'!L70 -> 5 | L81: =IF(J81=I81," ",K81-J81) | M81: =IF(H81<100, IF(K81>=G81,0,I81-K81), IF(H81<300, IF(K81>=F81,0,I81-K81), IF(K81>=E81,0,I81-K81))) -> 0 | N81: ='Управление ИБ'!Q70
A82: Управление ИБ | B82: Инвентаризация | C82: ='Управление ИБ'!B112 -> Ведется учет используемых и (или) эксплуатируемых физических устройств (АРМ, сервера, принтеры, коммутационное оборудование и т.п.) | D82: ='Управление ИБ'!C112 -> УИБ.ИН.1 | E82: ='Управление ИБ'!D112 -> 5 | F82: ='Управление ИБ'!E112 -> 3.2 | G82: ='Управление ИБ'!F112 -> 1.6 | H82: ='Управление ИБ'!P112 -> 15.01 | I82: ='Управление ИБ'!K112 -> 1.6 | J82: ='Управление ИБ'!I112 -> 0 | K82: ='Управление ИБ'!L112 -> 1.6 | L82: =IF(J82=I82," ",K82-J82) -> 1.6 | M82: =IF(H82<100, IF(K82>=G82,0,I82-K82), IF(H82<300, IF(K82>=F82,0,I82-K82), IF(K82>=E82,0,I82-K82))) -> 0 | N82: ='Управление ИБ'!Q112
A83: Управление ИБ | B83: Инвентаризация | C83: ='Управление ИБ'!B113 -> Ведется учет имеющегося и используемого ПО | D83: ='Управление ИБ'!C113 -> УИБ.ИН.2 | E83: ='Управление ИБ'!D113 -> 5 | F83: ='Управление ИБ'!E113 -> 3.2 | G83: ='Управление ИБ'!F113 -> 1.6 | H83: ='Управление ИБ'!P113 -> 15.02 | I83: ='Управление ИБ'!K113 -> 1.6 | J83: ='Управление ИБ'!I113 -> 0 | K83: ='Управление ИБ'!L113 -> 0 | L83: =IF(J83=I83," ",K83-J83) -> 0 | M83: =IF(H83<100, IF(K83>=G83,0,I83-K83), IF(H83<300, IF(K83>=F83,0,I83-K83), IF(K83>=E83,0,I83-K83))) -> 1.6 | N83: ='Управление ИБ'!Q113 -> - Разработать и поддерживать реестр используемого ПО: - Реестр должен содержать название ПО, разработчика, дату установки/начала использования и бизнес-задачу ПО; - При необходимости указаны версия, механизм развертывания и дата вывода из эксплуатации; - Для программ с веб- и мобильным доступом должны быть указаны их URL, магазин приложений; - Реестр должен пересматриваться и обновляться не реже одного раза в полугодие; - Для ведения учета имеющегося и используемого ПО применять средства автоматизации.
A84: Управление ИБ | B84: Инвентаризация | C84: ='Управление ИБ'!B114 -> Ведется персонифицированный учет учетных записей (УЗ), технологических УЗ, привилегированных УЗ и УЗ групповых почтовых ящиков | D84: ='Управление ИБ'!C114 -> УИБ.ИН.3 | E84: ='Управление ИБ'!D114 -> 5 | F84: ='Управление ИБ'!E114 -> 3.2 | G84: ='Управление ИБ'!F114 -> 1.6 | H84: ='Управление ИБ'!P114 -> 15.03 | I84: ='Управление ИБ'!K114 -> 1.6 | J84: ='Управление ИБ'!I114 -> 0 | K84: ='Управление ИБ'!L114 -> 1.6 | L84: =IF(J84=I84," ",K84-J84) -> 1.6 | M84: =IF(H84<100, IF(K84>=G84,0,I84-K84), IF(H84<300, IF(K84>=F84,0,I84-K84), IF(K84>=E84,0,I84-K84))) -> 0 | N84: ='Управление ИБ'!Q114
A85: Управление ИБ | B85: Инвентаризация | C85: ='Управление ИБ'!B115 -> Контроль белого (разрешенного) и черного (неразрешенного) списка программного обеспечения. | D85: ='Управление ИБ'!C115 -> УИБ.ИН.4 | E85: ='Управление ИБ'!D115 -> 5 | F85: ='Управление ИБ'!E115 -> 3.2 | G85: ='Управление ИБ'!F115 -> 1.6 | H85: ='Управление ИБ'!P115 -> 15.04 | I85: ='Управление ИБ'!K115 -> 1.6 | J85: ='Управление ИБ'!I115 -> 0 | K85: ='Управление ИБ'!L115 -> 0 | L85: =IF(J85=I85," ",K85-J85) -> 0 | M85: =IF(H85<100, IF(K85>=G85,0,I85-K85), IF(H85<300, IF(K85>=F85,0,I85-K85), IF(K85>=E85,0,I85-K85))) -> 1.6 | N85: ='Управление ИБ'!Q115 -> - Реализовать процесс авторизации ПО до начала его применения в Обществе; - Разработать и поддерживать реестр разрешенного и запрещенного ПО: v Реестр должен содержать название ПО, разработчика, дату установки/начала использования и бизнес-задачу ПО. При необходимости должны быть указаны версия, механизм развертывания и дата вывода из эксплуатации; - Для программ с веб- и мобильным доступом должны быть указаны их URL, магазин приложений; - Реестр должен пересматриваться и обновляться не реже одного раза в полугодие
A86: Управление ИБ | B86: Инвентаризация | C86: ='Управление ИБ'!B116 -> Ведется учет использования адресных пространств (IP) | D86: ='Управление ИБ'!C116 -> УИБ.ИН.5 | E86: ='Управление ИБ'!D116 -> 5 | F86: ='Управление ИБ'!E116 -> 3.2 | G86: ='Управление ИБ'!F116 -> 1.6 | H86: ='Управление ИБ'!P116 -> 15.05 | I86: ='Управление ИБ'!K116 -> 1.6 | J86: ='Управление ИБ'!I116 -> 0 | K86: ='Управление ИБ'!L116 -> 0 | L86: =IF(J86=I86," ",K86-J86) -> 0 | M86: =IF(H86<100, IF(K86>=G86,0,I86-K86), IF(H86<300, IF(K86>=F86,0,I86-K86), IF(K86>=E86,0,I86-K86))) -> 1.6 | N86: ='Управление ИБ'!Q116 -> - Разработать и поддерживать реестр адресных пространств (IP); - Реестр должен пересматриваться и обновляться не реже одного раза в полугодие
A87: Управление ИБ | B87: Инвентаризация | C87: ='Управление ИБ'!B117 -> Ведется учет созданных, используемых и (или) эксплуатируемых ИС | D87: ='Управление ИБ'!C117 -> УИБ.ИН.6 | E87: ='Управление ИБ'!D117 -> 5 | F87: ='Управление ИБ'!E117 -> 3.2 | G87: ='Управление ИБ'!F117 -> 1.6 | H87: ='Управление ИБ'!P117 -> 15.06 | I87: ='Управление ИБ'!K117 -> 1.6 | J87: ='Управление ИБ'!I117 -> 0 | K87: ='Управление ИБ'!L117 -> 0 | L87: =IF(J87=I87," ",K87-J87) -> 0 | M87: =IF(H87<100, IF(K87>=G87,0,I87-K87), IF(H87<300, IF(K87>=F87,0,I87-K87), IF(K87>=E87,0,I87-K87))) -> 1.6 | N87: ='Управление ИБ'!Q117 -> - Разработать и поддерживать реестр информационных систем; - Реестр должен пересматриваться и обновляться не реже одного раза в полугодие
A88: Управление ИБ | B88: Инвентаризация | C88: ='Управление ИБ'!B118 -> Ведется учет опубликованных на внешнем периметре информационные системы, домены | D88: ='Управление ИБ'!C118 -> УИБ.ИН.7 | E88: ='Управление ИБ'!D118 -> 5 | F88: ='Управление ИБ'!E118 -> 3.2 | G88: ='Управление ИБ'!F118 -> 3.2 | H88: ='Управление ИБ'!P118 -> 15.07 | I88: ='Управление ИБ'!K118 -> 3.2 | J88: ='Управление ИБ'!I118 -> 0 | K88: ='Управление ИБ'!L118 -> 0 | L88: =IF(J88=I88," ",K88-J88) -> 0 | M88: =IF(H88<100, IF(K88>=G88,0,I88-K88), IF(H88<300, IF(K88>=F88,0,I88-K88), IF(K88>=E88,0,I88-K88))) -> 3.2 | N88: ='Управление ИБ'!Q118 -> - Разработать и поддерживать реестр информационных систем и доменов, опубликованных на внешнем периметре; - Реестр должен пересматриваться и обновляться не реже одного раза в полугодие
A89: Управление ИБ | B89: Инвентаризация | C89: ='Управление ИБ'!B119 -> За информационными активами закреплены ответственные | D89: ='Управление ИБ'!C119 -> УИБ.ИН.8 | E89: ='Управление ИБ'!D119 -> 5 | F89: ='Управление ИБ'!E119 -> 3.2 | G89: ='Управление ИБ'!F119 -> 3.2 | H89: ='Управление ИБ'!P119 -> 15.08 | I89: ='Управление ИБ'!K119 -> 3.2 | J89: ='Управление ИБ'!I119 -> 0 | K89: ='Управление ИБ'!L119 -> 0 | L89: =IF(J89=I89," ",K89-J89) -> 0 | M89: =IF(H89<100, IF(K89>=G89,0,I89-K89), IF(H89<300, IF(K89>=F89,0,I89-K89), IF(K89>=E89,0,I89-K89))) -> 3.2 | N89: ='Управление ИБ'!Q119 -> 0
A90: Управление ИБ | B90: Инвентаризация | C90: ='Управление ИБ'!B120 -> Наличие специализированного ПО для хранения инвентаризационных данных | D90: ='Управление ИБ'!C120 -> УИБ.ИН.9 | E90: ='Управление ИБ'!D120 -> 5 | F90: ='Управление ИБ'!E120 -> 3.2 | G90: ='Управление ИБ'!F120 -> 0 | H90: ='Управление ИБ'!P120 -> 15.09 | I90: ='Управление ИБ'!K120 -> 0 | J90: ='Управление ИБ'!I120 -> 0 | K90: ='Управление ИБ'!L120 -> 0 | L90: =IF(J90=I90," ",K90-J90) | M90: =IF(H90<100, IF(K90>=G90,0,I90-K90), IF(H90<300, IF(K90>=F90,0,I90-K90), IF(K90>=E90,0,I90-K90))) -> 0 | N90: ='Управление ИБ'!Q120
A91: Управление ИБ | B91: Инвентаризация | C91: ='Управление ИБ'!B121 -> Используется инструментарий активного/пассивного обнаружения активов | D91: ='Управление ИБ'!C121 -> УИБ.ИН.10 | E91: ='Управление ИБ'!D121 -> 5 | F91: ='Управление ИБ'!E121 -> 3.2 | G91: ='Управление ИБ'!F121 -> 0 | H91: ='Управление ИБ'!P121 -> 15.1 | I91: ='Управление ИБ'!K121 -> 0 | J91: ='Управление ИБ'!I121 -> 0 | K91: ='Управление ИБ'!L121 -> 0 | L91: =IF(J91=I91," ",K91-J91) | M91: =IF(H91<100, IF(K91>=G91,0,I91-K91), IF(H91<300, IF(K91>=F91,0,I91-K91), IF(K91>=E91,0,I91-K91))) -> 0 | N91: ='Управление ИБ'!Q121
A92: Управление ИБ | B92: Инвентаризация | C92: ='Управление ИБ'!B122 -> Результаты работы сканеров уязвимости являются источниками для пополнения БД систем инвентаризации | D92: ='Управление ИБ'!C122 -> УИБ.ИН.11 | E92: ='Управление ИБ'!D122 -> 5 | F92: ='Управление ИБ'!E122 -> 3.2 | G92: ='Управление ИБ'!F122 -> 0 | H92: ='Управление ИБ'!P122 -> 15.11 | I92: ='Управление ИБ'!K122 -> 0 | J92: ='Управление ИБ'!I122 -> 0 | K92: ='Управление ИБ'!L122 -> 0 | L92: =IF(J92=I92," ",K92-J92) | M92: =IF(H92<100, IF(K92>=G92,0,I92-K92), IF(H92<300, IF(K92>=F92,0,I92-K92), IF(K92>=E92,0,I92-K92))) -> 0 | N92: ='Управление ИБ'!Q122
A93: Управление ИБ | B93: Инвентаризация | C93: ='Управление ИБ'!B123 -> Производится регулярный контроль фактического состава созданных, используемых и (или) эксплуатируемых информационных активов и их корректного размещения в сегментах вычислительных сетей | D93: ='Управление ИБ'!C123 -> УИБ.ИН.12 | E93: ='Управление ИБ'!D123 -> 5 | F93: ='Управление ИБ'!E123 -> 3.2 | G93: ='Управление ИБ'!F123 -> 0 | H93: ='Управление ИБ'!P123 -> 15.12 | I93: ='Управление ИБ'!K123 -> 0 | J93: ='Управление ИБ'!I123 -> 0 | K93: ='Управление ИБ'!L123 -> 0 | L93: =IF(J93=I93," ",K93-J93) | M93: =IF(H93<100, IF(K93>=G93,0,I93-K93), IF(H93<300, IF(K93>=F93,0,I93-K93), IF(K93>=E93,0,I93-K93))) -> 0 | N93: ='Управление ИБ'!Q123
A94: Управление ИБ | B94: Инвентаризация | C94: ='Управление ИБ'!B124 -> Осуществляется разработка, ведение, актуализация, хранение проектной, рабочей, эксплуатационной документации на информационные системы | D94: ='Управление ИБ'!C124 -> УИБ.ИН.13 | E94: ='Управление ИБ'!D124 -> 5 | F94: ='Управление ИБ'!E124 -> 3.2 | G94: ='Управление ИБ'!F124 -> 0 | H94: ='Управление ИБ'!P124 -> 15.13 | I94: ='Управление ИБ'!K124 -> 0 | J94: ='Управление ИБ'!I124 -> 0 | K94: ='Управление ИБ'!L124 -> 0 | L94: =IF(J94=I94," ",K94-J94) | M94: =IF(H94<100, IF(K94>=G94,0,I94-K94), IF(H94<300, IF(K94>=F94,0,I94-K94), IF(K94>=E94,0,I94-K94))) -> 0 | N94: ='Управление ИБ'!Q124
A95: Управление ИБ | B95: Управление доступом | C95: ='Управление ИБ'!B169 -> Наличие политики/регламентов управления доступом к ИА | D95: ='Управление ИБ'!C169 -> УИБ.УД.1 | E95: ='Управление ИБ'!D169 -> 3.2 | F95: ='Управление ИБ'!E169 -> 1.6 | G95: ='Управление ИБ'!F169 -> 0 | H95: ='Управление ИБ'!P169 -> 16.01 | I95: ='Управление ИБ'!K169 -> 0 | J95: ='Управление ИБ'!I169 -> 0 | K95: ='Управление ИБ'!L169 -> 0 | L95: =IF(J95=I95," ",K95-J95) | M95: =IF(H95<100, IF(K95>=G95,0,I95-K95), IF(H95<300, IF(K95>=F95,0,I95-K95), IF(K95>=E95,0,I95-K95))) -> 0 | N95: ='Управление ИБ'!Q169
A96: Управление ИБ | B96: Управление доступом | C96: ='Управление ИБ'!B170 -> Доступ к ИА Осуществляется на основе согласованных с ИБ ролевых моделей (исключение SoD-конфликтов) | D96: ='Управление ИБ'!C170 -> УИБ.УД.2 | E96: ='Управление ИБ'!D170 -> 5 | F96: ='Управление ИБ'!E170 -> 3.2 | G96: ='Управление ИБ'!F170 -> 1.6 | H96: ='Управление ИБ'!P170 -> 16.02 | I96: ='Управление ИБ'!K170 -> 1.6 | J96: ='Управление ИБ'!I170 -> 0 | K96: ='Управление ИБ'!L170 -> 0 | L96: =IF(J96=I96," ",K96-J96) -> 0 | M96: =IF(H96<100, IF(K96>=G96,0,I96-K96), IF(H96<300, IF(K96>=F96,0,I96-K96), IF(K96>=E96,0,I96-K96))) -> 1.6 | N96: ='Управление ИБ'!Q170 -> - Определить порядок формирования ролевых моделей; - Разработать ролевые модели для информационных систем и согласовать с подразделением ИБ.
A97: Управление ИБ | B97: Управление доступом | C97: ='Управление ИБ'!B171 -> ИБ участвует в согласовании и предоставлении доступа | D97: ='Управление ИБ'!C171 -> УИБ.УД.3 | E97: ='Управление ИБ'!D171 -> 5 | F97: ='Управление ИБ'!E171 -> 3.2 | G97: ='Управление ИБ'!F171 -> 1.6 | H97: ='Управление ИБ'!P171 -> 16.03 | I97: ='Управление ИБ'!K171 -> 1.6 | J97: ='Управление ИБ'!I171 -> 0 | K97: ='Управление ИБ'!L171 -> 0 | L97: =IF(J97=I97," ",K97-J97) -> 0 | M97: =IF(H97<100, IF(K97>=G97,0,I97-K97), IF(H97<300, IF(K97>=F97,0,I97-K97), IF(K97>=E97,0,I97-K97))) -> 1.6 | N97: ='Управление ИБ'!Q171 -> - Регламентировать процесс согласования прав доступа для ИС, находящихся в промышленной эксплуатации; - Включить подразделение ИБ в цепочку согласования.
A98: Управление ИБ | B98: Управление доступом | C98: ='Управление ИБ'!B172 -> При приеме нового сотрудника, изменении должности или роли осуществляется автоматическое назначение прав доступа | D98: ='Управление ИБ'!C172 -> УИБ.УД.4 | E98: ='Управление ИБ'!D172 -> 3.2 | F98: ='Управление ИБ'!E172 -> 1.6 | G98: ='Управление ИБ'!F172 -> 0 | H98: ='Управление ИБ'!P172 -> 16.04 | I98: ='Управление ИБ'!K172 -> 0 | J98: ='Управление ИБ'!I172 -> 0 | K98: ='Управление ИБ'!L172 -> 0 | L98: =IF(J98=I98," ",K98-J98) | M98: =IF(H98<100, IF(K98>=G98,0,I98-K98), IF(H98<300, IF(K98>=F98,0,I98-K98), IF(K98>=E98,0,I98-K98))) -> 0 | N98: ='Управление ИБ'!Q172
A99: Управление ИБ | B99: Управление доступом | C99: ='Управление ИБ'!B173 -> При увольнении работника происходит автоматический отзыв прав и блокировка УЗ | D99: ='Управление ИБ'!C173 -> УИБ.УД.5 | E99: ='Управление ИБ'!D173 -> 3.2 | F99: ='Управление ИБ'!E173 -> 1.6 | G99: ='Управление ИБ'!F173 -> 0 | H99: ='Управление ИБ'!P173 -> 16.05 | I99: ='Управление ИБ'!K173 -> 0 | J99: ='Управление ИБ'!I173 -> 0 | K99: ='Управление ИБ'!L173 -> 0 | L99: =IF(J99=I99," ",K99-J99) | M99: =IF(H99<100, IF(K99>=G99,0,I99-K99), IF(H99<300, IF(K99>=F99,0,I99-K99), IF(K99>=E99,0,I99-K99))) -> 0 | N99: ='Управление ИБ'!Q173
A100: Управление ИБ | B100: Управление доступом | C100: ='Управление ИБ'!B174 -> Проводится регулярный аудит УЗ и доступов не реже одного раза в год | D100: ='Управление ИБ'!C174 -> УИБ.УД.6 | E100: ='Управление ИБ'!D174 -> 5 | F100: ='Управление ИБ'!E174 -> 3.2 | G100: ='Управление ИБ'!F174 -> 1.6 | H100: ='Управление ИБ'!P174 -> 16.06 | I100: ='Управление ИБ'!K174 -> 1.6 | J100: ='Управление ИБ'!I174 -> 0 | K100: ='Управление ИБ'!L174 -> 1.6 | L100: =IF(J100=I100," ",K100-J100) -> 1.6 | M100: =IF(H100<100, IF(K100>=G100,0,I100-K100), IF(H100<300, IF(K100>=F100,0,I100-K100), IF(K100>=E100,0,I100-K100))) -> 0 | N100: ='Управление ИБ'!Q174
...

Sheet Управление ИБ
B1: Система управления ИБ | N1: =COUNTA(N2:N6960) -> 97
G40: =Расчет!$F$2 -> 45017 | H40: =Расчет!$H$2 -> 45444 | I40: 45657 | L40: =TODAY() -> 46038
B41: Категория | C41: Сокращенное наименование | D41: КБ3 | E41: КБ2 | F41: КБ1 | G41: Исторические данные | H41: Исторические данные | I41: Исторические данные | J41: 2026 | K41: Расчетный показатель 2025 | L41: Текущий показатель
B42: =B60 -> Система управления ИБ | C42: =C60 -> СУИБ | D42: =AVERAGE('Управление ИБ'!D61:D70) -> 5 | E42: =AVERAGE('Управление ИБ'!E61:E70) -> 4.64 | F42: =AVERAGE('Управление ИБ'!F61:F70) -> 2 | G42: =AVERAGE('Управление ИБ'!G61:G70) -> #DIV/0! | H42: =AVERAGE('Управление ИБ'!H61:H70) -> #DIV/0! | I42: =AVERAGE('Управление ИБ'!I61:I70) -> #DIV/0! | J42: =AVERAGE('Управление ИБ'!J61:J70) -> #DIV/0! | K42: =AVERAGE('Управление ИБ'!K61:K70) -> 2 | L42: =AVERAGE('Управление ИБ'!L61:L70) -> 3.32
B43: =B71 -> Управление рисками | C43: УР | D43: =AVERAGE('Управление ИБ'!D72:D76) -> 4.8 | E43: =AVERAGE('Управление ИБ'!E72:E76) -> 2 | F43: =AVERAGE('Управление ИБ'!F72:F76) -> 1 | G43: =AVERAGE('Управление ИБ'!G72:G76) -> #DIV/0! | H43: =AVERAGE('Управление ИБ'!H72:H76) -> #DIV/0! | I43: =AVERAGE('Управление ИБ'!I72:I76) -> #DIV/0! | J43: =AVERAGE('Управление ИБ'!J72:J76) -> #DIV/0! | K43: =AVERAGE('Управление ИБ'!K72:K76) -> 1 | L43: =AVERAGE('Управление ИБ'!L72:L76) -> 0
B44: =B107 -> Управление рисками в цепочке поставок | C44: ЦП | D44: =AVERAGE('Управление ИБ'!D108:D110) -> 5 | E44: =AVERAGE('Управление ИБ'!E108:E110) -> 3.2 | F44: =AVERAGE('Управление ИБ'!F108:F110) -> 1.6 | G44: =AVERAGE('Управление ИБ'!G108:G110) -> #DIV/0! | H44: =AVERAGE('Управление ИБ'!H108:H110) -> #DIV/0! | I44: =AVERAGE('Управление ИБ'!I108:I110) -> #DIV/0! | J44: =AVERAGE('Управление ИБ'!J108:J110) -> #DIV/0! | K44: =AVERAGE('Управление ИБ'!K108:K110) -> 1.6 | L44: =AVERAGE('Управление ИБ'!L108:L110) -> 0
B45: =B111 -> Инвентаризация | C45: ИН | D45: =AVERAGE('Управление ИБ'!D112:D124) -> 5 | E45: =AVERAGE('Управление ИБ'!E112:E124) -> 3.2 | F45: =AVERAGE('Управление ИБ'!F112:F124) -> 1.2307692 | G45: =AVERAGE('Управление ИБ'!G112:G124) -> #DIV/0! | H45: =AVERAGE('Управление ИБ'!H112:H124) -> #DIV/0! | I45: =AVERAGE('Управление ИБ'!I112:I124) -> #DIV/0! | J45: =AVERAGE('Управление ИБ'!J112:J124) -> #DIV/0! | K45: =AVERAGE('Управление ИБ'!K112:K124) -> 1.2307692 | L45: =AVERAGE('Управление ИБ'!L112:L124) -> 0.24615385
B46: =B101 -> Управление активами | C46: УА | D46: =AVERAGE('Управление ИБ'!D102:D106) -> 4.6 | E46: =AVERAGE('Управление ИБ'!E102:E106) -> 3.12 | F46: =AVERAGE('Управление ИБ'!F102:F106) -> 0.52 | G46: =AVERAGE('Управление ИБ'!G102:G106) -> #DIV/0! | H46: =AVERAGE('Управление ИБ'!H102:H106) -> #DIV/0! | I46: =AVERAGE('Управление ИБ'!I102:I106) -> #DIV/0! | J46: =AVERAGE('Управление ИБ'!J102:J106) -> #DIV/0! | K46: =AVERAGE('Управление ИБ'!K102:K106) -> 0.52 | L46: =AVERAGE('Управление ИБ'!L102:L106) -> 0.84
B47: =B168 -> Управление доступом | C47: =C168 -> УД | D47: =AVERAGE(D169:D178) -> 4.46 | E47: =AVERAGE(E169:E178) -> 3.26 | F47: =AVERAGE(F169:F178) -> 2.14 | G47: =AVERAGE(G169:G178) -> #DIV/0! | H47: =AVERAGE(H169:H178) -> #DIV/0! | I47: =AVERAGE(I169:I178) -> #DIV/0! | J47: =AVERAGE(J169:J178) -> #DIV/0! | K47: =AVERAGE(K169:K178) -> 2.14 | L47: =AVERAGE(L169:L178) -> 1.32
B48: =B179 -> Идентификация и аутентификация | C48: =C179 -> ИА | D48: =AVERAGE(D180:D188) -> 5 | E48: =AVERAGE(E180:E188) -> 4.6 | F48: =AVERAGE(F180:F188) -> 3.3111111 | G48: =AVERAGE(G180:G188) -> #DIV/0! | H48: =AVERAGE(H180:H188) -> #DIV/0! | I48: =AVERAGE(I180:I188) -> #DIV/0! | J48: =AVERAGE(J180:J188) -> #DIV/0! | K48: =AVERAGE(K180:K188) -> 3.3111111 | L48: =AVERAGE(L180:L188) -> 0
B49: =B189 -> Защита данных и информации | C49: =C189 -> Д | D49: =AVERAGE(D190:D193) -> 4.55 | E49: =AVERAGE(E190:E193) -> 3.7 | F49: =AVERAGE(F190:F193) -> 0.8 | G49: =AVERAGE(G190:G193) -> #DIV/0! | H49: =AVERAGE(H190:H193) -> #DIV/0! | I49: =AVERAGE(I190:I193) -> #DIV/0! | J49: =AVERAGE(J190:J193) -> #DIV/0! | K49: =AVERAGE(K190:K193) -> 0.8 | L49: =AVERAGE(L190:L193) -> 2.5
B50: =B125 -> Обеспечение доступности | C50: =C125 -> ОД | D50: =AVERAGE('Управление ИБ'!D126:D130) -> 5 | E50: =AVERAGE('Управление ИБ'!E126:E130) -> 3.92 | F50: =AVERAGE('Управление ИБ'!F126:F130) -> 0 | G50: =AVERAGE('Управление ИБ'!G129:G130) -> #DIV/0! | H50: =AVERAGE('Управление ИБ'!H129:H130) -> #DIV/0! | I50: =AVERAGE('Управление ИБ'!I126:I130) -> #DIV/0! | J50: =AVERAGE('Управление ИБ'!J126:J130) -> #DIV/0! | K50: =AVERAGE('Управление ИБ'!K126:K130) -> 0 | L50: =AVERAGE('Управление ИБ'!L126:L130) -> 0
B51: =B146 -> Персонал | C51: =C146 -> Люди | D51: =AVERAGE(D147:D149) -> 5 | E51: =AVERAGE(E147:E149) -> 5 | F51: =AVERAGE(F147:F149) -> 5 | G51: =AVERAGE(G147:G149) -> #DIV/0! | H51: =AVERAGE(H147:H149) -> #DIV/0! | I51: =AVERAGE(I147:I149) -> #DIV/0! | J51: =AVERAGE(J147:J149) -> #DIV/0! | K51: =AVERAGE(K147:K149) -> 5 | L51: =AVERAGE(L147:L149) -> 0
B52: =B156 -> Осведомленность пользователей и обучение персонала | C52: =C156 -> AW | D52: =AVERAGE(D157:D167) -> 5 | E52: =AVERAGE(E157:E167) -> 3.2 | F52: =AVERAGE(F157:F167) -> 1.6 | G52: =AVERAGE(G157:G167) -> #DIV/0! | H52: =AVERAGE(H157:H167) -> #DIV/0! | I52: =AVERAGE(I157:I167) -> #DIV/0! | J52: =AVERAGE(J157:J167) -> #DIV/0! | K52: =AVERAGE(K157:K167) -> 1.6 | L52: =AVERAGE(L157:L167) -> 0.14545455
B53: =B77 -> Процессы | C53: ПР | D53: =AVERAGE(D78:D100) -> 4.0869565 | E53: =AVERAGE(E78:E100) -> 2.8 | F53: =AVERAGE(F78:F100) -> 0.67826087 | G53: =AVERAGE(G78:G100) -> 0 | H53: =AVERAGE(H78:H100) -> 0 | I53: =AVERAGE(I78:I100) -> 0 | J53: =AVERAGE(J78:J100) -> 0 | K53: =AVERAGE(K78:K100) -> 0.67826087 | L53: =AVERAGE(L78:L100) -> 0.24347826
B54: =B131 -> Безопасная разработка | C54: =C131 -> БР | D54: =AVERAGE(D132:D145)*IF(БР="да",1,0) -> 4.9285714 | E54: =AVERAGE(E132:E145)*IF(БР="да",1,0) -> 3.8285714 | F54: =AVERAGE(F132:F145)*IF(БР="да",1,0) -> 0.98571429 | G54: =AVERAGE(G132:G145) -> #DIV/0! | H54: =AVERAGE(H132:H145) -> #DIV/0! | I54: =AVERAGE(I132:I145) -> #DIV/0! | J54: =AVERAGE(J132:J145) -> #DIV/0! | K54: =AVERAGE(K132:K145) -> 0.98571429 | L54: =AVERAGE(L132:L145) -> 0
B55: =B150 -> Физический доступ | C55: =C150 -> ФД | D55: =AVERAGE(D151:D155) -> 5 | E55: =AVERAGE(E151:E155) -> 4.64 | F55: =AVERAGE(F151:F155) -> 4.32 | G55: =AVERAGE(G151:G155) -> #DIV/0! | H55: =AVERAGE(H151:H155) -> #DIV/0! | I55: =AVERAGE(I151:I155) -> #DIV/0! | J55: =AVERAGE(J151:J155) -> #DIV/0! | K55: =AVERAGE(K151:K155) -> 4.32 | L55: =AVERAGE(L151:L155) -> 0
P59: Приоритет | Q59: Очередь 1 (КБ1) | S59: Очередь 2 (КБ2) | U59: Очередь 3 (КБ3)
B60: Система управления ИБ | C60: СУИБ | P60: =VLOOKUP(B60,Приоритет!$G$9:$K$52,5,0) -> 14 | Q60: СУИБ | R60: =P60+200 -> 214 | S60: СУИБ | T60: =P60+300 -> 314 | U60: СУИБ
B61: Утверждена Политика информационной безопасности Общества | C61: СУИБ.УР.1 | D61: 5 | E61: 5 | F61: 5 | K61: 5 | L61: =VALUE(LEFT(N61,3)) -> 5 | M61: =L61-K61 -> 0 | N61: 5 -да | P61: =P60+0.01 -> 14.01 | Q61: =IF(($L61-$F61)>=0,"", "- Разработать или Получить в Блоке ИБ ПАО Ростелеком типовую политику ИБ; - Утвердить в Обществе Политику ИБ") | R61: =R60+0.01 -> 214.01 | S61: =IF(($L61-$E61)>=0,"","") | T61: =T60+0.01 -> 314.01 | U61: =IF(($L61-$D61)>=0,"","")
B62: Назначено лицо, ответственное за обеспечение информационной безопасности | C62: СУИБ.УР.10 | D62: 5 | E62: 5 | F62: 5 | K62: 5 | L62: =VALUE(LEFT(N62,3)) -> 5 | M62: =L62-K62 -> 0 | N62: 5 -да | P62: =P61+0.01 -> 14.02 | Q62: =IF(($L62-$F62)>=0,"","- Определить полномочия ответственного за обеспечение ИБ в Обществе."&" - Подготовить и утвердить приказ об ответственном за обеспечение ИБ в Обществе") | R62: =R61+0.01 -> 214.02 | T62: =T61+0.01 -> 314.02
B63: Создано подразделение по ИБ или задачи возложены на подразделение | C63: СУИБ.УР.11 | D63: 5 | E63: 5 | F63: 5 | K63: 5 | L63: =VALUE(LEFT(N63,3)) -> 5 | M63: =L63-K63 -> 0 | N63: 5 -да | P63: =P62+0.01 -> 14.03 | Q63: =IF(($L63-$F63)>=0,"", " - Определить полномочия для подразделения, ответственное за ИБ (как минимум уровня отдела ИБ). - Подготовить положение о подразделении, обеспечивающим ИБ в Обществе."&" - Создать выделенное подразделение, ответственное за ИБ (как минимум уровня отдела ИБ): - Утвердить приказом по орг. структуре создание подразделения ИБ."&" - Утвердить положение о подразделении, обеспечивающим ИБ в Обществе. - Распоряжением/приказом определили подразделение ИБ, как подразделение Общества, ответственное за обеспечение ИБ") | R63: =R62+0.01 -> 214.03 | T63: =T62+0.01 -> 314.03
B64: Определены цели обеспечения ИБ | C64: СУИБ.УР.2 | D64: 5 | E64: 5 | F64: 0 | K64: 0 | L64: =VALUE(LEFT(N64,3)) -> 5 | M64: =L64-K64 -> 5 | N64: 5 -да | P64: =P63+0.01 -> 14.04 | Q64: =IF(($L64-$F64)>=0,"",) | R64: =R63+0.01 -> 214.04 | S64: =IF(($L64-$E64)>=0,"", "- Провести анализ целей Общества в области ИБ и отразить в Политике ИБ, стратегии развития или планах развития") | T64: =T63+0.01 -> 314.04 | U64: =IF(($L64-$D64)>=0,""," ")
B65: Наличие планов развития ИБ | C65: СУИБ.УР.3 | D65: 5 | E65: 5 | F65: 5 | K65: 5 | L65: =VALUE(LEFT(N65,3)) -> 5 | M65: =L65-K65 -> 0 | N65: 5 -да | P65: =P64+0.01 -> 14.05 | Q65: =IF(($L65-$F65)>=0,"", "- Разработать планы развития ИБ или адаптировать типовые планы, предоставленные ПАО Ростелеком") | R65: =R64+0.01 -> 214.05 | S65: =IF(($L65-$E65)>=0,"","") | T65: =T64+0.01 -> 314.05 | U65: =IF(($L65-$D65)>=0,"","")
B66: Статус достижения целей ИБ регулярно доводится до руководства Общества | C66: СУИБ.УР.4 | D66: 5 | E66: 3.2 | F66: 0 | K66: 0 | L66: =VALUE(LEFT(N66,3)) -> 1.6 | M66: =L66-K66 -> 1.6 | N66: 1,6 - Не формализовано, доводится | P66: =P65+0.01 -> 14.06 | Q66: =IF(($L66-$F66)>=0,"",) | R66: =R65+0.01 -> 214.06 | S66: =IF(($L66-$E66)>=0,""," Сформировать отчет о достижении целей ИБ. Представить отчет руководству Общества") -> Сформировать отчет о достижении целей ИБ. Представить отчет руководству Общества | T66: =T65+0.01 -> 314.06 | U66: =IF(($L66-$D66)>=0,"","Организовать процесс регулярной отчетности перед руководством по достижению целей ИБ") -> Организовать процесс регулярной отчетности перед руководством по достижению целей ИБ
B67: Проводится регулярный (ежегодный) внешний аудит | C67: СУИБ.УР.5 | D67: 5 | E67: 5 | F67: 0 | K67: 0 | L67: =VALUE(LEFT(N67,3)) -> 0 | M67: =L67-K67 -> 0 | N67: 0 - нет | P67: =P66+0.01 -> 14.07 | Q67: =IF(($L67-$F67)>=0,"",) | R67: =R66+0.01 -> 214.07 | S67: =IF(($L67-$E67)>=0,""," Организовать и провести внешний аудит ИБ. Принять меры по повышению уровня ИБ по результатам аудита") -> Организовать и провести внешний аудит ИБ. Принять меры по повышению уровня ИБ по результатам аудита | T67: =T66+0.01 -> 314.07 | U67: =IF(($L67-$D67)>=0,"","Организовать процесс регулярных внешних аудитов ИБ. Определить требования к процессу внешнего аудита") -> Организовать процесс регулярных внешних аудитов ИБ. Определить требования к процессу внешнего аудита
B68: Проводятся регулярные (ежегодные) киберучения | C68: СУИБ.УР.6 | D68: 5 | E68: 5 | F68: 0 | K68: 0 | L68: =VALUE(LEFT(N68,3)) -> 0 | M68: =L68-K68 -> 0 | N68: 0 - нет | P68: =P67+0.01 -> 14.08 | Q68: =IF(($L68-$F68)>=0,"",) | R68: =R67+0.01 -> 214.08 | S68: =IF(($L68-$E68)>=0,""," ") | T68: =T67+0.01 -> 314.08 | U68: =IF(($L68-$D68)>=0,"", "")
B69: Требования по ИБ к информационным активам (ИА) предьявляются на стадиях принятия решения о создании/приобретении ИА | C69: СУИБ.УР.7 | D69: 5 | E69: 3.2 | F69: 0 | K69: 0 | L69: =VALUE(LEFT(N69,3)) -> 1.6 | M69: =L69-K69 -> 1.6 | N69: 1,6 - Объем покрытия минимальный | P69: =P68+0.01 -> 14.09 | Q69: =IF(($L69-$F69)>=0,"",) | R69: =R68+0.01 -> 214.09 | S69: =IF(($L69-$E69)>=0,"", "- Организовать процесс создания / приобретения ИА; - Определить требования к процессу; - Обеспечить участие подразделения ИБ в процессе;"&" - Обеспечить формирование требований ИБ на этапе принятия решения о создании/приобретении ИА.") -> - Организовать процесс создания / приобретения ИА; - Определить требования к процессу; - Обеспечить участие подразделения ИБ в процессе; - Обеспечить формирование требований ИБ на этапе принятия решения о создании/приобретении ИА. | T69: =T68+0.01 -> 314.09 | U69: =IF(($L69-$D69)>=0,"", "- Обеспечить формирование, коректировку, согласование, контроль исполнения требований ИБ на каждом этапе создания / приобретения ИА") -> - Обеспечить формирование, коректировку, согласование, контроль исполнения требований ИБ на каждом этапе создания / приобретения ИА
B70: Актуализация внутренних нормативных документов в соответствии с изменениями в нормативно-правовых актах и распоряжениях регуляторов и контрольных (надзорных) ведомств в сфере ИБ | C70: СУИБ.УР.8 | D70: 5 | E70: 5 | F70: 0 | K70: 0 | L70: =VALUE(LEFT(N70,3)) -> 5 | M70: =L70-K70 -> 5 | N70: 5 -да | P70: =P69+0.01 -> 14.1 | Q70: =IF(($L70-$F70)>=0,"",) | R70: =R69+0.01 -> 214.1 | S70: =IF(($L70-$E70)>=0,"", "- Определить ответственных за мониторинг НПА и организовать процесс мониторинга; - Организовать процесс доведения информации до всех заинтересованных подразделений. Реализовать процесс выполнения требований НПА.") | T70: =T69+0.01 -> 314.1 | U70: =IF(($L70-$D70)>=0,"", "- Определить ответственных за мониторинг НПА и организовать процесс мониторинга - Организовать процесс доведения информации до всех заинтересованных подразделений. Реализовать процесс выполнения требований НПА.")
B71: Управление рисками | C71: УР | M71: =L71-K71 -> 0 | P71: =VLOOKUP(B71,Приоритет!$G$9:$K$52,5,0) -> 41 | Q71: УР | R71: =P71+200 -> 241 | S71: УР | T71: =P71+300 -> 341 | U71: УР
B72: Определены основные нежелательные события ИБ | C72: УИБ.УР.1 | D72: 5 | E72: 5 | F72: 5 | K72: 5 | L72: =VALUE(LEFT(N72,3)) -> 0 | M72: =L72-K72 -> -5 | N72: 0 - нет | P72: =P71+0.01 -> 41.01 | Q72: =IF(($L72-$F72)>=0,"","- Составить перечень нежелательныхх событий в ИБ. Согласовать перечень с руководством Общества и со всеми заинтересованными подразделениями. Утвердить перечень ") -> - Составить перечень нежелательныхх событий в ИБ. Согласовать перечень с руководством Общества и со всеми заинтересованными подразделениями. Утвердить перечень | R72: =R71+0.01 -> 241.01 | S72: =IF(($L72-$E72)>=0,"","") | T72: =T71+0.01 -> 341.01 | U72: =IF(($L72-$D72)>=0,"","")
B73: Разработана и утверждена Политика управления рисками ИБ | C73: УИБ.УР.2 | D73: 5 | E73: 0 | F73: 0 | K73: 0 | L73: =VALUE(LEFT(N73,3)) -> 0 | N73: 0 - нет | P73: =P72+0.01 -> 41.02 | Q73: =IF(($L73-$F73)>=0,"",) | R73: =R72+0.01 -> 241.02 | S73: =IF(($L73-$E73)>=0,"","") | T73: =T72+0.01 -> 341.02 | U73: =IF(($L73-$D73)>=0,"", "- Разработать или Получить в Блоке ИБ ПАО Ростелеком типовую политику управления рисками; - Утвердить в Обществе политику управления рисками") -> - Разработать или Получить в Блоке ИБ ПАО Ростелеком типовую политику управления рисками; - Утвердить в Обществе политику управления рисками
B74: Риски определены качественно | C74: УИБ.УР.3 | D74: 5 | E74: 5 | F74: 0 | K74: 0 | L74: =VALUE(LEFT(N74,3)) -> 0 | N74: 0 - нет | P74: =P73+0.01 -> 41.03 | Q74: =IF(($L74-$F74)>=0,"") | R74: =R73+0.01 -> 241.03 | S74: =IF(($L74-$E74)>=0,"- Реализовать процесс качественной оценки рисков ИБ на основе экспертной оценки",) -> 0 | T74: =T73+0.01 -> 341.03 | U74: =IF(($L74-$D74)>=0,"",) -> 0
B75: Внедрен процесс количественной оценки рисков | C75: УИБ.УР.4 | D75: 4 | E75: 0 | F75: 0 | K75: 0 | L75: =VALUE(LEFT(N75,3)) -> 0 | M75: =L75-K75 -> 0 | N75: 0 - Процесс отсутствует | P75: =P74+0.01 -> 41.04 | Q75: =IF(($L75-$F75)>=0,"",) | R75: =R74+0.01 -> 241.04 | S75: =IF(($L75-$E75)>=0,"","") | T75: =T74+0.01 -> 341.04 | U75: =IF(($L75-$D75)>=0,"","")
B76: Процесс оценки рисков ИБ интегрирован в общую систему управления рисками Общества | C76: УИБ.УР.5 | D76: 5 | E76: 0 | F76: 0 | K76: 0 | L76: =VALUE(LEFT(N76,3)) -> 0 | M76: =L76-K76 -> 0 | N76: 0 - нет | P76: =P75+0.01 -> 41.05 | Q76: =IF(($L76-$F76)>=0,"",) | R76: =R75+0.01 -> 241.05 | S76: =IF(($L76-$E76)>=0,"","") | T76: =T75+0.01 -> 341.05 | U76: =IF(($L76-$D76)>=0,"","")
B77: Процессы | C77: ПР | M77: =L77-K77 -> 0 | P77: =VLOOKUP(B77,Приоритет!$G$9:$K$52,5,0) -> 28 | Q77: ПР | R77: =P77+200 -> 228 | S77: ПР | T77: =P77+300 -> 328 | U77: ПР
B78: =СЗИ!B88 -> Внедрен процесс управления уязвимостями | C78: =СЗИ!C88 -> СЗИ.САЗ.3 | D78: =СЗИ!D88 -> 4 | E78: =СЗИ!E88 -> 3 | F78: =СЗИ!F88 -> 0 | G78: =СЗИ!G88 -> 0 | H78: =СЗИ!H88 -> 0 | I78: =СЗИ!I88 -> 0 | ... L78: =СЗИ!L88 -> 1 | P78: =P77+0.01 -> 28.01 | Q78: =СЗИ!Q88 | R78: =R77+0.01 -> 228.01 | S78: =СЗИ!S88 -> - Разработать или Получить в Блоке ИБ ПАО Ростелеком типовое описание процесса управления уязвимостями; - Реализовать процесс управления уязвимостями; - Обеспечить устранение или митигацию всех выявленных уязвимостей; - Обеспечить устранение уязвимостей критичного уровня в срок не более 3 рабочих дней при их обнаружении. | T78: =T77+0.01 -> 328.01 | U78: =СЗИ!U88 -> - Автоматизировать процесс управления уязвимостями. Обеспечить устранение уязвимостей критичного уровня в срок не более 24 часов, высокого уровня в срок не более 72 часов; - Разработать систему метрик для процесса управления уязвимостями; - Создать средство визуального мониторинга параметров процесса управления уязвимостями; - Реализовать мониторинг параметров процесса управления уязвимостями; - Реализовать реагирование на факты отклонения параметров процесса управления уязвимостями от определенных показателей.
B79: =СЗИ!B62 -> Внедрен процесс управления уязвимостями на периметре (CPT) | C79: =СЗИ!C62 -> СЗИ.CPT.3 | D79: =СЗИ!D62 -> 4 | E79: =СЗИ!E62 -> 3 | F79: =СЗИ!F62 -> 1 | G79: =СЗИ!G62 -> 0 | H79: =СЗИ!H62 -> 0 | I79: =СЗИ!I62 -> 0 | ... L79: =СЗИ!L62 -> 0 | P79: =P78+0.01 -> 28.02 | Q79: =СЗИ!Q62 -> - Разработать или Получить в Блоке ИБ ПАО Ростелеком типовое описание процесса контроля уязвимостей | R79: =R78+0.01 -> 228.02 | S79: =СЗИ!S62 -> - Реализовать в Обществе процесс управления уязвимостями на периметре. - Автоматизировать процесс управления выявленными уязвимостями (учет, информирование, контроль устранения). | T79: =T78+0.01 -> 328.02 | U79: =СЗИ!U62 -> - Разработать систему метрик для процесса CPT; - Создать средство визуального мониторинга параметров процесса CPT; - Реализовать мониторинг параметров процесса CPT; - Реализовать реагирование на факты отклонения параметров процесса CPT
B80: =Мониторинг!B61 -> Процесс анализа информации о киберугрозах | C80: =Мониторинг!C61 -> МНТ.ПР.1 | D80: =Мониторинг!D61 -> 4 | E80: =Мониторинг!E61 -> 1 | F80: =Мониторинг!F61 -> 0 | G80: =Мониторинг!G61 -> 0 | H80: =Мониторинг!H61 -> 0 | I80: =Мониторинг!I61 -> 0 | ... L80: =Мониторинг!L61 -> 0 | P80: =P79+0.01 -> 28.03 | Q80: =Мониторинг!Q61 | R80: =R79+0.01 -> 228.03 | S80: =Мониторинг!S61 -> - Организовать процесс анализа информации об угрозах, направлемой РТК, ФСТЭК и НКЦКИ. Выполнять проверку применимости угроз и мер защиты в Обществе. Выполнять рекомендуемые меры. | T80: =T79+0.01 -> 328.03 | U80: =Мониторинг!U61 -> - Организовать получение данных от поставщиков информации об угрозах и из открытых источников. Реализовать процесс анализа угроз и защиты от релевантных угроз.
B81: =Мониторинг!B62 -> Процесс мониторинга событий ИБ | C81: =Мониторинг!C62 -> МНТ.ПР.2 | D81: =Мониторинг!D62 -> 4 | E81: =Мониторинг!E62 -> 4 | F81: =Мониторинг!F62 -> 0 | G81: =Мониторинг!G62 -> 0 | H81: =Мониторинг!H62 -> 0 | I81: =Мониторинг!I62 -> 0 | ... L81: =Мониторинг!L62 -> 0 | P81: =P80+0.01 -> 28.04 | Q81: =Мониторинг!Q62 | R81: =R80+0.01 -> 228.04 | S81: =Мониторинг!S62 -> - Регламентировать процесс мониторинга событий ИБ, определить критерии определения и классификации инцидентов, Определить порядок инициации реагирования на инцидент. | T81: =T80+0.01 -> 328.04 | U81: =Мониторинг!U62
B82: =Реагирование!B40 -> Процесс категорирования инцидентов ИБ | C82: =Реагирование!C40 -> РЕАГ.ПЛР.2 | D82: =Реагирование!D40 -> 4 | E82: =Реагирование!E40 -> 3 | F82: =Реагирование!F40 -> 1 | G82: =Реагирование!G40 -> 0 | H82: =Реагирование!H40 -> 0 | I82: =Реагирование!I40 -> 0 | ... L82: =Реагирование!L40 -> 0 | P82: =P81+0.01 -> 28.05 | Q82: =Реагирование!Q40 -> - В Обществе неформально определить категории инцидентов ИБ | R82: =R81+0.01 -> 228.05 | S82: =Реагирование!S40 -> - Формализовать критерии определения критичности инцидентов ИБ; - Определить мандаты на действия участников процесса; - Официально сформировать ГЭР и ОКУ; - Не реже 1 раза в год проводить учения в формате штабных игр. | T82: =T81+0.01 -> 328.05 | U82: =Реагирование!U40 -> - Реализовать возможность корректировки категорий инцидента ИБ в процессе реагирования
B83: =Реагирование!B51 -> Процесс расследования инцидентов | C83: =Реагирование!C51 -> РЕАГ.АНЛЗ.2 | D83: =Реагирование!D51 -> 4 | E83: =Реагирование!E51 -> 3 | F83: =Реагирование!F51 -> 1 | G83: =Реагирование!G51 -> 0 | H83: =Реагирование!H51 -> 0 | I83: =Реагирование!I51 -> 0 | ... L83: =Реагирование!L51 -> 1 | P83: =P82+0.01 -> 28.06 | Q83: =Реагирование!Q51 | R83: =R82+0.01 -> 228.06 | S83: =Реагирование!S51 -> - Разработать и задокументировать процесс расследования инцидентов, довести до сведения заинтересованных лиц; - Расследование инцидентов должно проводиться с использованием средств автоматизации; - Создать единую базу знаний по расследованиям. Результаты расследований и артефакты хранить в единой базе знаний. | T83: =T82+0.01 -> 328.06 | U83: =Реагирование!U51 -> - Определить метрики процесса реагирования на инциденты и расследования; - На постоянной основе проводить мониторинг процесса по утвержденным метрикам и показателям; - Интегрировать процесс расследования инцидентов в единый процесс управления инцидентами ИБ
B84: =Реагирование!B47 -> Определен порядок взаимодействия с регуляторами по инцидентам ИБ | C84: =Реагирование!C47 -> РЕАГ.КМНК.4 | D84: =Реагирование!D47 -> 5 | E84: =Реагирование!E47 -> 3.2 | F84: =Реагирование!F47 -> 1.6 | G84: =Реагирование!G47 -> 0 | H84: =Реагирование!H47 -> 0 | I84: =Реагирование!I47 -> 0 | ... L84: =Реагирование!L47 -> 1.6 | P84: =P83+0.01 -> 28.07 | Q84: =Реагирование!Q47 -> - Взаимодействовать с регуляторами по инциденту ИБ в установленных законом случаях | R84: =R83+0.01 -> 228.07 | S84: =Реагирование!S47 -> - Регламентировать процесс взаимодействия с регуляторами; - Определить ответственных за взаимодействие; - Определить состав и объем предоставляемой информации об инцидентах. | T84: =T83+0.01 -> 328.07 | U84: =Реагирование!U47
B85: =Реагирование!B39 -> Процесс реагирования на инциденты ИБ | C85: =Реагирование!C39 -> РЕАГ.ПЛР.1 | D85: =Реагирование!D39 -> 4 | E85: =Реагирование!E39 -> 3 | F85: =Реагирование!F39 -> 1 | G85: =Реагирование!G39 -> 0 | H85: =Реагирование!H39 -> 0 | I85: =Реагирование!I39 -> 0 | ... L85: =Реагирование!L39 -> 0 | P85: =P84+0.01 -> 28.08 | Q85: =Реагирование!Q39 -> - Назначить ответственных за решение инцидентов ИБ, включая ответственного за коммуникации внутри и со сторонними компаниями; - Составить и актуализировать список заинтересованных лиц, которые должны получить уведомление об инциденте; - Для критичных инцидентов определить SLA и порядок действий по реагированию; - Автоматизировать процесс реагирования на инциденты ИБ с применением не специализированных средств. | R85: =R84+0.01 -> 228.08 | S85: =Реагирование!S39 -> - Разработать или Получить в Блоке ИБ ПАО Ростелеком типовое описание процесса реагирования на инциденты ИБ (Политика, Регламенты, процедуры реагирования на инциденты ИБ); - Определить ответственность за координацию процесса работы с инцидентами и документирование результатов в процессе решения инцидента; - Составить список заинтересованных лиц, которые должны получить уведомление об инциденте, актуализиировать и пересматривать его не реже раза в год; - Для всех инцидентов определить SLA по реагированию, механизмы обращения, минимальная информация для создания инцидента/Процедуру довести до всех работников Общества; - Определить роли и обязанности, план коммуникации по поводу инцидента; - Составить план реагирования на инциденты, включая сценарии реагирования с привлечением юристов, специалистов по ИТ и ИБ, служб PR, HR и аналитиков; - Разработать учебные сценарии по реагированию, включающие взаимодействие заинтересованных лиц и позволяющие тестировать постановку задач, процессы коммуникации и принятия решений; - Разработать сценарии реагирования для разных событий безопасности: подозрительной активности, обнаруженной уязвимости, утечки информации; - Для автоматизации процесса внедрить специализированное ПО: SIEM, IRP/ServiceDesk. | T85: =T84+0.01 -> 328.08 | U85: =Реагирование!U39 -> - Разработать КПЭ по процессу реагирования на инциденты ИБ для руководства ИБ; - Разработать метрики по процессу; - Назначить сервис-менеджеров процесса; - Создать средство визуального мониторинга параметров процесса; - Реализовать мониторинг параметров процесса; - Реализовать реагирование на факты отклонения параметров процесса от определенных показателей
B86: =Реагирование!B53 -> Процесс пост-анализа инцидентов | C86: =Реагирование!C53 -> РЕАГ.АНЛЗ.4 | D86: =Реагирование!D53 -> 4 | E86: =Реагирование!E53 -> 3 | F86: =Реагирование!F53 -> 1 | G86: =Реагирование!G53 -> 0 | H86: =Реагирование!H53 -> 0 | I86: =Реагирование!I53 -> 0 | ... L86: =Реагирование!L53 -> 1 | P86: =P85+0.01 -> 28.09 | Q86: =Реагирование!Q53 | R86: =R85+0.01 -> 228.09 | S86: =Реагирование!S53 -> - Формализовать и утвердить процесс пост-анализа инцидентов ИБ; - Довести процесс до заинтересованных лиц; - Создать единую базу знаний инцидентов ИБ; - Проводить оценку и анализ инцидентов ИБ; - По результатам расследования инцидентов разрабатывать рекомендации по устранению выявленных уязвимостей и предотвращению аналогичных инцидентов в будущем; - Разрабатывать рекомендации по улучшению применяемы | T86: =T85+0.01 -> 328.09 | U86: =Реагирование!U53 -> - Обеспечить проведение пост-анализа инцидентов ИБ с применением средств автоматизации; - Обеспечить контроль за выполнением рекомендаций и оценку эффективности выполненных мероприятий; - На постоянной основе проводить мониторинг процесса по утвержденным метрикам и показателям; - Назначить ответственных за соблюдением сроков проведения утвержденных мероприятий.
B87: =Мониторинг!B63 -> Процесс создания решающих правил | C87: =Мониторинг!C63 -> МНТ.ПР.3 | D87: =Мониторинг!D63 -> 4 | E87: =Мониторинг!E63 -> 3 | F87: =Мониторинг!F63 -> 0 | G87: =Мониторинг!G63 -> 0 | H87: =Мониторинг!H63 -> 0 | I87: =Мониторинг!I63 -> 0 | ... L87: =Мониторинг!L63 -> 0 | P87: =P86+0.01 -> 28.1 | Q87: =Мониторинг!Q63 | R87: =R86+0.01 -> 228.1 | S87: =Мониторинг!S63 -> - Получить типовые решающие правила SIEM от разработчика SIEM и из других доступных источников. Адаптировать решающие правила для применения в инфрастурктуре организации. | T87: =T86+0.01 -> 328.1 | U87: =Мониторинг!U63 -> - Организовать процесс разработки решающих правил; - Создать базу знаний или инструкции по разработке решающих правил; - Составить план разработки решающих правил; - Организовать процесс анализа журналов событий для разработки решающих правил SIEM; - Применить результаты расследования инцидентов для разработки решающих правил.
B88: =Мониторинг!B64 -> Процесс подключения источников информации | C88: =Мониторинг!C64 -> МНТ.ПР.4 | D88: =Мониторинг!D64 -> 4 | E88: =Мониторинг!E64 -> 2 | F88: =Мониторинг!F64 -> 0 | G88: =Мониторинг!G64 -> 0 | H88: =Мониторинг!H64 -> 0 | I88: =Мониторинг!I64 -> 0 | ... L88: =Мониторинг!L64 -> 0 | P88: =P87+0.01 -> 28.11 | Q88: =Мониторинг!Q64 | R88: =R87+0.01 -> 228.11 | S88: =Мониторинг!S64 -> - Провести инвентаризацию источников событий и подключить их к SIEM | T88: =T87+0.01 -> 328.11 | U88: =Мониторинг!U64 -> - Регламентировать порядок подключения источников информации к SIEM; - Определить требования по обязательному подключению; - Реализовать процесс подключения источников, с инвентаризацией и контролем неподключенных источников; - Установить SLA по подключению.
B89: =Мониторинг!B65 -> Процесс контроля источников информации | C89: =Мониторинг!C65 -> МНТ.ПР.5 | D89: =Мониторинг!D65 -> 4 | E89: =Мониторинг!E65 -> 3 | F89: =Мониторинг!F65 -> 0 | G89: =Мониторинг!G65 -> 0 | H89: =Мониторинг!H65 -> 0 | I89: =Мониторинг!I65 -> 0 | ... L89: =Мониторинг!L65 -> 0 | P89: =P88+0.01 -> 28.12 | Q89: =Мониторинг!Q65 | R89: =R88+0.01 -> 228.12 | S89: =Мониторинг!S65 -> - Проводить аудит ИС для выявления неподключенных к SIEM источников; - Проверять, что источники подключены и успешно передают события. | T89: =T88+0.01 -> 328.12 | U89: =Мониторинг!U65 -> - Регламентировать процесс контроля источников
B90: =Мониторинг!B56 -> Внедрен процесс управления сбоями и мониторинга работоспособности SIEM | C90: =Мониторинг!C56 -> МНТ.SIEM.12 | D90: =Мониторинг!D56 -> 4 | E90: =Мониторинг!E56 -> 3 | F90: =Мониторинг!F56 -> 0 | G90: =Мониторинг!G56 -> 0 | H90: =Мониторинг!H56 -> 0 | I90: =Мониторинг!I56 -> 0 | ... L90: =Мониторинг!L56 -> 0 | P90: =P89+0.01 -> 28.13 | Q90: =Мониторинг!Q56 | R90: =R89+0.01 -> 228.13 | S90: =Мониторинг!S56 -> - Организовать контроль непрерывности мониторинга; - Обеспечить восстановление мониторинга при сбоях в срок не более чем 6 часов; - Обеспечить сохранность данных об инцидентах в случае сбоев; - Обеспечить переключение источников событий на резервный SIEM в случае сбоев. | T90: =T89+0.01 -> 328.13 | U90: =Мониторинг!U56 -> - Приобрести лицензии SIEM, достаточные для полного покрытия мониторингом всех ИА.
B91: Процесс эскалации инцидентов | C91: =Реагирование!C46 -> РЕАГ.КМНК.3 | D91: =Реагирование!D46 -> 5 | E91: =Реагирование!E46 -> 3.2 | F91: =Реагирование!F46 -> 0 | G91: =Реагирование!G46 -> 0 | H91: =Реагирование!H46 -> 0 | I91: =Реагирование!I46 -> 0 | J91: =Реагирование!J46 -> 0 | ... L91: =Реагирование!L46 -> 0 | P91: =P90+0.01 -> 28.14 | Q91: =Реагирование!Q46 | R91: =R90+0.01 -> 228.14 | S91: =Реагирование!S46 -> - Определить критерии и порядок эскалации инцидентов; - Определить маршруты эскалации; - Регламентировать процесс эскалации. | T91: =T90+0.01 -> 328.14 | U91: =Реагирование!U46 -> - Контролировать и оценивать эффективность процесса реагирования на инциденты при эскалациях.
B92: Процесс отчетности | C92: =Реагирование!C67 -> РЕАГ.PB.5.9.3.12 | D92: =Реагирование!D67 -> 4 | E92: =Реагирование!E67 -> 3 | F92: =Реагирование!F67 -> 0 | G92: =Реагирование!G67 -> 0 | H92: =Реагирование!H67 -> 0 | I92: =Реагирование!I67 -> 0 | J92: =Реагирование!J67 -> 0 | ... L92: =Реагирование!L67 -> 0 | P92: =P91+0.01 -> 28.15 | Q92: =Реагирование!Q67 | R92: =R91+0.01 -> 228.15 | S92: =Реагирование!S67 -> - Разработать систему отчетности по выполнению плейбуков; - Разработать систему метрик для оценки процесса; - Создать средства контроля и отчетности по рагированию на инциденты; - Реализовать мониторинг параметров процесса; - Реализовать реагирование на факты отклонения параметров процесса от определенных показателей. | T92: =T91+0.01 -> 328.15 | U92: =Реагирование!U67
B93: Количественная оценка рисков | C93: ='Управление ИБ'!C75 -> УИБ.УР.4 | D93: ='Управление ИБ'!D75 -> 4 | E93: ='Управление ИБ'!E75 -> 0 | F93: ='Управление ИБ'!F75 -> 0 | G93: ='Управление ИБ'!G75 -> 0 | H93: ='Управление ИБ'!H75 -> 0 | I93: ='Управление ИБ'!I75 -> 0 | J93: ='Управление ИБ'!J75 -> 0 | ... L93: ='Управление ИБ'!L75 -> 0 | P93: =P92+0.01 -> 28.16 | Q93: =Q75 | R93: =R92+0.01 -> 228.16 | S93: =S75 | T93: =T92+0.01 -> 328.16 | U93: =U75
B94: ='Управление ИБ'!B106 -> Внедрен процесс контроля изменений конфигурации | C94: ='Управление ИБ'!C106 -> УИБ.УА.5 | D94: ='Управление ИБ'!D106 -> 4 | E94: ='Управление ИБ'!E106 -> 3 | F94: ='Управление ИБ'!F106 -> 0 | G94: ='Управление ИБ'!G106 -> 0 | H94: ='Управление ИБ'!H106 -> 0 | I94: ='Управление ИБ'!I106 -> 0 | ... L94: ='Управление ИБ'!L106 -> 0 | P94: =P93+0.01 -> 28.17 | Q94: =Q106 | R94: =R93+0.01 -> 228.17 | S94: =S106 -> - Контролировать соответствие сетевых взаимодействий документации, применение и неизменность безопасных конфигураций не реже чем раз в 1 год. | T94: =T93+0.01 -> 328.17 | U94: =U106 -> - Автоматизировать контроль и проверять неизменнность конфигураций на регулярной основе; - Отслеживать события изменения конфигурации.
B95: =B103 -> Внедрен процесс инвентаризации и категорирования информационных активов | C95: =C103 -> УИБ.УА.2 | D95: =D103 -> 4 | E95: =E103 -> 3 | F95: =F103 -> 1 | G95: =G103 -> 0 | H95: =H103 -> 0 | I95: =I103 -> 0 | ... L95: =L103 -> 1 | P95: =P94+0.01 -> 28.18 | Q95: =Q103 | R95: =R94+0.01 -> 228.18 | S95: =S103 -> - Провести категорирование всех ИА; - Реализовать процесс обеспечения требований ИБ в соответствии с категорией. | T95: =T94+0.01 -> 328.18 | U95: =U103 -> - Обеспечить категорирование всех вновь сосздаваемых ИА и периодический пересмотр данных о категорировании.
B96: Процесс тестирования исходного кода на уязвимости ИБ | C96: =C135 -> УИБ.БР.5.9.4 | D96: =D135 -> 4 | E96: =E135 -> 3 | F96: =F135 -> 1 | G96: =G135 -> 0 | H96: =H135 -> 0 | I96: =I135 -> 0 | J96: =J135 -> 0 | ... L96: =L135 -> 0 | P96: =P95+0.01 -> 28.19 | Q96: =Q135 -> Для систем Mission Critical определить порядок тестирования ПО. | R96: =R95+0.01 -> 228.19 | S96: =S135 -> 1. Для всех систем формализовать: -регламент проведения динамического анализа исходного кода ПО; -регламент функционального тестирования; -регламент нефункционального тестирования. 2.Автоматизировать процесс тестирование ПО; 3.Мониторить процессы тестирования ПО в CI/CD-конвейере. | T96: =T95+0.01 -> 328.19 | U96: =U135 -> Качество процесса отслеживать с помощью метрик.
B97: =СЗИ!B51 -> Процесс контроля работоспособности САВЗ | C97: =СЗИ!C51 -> СЗИ.ВПО.6 | D97: =СЗИ!D51 -> 4 | E97: =СЗИ!E51 -> 3 | F97: =СЗИ!F51 -> 2 | G97: =СЗИ!G51 -> 0 | H97: =СЗИ!H51 -> 0 | I97: =СЗИ!I51 -> 0 | ... L97: =СЗИ!L51 -> 0 | P97: =P96+0.01 -> 28.2 | Q97: =СЗИ!Q51 -> - Разработать или Получить в Блоке ИБ ПАО Ростелеком типовое описание процесса контроля рабоспособности средств АВЗ _x000D_- Утвердить в Обществе ВНД, описывающий процесс контроля рабоспособности средств АВЗ | R97: =R96+0.01 -> 228.2 | S97: =СЗИ!S51 -> - Реализовать в Обществе процесс контроля рабоспособности средств АВЗ | T97: =T96+0.01 -> 328.2 | U97: =СЗИ!U51 -> - Разработать систему метрик для процесса контроля рабоспособности средств АВЗ _x000D_- Создать средство визуального мониторинга параметров процесса контроля работоспособности средств АВЗ _x000D_- Реализовать мониторинг параметров процесса контроля работоспособности средств АВЗ _x000D_- Реализовать реагирование на факты отклонения параметров процесса контроля работоспособности средств АВЗ от определенных показателей
B98: =СЗИ!B52 -> Процесс обновления антивирусных средств | C98: =СЗИ!C52 -> СЗИ.ВПО.7 | D98: =СЗИ!D52 -> 4 | E98: =СЗИ!E52 -> 3 | F98: =СЗИ!F52 -> 2 | G98: =СЗИ!G52 -> 0 | H98: =СЗИ!H52 -> 0 | I98: =СЗИ!I52 -> 0 | ... L98: =СЗИ!L52 -> 0 | P98: =P97+0.01 -> 28.21 | Q98: =СЗИ!Q52 -> - Разработать или Получить в Блоке ИБ ПАО Ростелеком типовое описание процесса обновления средств АВЗ _x000D_- Утвердить в Обществе ВНД, описывающий процесс обновления средств АВЗ | R98: =R97+0.01 -> 228.21 | S98: =СЗИ!S52 -> - Реализовать в Обществе процесс обновления средств АВЗ | T98: =T97+0.01 -> 328.21 | U98: =СЗИ!U52 -> - Разработать систему метрик для процесса обновления средств АВЗ _x000D_- Создать средство визуального мониторинга параметров процесса обновления средств АВЗ _x000D_- Реализовать мониторинг параметров процесса обновления средств АВЗ _x000D_- Реализовать реагирование на факты отклонения параметров процесса обновления средств АВЗ от определенных показателей
B99: =СЗИ!B53 -> Процесс реагирования на события САВЗ | C99: =СЗИ!C53 -> СЗИ.ВПО.8 | D99: =СЗИ!D53 -> 4 | E99: =СЗИ!E53 -> 3 | F99: =СЗИ!F53 -> 2 | G99: =СЗИ!G53 -> 0 | H99: =СЗИ!H53 -> 0 | I99: =СЗИ!I53 -> 0 | ... L99: =СЗИ!L53 -> 0 | P99: =P98+0.01 -> 28.22 | Q99: =СЗИ!Q53 -> - Разработать или Получить в Блоке ИБ ПАО Ростелеком типовое описание процесса реагирования на события средств АВЗ _x000D_- Утвердить в Обществе ВНД, описывающий процесс реагирования на события средств АВЗ | R99: =R98+0.01 -> 228.22 | S99: =СЗИ!S53 -> - Реализовать в Обществе процесс реагирования на события средств АВЗ | T99: =T98+0.01 -> 328.22 | U99: =СЗИ!U53 -> - Разработать систему метрик для процесса реагирования на события средств АВЗ _x000D_- Создать средство визуального мониторинга параметров процесса реагирования на события средств АВЗ _x000D_- Реализовать мониторинг параметров процесса реагирования на события средств АВЗ _x000D_- Реализовать реагирование на факты отклонения параметров процесса реагирования на события средств АВЗ от определенных показателей
B100: Процедура публикации внешних ресурсов | C100: =СЗИ!C103 -> СЗИ.WAF.2 | D100: =СЗИ!D103 -> 4 | E100: =СЗИ!E103 -> 3 | F100: =СЗИ!F103 -> 1 | G100: =СЗИ!G103 -> 0 | H100: =СЗИ!H103 -> 0 | I100: =СЗИ!I103 -> 0 | J100: =СЗИ!J103 -> 0 | ... L100: =СЗИ!L103 -> 0 | P100: =P99+0.01 -> 28.23 | Q100: =СЗИ!Q103 -> 0 | R100: =R99+0.01 -> 228.23 | S100: =СЗИ!S103 -> 0 | T100: =T99+0.01 -> 328.23 | U100: =СЗИ!U103 -> - Разработать или Получить в Блоке ИБ ПАО Ростелеком типовое описание процесса публикации сервиса в интернете; - Утвердить в Обществе ВНД, описывающий процесс публикации сервиса в интернете; - Реализовать процесс проверки и согласования до публикации сервиса в интернете; - Обеспечить контроль защищенности и отсутствия уязвимостей до публикации.
B101: Управление активами | C101: УА | P101: =VLOOKUP(B101,Приоритет!$G$9:$K$48,5,0) -> 29 | Q101: УА | R101: =P101+200 -> 229 | S101: УА | T101: =P101+300 -> 329 | U101: УА
B102: Информационные системы Общества соотнесены с ресурсами, на которых они функциониуют | C102: УИБ.УА.1 | D102: 5 | E102: 3.2 | F102: 1.6 | K102: 1.6 | L102: =VALUE(LEFT(N102,3)) -> 1.6 | M102: =L102-K102 -> 0 | N102: 1,6 - Объем покрытия минимальный | P102: =P101+0.01 -> 29.01 | Q102: =IF(($L102-$F102)>=0,"", " - Выполнить инвентаризацию ИС и информационных ресурсов. Установить принадлежность ресурсов к ИС") | R102: =R101+0.01 -> 229.01 | S102: =IF(($L102-$E102)>=0,""," - Автоматизировать учет ИС и информационных ресурсов и сформировать единую базу данных.") -> - Автоматизировать учет ИС и информационных ресурсов и сформировать единую базу данных. | T102: =T101+0.01 -> 329.01 | U102: =IF(($L102-$D102)>=0,"", " - Обеспечить непрерывный учет и актуальность данных об ИС и их ресурсах.") -> - Обеспечить непрерывный учет и актуальность данных об ИС и их ресурсах.
B103: Внедрен процесс инвентаризации и категорирования информационных активов | C103: УИБ.УА.2 | D103: 4 | E103: 3 | F103: 1 | K103: 1 | L103: =VALUE(LEFT(N103,3)) -> 1 | M103: =L103-K103 -> 0 | N103: 1 - Начальный/Повторяющийся эпизодически и бессистемно. Процессы используются разово или в отдельных случаях по образцу. | P103: =P102+0.01 -> 29.02 | Q103: =IF(($L103-$F103)>=0,"", " - Установить критерии категорирования ИА на основании законодательства и внутренних требований; - Реализовать процесс категорирования; - Сформировать требования к обеспечению ИБ на основе категорий ИА") | R103: =R102+0.01 -> 229.02 | S103: =IF(($L103-$E103)>=0,"", " - Провести категорирование всех ИА; - Реализовать процесс обеспечения требований ИБ в соответствии с категорией.") -> - Провести категорирование всех ИА; - Реализовать процесс обеспечения требований ИБ в соответствии с категорией. | T103: =T102+0.01 -> 329.02 | U103: =IF(($L103-$D103)>=0,"", " - Обеспечить категорирование всех вновь сосздаваемых ИА и периодический пересмотр данных о категорировании.") -> - Обеспечить категорирование всех вновь сосздаваемых ИА и периодический пересмотр данных о категорировании.
B104: Описаны все сетевые взаимодействия между компонентами инфраструктуры и информационными системами | C104: УИБ.УА.3 | D104: 5 | E104: 3.2 | F104: 0 | K104: 0 | L104: =VALUE(LEFT(N104,3)) -> 1.6 | M104: =L104-K104 -> 1.6 | N104: 1,6 - Объем покрытия минимальный | P104: =P103+0.01 -> 29.03 | Q104: =IF(($L104-$F104)>=0,"",) | R104: =R103+0.01 -> 229.03 | S104: =IF(($L104-$E104)>=0,"", " - Регламентировать порядок описания сетевых взаимодействий;"&" - Документировать перечень разрешенных сетевых взаимодействий для компонентов инфраструктуры и не менее чем для 30% ИС;"&" - По результатам документирования привести в соответствие правила межсетевых экранов.") -> - Регламентировать порядок описания сетевых взаимодействий; - Документировать перечень разрешенных сетевых взаимодействий для компонентов инфраструктуры и не менее чем для 30% ИС; - По результатам документирования привести в соответствие правила межсетевых экранов. | T104: =T103+0.01 -> 329.03 | U104: =IF(($L104-$D104)>=0,"", " - Документировать перечень разрешенных сетевых взаимодействий для всех ИС;"&" - Документировать конфигурацию сети (состав сетевых сегментов, сетевые маршруты, правила межсетевых экранов);"&" - Регламентировать и реализовать процесс согласования и изменения конфигурации сети.") -> - Документировать перечень разрешенных сетевых взаимодействий для всех ИС; - Документировать конфигурацию сети (состав сетевых сегментов, сетевые маршруты, правила межсетевых экранов); - Регламентировать и реализовать процесс согласования и изменения конфигурации сети.
B105: Определены правила конфигурирования ативов (Харденинг) | C105: УИБ.УА.4 | D105: 5 | E105: 3.2 | F105: 0 | K105: 0 | L105: =VALUE(LEFT(N105,3)) -> 0 | M105: =L105-K105 -> 0 | N105: 0 - Контроль не выполняется | P105: =P104+0.01 -> 29.04 | Q105: =IF(($L105-$F105)>=0,"",) | R105: =R104+0.01 -> 229.04 | S105: =IF(($L105-$E105)>=0,"", " - Разработать или Получить в Блоке ИБ ПАО Ростелеком типовые защищенные конфигурации;"&" - Обеспечить применение безопасных конфигураций на не менее чем 50% хостов.") -> - Разработать или Получить в Блоке ИБ ПАО Ростелеком типовые защищенные конфигурации; - Обеспечить применение безопасных конфигураций на не менее чем 50% хостов. | T105: =T104+0.01 -> 329.04 | U105: =IF(($L105-$D105)>=0,"", " - Обеспечить применение безопасных конфигураций на 100% хостов; - Разработать безопасные конфигурации для видов ПО, применяемых в Обществе.") -> - Обеспечить применение безопасных конфигураций на 100% хостов; - Разработать безопасные конфигурации для видов ПО, применяемых в Обществе.
B106: Внедрен процесс контроля изменений конфигурации | C106: УИБ.УА.5 | D106: 4 | E106: 3 | F106: 0 | K106: 0 | L106: =VALUE(LEFT(N106,3)) -> 0 | M106: =L106-K106 -> 0 | N106: 0 - Процесс отсутствует | P106: =P105+0.01 -> 29.05 | Q106: =IF(($L106-$F106)>=0,"",) | R106: =R105+0.01 -> 229.05 | S106: =IF(($L106-$E106)>=0,"", " - Контролировать соответствие сетевых взаимодействий документации, применение и неизменность безопасных конфигураций не реже чем раз в 1 год.") -> - Контролировать соответствие сетевых взаимодействий документации, применение и неизменность безопасных конфигураций не реже чем раз в 1 год. | T106: =T105+0.01 -> 329.05 | U106: =IF(($L106-$D106)>=0,"", " - Автоматизировать контроль и проверять неизменнность конфигураций на регулярной основе; - Отслеживать события изменения конфигурации.") -> - Автоматизировать контроль и проверять неизменнность конфигураций на регулярной основе; - Отслеживать события изменения конфигурации.
B107: Управление рисками в цепочке поставок | C107: ЦП | P107: =VLOOKUP(B107,Приоритет!$G$9:$K$48,5,0) -> 35 | Q107: ЦП | R107: =P107+200 -> 235 | S107: ЦП | T107: =P107+300 -> 335 | U107: ЦП
B108: Процессы взаимодействия в ИТ цепочке c участниками цепочки поставок определены, управляются и согласовываются заинтересованными сторонами Общества | C108: УИБ.ЦП.1 | D108: 5 | E108: 3.2 | F108: 1.6 | K108: 1.6 | L108: =VALUE(LEFT(N108,3)) -> 0 | M108: =L108-K108 -> -1.6 | N108: 0 - Контроль не выполняется | P108: =P107+0.01 -> 35.01 | Q108: =IF(($L108-$F108)>=0,"", "- Определить типовые требования по обеспечнию ИБ к разработчикам ИС, поставщикам, сервис-провайдерам; - Включить подразделение ИБ в согласование договоров.") -> - Определить типовые требования по обеспечнию ИБ к разработчикам ИС, поставщикам, сервис-провайдерам; - Включить подразделение ИБ в согласование договоров. | R108: =R107+0.01 -> 235.01 | S108: =IF(($L108-$E108)>=0,"",) -> 0 | T108: =T107+0.01 -> 335.01 | U108: =IF(($L108-$D108)>=0,"", "")
B109: В договорах со всеми подрядчиками прописана необходимость соблюдения мер информационной безопасности | C109: УИБ.ЦП.2 | D109: 5 | E109: 3.2 | F109: 1.6 | K109: 1.6 | L109: =VALUE(LEFT(N109,3)) -> 0 | M109: =L109-K109 -> -1.6 | N109: 0 - Контроль не выполняется | P109: =P108+0.01 -> 35.02 | Q109: =IF(($L109-$F109)>=0,"", " - Сформировать или получить в ПАО Ростелеком типовые требования к контрагентам по принятию мер информационной безопасности;"&" - Обеспечить включение в договоры требований и ответственности контрагента за их неисполнение. ") -> - Сформировать или получить в ПАО Ростелеком типовые требования к контрагентам по принятию мер информационной безопасности; - Обеспечить включение в договоры требований и ответственности контрагента за их неисполнение. | R109: =R108+0.01 -> 235.02 | S109: =IF(($L109-$E109)>=0,"", " - Составить перечень подрядчиков, чья деятельность может влиять на Общество; - Включить в договоры требования к услугам в части обеспечения ИБ.") -> - Составить перечень подрядчиков, чья деятельность может влиять на Общество; - Включить в договоры требования к услугам в части обеспечения ИБ. | T109: =T108+0.01 -> 335.02 | U109: =IF(($L109-$D109)>=0,"", " - Вести мониторинг работы подрядчиков и контролировать соблюдение мер ИБ.") -> - Вести мониторинг работы подрядчиков и контролировать соблюдение мер ИБ.
B110: Поставщики и сторонние партнеры регулярно проходят оценку, чтобы подтвердить, что они выполняют свои договорные обязательства. Проводятся обзоры аудитов, резюме результатов испытаний или другие эквивалентные оценки поставщиков | C110: УИБ.ЦП.3 | D110: 5 | E110: 3.2 | F110: 1.6 | K110: 1.6 | L110: =VALUE(LEFT(N110,3)) -> 0 | M110: =L110-K110 -> -1.6 | N110: 0 - Контроль не выполняется | P110: =P109+0.01 -> 35.03 | Q110: =IF(($L110-$F110)>=0,"",) -> 0 | R110: =R109+0.01 -> 235.03 | S110: =IF(($L110-$E110)>=0,"", " - Получить от подрядчиков подтверждение соблюдения мер ИБ (отчеты о внутреннем и внешнем аудите)") -> - Получить от подрядчиков подтверждение соблюдения мер ИБ (отчеты о внутреннем и внешнем аудите) | T110: =T109+0.01 -> 335.03 | U110: =IF(($L110-$D110)>=0,"", " - Регулярно запрашивать у подрядчиков отчеты о пройденных аудитах.") -> - Регулярно запрашивать у подрядчиков отчеты о пройденных аудитах.
B111: Инвентаризация | C111: ИН | P111: =VLOOKUP(B111,Приоритет!$G$9:$K$48,5,0) -> 15 | Q111: ИН | R111: =P111+200 -> 215 | S111: ИН | T111: =P111+300 -> 315 | U111: ИН
B112: Ведется учет используемых и (или) эксплуатируемых физических устройств (АРМ, сервера, принтеры, коммутационное оборудование и т.п.) | C112: УИБ.ИН.1 | D112: 5 | E112: 3.2 | F112: 1.6 | K112: 1.6 | L112: =VALUE(LEFT(N112,3)) -> 1.6 | M112: =L112-K112 -> 0 | N112: 1,6 - Объем покрытия минимальный | P112: =P111+0.01 -> 15.01 | Q112: =IF(($L112-$F112)>=0,"", " - Разработать и поддерживать детальный реестр эксплуатируемых АРМ и серверов;"&" - Записи реестра должны содержать сетевой адрес (если он статический), аппаратный адрес, имя машины, ее владельца, подразделение и разрешение на подключение к сети;"&" - Реестр должен пересматриваться и обновляться не реже одного раза в полугодие.") | R112: =R111+0.01 -> 215.01 | S112: =IF(($L112-$E112)>=0,"", " - Реестр должен формироваться на основании результатов автоматизированной инвентаризации не реже одного раза в месяц;"&" - Должна проводиться проверка актуальности данных реестра и полноты учета; - Количество не учтенных в реестре устройств не должно превышать 5%.") -> - Реестр должен формироваться на основании результатов автоматизированной инвентаризации не реже одного раза в месяц; - Должна проводиться проверка актуальности данных реестра и полноты учета; - Количество не учтенных в реестре устройств не должно превышать 5%. | T112: =T111+0.01 -> 315.01 | U112: =IF(($L112-$D112)>=0,"", " - Разработать и поддерживать реестр эксплуатируемых АРМ, серверов, коммутационного оборудования, перефирийных устройств, машинных носителей информации;"&" - В реестр должны быть внесены все устройства, которые регулярно подключаются к корпоративной сетевой инфраструктуре физически, удаленно или виртуально, даже если они не контролируются организацией;"&" - На всех DHCP-серверах вести журналы для обновления реестра/ Данные в реестре обновлять раз в неделю или чаще;"&" - При выявлении неучтенных устройств отключать обеспечить их вывод из эксплуатации.") -> - Разработать и поддерживать реестр эксплуатируемых АРМ, серверов, коммутационного оборудования, перефирийных устройств, машинных носителей информации; - В реестр должны быть внесены все устройства, которые регулярно подключаются к корпоративной сетевой инфраструктуре физически, удаленно или виртуально, даже если они не контролируются организацией; - На всех DHCP-серверах вести журналы для обновления реестра/ Данные в реестре обновлять раз в неделю или чаще; - При выявлении неучтенных устройств отключать обеспечить их вывод из эксплуатации.
B113: Ведется учет имеющегося и используемого ПО | C113: УИБ.ИН.2 | D113: 5 | E113: 3.2 | F113: 1.6 | K113: 1.6 | L113: =VALUE(LEFT(N113,3)) -> 0 | M113: =L113-K113 -> -1.6 | N113: 0 - Контроль не выполняется | P113: =P112+0.01 -> 15.02 | Q113: =IF(($L113-$F113)>=0,"", " - Разработать и поддерживать реестр используемого ПО: - Реестр должен содержать название ПО, разработчика, дату установки/начала использования и бизнес-задачу ПО; - При необходимости указаны версия, механизм развертывания и дата вывода из эксплуатации;"&" - Для программ с веб- и мобильным доступом должны быть указаны их URL, магазин приложений;"&" - Реестр должен пересматриваться и обновляться не реже одного раза в полугодие; - Для ведения учета имеющегося и используемого ПО применять средства автоматизации. ") -> - Разработать и поддерживать реестр используемого ПО: - Реестр должен содержать название ПО, разработчика, дату установки/начала использования и бизнес-задачу ПО; - При необходимости указаны версия, механизм развертывания и дата вывода из эксплуатации; - Для программ с веб- и мобильным доступом должны быть указаны их URL, магазин приложений; - Реестр должен пересматриваться и обновляться не реже одного раза в полугодие; - Для ведения учета имеющегося и используемого ПО применять средства автоматизации. | R113: =R112+0.01 -> 215.02 | S113: =IF(($L113-$E113)>=0,"", "- Проверять, что авторизованное программное обеспечение из реестра поддерживается вендором: - В реестре авторизованного ПО должны содержаться только программы, которые поддерживаются производителем;"&" - Если ПО не поддерживается, но все еще используется, для него необходимо предусмотреть компенсирующие меры при выявлении уязвимостей;"&" - Наличие поддержки от вендора должно проверяться для всего ПО не реже одного раза в год. ") -> - Проверять, что авторизованное программное обеспечение из реестра поддерживается вендором: - В реестре авторизованного ПО должны содержаться только программы, которые поддерживаются производителем; - Если ПО не поддерживается, но все еще используется, для него необходимо предусмотреть компенсирующие меры при выявлении уязвимостей; - Наличие поддержки от вендора должно проверяться для всего ПО не реже одного раза в год. | T113: =T112+0.01 -> 315.02 | U113: =IF(($L113-$D113)>=0,"", " - Проверять, что всё используемое ПО включено в реестр, при выявлении неучтенного ПО обеспечивать его удаление; - Автоматизировать процесс проверки использования неучтенного ПО.") -> - Проверять, что всё используемое ПО включено в реестр, при выявлении неучтенного ПО обеспечивать его удаление; - Автоматизировать процесс проверки использования неучтенного ПО.
B114: Ведется персонифицированный учет учетных записей (УЗ), технологических УЗ, привилегированных УЗ и УЗ групповых почтовых ящиков | C114: УИБ.ИН.3 | D114: 5 | E114: 3.2 | F114: 1.6 | K114: 1.6 | L114: =VALUE(LEFT(N114,3)) -> 1.6 | M114: =L114-K114 -> 0 | N114: 1,6 - Объем покрытия минимальный | P114: =P113+0.01 -> 15.03 | Q114: =IF(($L114-$F114)>=0,"", " - Разработать или Получить в Блоке ИБ ПАО Ростелеком типовое описание процесса управления учетными записями. - Внедрить централизованное управление учетными записями: для централизации должна использоваться служба каталогов или служба идентификации;"&" Создать и поддерживать реестр учетных записей: - Реестр должен включать учетные данные рядовых пользователей и администраторов;"&" - Реестр должен содержать имя, фамилию, подразделение, дату создания/закрытия учетной записи;"&" - Проверка учетных записей должна осуществляться не реже одного раза в квартал. Учетные записи уволенных работников должны быть заблокированы.") | R114: =R113+0.01 -> 215.03 | S114: =IF(($L114-$E114)>=0,"", " - Реализовать автоматическую блокировку доменных учетных запией уволенных работников/ Интегрировать доменную службу каталогов с кадровой системой;"&" - Создать и поддерживать реестр служебных учетных записей: Для каждой служебной записи должно быть указано подразделение-владелец, цели учетной записи и дата пересмотра;"&" Создать и поддерживать реестр локальных учетных записей; Внедрить централизованное управление учетными записями для сетевого оборудования.") -> - Реализовать автоматическую блокировку доменных учетных запией уволенных работников/ Интегрировать доменную службу каталогов с кадровой системой; - Создать и поддерживать реестр служебных учетных записей: Для каждой служебной записи должно быть указано подразделение-владелец, цели учетной записи и дата пересмотра; Создать и поддерживать реестр локальных учетных записей; Внедрить централизованное управление учетными записями для сетевого оборудования. | T114: =T113+0.01 -> 315.03 | U114: =IF(($L114-$D114)>=0,"", " - Регламентировать процесс аудита учетных записей; - Контролировать выполнение аудита учетных записей; - Определить метрики процесса аудита, отслеживать результаты;"&" - Обеспечить аудит 100% учетных записей во всех системах, включая локальные. ") -> - Регламентировать процесс аудита учетных записей; - Контролировать выполнение аудита учетных записей; - Определить метрики процесса аудита, отслеживать результаты; - Обеспечить аудит 100% учетных записей во всех системах, включая локальные.
B115: Контроль белого (разрешенного) и черного (неразрешенного) списка программного обеспечения. | C115: УИБ.ИН.4 | D115: 5 | E115: 3.2 | F115: 1.6 | K115: 1.6 | L115: =VALUE(LEFT(N115,3)) -> 0 | M115: =L115-K115 -> -1.6 | N115: 0 - Контроль не выполняется | P115: =P114+0.01 -> 15.04 | Q115: =IF(($L115-$F115)>=0,"", " - Реализовать процесс авторизации ПО до начала его применения в Обществе; - Разработать и поддерживать реестр разрешенного и запрещенного ПО:"&" v Реестр должен содержать название ПО, разработчика, дату установки/начала использования и бизнес-задачу ПО. При необходимости должны быть указаны версия, механизм развертывания и дата вывода из эксплуатации;"&" - Для программ с веб- и мобильным доступом должны быть указаны их URL, магазин приложений;"&" - Реестр должен пересматриваться и обновляться не реже одного раза в полугодие") -> - Реализовать процесс авторизации ПО до начала его применения в Обществе; - Разработать и поддерживать реестр разрешенного и запрещенного ПО: v Реестр должен содержать название ПО, разработчика, дату установки/начала использования и бизнес-задачу ПО. При необходимости должны быть указаны версия, механизм развертывания и дата вывода из эксплуатации; - Для программ с веб- и мобильным доступом должны быть указаны их URL, магазин приложений; - Реестр должен пересматриваться и обновляться не реже одного раза в полугодие | R115: =R114+0.01 -> 215.04 | S115: =IF(($L115-$E115)>=0,"", " - Использовать белые списки авторизованного ПО для АРМ пользователей. Проводить проверку ПО, установленного на АРМ;"&" - Проверять, что всё используемое ПО включено в реестр, при выявлении неучтенного ПО обеспечивать его удаление/Автоматизировать процесс проверки. ") -> - Использовать белые списки авторизованного ПО для АРМ пользователей. Проводить проверку ПО, установленного на АРМ; - Проверять, что всё используемое ПО включено в реестр, при выявлении неучтенного ПО обеспечивать его удаление/Автоматизировать процесс проверки. | T115: =T114+0.01 -> 315.04 | U115: =IF(($L115-$D115)>=0,"", " - Использовать белые списки авторизованного ПО для информационных систем; - Реализовать процесс авторизации состава ПО на этапе проектирования ИС;"&" - Реализовать процесс контроля состава ПО ИС.") -> - Использовать белые списки авторизованного ПО для информационных систем; - Реализовать процесс авторизации состава ПО на этапе проектирования ИС; - Реализовать процесс контроля состава ПО ИС.
B116: Ведется учет использования адресных пространств (IP) | C116: УИБ.ИН.5 | D116: 5 | E116: 3.2 | F116: 1.6 | K116: 1.6 | L116: =VALUE(LEFT(N116,3)) -> 0 | M116: =L116-K116 -> -1.6 | N116: 0 - Контроль не выполняется | P116: =P115+0.01 -> 15.05 | Q116: =IF(($L116-$F116)>=0,"", " - Разработать и поддерживать реестр адресных пространств (IP); - Реестр должен пересматриваться и обновляться не реже одного раза в полугодие") -> - Разработать и поддерживать реестр адресных пространств (IP); - Реестр должен пересматриваться и обновляться не реже одного раза в полугодие | R116: =R115+0.01 -> 215.05 | S116: =IF(($L116-$E116)>=0,"", " - Регламентировать порядок учета управления IP-адресным пространством.") -> - Регламентировать порядок учета управления IP-адресным пространством. | T116: =T115+0.01 -> 315.05 | U116: =IF(($L116-$D116)>=0,"", "- Применять средства автоматизации для централизованного учета и управления IP-адресным пространством.") -> - Применять средства автоматизации для централизованного учета и управления IP-адресным пространством.
B117: Ведется учет созданных, используемых и (или) эксплуатируемых ИС | C117: УИБ.ИН.6 | D117: 5 | E117: 3.2 | F117: 1.6 | K117: 1.6 | L117: =VALUE(LEFT(N117,3)) -> 0 | M117: =L117-K117 -> -1.6 | N117: 0 - Контроль не выполняется | P117: =P116+0.01 -> 15.06 | Q117: =IF(($L117-$F117)>=0,"", " - Разработать и поддерживать реестр информационных систем; - Реестр должен пересматриваться и обновляться не реже одного раза в полугодие") -> - Разработать и поддерживать реестр информационных систем; - Реестр должен пересматриваться и обновляться не реже одного раза в полугодие | R117: =R116+0.01 -> 215.06 | S117: =IF(($L117-$E117)>=0,"", " - Порядок ввода в экплуатацию, учета и вывода из эксплуатации информационных систем определить внутренними нормативными документами.") -> - Порядок ввода в экплуатацию, учета и вывода из эксплуатации информационных систем определить внутренними нормативными документами. | T117: =T116+0.01 -> 315.06 | U117: =IF(($L117-$D117)>=0,"", " - Применять средства автоматизации для учета созданных, используемых, эксплуатируемых и выведенных из эксплуатации информационных систем, Вести учет состава и компонентов ИС.") -> - Применять средства автоматизации для учета созданных, используемых, эксплуатируемых и выведенных из эксплуатации информационных систем, Вести учет состава и компонентов ИС.
B118: Ведется учет опубликованных на внешнем периметре информационные системы, домены | C118: УИБ.ИН.7 | D118: 5 | E118: 3.2 | F118: 3.2 | K118: 3.2 | L118: =VALUE(LEFT(N118,3)) -> 0 | M118: =L118-K118 -> -3.2 | N118: 0 - Контроль не выполняется | P118: =P117+0.01 -> 15.07 | Q118: =IF(($L118-$F118)>=0,"", " - Разработать и поддерживать реестр информационных систем и доменов, опубликованных на внешнем периметре;"&" - Реестр должен пересматриваться и обновляться не реже одного раза в полугодие") -> - Разработать и поддерживать реестр информационных систем и доменов, опубликованных на внешнем периметре; - Реестр должен пересматриваться и обновляться не реже одного раза в полугодие | R118: =R117+0.01 -> 215.07 | S118: =IF(($L118-$E118)>=0,"",) -> 0 | T118: =T117+0.01 -> 315.07 | U118: =IF(($L118-$D118)>=0,"", " - Для учета применять средства автоматизации; - Для актуализации реестра использовать инструменты активного/пассивного обнаружения активов.") -> - Для учета применять средства автоматизации; - Для актуализации реестра использовать инструменты активного/пассивного обнаружения активов.
B119: За информационными активами закреплены ответственные | C119: УИБ.ИН.8 | D119: 5 | E119: 3.2 | F119: 3.2 | K119: 3.2 | L119: =VALUE(LEFT(N119,3)) -> 0 | M119: =L119-K119 -> -3.2 | N119: 0 - Контроль не выполняется | P119: =P118+0.01 -> 15.08 | Q119: =IF(($L119-$F119)>=0,"",) -> 0 | R119: =R118+0.01 -> 215.08 | S119: =IF(($L119-$E119)>=0,"",) -> 0 | T119: =T118+0.01 -> 315.08 | U119: =IF(($L119-$D119)>=0,"", " - Издать внутренние приказы по закреплению ответственных за каждым информационным активом;"&" - Проводить периодическую сверку. Определить функции и обязанности ответственных.") -> - Издать внутренние приказы по закреплению ответственных за каждым информационным активом; - Проводить периодическую сверку. Определить функции и обязанности ответственных.
B120: Наличие специализированного ПО для хранения инвентаризационных данных | C120: УИБ.ИН.9 | D120: 5 | E120: 3.2 | F120: 0 | K120: 0 | L120: =VALUE(LEFT(N120,3)) -> 0 | M120: =L120-K120 -> 0 | N120: 0 - Контроль не выполняется | P120: =P119+0.01 -> 15.09 | Q120: =IF(($L120-$F120)>=0,"",) | R120: =R119+0.01 -> 215.09 | S120: =IF(($L120-$E120)>=0,"", " - Применять для каждого вида активов локальные базы данных, информационные ресурсы для хранения инвентаризационных данных") -> - Применять для каждого вида активов локальные базы данных, информационные ресурсы для хранения инвентаризационных данных | T120: =T119+0.01 -> 315.09 | U120: =IF(($L120-$D120)>=0,"", "Применять для хранения и управления инвентаризационными данными автоматизированную систему учета активов класса CMDB (Configuration Management Database)") -> Применять для хранения и управления инвентаризационными данными автоматизированную систему учета активов класса CMDB (Configuration Management Database)
B121: Используется инструментарий активного/пассивного обнаружения активов | C121: УИБ.ИН.10 | D121: 5 | E121: 3.2 | F121: 0 | K121: 0 | L121: =VALUE(LEFT(N121,3)) -> 0 | M121: =L121-K121 -> 0 | N121: 0 - нет | P121: =P120+0.01 -> 15.1 | Q121: =IF(($L121-$F121)>=0,"",) | R121: =R120+0.01 -> 215.1 | S121: =IF(($L121-$E121)>=0,"", " - Для обнаружения новых активов применять инструменты для активного обнаружения;"&" - Обнаружение подключенных к сети устройств запускается по расписанию не реже одного раза в день.") -> - Для обнаружения новых активов применять инструменты для активного обнаружения; - Обнаружение подключенных к сети устройств запускается по расписанию не реже одного раза в день. | T121: =T120+0.01 -> 315.1 | U121: =IF(($L121-$D121)>=0,"", " - Для обнаружения новых активов применять инструменты для пассивного обнаружения устройств;"&" - Результаты сканирования используются для обновления реестра устройств не реже одного раза в неделю; - Выполнять авторизацию каждого выявленного актива. ") -> - Для обнаружения новых активов применять инструменты для пассивного обнаружения устройств; - Результаты сканирования используются для обновления реестра устройств не реже одного раза в неделю; - Выполнять авторизацию каждого выявленного актива.
B122: Результаты работы сканеров уязвимости являются источниками для пополнения БД систем инвентаризации | C122: УИБ.ИН.11 | D122: 5 | E122: 3.2 | F122: 0 | K122: 0 | L122: =VALUE(LEFT(N122,3)) -> 0 | M122: =L122-K122 -> 0 | N122: 0 - Контроль не выполняется | P122: =P121+0.01 -> 15.11 | Q122: =IF(($L122-$F122)>=0,"",) | R122: =R121+0.01 -> 215.11 | S122: =IF(($L122-$E122)>=0,"", " - Обеспечить актуализацию инвентаризационных реестров по результатам сканирования в автоматизированном режиме (возможно в ручном режиме)") -> - Обеспечить актуализацию инвентаризационных реестров по результатам сканирования в автоматизированном режиме (возможно в ручном режиме) | T122: =T121+0.01 -> 315.11 | U122: =IF(($L122-$D122)>=0,"", " - Интегрировать инструменты анализа защищенности и СРТ с автоматизированной системой учета активов.") -> - Интегрировать инструменты анализа защищенности и СРТ с автоматизированной системой учета активов.
B123: Производится регулярный контроль фактического состава созданных, используемых и (или) эксплуатируемых информационных активов и их корректного размещения в сегментах вычислительных сетей | C123: УИБ.ИН.12 | D123: 5 | E123: 3.2 | F123: 0 | K123: 0 | L123: =VALUE(LEFT(N123,3)) -> 0 | M123: =L123-K123 -> 0 | N123: 0 - Контроль не выполняется | P123: =P122+0.01 -> 15.12 | Q123: =IF(($L123-$F123)>=0,"",) | R123: =R122+0.01 -> 215.12 | S123: =IF(($L123-$E123)>=0,"", " - Разработать и внедрить процесс контроля фактического состава созданных, используемых и (или) эксплуатируемых информационных активов и их корректного размещения в сегментах вычислительных сетей") -> - Разработать и внедрить процесс контроля фактического состава созданных, используемых и (или) эксплуатируемых информационных активов и их корректного размещения в сегментах вычислительных сетей | T123: =T122+0.01 -> 315.12 | U123: =IF(($L123-$D123)>=0,"", " - Процесс контроля осуществляется с применением средств автоматизации") -> - Процесс контроля осуществляется с применением средств автоматизации
B124: Осуществляется разработка, ведение, актуализация, хранение проектной, рабочей, эксплуатационной документации на информационные системы | C124: УИБ.ИН.13 | D124: 5 | E124: 3.2 | F124: 0 | K124: 0 | L124: =VALUE(LEFT(N124,3)) -> 0 | M124: =L124-K124 -> 0 | N124: 0 - Контроль не выполняется | P124: =P123+0.01 -> 15.13 | Q124: =IF(($L124-$F124)>=0,"",) | R124: =R123+0.01 -> 215.13 | S124: =IF(($L124-$E124)>=0,"", " - Определить порядок ввода в экплуатацию, учета и вывода из эксплуатации информационных систем внутренними нормативными документами;"&" - В указанных документах должны быть описаны процедуры разработки, ведения, актуализации, хранения проектной, рабочей, эксплуатационной документации на информационные системы;"&" - Проектную, рабочую, эксплуатационную и иную документацию на информационные системы необходимо хранить в локальных базах данных") -> - Определить порядок ввода в экплуатацию, учета и вывода из эксплуатации информационных систем внутренними нормативными документами; - В указанных документах должны быть описаны процедуры разработки, ведения, актуализации, хранения проектной, рабочей, эксплуатационной документации на информационные системы; - Проектную, рабочую, эксплуатационную и иную документацию на информационные системы необходимо хранить в локальных базах данных | T124: =T123+0.01 -> 315.13 | U124: =IF(($L124-$D124)>=0,"", " - Сведения и артефакты о проектной, рабочей, эксплуатационной документации на информационные системы необходимо хранить и актуализировать в единой автоматизированной системе учета") -> - Сведения и артефакты о проектной, рабочей, эксплуатационной документации на информационные системы необходимо хранить и актуализировать в единой автоматизированной системе учета
B125: Обеспечение доступности | C125: ОД | M125: =L125-K125 -> 0 | P125: =VLOOKUP(B125,Приоритет!$G$9:$K$48,5,0) -> 39 | Q125: ОД | R125: =P125+200 -> 239 | S125: ОД | T125: =P125+300 -> 339 | U125: ОД
B126: Определены требования к отказоустойчивости компонент | C126: УИБ.ОД.1 | D126: 5 | E126: 5 | F126: 0 | K126: 0 | L126: =VALUE(LEFT(N126,3)) -> 0 | M126: =L126-K126 -> 0 | N126: 0 - нет | P126: =P125+0.01 -> 39.01 | Q126: =IF(($L126-$F126)>=0,"", " - Определить критерии для определения критичности ИС;"&" - Определить требования к обеспечению отказоустойчивости в соответствии с критичностью ИС; - Провести анализ ИС, выделить наиболее критичные с точки зрения непрерывности, определить требования по отказоустойчивости для данных ИС;"&" - Выполнить требования к отказоустойчивости.") | R126: =R125+0.01 -> 239.01 | S126: =IF(($L126-$E126)>=0,"", " - Провести анализ всех ИС и определить требования к отказоустойчивости для каждой;"&" - Определить требования к характеристикам отказоустойчивости, дублированию, резервированию всех программных"&" и аппаратных компонентов ИС, обеспечивающих систем, внешних сервисов, облачных провайдеров, каналов связи, ЦОД; - Обеспечить реализацию требований.") -> - Провести анализ всех ИС и определить требования к отказоустойчивости для каждой; - Определить требования к характеристикам отказоустойчивости, дублированию, резервированию всех программных и аппаратных компонентов ИС, обеспечивающих систем, внешних сервисов, облачных провайдеров, каналов связи, ЦОД; - Обеспечить реализацию требований. | T126: =T125+0.01 -> 339.01 | U126: =IF(($L126-$D126)>=0,"", " - Регламентировать процесс обеспечения отказоустойчивости; - Контролировать выполнение требований к отказоустойчивости.") -> - Регламентировать процесс обеспечения отказоустойчивости; - Контролировать выполнение требований к отказоустойчивости.
B127: Осуществляется дублирование инфраструктуры в разных территориально разделенных ЦОД | C127: УИБ.ОД.2 | D127: 5 | E127: 3.2 | F127: 0 | K127: 0 | L127: =VALUE(LEFT(N127,3)) -> 0 | M127: =L127-K127 -> 0 | N127: 0 - нет | P127: =P126+0.01 -> 39.02 | Q127: =IF(($L127-$F127)>=0,"",) | R127: =R126+0.01 -> 239.02 | S127: =IF(($L127-$E127)>=0,"", " - Обеспечить дублирование инфраструктуры в разных ЦОД для критичных ИС.") -> - Обеспечить дублирование инфраструктуры в разных ЦОД для критичных ИС. | T127: =T126+0.01 -> 339.02 | U127: =IF(($L127-$D127)>=0,"", " - Обеспечить дублирование инфраструктуры в разных ЦОД для всех ИС и хранилищ резервных копий;"&" - Регламентировать порядок дублирования инфраструктуры в территориально разделенных ЦОД.") -> - Обеспечить дублирование инфраструктуры в разных ЦОД для всех ИС и хранилищ резервных копий; - Регламентировать порядок дублирования инфраструктуры в территориально разделенных ЦОД.
B128: Осуществляется кластеризация компонентов Mission Critical и Busines Critical систем | C128: УИБ.ОД.3 | D128: 5 | E128: 5 | F128: 0 | K128: 0 | L128: =VALUE(LEFT(N128,3)) -> 0 | M128: =L128-K128 -> 0 | N128: 0 - нет | P128: =P127+0.01 -> 39.03 | Q128: =IF(($L128-$F128)>=0,"", " - Обеспечить кластеризацию критичных компонентов ИС и инфрастурктуры") | R128: =R127+0.01 -> 239.03 | S128: =IF(($L128-$E128)>=0,"", " - Определить требования к кластеризации компонентов ИС; - Обеспечить кластеризацию критичных ИС;"&" - Реализовать мониторинг состояния кластеров; - Обеспечить отказоустойчивость кластеров при сбоях") -> - Определить требования к кластеризации компонентов ИС; - Обеспечить кластеризацию критичных ИС; - Реализовать мониторинг состояния кластеров; - Обеспечить отказоустойчивость кластеров при сбоях | T128: =T127+0.01 -> 339.03 | U128: =IF(($L128-$D128)>=0,"", " - Реализовать процесс периодического тестирования кластеризованных компонентов на отказоустойчивость.") -> - Реализовать процесс периодического тестирования кластеризованных компонентов на отказоустойчивость.
B129: Наличие достаточного перечня запасных частей и материалов, а также активной технической поддержки на оборудование и программное обеспечение | C129: УИБ.ОД.6 | D129: 5 | E129: 3.2 | F129: 0 | K129: 0 | L129: =VALUE(LEFT(N129,3)) -> 0 | M129: =L129-K129 -> 0 | N129: 0 - нет | P129: =P128+0.01 -> 39.04 | Q129: =IF(($L129-$F129)>=0,"",) | R129: =R128+0.01 -> 239.04 | S129: =IF(($L129-$E129)>=0,"", " - Определить перечень запасных частей и материалов, необходимых для обеспечения непрерывной работы информационных систем и проведения аварийно-восстановительных работ;"&" - Закупить в требуемом объеме запасные части и материалы. ") -> - Определить перечень запасных частей и материалов, необходимых для обеспечения непрерывной работы информационных систем и проведения аварийно-восстановительных работ; - Закупить в требуемом объеме запасные части и материалы. | T129: =T128+0.01 -> 339.04 | U129: =IF(($L129-$D129)>=0,"", " - Определить перечень запасных частей и материалов, необходимых для обеспечения непрерывной работы информационных систем, плановой замены, развития, восстановления при авариях;"&" - Закупить в требуемом объеме запасные части и материалы; - Заключить договоры на техническую поддержку оборудования и ПО;"&" - Регламентировать процессы обеспечения запасными частями и материалами, требуемые объемы и уровни запасов с учетом критичности информационных систем.") -> - Определить перечень запасных частей и материалов, необходимых для обеспечения непрерывной работы информационных систем, плановой замены, развития, восстановления при авариях; - Закупить в требуемом объеме запасные части и материалы; - Заключить договоры на техническую поддержку оборудования и ПО; - Регламентировать процессы обеспечения запасными частями и материалами, требуемые объемы и уровни запасов с учетом критичности информационных систем.
B130: Обеспечивается уровень доступности систем и средств защиты не ниже, чем уровень доступности защищаемых информационных систем | C130: УИБ.ОД.7 | D130: 5 | E130: 3.2 | F130: 0 | K130: 0 | L130: =VALUE(LEFT(N130,3)) -> 0 | M130: =L130-K130 -> 0 | N130: 0 - Контроль не выполняется | P130: =P129+0.01 -> 39.05 | Q130: =IF(($L130-$F130)>=0,"", " - Определить требования к уровню доступности средств защиты и обеспечить его выполнение;"&" - Обеспечить уровень доступности средств защиты не ниже чем уровень доступности защищаемых ИС") | R130: =R129+0.01 -> 239.05 | S130: =IF(($L130-$E130)>=0,"", " - Определить требования к уровню доступности средств защиты и обеспечить его выполнение;"&" - Обеспечить уровень доступности средств защиты не ниже чем уровень доступности защищаемых ИС;"&" - Обеспечить доступность средств защиты при авариях и сбоях ИС; - Обеспечить применение компенсирующих мер защиты при сбоях и авариях средств защиты.") -> - Определить требования к уровню доступности средств защиты и обеспечить его выполнение; - Обеспечить уровень доступности средств защиты не ниже чем уровень доступности защищаемых ИС; - Обеспечить доступность средств защиты при авариях и сбоях ИС; - Обеспечить применение компенсирующих мер защиты при сбоях и авариях средств защиты. | T130: =T129+0.01 -> 339.05 | U130: =IF(($L130-$D130)>=0,"", " - Реализовать процесс периодического тестирования средств защиты в рамках общего процесса тестирования ИС на отказоустойчивость.") -> - Реализовать процесс периодического тестирования средств защиты в рамках общего процесса тестирования ИС на отказоустойчивость.
B131: Безопасная разработка | C131: БР | M131: =L131-K131 -> 0 | P131: =VLOOKUP(B131,Приоритет!$G$9:$K$48,5,0) -> 33 | Q131: БР | R131: =P131+200 -> 233 | S131: БР | T131: =P131+300 -> 333 | U131: =IF(($L131-$D131)>=0,"", "Реализовать процесс периодического тестирования средств защиты в рамках общего процесса тестирования ИС на отказоустойчивость.")
B132: Назначен ответственный за безопасную разработку ПО | C132: УИБ.БР.5.9.1 | D132: =5*IF(БР="да",1,0) -> 5 | E132: =5*IF(БР="да",1,0) -> 5 | F132: 0 | K132: 0 | L132: =VALUE(LEFT(N132,3)) -> 0 | M132: =L132-K132 -> 0 | N132: 0 - нет | P132: =P131+0.01 -> 33.01 | Q132: =IF(($L132-$F132)>=0,"", " ") | R132: =R131+0.01 -> 233.01 | S132: =IF(($L132-$E132)>=0,"", " Определить и официально назначить ответственного сотрудника за безопасную разработку ПО;") -> Определить и официально назначить ответственного сотрудника за безопасную разработку ПО; | T132: =T131+0.01 -> 333.01 | U132: =IF(($L132-$D132)>=0,"",) -> 0
B133: Требования ИБ формируются на этапе разработки требований к ПО | C133: УИБ.БР.5.9.2 | D133: =5*IF(БР="да",1,0) -> 5 | E133: =3.2*IF(БР="да",1,0) -> 3.2 | F133: =1.6*IF(БР="да",1,0) -> 1.6 | K133: =1.6*IF(БР="да",1,0) -> 1.6 | L133: =VALUE(LEFT(N133,3)) -> 0 | M133: =L133-K133 -> -1.6 | N133: 0 - Не реализовано | P133: =P132+0.01 -> 33.02 | Q133: =IF(($L133-$F133)>=0,"", " Для систем Mission Critical определить: -требования безопасности ПО; -типовой набор требований безопасности ПО.") -> Для систем Mission Critical определить: -требования безопасности ПО; -типовой набор требований безопасности ПО. | R133: =R132+0.01 -> 233.02 | S133: =IF(($L133-$E133)>=0,"", " 1. Для систем Business Critical формализовать: -требования безопасности ПО; -типовой набор требований безопасности ПО. 2.Автоматизировать процесс предоставления, получения и выполнения требований безопасности ПО;") -> 1. Для систем Business Critical формализовать: -требования безопасности ПО; -типовой набор требований безопасности ПО. 2.Автоматизировать процесс предоставления, получения и выполнения требований безопасности ПО; | T133: =T132+0.01 -> 333.02 | U133: =IF(($L133-$D133)>=0,"", " Для всех систем формализовать: -требования безопасности ПО; -типовой набор требований безопасности ПО.") -> Для всех систем формализовать: -требования безопасности ПО; -типовой набор требований безопасности ПО.
B134: Определен Порядок фиксации замечаний по безопасности и последующего исправления багов | C134: УИБ.БР.5.9.3 | D134: =5*IF(БР="да",1,0) -> 5 | E134: =5*IF(БР="да",1,0) -> 5 | F134: 0 | K134: 0 | L134: =VALUE(LEFT(N134,3)) -> 0 | M134: =L134-K134 -> 0 | N134: 0 - нет | P134: =P133+0.01 -> 33.03 | Q134: =IF(($L134-$F134)>=0,"","") | R134: =R133+0.01 -> 233.03 | S134: =IF(($L134-$E134)>=0,""," Разработать и утвердить Порядок фиксации замечаний по безопасности и последующего исправления багов") -> Разработать и утвердить Порядок фиксации замечаний по безопасности и последующего исправления багов | T134: =T133+0.01 -> 333.03 | U134: =IF(($L134-$D134)>=0,"","")
B135: Организован процесс тестирования ПО | C135: УИБ.БР.5.9.4 | D135: =4*IF(БР="да",1,0) -> 4 | E135: =3*IF(БР="да",1,0) -> 3 | F135: =1*IF(БР="да",1,0) -> 1 | K135: =1*IF(БР="да",1,0) -> 1 | L135: =VALUE(LEFT(N135,3)) -> 0 | M135: =L135-K135 -> -1 | N135: 0 - Процесс отсутствует | P135: =P134+0.01 -> 33.04 | Q135: =IF(($L135-$F135)>=0,"", "Для систем Mission Critical определить порядок тестирования ПО.") -> Для систем Mission Critical определить порядок тестирования ПО. | R135: =R134+0.01 -> 233.04 | S135: =IF(($L135-$E135)>=0,"", "1. Для всех систем формализовать: -регламент проведения динамического анализа исходного кода ПО; -регламент функционального тестирования;"&" -регламент нефункционального тестирования. 2.Автоматизировать процесс тестирование ПО; 3.Мониторить процессы тестирования ПО в CI/CD-конвейере.") -> 1. Для всех систем формализовать: -регламент проведения динамического анализа исходного кода ПО; -регламент функционального тестирования; -регламент нефункционального тестирования. 2.Автоматизировать процесс тестирование ПО; 3.Мониторить процессы тестирования ПО в CI/CD-конвейере. | T135: =T134+0.01 -> 333.04 | U135: =IF(($L135-$D135)>=0,"","Качество процесса отслеживать с помощью метрик.") -> Качество процесса отслеживать с помощью метрик.
B136: Организован процесс приемки и инсталляции ПО: - порядок приемки ПО перед его запуском в продуктивной среде - порядок передачи ПО в продуктивную среду - состав и содержание эксплуатационных документов на ПО | C136: УИБ.БР.5.9.5 | D136: =5*IF(БР="да",1,0) -> 5 | E136: =3.2*IF(БР="да",1,0) -> 3.2 | F136: =1.6*IF(БР="да",1,0) -> 1.6 | K136: =1.6*IF(БР="да",1,0) -> 1.6 | L136: =VALUE(LEFT(N136,3)) -> 0 | M136: =L136-K136 -> -1.6 | N136: 0 - Не реализовано | P136: =P135+0.01 -> 33.05 | Q136: =IF(($L136-$F136)>=0,"", " Для систем Mission Critical определить: -порядок приемки ПО перед его запуском в продуктивной среде; - порядок передачи ПО в продуктивную среду; -состав и содержание эксплуатационных документов на ПО.") -> Для систем Mission Critical определить: -порядок приемки ПО перед его запуском в продуктивной среде; - порядок передачи ПО в продуктивную среду; -состав и содержание эксплуатационных документов на ПО. | R136: =R135+0.01 -> 233.05 | S136: =IF(($L136-$E136)>=0,"", "Для систем Mission и Business Critical формализовать: - порядок приемки ПО перед его запуском в продуктивной среде; - порядок передачи ПО в продуктивную среду; - состав и содержание эксплуатационных документов на ПО. ") -> Для систем Mission и Business Critical формализовать: - порядок приемки ПО перед его запуском в продуктивной среде; - порядок передачи ПО в продуктивную среду; - состав и содержание эксплуатационных документов на ПО. | T136: =T135+0.01 -> 333.05 | U136: =IF(($L136-$D136)>=0,"", "Для всех систем формализовать: - порядок приемки ПО перед его запуском в продуктивной среде; - порядок передачи ПО в продуктивную среду; - состав и содержание эксплуатационных документов на ПО.") -> Для всех систем формализовать: - порядок приемки ПО перед его запуском в продуктивной среде; - порядок передачи ПО в продуктивную среду; - состав и содержание эксплуатационных документов на ПО.
B137: Организован процесс эксплуатации ПО: - назначены ответственные за техническую поддержку пользователей ПО - сформирован порядок информирования пользователей об обновлениях ПО, обнаруженных уязвимостях и окончании технической поддержки - назначены ответственные за поиск уязвимостей ПО и их устранение | C137: УИБ.БР.5.9.6 | D137: =5*IF(БР="да",1,0) -> 5 | E137: =3.2*IF(БР="да",1,0) -> 3.2 | F137: =1.6*IF(БР="да",1,0) -> 1.6 | K137: =1.6*IF(БР="да",1,0) -> 1.6 | L137: =VALUE(LEFT(N137,3)) -> 0 | M137: =L137-K137 -> -1.6 | N137: 0 - Не реализовано | P137: =P136+0.01 -> 33.06 | Q137: =IF(($L137-$F137)>=0,"", "Для систем Mission Critical определить: - ответственных за техническую поддержку пользователей ПО;"&" - порядок информирования пользователей об обновлениях ПО,обнаруженных уязвимостях и окончании технической поддержки - ответственных за поиск уязвимостей ПО и их устранение.") -> Для систем Mission Critical определить: - ответственных за техническую поддержку пользователей ПО; - порядок информирования пользователей об обновлениях ПО,обнаруженных уязвимостях и окончании технической поддержки - ответственных за поиск уязвимостей ПО и их устранение. | R137: =R136+0.01 -> 233.06 | S137: =IF(($L137-$E137)>=0,"", "Для систем Business Critical. : - назначить ответственных за техническую поддержку пользователей ПО;"&" - формализовать порядок информирования пользователей об обновлениях ПО, обнаруженных уязвимостях и окончании технической поддержки; - назначить о ответственных за поиск уязвимостей ПО и их устранение. ") -> Для систем Business Critical. : - назначить ответственных за техническую поддержку пользователей ПО; - формализовать порядок информирования пользователей об обновлениях ПО, обнаруженных уязвимостях и окончании технической поддержки; - назначить о ответственных за поиск уязвимостей ПО и их устранение. | T137: =T136+0.01 -> 333.06 | U137: =IF(($L137-$D137)>=0,"","Для всех систем: - назначить ответственных за техническую поддержку пользователей ПО;"&" - формализовать порядок информирования пользователей об обновлениях ПО,обнаруженных уязвимостях и окончании технической поддержки - назначить о ответственных за поиск уязвимостей ПО и их устранение. ") -> Для всех систем: - назначить ответственных за техническую поддержку пользователей ПО; - формализовать порядок информирования пользователей об обновлениях ПО,обнаруженных уязвимостях и окончании технической поддержки - назначить о ответственных за поиск уязвимостей ПО и их устранение.
B138: Используются проверенные модули безопасности (шифрования, ведения журналов, идентификации/аутентификапции) | C138: УИБ.БР.5.9.7 | D138: =5*IF(БР="да",1,0) -> 5 | E138: =5*IF(БР="да",1,0) -> 5 | F138: 0 | K138: 0 | L138: =VALUE(LEFT(N138,3)) -> 0 | M138: =L138-K138 -> 0 | N138: 0 - нет | P138: =P137+0.01 -> 33.07 | Q138: =IF(($L138-$F138)>=0,"", "" ) | R138: =R137+0.01 -> 233.07 | S138: =IF(($L138-$E138)>1.6,"","- Провести инвентаризацию всех используемых модулей и служб в текущей инфраструктуре; - Определить критерии оценки модулей и служб (наличие сертификаций, регулярные обновления, отзывы сообщества); "&" - Разработать реестр проверенных модулей и служб, с указанием источника и даты проверки;"& " - Обеспечить использование модулей и служб, внесенных в реестр; - Настроить автоматические обновления для всех используемых модулей и служб") -> - Провести инвентаризацию всех используемых модулей и служб в текущей инфраструктуре; - Определить критерии оценки модулей и служб (наличие сертификаций, регулярные обновления, отзывы сообщества); - Разработать реестр проверенных модулей и служб, с указанием источника и даты проверки; - Обеспечить использование модулей и служб, внесенных в реестр; - Настроить автоматические обновления для всех используемых модулей и служб | T138: =T137+0.01 -> 333.07 | U138: =IF(($L138-$D138)>=0,"","")
B139: Организован процесс обучения сотрудников | C139: УИБ.БР.5.9.8 | D139: =5*IF(БР="да",1,0) -> 5 | E139: =3.2*IF(БР="да",1,0) -> 3.2 | F139: =1.6*IF(БР="да",1,0) -> 1.6 | K139: =1.6*IF(БР="да",1,0) -> 1.6 | L139: =VALUE(LEFT(N139,3)) -> 0 | M139: =L139-K139 -> -1.6 | N139: 0 - Не реализовано | P139: =P138+0.01 -> 33.08 | Q139: =IF(($L139-$F139)>=0,"","Определить порядок повышения и поддержания на должном уровне компетенций разработчиков в области безопасности ПО; ") -> Определить порядок повышения и поддержания на должном уровне компетенций разработчиков в области безопасности ПО; | R139: =R138+0.01 -> 233.08 | S139: =IF(($L139-$E139)>=0,"", " 1. Формализовать: - порядок повышения и поддержания на должном уровне компетенций разработчиков в области безопасности ПО; - программу и план обучения в области безопасности ПО; "&" 2. Автоматизировать процесс обучения; 3. Мониторить процесс обучения.") -> 1. Формализовать: - порядок повышения и поддержания на должном уровне компетенций разработчиков в области безопасности ПО; - программу и план обучения в области безопасности ПО; 2. Автоматизировать процесс обучения; 3. Мониторить процесс обучения. | T139: =T138+0.01 -> 333.08 | U139: =IF(($L139-$D139)>=0,"","Качество процесса отслеживать с помощью метрик") -> Качество процесса отслеживать с помощью метрик
B140: Формализованы и определены процедуры контроля сторонней разработки. Заказчиком осуществляется контроль безопасности ПО при заказе разработки ПО | C140: УИБ.БР.5.9.9 | D140: =5*IF(БР="да",1,0) -> 5 | E140: =3.2*IF(БР="да",1,0) -> 3.2 | F140: =1.6*IF(БР="да",1,0) -> 1.6 | K140: =1.6*IF(БР="да",1,0) -> 1.6 | L140: =VALUE(LEFT(N140,3)) -> 0 | M140: =L140-K140 -> -1.6 | N140: 0 - Не реализовано | P140: =P139+0.01 -> 33.09 | Q140: =IF(($L140-$F140)>=0,"","1.Разработать и утвердить документы: лицензионный договор; акт приема-передачи. 2.Вести отчетность по анализу кода ПО, полученного через цепочки поставок, на предмет внедрения вредоносного программного обеспечения для систем Mission Critical.") -> 1.Разработать и утвердить документы: лицензионный договор; акт приема-передачи. 2.Вести отчетность по анализу кода ПО, полученного через цепочки поставок, на предмет внедрения вредоносного программного обеспечения для систем Mission Critical. | R140: =R139+0.01 -> 233.09 | S140: =IF(($L140-$E140)>=0,"", " Мероприятия на КБ1 + 1.Вести отчетность по анализу кода ПО, полученного через цепочки поставок, на предмет внедрения вредоносного программного обеспечения для систем Business Critical."&" 2. Автоматизировать контроль безопасности ПО для систем Business Critical.") -> Мероприятия на КБ1 + 1.Вести отчетность по анализу кода ПО, полученного через цепочки поставок, на предмет внедрения вредоносного программного обеспечения для систем Business Critical. 2. Автоматизировать контроль безопасности ПО для систем Business Critical. | T140: =T139+0.01 -> 333.09 | U140: =IF(($L140-$D140)>=0,"","1. Вести отчетность по анализу кода ПО, полученного через цепочки поставок, на предмет внедрения вредоносного программного обеспечения для всех систем ; 2. Автоматизировать контроль безопасности ПО для всех систем;") -> 1. Вести отчетность по анализу кода ПО, полученного через цепочки поставок, на предмет внедрения вредоносного программного обеспечения для всех систем ; 2. Автоматизировать контроль безопасности ПО для всех систем;
B141: Создан и актуален реестр одобренных компонентов ПО, принадлежащих сторонним производителям. Отслеживаются обновления и свежие версии компонентов не реже раз в месяц. | C141: УИБ.БР.5.9.10 | D141: =5*IF(БР="да",1,0) -> 5 | E141: =3.2*IF(БР="да",1,0) -> 3.2 | F141: =1.6*IF(БР="да",1,0) -> 1.6 | K141: =1.6*IF(БР="да",1,0) -> 1.6 | L141: =VALUE(LEFT(N141,3)) -> 0 | M141: =L141-K141 -> -1.6 | N141: 0 - нет | P141: =P140+0.01 -> 33.1 | Q141: =IF(($L141-$F141)>=0,"", "1.Задокументировать порядок формирования списка доверенных компонентов, критерии доверия и правила использования. 2.Создать реестр одобренных компонентов ПО;") -> 1.Задокументировать порядок формирования списка доверенных компонентов, критерии доверия и правила использования. 2.Создать реестр одобренных компонентов ПО; | R141: =R140+0.01 -> 233.1 | S141: =IF(($L141-$E141)>=0,"", " -Мероприятия для КБ1 + 1. Автоматизировать поиск узявимостей в реестре одобренных компонентов ПО; 2. Автоматизировать процесс отслеживания обновления ПО и информации об уязвимостях.") -> -Мероприятия для КБ1 + 1. Автоматизировать поиск узявимостей в реестре одобренных компонентов ПО; 2. Автоматизировать процесс отслеживания обновления ПО и информации об уязвимостях. | T141: =T140+0.01 -> 333.1 | U141: =IF(($L141-$D141)>=0,"","1.Мониторить процесс поиска узявимостей в реестре одобренных компонентов ПО; 2.Отслеживать с помощью метрик процесс обновления ПО и информации об уязвимостях не реже одного раза в месяц.") -> 1.Мониторить процесс поиска узявимостей в реестре одобренных компонентов ПО; 2.Отслеживать с помощью метрик процесс обновления ПО и информации об уязвимостях не реже одного раза в месяц.
...

Sheet Нормативное соответствие
B1: Нормативное соответствие | N1: =COUNTA(N2:N6987) -> 54
G40: =Расчет!$F$2 -> 45017 | H40: =Расчет!$H$2 -> 45444 | I40: 0 - 01.2024 | L40: =TODAY() -> 46038
B41: Категория | C41: Сокращенное наименование | D41: КБ3 | E41: КБ2 | F41: КБ1 | G41: Исторические данные | H41: Исторические данные | I41: Исторические данные | J41: 2026 | K41: Расчетный показатель 2025 | L41: Текущий показатель
B42: =B49 -> Персональные данные | C42: =C49 -> ПР | D42: =AVERAGE('Нормативное соответствие'!D50:D73) -> 5 | E42: =AVERAGE('Нормативное соответствие'!E50:E73) -> 5 | F42: =AVERAGE('Нормативное соответствие'!F50:F73) -> 5 | G42: =AVERAGE(G50:G73) -> #DIV/0! | H42: =AVERAGE(H50:H73) -> #DIV/0! | I42: =AVERAGE(I50:I73) -> #DIV/0! | J42: =AVERAGE('Нормативное соответствие'!J50:J73) -> #DIV/0! | K42: =AVERAGE('Нормативное соответствие'!K50:K73) -> 5 | L42: =AVERAGE('Нормативное соответствие'!L50:L73) -> 0.20833333
B43: =B74 -> КИИ | C43: =C74 -> КИИ | D43: =AVERAGE('Нормативное соответствие'!D75:D87)*IF(КИИ="да",1,0) -> 0 | E43: =AVERAGE('Нормативное соответствие'!E75:E87)*IF(КИИ="да",1,0) -> 0 | F43: =AVERAGE('Нормативное соответствие'!F75:F87)*IF(КИИ="да",1,0) -> 0 | G43: =AVERAGE('Нормативное соответствие'!G75:G87) -> #DIV/0! | H43: =AVERAGE('Нормативное соответствие'!H75:H87) -> #DIV/0! | I43: =AVERAGE('Нормативное соответствие'!I75:I87) -> #DIV/0! | J43: =AVERAGE('Нормативное соответствие'!J75:J87) -> #DIV/0! | K43: =AVERAGE('Нормативное соответствие'!K75:K87) -> 0 | L43: =AVERAGE('Нормативное соответствие'!L75:L87) -> 0
B44: =B90 -> Коммерческая тайна | C44: =C90 -> КТ | D44: =AVERAGE('Нормативное соответствие'!D91:D95)*IF(КТ="да",1,0) -> 5 | E44: =AVERAGE('Нормативное соответствие'!E91:E95)*IF(КТ="да",1,0) -> 5 | F44: =AVERAGE('Нормативное соответствие'!F91:F95)*IF(КТ="да",1,0) -> 5 | G44: =AVERAGE('Нормативное соответствие'!G91:G95) -> #DIV/0! | H44: =AVERAGE('Нормативное соответствие'!H91:H95) -> #DIV/0! | I44: =AVERAGE('Нормативное соответствие'!I91:I95) -> #DIV/0! | J44: =AVERAGE('Нормативное соответствие'!J91:J95) -> #DIV/0! | K44: =AVERAGE('Нормативное соответствие'!K91:K95) -> 5 | L44: =AVERAGE('Нормативное соответствие'!L91:L95) -> 1
B45: =B96 -> Средства криптографической защиты информации (СКЗИ ГОСТ) | C45: =C96 -> СКЗИ | D45: =AVERAGE('Нормативное соответствие'!D97:D106)*IF(СКЗИ="да",1,0) -> 5 | E45: =AVERAGE('Нормативное соответствие'!E97:E106)*IF(СКЗИ="да",1,0) -> 4.82 | F45: =AVERAGE('Нормативное соответствие'!F97:F106)*IF(СКЗИ="да",1,0) -> 4.66 | G45: =AVERAGE(G97:G106) -> #DIV/0! | H45: =AVERAGE(H97:H106) -> #DIV/0! | I45: =AVERAGE(I97:I106) -> #DIV/0! | J45: =AVERAGE(J97:J106) -> #DIV/0! | K45: =AVERAGE(K97:K106) -> 4.66 | L45: =AVERAGE(L97:L106) -> 0
B46: =B107 -> 250 указ | C46: =C107 -> 250 | D46: =AVERAGE('Нормативное соответствие'!D108:D113)*IF(КИИ="да",1,0) -> 0 | E46: =AVERAGE('Нормативное соответствие'!E108:E113)*IF(КИИ="да",1,0) -> 0 | F46: =AVERAGE('Нормативное соответствие'!F108:F113)*IF(КИИ="да",1,0) -> 0 | G46: =AVERAGE('Нормативное соответствие'!G108:G113) -> #DIV/0! | H46: =AVERAGE('Нормативное соответствие'!H108:H113) -> #DIV/0! | I46: =AVERAGE('Нормативное соответствие'!I108:I113) -> #DIV/0! | J46: =AVERAGE('Нормативное соответствие'!J108:J113) -> #DIV/0! | K46: =AVERAGE('Нормативное соответствие'!K108:K113) -> 0.43402778 | L46: =AVERAGE('Нормативное соответствие'!L108:L113) -> 0.48611111
M48: ФЛАГ ОТКЛОНЕНИЯ | P48: Приоритет | Q48: Очередь 1 (КБ1) | R48: Приоритет | S48: Очередь 2 (КБ2) | T48: Приоритет | U48: Очередь 3 (КБ3)
B49: Персональные данные | C49: ПР | P49: =VLOOKUP(B49,Приоритет!$G$9:$K$52,5,0) -> 26 | Q49: Перс.данные | R49: =P49+200 -> 226 | S49: Перс.данные | T49: =P49+300 -> 326 | U49: Перс.данные
B50: Наличие политики в отношении обработки ПДН, соответствующей требованиям законодательтсва (https://62.rkn.gov.ru/directions/p3535/p6528) | C50: НС.ПР.5.8.15.1 | D50: 5 | E50: 5 | F50: 5 | K50: 5 | L50: =VALUE(LEFT(N50,3)) -> 5 | M50: =L50-K50 -> 0 | N50: 5 -да | P50: =P49+0.01 -> 26.01 | Q50: =IF(($L50-$F50)>=0,"", " - Разработать и утвердить Политику по обработке персональных данных в Обществе - Обеспечить регулярную проверку актуальности Политики по обработке персональных данных в Обществе и её соответствия действующим нормам законодательства") | R50: =R49+0.01 -> 226.01 | S50: =IF(($L50-$E50)>=0,"","") | T50: =T49+0.01 -> 326.01 | U50: =IF(($L50-$D50)>=0,"","")
B51: Политика опубликована и/или доступна (вебсайт или иные ресурсы) для чтения субъектам ПДН | C51: НС.ПР.5.8.15.2 | D51: 5 | E51: 5 | F51: 5 | K51: 5 | L51: =VALUE(LEFT(N51,3)) -> 0 | M51: =L51-K51 -> -5 | N51: 0 - нет | P51: =P50+0.01 -> 26.02 | Q51: =IF(($L51-$F51)>=0,"", " - Разместить Политику по обработке персональных данных в Организации (или выписку из неё) на веб-сайте Организации; - Разместить печатную версию Политики по обработке персональных данных в Организации в общедоступной части офиса Организации;"&" - Обеспечить ознакомление всех работников Организации с Политикой по обработке персональных"&" данных в Организации (с возможностью подтверждения такого ознакомления - посредством системы электронного документооборота или под роспись на бумажном носителе") -> - Разместить Политику по обработке персональных данных в Организации (или выписку из неё) на веб-сайте Организации; - Разместить печатную версию Политики по обработке персональных данных в Организации в общедоступной части офиса Организации; - Обеспечить ознакомление всех работников Организации с Политикой по обработке персональных данных в Организации (с возможностью подтверждения такого ознакомления - посредством системы электронного документооборота или под роспись на бумажном носителе | R51: =R50+0.01 -> 226.02 | S51: =IF(($L51-$E51)>=0,"","") | T51: =T50+0.01 -> 326.02 | U51: =IF(($L51-$D51)>=0,"","")
B52: Назначено лицо, ответственное за организацию обработки персональных данных, определены его функции и обязанности | C52: НС.ПР.5.8.15.3 | D52: 5 | E52: 5 | F52: 5 | K52: 5 | L52: =VALUE(LEFT(N52,3)) -> 0 | M52: =L52-K52 -> -5 | N52: 0 - нет | P52: =P51+0.01 -> 26.03 | Q52: =IF(($L52-$F52)>=0,"", " - Разработать и утвердить Приказ о назначении лица, ответственного за организацию обработки персональных данных.") -> - Разработать и утвердить Приказ о назначении лица, ответственного за организацию обработки персональных данных. | R52: =R51+0.01 -> 226.03 | S52: =IF(($L52-$E52)>=0,"","") | T52: =T51+0.01 -> 326.03 | U52: =IF(($L52-$D52)>=0,"","")
B53: Уведомление об обработке персональных данных направлено в Роскомнадзор, сведения об организации в реестре РКН поддерживаются в акутальном состоянии | C53: НС.ПР.5.8.15.4 | D53: 5 | E53: 5 | F53: 5 | K53: 5 | L53: =VALUE(LEFT(N53,3)) -> 0 | M53: =L53-K53 -> -5 | N53: 0 - нет | P53: =P52+0.01 -> 26.04 | Q53: =IF(($L53-$F53)>=0,"", " - Разработать и направить в Роскомнадзор Уведомление об обработке персональных данных") -> - Разработать и направить в Роскомнадзор Уведомление об обработке персональных данных | R53: =R52+0.01 -> 226.04 | S53: =IF(($L53-$E53)>=0,"","") | T53: =T52+0.01 -> 326.04 | U53: =IF(($L53-$D53)>=0,"","")
B54: Наличие ВНД, регламентирующих порядок реализации процессов обработки ПДН в соответствии с рекомендациями ПАО "Ростелеком" (размещено на киберпортале) | C54: НС.ПР.5.8.15.5 | D54: 5 | E54: 5 | F54: 5 | K54: 5 | L54: =VALUE(LEFT(N54,3)) -> 0 | M54: =L54-K54 -> -5 | N54: 0 - нет | P54: =P53+0.01 -> 26.05 | Q54: =IF(($L54-$F54)>=0,"", " - Провести процедуру сверки указанных в Уведомлении об обработке персональных данных сведений и реально существующих процессов обработки персональных данных в организации;"&" - В случае выявления необходимости, актуализировать и направить повторно Уведомление в Роскомнадзор;"&" - Запланировать регулярный процесс сверки указанных в Уведомлении об обработке персональных данных сведений и реально существующих процессов обработки персональных данных в организации и подачи актуальных сведений в Роскомнадзор") -> - Провести процедуру сверки указанных в Уведомлении об обработке персональных данных сведений и реально существующих процессов обработки персональных данных в организации; - В случае выявления необходимости, актуализировать и направить повторно Уведомление в Роскомнадзор; - Запланировать регулярный процесс сверки указанных в Уведомлении об обработке персональных данных сведений и реально существующих процессов обработки персональных данных в организации и подачи актуальных сведений в Роскомнадзор | R54: =R53+0.01 -> 226.05 | S54: =IF(($L54-$E54)>=0,"","") | T54: =T53+0.01 -> 326.05 | U54: =IF(($L54-$D54)>=0,"","")
B55: Наличие согласия на обработку персональных данных от субъекта персональных данных в соответствии с законодательством РФ | C55: НС.ПР.5.8.15.6 | D55: 5 | E55: 5 | F55: 5 | K55: 5 | L55: =VALUE(LEFT(N55,3)) -> 0 | M55: =L55-K55 -> -5 | N55: 0 - Контроль не выполняется | P55: =P54+0.01 -> 26.06 | Q55: =IF(($L55-$F55)>=0,"", " - Провести процедуру определения оснований для обработки персональных данных для каждой заявленной в ВНД организации цели их обработки;"&" - Разработать формы Согласия на обработку персональных данных от субъекта персональных данных для всех случаев (целей) обработки персональных данных в организации, для которых отсутствует иное законное основание;"&" - Обеспечить сбор Согласий на обработку персональных данных от субъектов персональных данных согласно разработанным формам;"&" - Разработать процесс учета и хранения Согласий на обработку персональных данных от субъектов персональных данных для всех случаев (целей) обработки персональных данных в организации") -> - Провести процедуру определения оснований для обработки персональных данных для каждой заявленной в ВНД организации цели их обработки; - Разработать формы Согласия на обработку персональных данных от субъекта персональных данных для всех случаев (целей) обработки персональных данных в организации, для которых отсутствует иное законное основание; - Обеспечить сбор Согласий на обработку персональных данных от субъектов персональных данных согласно разработанным формам; - Разработать процесс учета и хранения Согласий на обработку персональных данных от субъектов персональных данных для всех случаев (целей) обработки персональных данных в организации | R55: =R54+0.01 -> 226.06 | S55: =IF(($L55-$E55)>=0,"","") | T55: =T54+0.01 -> 326.06 | U55: =IF(($L55-$D55)>=0,"","")
B56: При поступлении на работу работник дает согласие на передачу его персональных данных третьим лицам | C56: НС.ПР.5.8.15.7 | D56: 5 | E56: 5 | F56: 5 | K56: 5 | L56: =VALUE(LEFT(N56,3)) -> 0 | M56: =L56-K56 -> -5 | N56: 0 - нет | P56: =P55+0.01 -> 26.07 | Q56: =IF(($L56-$F56)>=0,"", " - Разработать или получить в Блоке ИБ ПАО Ростелеком типовую форму Согласия на передачу персональных данных работника;"&" - Провести аудит процессов обработки персональных данных работников с целью выявления случаев их передачи третьим лицам;"&" - Проанализировать выявленные случаи передачи персональных данных работников третьим лицам на предмет отсеивания случаев, когда такая передача осуществляется в целях соблюдения законодательства Российской федерации;"&" - Адаптировать форму Согласия на передачу персональных данных работника для выявленных случаев, не имеющих правовых оснований для передачи;"&" - Разработать процесс учета и хранения Согласий на передачу персональных данных работников третьим лицам;"&" - Разработать и внедрить процедуру адаптации формы Согласия на передачу персональных данных работников третьим лицам для всех вновь возникающих в организации случаев такой передачи.") -> - Разработать или получить в Блоке ИБ ПАО Ростелеком типовую форму Согласия на передачу персональных данных работника; - Провести аудит процессов обработки персональных данных работников с целью выявления случаев их передачи третьим лицам; - Проанализировать выявленные случаи передачи персональных данных работников третьим лицам на предмет отсеивания случаев, когда такая передача осуществляется в целях соблюдения законодательства Российской федерации; - Адаптировать форму Согласия на передачу персональных данных работника для выявленных случаев, не имеющих правовых оснований для передачи; - Разработать процесс учета и хранения Согласий на передачу персональных данных работников третьим лицам; - Разработать и внедрить процедуру адаптации формы Согласия на передачу персональных данных работников третьим лицам для всех вновь возникающих в организации случаев такой передачи. | R56: =R55+0.01 -> 226.07 | S56: =IF(($L56-$E56)>=0,"","") | T56: =T55+0.01 -> 326.07 | U56: =IF(($L56-$D56)>=0,"","")
B57: Обеспечивается ли прекращение обработки персональных данных в случае отзыва субъектом персональных данных согласия на обработку своих персональных данных в срок, установленный законодательством РФ? | C57: НС.ПР.5.8.15.8 | D57: 5 | E57: 5 | F57: 5 | K57: 5 | L57: =VALUE(LEFT(N57,3)) -> 0 | M57: =L57-K57 -> -5 | N57: 0 - нет | P57: =P56+0.01 -> 26.08 | Q57: =IF(($L57-$F57)>=0,"", " - Разработать Порядок отзыва субъектом персональных данных согласия на обработку его персональных данных, определяющий процедуру и сроки прекращения обработки"&" его персональных данных (блокирование, уничтожение) в случае невозможности обеспечения правомерности дальнейшей их обработки") -> - Разработать Порядок отзыва субъектом персональных данных согласия на обработку его персональных данных, определяющий процедуру и сроки прекращения обработки его персональных данных (блокирование, уничтожение) в случае невозможности обеспечения правомерности дальнейшей их обработки | R57: =R56+0.01 -> 226.08 | S57: =IF(($L57-$E57)>=0,"","") | T57: =T56+0.01 -> 326.08 | U57: =IF(($L57-$D57)>=0,"","")
B58: Осуществляется ознакомление всех работников с требованием о неразглашении информации, содержащей персональные данные субъектов персональных данных третьим лицам | C58: НС.ПР.5.8.15.9 | D58: 5 | E58: 5 | F58: 5 | K58: 5 | L58: =VALUE(LEFT(N58,3)) -> 0 | M58: =L58-K58 -> -5 | N58: 0 - нет | P58: =P57+0.01 -> 26.09 | Q58: =IF(($L58-$F58)>=0,"", " - Разработать или получить в Блоке ИБ ПАО Ростелеком типовую форму Обязательства о неразглашении конфиденциальной информации (персональных данных);"&" - Разработать процесс сбора Обязательств о неразглашении конфиденциальной информации (персональных данных) с вновь устроившихся работников организации, либо подтверждения их ознакомления в с требованием о неразглашении в иной форме") -> - Разработать или получить в Блоке ИБ ПАО Ростелеком типовую форму Обязательства о неразглашении конфиденциальной информации (персональных данных); - Разработать процесс сбора Обязательств о неразглашении конфиденциальной информации (персональных данных) с вновь устроившихся работников организации, либо подтверждения их ознакомления в с требованием о неразглашении в иной форме | R58: =R57+0.01 -> 226.09 | S58: =IF(($L58-$E58)>=0,"","") | T58: =T57+0.01 -> 326.09 | U58: =IF(($L58-$D58)>=0,"","")
B59: Наличие документа, подтверждающего определение угроз безопасности ПДн при их обработке | C59: НС.ПР.5.8.15.10 | D59: 5 | E59: 5 | F59: 5 | K59: 5 | L59: =VALUE(LEFT(N59,3)) -> 0 | M59: =L59-K59 -> -5 | N59: 0 - нет | P59: =P58+0.01 -> 26.1 | Q59: =IF(($L59-$F59)>=0,"", " Разработать нормативный документ, в котором определены угрозы безопасности ПДн при их обработке;"&"" ) -> Разработать нормативный документ, в котором определены угрозы безопасности ПДн при их обработке; | R59: =R58+0.01 -> 226.1 | S59: =IF(($L59-$E59)>=0,"","") | T59: =T58+0.01 -> 326.1 | U59: =IF(($L59-$D59)>=0,"","")
